Workbook

Sheet Dashboard
B1: =CoName&" · SmartTrader ERP" -> Your Trading Co. · SmartTrader ERP
B2: ="Live business cockpit · Period: "&DAY(D4)&"/"&MONTH(D4)&"/"&YEAR(D4)&" to "&DAY(G4)&"/"&MONTH(G4)&"/"&YEAR(G4) -> Live business cockpit · Period: 1/4/2026 to 11/10/2026
B3: =IF(IsPro,LicStatus&" · lines used: "&"Sales "&COUNTA(Sales!$D$5:$D$3004)&" · Purchases "&COUNTA(Purchases!$D$5:$D$3004)&" · Cash Book "&COUNTA(CashBook!$C$5:$C$3004),LicStatus&" · first 200 lines per register · used: "&"Sales "&COUNTA(Sales!$D$5:$D$3004)&" · Purchases "&COUNTA(Purchases!$D$5:$D$3004)&" · Cash Book "&COUNTA(CashBook!$C$5:$C$3004)&IF(OverFreeLimit," >> LIMIT REACHED: newer lines are not counted - upgrade on the Plans sheet","")) -> FREE PLAN · first 200 lines per register · used: Sales 151 · Purchases 33 · Cash Book 121
B4: From | D4: =FYStart -> 46113 | E4: To | G4: =AsOf -> 46306 | H4: ← overwrite these dates to analyse any period
B6: New Sale | C6: Purchase | D6: Cash Book | E6: Items | F6: Parties | G6: Invoice | H6: Adjust | I6: Reports | J6: Settings | K6: Guide | L6: PRO Plans
B8: SALES (excl. GST) | D8: GROSS PROFIT | F8: NET PROFIT | H8: PURCHASES (excl. GST) | J8: EXPENSES
B9: =SUMIFS(Sales!$L$5:INDEX(Sales!$L$5:$L$3004,TxRows),Sales!$A$5:INDEX(Sales!$A$5:$A$3004,TxRows),">="&DFrom,Sales!$A$5:INDEX(Sales!$A$5:$A$3004,TxRows),"<="&DTo) -> 1288883.1 | D9: =SUMIFS(Sales!$S$5:INDEX(Sales!$S$5:$S$3004,TxRows),Sales!$A$5:INDEX(Sales!$A$5:$A$3004,TxRows),">="&DFrom,Sales!$A$5:INDEX(Sales!$A$5:$A$3004,TxRows),"<="&DTo) -> 291168.19 | F9: =D9-SUMIFS(CashBook!$G$5:INDEX(CashBook!$G$5:$G$3004,TxRows),CashBook!$C$5:INDEX(CashBook!$C$5:$C$3004,TxRows),"Expense",CashBook!$A$5:INDEX(CashBook!$A$5:$A$3004,TxRows),">="&DFrom,CashBook!$A$5:INDEX(CashBook!$A$5:$A$3004,TxRows),"<="&DTo)+SUMIFS(CashBook!$G$5:INDEX(CashBook!$G$5:$G$3004,TxRows),CashBook!$C$5:INDEX(CashBook!$C$5:$C$3004,TxRows),"Other Income",CashBook!$A$5:INDEX(CashBook!$A$5:$A$3004,TxRows),">="&DFrom,CashBook!$A$5:INDEX(CashBook!$A$5:$A$3004,TxRows),"<="&DTo)+SUMIFS(Adjustments!$G$5:$G$504,Adjustments!$A$5:$A$504,">="&DFrom,Adjustments!$A$5:$A$504,"<="&DTo) -> 56840.39 | H9: =SUMIFS(Purchases!$K$5:INDEX(Purchases!$K$5:$K$3004,TxRows),Purchases!$A$5:INDEX(Purchases!$A$5:$A$3004,TxRows),">="&DFrom,Purchases!$A$5:INDEX(Purchases!$A$5:$A$3004,TxRows),"<="&DTo) -> 1074712 | J9: =SUMIFS(CashBook!$G$5:INDEX(CashBook!$G$5:$G$3004,TxRows),CashBook!$C$5:INDEX(CashBook!$C$5:$C$3004,TxRows),"Expense",CashBook!$A$5:INDEX(CashBook!$A$5:$A$3004,TxRows),">="&DFrom,CashBook!$A$5:INDEX(CashBook!$A$5:$A$3004,TxRows),"<="&DTo) -> 233298
B11: GP MARGIN | D11: RECEIVABLES (owed to you) | F11: PAYABLES (you owe) | H11: STOCK VALUE (at cost) | J11: NET GST PAYABLE
B12: =IF(B9=0,0,D9/B9) -> 0.22590736 | D12: =SUMIF(Parties!$N$5:$N$304,">0") -> 67030.63 | F12: =-SUMIF(Parties!$N$5:$N$304,"<0") -> 37223.86 | H12: =SUM(Items!$Q$5:$Q$504) -> 478767.28 | J12: =SUMIFS(Sales!$N$5:INDEX(Sales!$N$5:$N$3004,TxRows),Sales!$A$5:INDEX(Sales!$A$5:$A$3004,TxRows),">="&DFrom,Sales!$A$5:INDEX(Sales!$A$5:$A$3004,TxRows),"<="&DTo)+SUMIFS(Sales!$O$5:INDEX(Sales!$O$5:$O$3004,TxRows),Sales!$A$5:INDEX(Sales!$A$5:$A$3004,TxRows),">="&DFrom,Sales!$A$5:INDEX(Sales!$A$5:$A$3004,TxRows),"<="&DTo)+SUMIFS(Sales!$P$5:INDEX(Sales!$P$5:$P$3004,TxRows),Sales!$A$5:INDEX(Sales!$A$5:$A$3004,TxRows),">="&DFrom,Sales!$A$5:INDEX(Sales!$A$5:$A$3004,TxRows),"<="&DTo)-SUMIFS(Purchases!$M$5:INDEX(Purchases!$M$5:$M$3004,TxRows),Purchases!$A$5:INDEX(Purchases!$A$5:$A$3004,TxRows),">="&DFrom,Purchases!$A$5:INDEX(Purchases!$A$5:$A$3004,TxRows),"<="&DTo)-SUMIFS(Purchases!$N$5:INDEX(Purchases!$N$5:$N$3004,TxRows),Purchases!$A$5:INDEX(Purchases!$A$5:$A$3004,TxRows),">="&DFrom,Purchases!$A$5:INDEX(Purchases!$A$5:$A$3004,TxRows),"<="&DTo)-SUMIFS(Purchases!$O$5:INDEX(Purchases!$O$5:$O$3004,TxRows),Purchases!$A$5:INDEX(Purchases!$A$5:$A$3004,TxRows),">="&DFrom,Purchases!$A$5:INDEX(Purchases!$A$5:$A$3004,TxRows),"<="&DTo) -> 23042.26
B14: ITEMS TO REORDER | D14: DEAD-STOCK ITEMS | F14: OVERDUE CUSTOMERS | H14: PENDING DELIVERIES (lines) | J14: NEXT INVOICE No.
B15: =COUNTIF(Items!$R$5:$R$504,"REORDER")+COUNTIF(Items!$R$5:$R$504,"OUT OF STOCK")+COUNTIF(Items!$R$5:$R$504,"NEGATIVE") -> 1 | D15: =COUNTIF(Items!$R$5:$R$504,"DEAD STOCK") -> 0 | F15: =COUNTIF(Parties!$S$5:$S$304,"OVERDUE")+COUNTIF(Parties!$S$5:$S$304,"OVER LIMIT") -> 0 | H15: =COUNTIFS(Sales!$I$5:INDEX(Sales!$I$5:$I$3004,TxRows),"Pending")+COUNTIFS(Sales!$I$5:INDEX(Sales!$I$5:$I$3004,TxRows),"Packed") -> 2 | J15: =InvPrefix&TEXT(MAX(Sales!$W$5:INDEX(Sales!$W$5:$W$3004,TxRows))+1,"0000") -> INV-0128
B18: CASH & BANK BALANCES (as of 'To' date) | I18: TOP 10 ITEMS BY SALES (all time)
B19: Account | D19: Opening | E19: In | F19: Out | G19: Balance | I19: # | J19: Item | L19: Sales (₹) | M19: Stock | N19: Status
B20: =IF(Settings!$A$18="","",Settings!$A$18) -> Cash | D20: =IF(B20="","",N(Settings!$B$18)) -> 50000 | E20: =IF(B20="","",SUMIFS(CashBook!$I$5:INDEX(CashBook!$I$5:$I$3004,TxRows),CashBook!$F$5:INDEX(CashBook!$F$5:$F$3004,TxRows),B20,CashBook!$A$5:INDEX(CashBook!$A$5:$A$3004,TxRows),"<="&DTo)+SUMIFS(Sales!$X$5:INDEX(Sales!$X$5:$X$3004,TxRows),Sales!$H$5:INDEX(Sales!$H$5:$H$3004,TxRows),B20,Sales!$A$5:INDEX(Sales!$A$5:$A$3004,TxRows),"<="&DTo)) -> 539651.8 | F20: =IF(B20="","",SUMIFS(CashBook!$J$5:INDEX(CashBook!$J$5:$J$3004,TxRows),CashBook!$F$5:INDEX(CashBook!$F$5:$F$3004,TxRows),B20,CashBook!$A$5:INDEX(CashBook!$A$5:$A$3004,TxRows),"<="&DTo)+SUMIFS(Purchases!$S$5:INDEX(Purchases!$S$5:$S$3004,TxRows),Purchases!$H$5:INDEX(Purchases!$H$5:$H$3004,TxRows),B20,Purchases!$A$5:INDEX(Purchases!$A$5:$A$3004,TxRows),"<="&DTo)) -> 515325 | G20: =IF(B20="","",D20+E20-F20) -> 74326.8 | I20: 1 | J20: =IFERROR(IF(INDEX(Items!$U$5:$U$504,MATCH(LARGE(Items!$Z$5:$Z$504,1),Items!$Z$5:$Z$504,0))=0,"",INDEX(Items!$A$5:$A$504,MATCH(LARGE(Items!$Z$5:$Z$504,1),Items!$Z$5:$Z$504,0))),"") -> Refined Oil 15L | L20: =IF(J20="","",INDEX(Items!$U$5:$U$504,MATCH(LARGE(Items!$Z$5:$Z$504,1),Items!$Z$5:$Z$504,0))) -> 226435.2 | M20: =IF(J20="","",INDEX(Items!$O$5:$O$504,MATCH(LARGE(Items!$Z$5:$Z$504,1),Items!$Z$5:$Z$504,0))) -> 11 | N20: =IF(J20="","",INDEX(Items!$R$5:$R$504,MATCH(LARGE(Items!$Z$5:$Z$504,1),Items!$Z$5:$Z$504,0))) -> OK
B21: =IF(Settings!$A$19="","",Settings!$A$19) -> Bank | D21: =IF(B21="","",N(Settings!$B$19)) -> 250000 | E21: =IF(B21="","",SUMIFS(CashBook!$I$5:INDEX(CashBook!$I$5:$I$3004,TxRows),CashBook!$F$5:INDEX(CashBook!$F$5:$F$3004,TxRows),B21,CashBook!$A$5:INDEX(CashBook!$A$5:$A$3004,TxRows),"<="&DTo)+SUMIFS(Sales!$X$5:INDEX(Sales!$X$5:$X$3004,TxRows),Sales!$H$5:INDEX(Sales!$H$5:$H$3004,TxRows),B21,Sales!$A$5:INDEX(Sales!$A$5:$A$3004,TxRows),"<="&DTo)) -> 1164653.8 | F21: =IF(B21="","",SUMIFS(CashBook!$J$5:INDEX(CashBook!$J$5:$J$3004,TxRows),CashBook!$F$5:INDEX(CashBook!$F$5:$F$3004,TxRows),B21,CashBook!$A$5:INDEX(CashBook!$A$5:$A$3004,TxRows),"<="&DTo)+SUMIFS(Purchases!$S$5:INDEX(Purchases!$S$5:$S$3004,TxRows),Purchases!$H$5:INDEX(Purchases!$H$5:$H$3004,TxRows),B21,Purchases!$A$5:INDEX(Purchases!$A$5:$A$3004,TxRows),"<="&DTo)) -> 1340591.2 | G21: =IF(B21="","",D21+E21-F21) -> 74062.58 | I21: 2 | J21: =IFERROR(IF(INDEX(Items!$U$5:$U$504,MATCH(LARGE(Items!$Z$5:$Z$504,2),Items!$Z$5:$Z$504,0))=0,"",INDEX(Items!$A$5:$A$504,MATCH(LARGE(Items!$Z$5:$Z$504,2),Items!$Z$5:$Z$504,0))),"") -> Basmati Rice 25kg | L21: =IF(J21="","",INDEX(Items!$U$5:$U$504,MATCH(LARGE(Items!$Z$5:$Z$504,2),Items!$Z$5:$Z$504,0))) -> 195710.58 | M21: =IF(J21="","",INDEX(Items!$O$5:$O$504,MATCH(LARGE(Items!$Z$5:$Z$504,2),Items!$Z$5:$Z$504,0))) -> 51 | N21: =IF(J21="","",INDEX(Items!$R$5:$R$504,MATCH(LARGE(Items!$Z$5:$Z$504,2),Items!$Z$5:$Z$504,0))) -> OK
B22: =IF(Settings!$A$20="","",Settings!$A$20) -> UPI | D22: =IF(B22="","",N(Settings!$B$20)) -> 0 | E22: =IF(B22="","",SUMIFS(CashBook!$I$5:INDEX(CashBook!$I$5:$I$3004,TxRows),CashBook!$F$5:INDEX(CashBook!$F$5:$F$3004,TxRows),B22,CashBook!$A$5:INDEX(CashBook!$A$5:$A$3004,TxRows),"<="&DTo)+SUMIFS(Sales!$X$5:INDEX(Sales!$X$5:$X$3004,TxRows),Sales!$H$5:INDEX(Sales!$H$5:$H$3004,TxRows),B22,Sales!$A$5:INDEX(Sales!$A$5:$A$3004,TxRows),"<="&DTo)) -> 384192.26 | F22: =IF(B22="","",SUMIFS(CashBook!$J$5:INDEX(CashBook!$J$5:$J$3004,TxRows),CashBook!$F$5:INDEX(CashBook!$F$5:$F$3004,TxRows),B22,CashBook!$A$5:INDEX(CashBook!$A$5:$A$3004,TxRows),"<="&DTo)+SUMIFS(Purchases!$S$5:INDEX(Purchases!$S$5:$S$3004,TxRows),Purchases!$H$5:INDEX(Purchases!$H$5:$H$3004,TxRows),B22,Purchases!$A$5:INDEX(Purchases!$A$5:$A$3004,TxRows),"<="&DTo)) -> 291973 | G22: =IF(B22="","",D22+E22-F22) -> 92219.26 | I22: 3 | J22: =IFERROR(IF(INDEX(Items!$U$5:$U$504,MATCH(LARGE(Items!$Z$5:$Z$504,3),Items!$Z$5:$Z$504,0))=0,"",INDEX(Items!$A$5:$A$504,MATCH(LARGE(Items!$Z$5:$Z$504,3),Items!$Z$5:$Z$504,0))),"") -> Sugar 50kg | L22: =IF(J22="","",INDEX(Items!$U$5:$U$504,MATCH(LARGE(Items!$Z$5:$Z$504,3),Items!$Z$5:$Z$504,0))) -> 140580.2 | M22: =IF(J22="","",INDEX(Items!$O$5:$O$504,MATCH(LARGE(Items!$Z$5:$Z$504,3),Items!$Z$5:$Z$504,0))) -> 23 | N22: =IF(J22="","",INDEX(Items!$R$5:$R$504,MATCH(LARGE(Items!$Z$5:$Z$504,3),Items!$Z$5:$Z$504,0))) -> OK
B23: =IF(Settings!$A$21="","",Settings!$A$21) | D23: =IF(B23="","",N(Settings!$B$21)) | E23: =IF(B23="","",SUMIFS(CashBook!$I$5:INDEX(CashBook!$I$5:$I$3004,TxRows),CashBook!$F$5:INDEX(CashBook!$F$5:$F$3004,TxRows),B23,CashBook!$A$5:INDEX(CashBook!$A$5:$A$3004,TxRows),"<="&DTo)+SUMIFS(Sales!$X$5:INDEX(Sales!$X$5:$X$3004,TxRows),Sales!$H$5:INDEX(Sales!$H$5:$H$3004,TxRows),B23,Sales!$A$5:INDEX(Sales!$A$5:$A$3004,TxRows),"<="&DTo)) | F23: =IF(B23="","",SUMIFS(CashBook!$J$5:INDEX(CashBook!$J$5:$J$3004,TxRows),CashBook!$F$5:INDEX(CashBook!$F$5:$F$3004,TxRows),B23,CashBook!$A$5:INDEX(CashBook!$A$5:$A$3004,TxRows),"<="&DTo)+SUMIFS(Purchases!$S$5:INDEX(Purchases!$S$5:$S$3004,TxRows),Purchases!$H$5:INDEX(Purchases!$H$5:$H$3004,TxRows),B23,Purchases!$A$5:INDEX(Purchases!$A$5:$A$3004,TxRows),"<="&DTo)) | G23: =IF(B23="","",D23+E23-F23) | I23: 4 | J23: =IFERROR(IF(INDEX(Items!$U$5:$U$504,MATCH(LARGE(Items!$Z$5:$Z$504,4),Items!$Z$5:$Z$504,0))=0,"",INDEX(Items!$A$5:$A$504,MATCH(LARGE(Items!$Z$5:$Z$504,4),Items!$Z$5:$Z$504,0))),"") -> Copper Wire 90m | L23: =IF(J23="","",INDEX(Items!$U$5:$U$504,MATCH(LARGE(Items!$Z$5:$Z$504,4),Items!$Z$5:$Z$504,0))) -> 129570.84 | M23: =IF(J23="","",INDEX(Items!$O$5:$O$504,MATCH(LARGE(Items!$Z$5:$Z$504,4),Items!$Z$5:$Z$504,0))) -> 14 | N23: =IF(J23="","",INDEX(Items!$R$5:$R$504,MATCH(LARGE(Items!$Z$5:$Z$504,4),Items!$Z$5:$Z$504,0))) -> OK
B24: TOTAL LIQUIDITY | G24: =SUM(G20:G23) -> 240608.64 | I24: 5 | J24: =IFERROR(IF(INDEX(Items!$U$5:$U$504,MATCH(LARGE(Items!$Z$5:$Z$504,5),Items!$Z$5:$Z$504,0))=0,"",INDEX(Items!$A$5:$A$504,MATCH(LARGE(Items!$Z$5:$Z$504,5),Items!$Z$5:$Z$504,0))),"") -> PVC Pipe 1in 6m | L24: =IF(J24="","",INDEX(Items!$U$5:$U$504,MATCH(LARGE(Items!$Z$5:$Z$504,5),Items!$Z$5:$Z$504,0))) -> 96569.55 | M24: =IF(J24="","",INDEX(Items!$O$5:$O$504,MATCH(LARGE(Items!$Z$5:$Z$504,5),Items!$Z$5:$Z$504,0))) -> 168 | N24: =IF(J24="","",INDEX(Items!$R$5:$R$504,MATCH(LARGE(Items!$Z$5:$Z$504,5),Items!$Z$5:$Z$504,0))) -> OK
I25: 6 | J25: =IFERROR(IF(INDEX(Items!$U$5:$U$504,MATCH(LARGE(Items!$Z$5:$Z$504,6),Items!$Z$5:$Z$504,0))=0,"",INDEX(Items!$A$5:$A$504,MATCH(LARGE(Items!$Z$5:$Z$504,6),Items!$Z$5:$Z$504,0))),"") -> LED Bulb 9W | L25: =IF(J25="","",INDEX(Items!$U$5:$U$504,MATCH(LARGE(Items!$Z$5:$Z$504,6),Items!$Z$5:$Z$504,0))) -> 93178.81 | M25: =IF(J25="","",INDEX(Items!$O$5:$O$504,MATCH(LARGE(Items!$Z$5:$Z$504,6),Items!$Z$5:$Z$504,0))) -> 366 | N25: =IF(J25="","",INDEX(Items!$R$5:$R$504,MATCH(LARGE(Items!$Z$5:$Z$504,6),Items!$Z$5:$Z$504,0))) -> OK
I26: 7 | J26: =IFERROR(IF(INDEX(Items!$U$5:$U$504,MATCH(LARGE(Items!$Z$5:$Z$504,7),Items!$Z$5:$Z$504,0))=0,"",INDEX(Items!$A$5:$A$504,MATCH(LARGE(Items!$Z$5:$Z$504,7),Items!$Z$5:$Z$504,0))),"") -> Ceiling Fan 1200mm | L26: =IF(J26="","",INDEX(Items!$U$5:$U$504,MATCH(LARGE(Items!$Z$5:$Z$504,7),Items!$Z$5:$Z$504,0))) -> 91510.02 | M26: =IF(J26="","",INDEX(Items!$O$5:$O$504,MATCH(LARGE(Items!$Z$5:$Z$504,7),Items!$Z$5:$Z$504,0))) -> 25 | N26: =IF(J26="","",INDEX(Items!$R$5:$R$504,MATCH(LARGE(Items!$Z$5:$Z$504,7),Items!$Z$5:$Z$504,0))) -> OK
I27: 8 | J27: =IFERROR(IF(INDEX(Items!$U$5:$U$504,MATCH(LARGE(Items!$Z$5:$Z$504,8),Items!$Z$5:$Z$504,0))=0,"",INDEX(Items!$A$5:$A$504,MATCH(LARGE(Items!$Z$5:$Z$504,8),Items!$Z$5:$Z$504,0))),"") -> Detergent 5kg | L27: =IF(J27="","",INDEX(Items!$U$5:$U$504,MATCH(LARGE(Items!$Z$5:$Z$504,8),Items!$Z$5:$Z$504,0))) -> 91039.25 | M27: =IF(J27="","",INDEX(Items!$O$5:$O$504,MATCH(LARGE(Items!$Z$5:$Z$504,8),Items!$Z$5:$Z$504,0))) -> 75 | N27: =IF(J27="","",INDEX(Items!$R$5:$R$504,MATCH(LARGE(Items!$Z$5:$Z$504,8),Items!$Z$5:$Z$504,0))) -> OK
I28: 9 | J28: =IFERROR(IF(INDEX(Items!$U$5:$U$504,MATCH(LARGE(Items!$Z$5:$Z$504,9),Items!$Z$5:$Z$504,0))=0,"",INDEX(Items!$A$5:$A$504,MATCH(LARGE(Items!$Z$5:$Z$504,9),Items!$Z$5:$Z$504,0))),"") -> Cement 50kg | L28: =IF(J28="","",INDEX(Items!$U$5:$U$504,MATCH(LARGE(Items!$Z$5:$Z$504,9),Items!$Z$5:$Z$504,0))) -> 86125.9 | M28: =IF(J28="","",INDEX(Items!$O$5:$O$504,MATCH(LARGE(Items!$Z$5:$Z$504,9),Items!$Z$5:$Z$504,0))) -> 216 | N28: =IF(J28="","",INDEX(Items!$R$5:$R$504,MATCH(LARGE(Items!$Z$5:$Z$504,9),Items!$Z$5:$Z$504,0))) -> OK
I29: 10 | J29: =IFERROR(IF(INDEX(Items!$U$5:$U$504,MATCH(LARGE(Items!$Z$5:$Z$504,10),Items!$Z$5:$Z$504,0))=0,"",INDEX(Items!$A$5:$A$504,MATCH(LARGE(Items!$Z$5:$Z$504,10),Items!$Z$5:$Z$504,0))),"") -> Tea Premium 1kg | L29: =IF(J29="","",INDEX(Items!$U$5:$U$504,MATCH(LARGE(Items!$Z$5:$Z$504,10),Items!$Z$5:$Z$504,0))) -> 61737.24 | M29: =IF(J29="","",INDEX(Items!$O$5:$O$504,MATCH(LARGE(Items!$Z$5:$Z$504,10),Items!$Z$5:$Z$504,0))) -> 92 | N29: =IF(J29="","",INDEX(Items!$R$5:$R$504,MATCH(LARGE(Items!$Z$5:$Z$504,10),Items!$Z$5:$Z$504,0))) -> OK

Sheet Sales
A1: SALES / INVOICES (DELIVER) | Z1: « Home
A2: One line per item sold. Keep all lines of an invoice together. Leave Rate blank to use the standard sale rate.
A3: Blue / cream = type here | J3: Grey = automatic (do not type)
A4: Date * | B4: Invoice No * | C4: Customer * | D4: Item * | E4: Qty * | F4: Rate (₹) blank=std | G4: Disc % | H4: Paid Via (blank=Credit) | I4: Delivery | J4: Unit | K4: Rate Used (₹) | L4: Taxable (₹) | M4: GST % | N4: CGST (₹) | O4: SGST (₹) | P4: IGST (₹) | Q4: Line Total (₹) | R4: COGS (₹) | S4: Profit (₹) | T4: Stock Check | U4: itemRow | V4: partyRow | W4: invNum | X4: Paid Now (₹)
A5: 46114 | B5: INV-0001 | C5: Sharma Kirana Store | D5: Basmati Rice 25kg | E5: 3 | G5: 0.02 | H5: Bank | I5: Delivered | J5: =IF($D5="","",IFERROR(INDEX(Items!$D$5:$D$504,U5),"")) -> Bag | K5: =IF($D5="","",IF($F5="",IFERROR(INDEX(Items!$H$5:$H$504,U5),0),$F5)) -> 2106 | L5: =IF($D5="","",ROUND(N($E5)*K5*(1-N($G5)),2)) -> 6191.64 | M5: =IF($D5="","",IFERROR(INDEX(Items!$F$5:$F$504,U5),0)) -> 0.05 | N5: =IF($D5="","",IF(AND(V5<>"",INDEX(Parties!$E$5:$E$304,V5)<>"",INDEX(Parties!$E$5:$E$304,V5)<>HomeState),0,ROUND(L5*M5/2,2))) -> 154.79 | O5: =IF($D5="","",N5) -> 154.79 | P5: =IF($D5="","",IF(AND(V5<>"",INDEX(Parties!$E$5:$E$304,V5)<>"",INDEX(Parties!$E$5:$E$304,V5)<>HomeState),ROUND(L5*M5,2),0)) -> 0 | Q5: =IF($D5="","",L5+N5+O5+P5) -> 6501.22 | R5: =IF($D5="","",ROUND(N($E5)*IFERROR(INDEX(Items!$P$5:$P$504,U5),0),2)) -> 4942.29 | S5: =IF($D5="","",L5-R5) -> 1249.35 | T5: =IF($D5="","",IF(U5="","UNKNOWN ITEM",IF(INDEX(Items!$O$5:$O$504,U5)<0,"NEG STOCK",IF(K5<INDEX(Items!$P$5:$P$504,U5),"BELOW COST","OK")))) -> OK | U5: =IF($D5="","",IFERROR(MATCH($D5,Items!$A$5:$A$504,0),"")) -> 1 | V5: =IF($C5="","",IFERROR(MATCH($C5,Parties!$A$5:$A$304,0),"")) -> 1 | W5: =IF($B5="","",IFERROR(VALUE(SUBSTITUTE($B5,InvPrefix,"")),0)) -> 1 | X5: =IF($D5="","",IF(OR($H5="",$H5="Credit"),0,Q5)) -> 6501.22
A6: 46116 | B6: INV-0002 | C6: Gupta Electricals | D6: Basmati Rice 25kg | E6: 8 | H6: Bank | I6: Delivered | J6: =IF($D6="","",IFERROR(INDEX(Items!$D$5:$D$504,U6),"")) -> Bag | K6: =IF($D6="","",IF($F6="",IFERROR(INDEX(Items!$H$5:$H$504,U6),0),$F6)) -> 2106 | L6: =IF($D6="","",ROUND(N($E6)*K6*(1-N($G6)),2)) -> 16848 | M6: =IF($D6="","",IFERROR(INDEX(Items!$F$5:$F$504,U6),0)) -> 0.05 | N6: =IF($D6="","",IF(AND(V6<>"",INDEX(Parties!$E$5:$E$304,V6)<>"",INDEX(Parties!$E$5:$E$304,V6)<>HomeState),0,ROUND(L6*M6/2,2))) -> 421.2 | O6: =IF($D6="","",N6) -> 421.2 | P6: =IF($D6="","",IF(AND(V6<>"",INDEX(Parties!$E$5:$E$304,V6)<>"",INDEX(Parties!$E$5:$E$304,V6)<>HomeState),ROUND(L6*M6,2),0)) -> 0 | Q6: =IF($D6="","",L6+N6+O6+P6) -> 17690.4 | R6: =IF($D6="","",ROUND(N($E6)*IFERROR(INDEX(Items!$P$5:$P$504,U6),0),2)) -> 13179.44 | S6: =IF($D6="","",L6-R6) -> 3668.56 | T6: =IF($D6="","",IF(U6="","UNKNOWN ITEM",IF(INDEX(Items!$O$5:$O$504,U6)<0,"NEG STOCK",IF(K6<INDEX(Items!$P$5:$P$504,U6),"BELOW COST","OK")))) -> OK | U6: =IF($D6="","",IFERROR(MATCH($D6,Items!$A$5:$A$504,0),"")) -> 1 | V6: =IF($C6="","",IFERROR(MATCH($C6,Parties!$A$5:$A$304,0),"")) -> 2 | W6: =IF($B6="","",IFERROR(VALUE(SUBSTITUTE($B6,InvPrefix,"")),0)) -> 2 | X6: =IF($D6="","",IF(OR($H6="",$H6="Credit"),0,Q6)) -> 17690.4
A7: 46119 | B7: INV-0003 | C7: Sharma Kirana Store | D7: PVC Pipe 1in 6m | E7: 32 | I7: Delivered | J7: =IF($D7="","",IFERROR(INDEX(Items!$D$5:$D$504,U7),"")) -> Pcs | K7: =IF($D7="","",IF($F7="",IFERROR(INDEX(Items!$H$5:$H$504,U7),0),$F7)) -> 297 | L7: =IF($D7="","",ROUND(N($E7)*K7*(1-N($G7)),2)) -> 9504 | M7: =IF($D7="","",IFERROR(INDEX(Items!$F$5:$F$504,U7),0)) -> 0.18 | N7: =IF($D7="","",IF(AND(V7<>"",INDEX(Parties!$E$5:$E$304,V7)<>"",INDEX(Parties!$E$5:$E$304,V7)<>HomeState),0,ROUND(L7*M7/2,2))) -> 855.36 | O7: =IF($D7="","",N7) -> 855.36 | P7: =IF($D7="","",IF(AND(V7<>"",INDEX(Parties!$E$5:$E$304,V7)<>"",INDEX(Parties!$E$5:$E$304,V7)<>HomeState),ROUND(L7*M7,2),0)) -> 0 | Q7: =IF($D7="","",L7+N7+O7+P7) -> 11214.72 | R7: =IF($D7="","",ROUND(N($E7)*IFERROR(INDEX(Items!$P$5:$P$504,U7),0),2)) -> 6708.26 | S7: =IF($D7="","",L7-R7) -> 2795.74 | T7: =IF($D7="","",IF(U7="","UNKNOWN ITEM",IF(INDEX(Items!$O$5:$O$504,U7)<0,"NEG STOCK",IF(K7<INDEX(Items!$P$5:$P$504,U7),"BELOW COST","OK")))) -> OK | U7: =IF($D7="","",IFERROR(MATCH($D7,Items!$A$5:$A$504,0),"")) -> 9 | V7: =IF($C7="","",IFERROR(MATCH($C7,Parties!$A$5:$A$304,0),"")) -> 1 | W7: =IF($B7="","",IFERROR(VALUE(SUBSTITUTE($B7,InvPrefix,"")),0)) -> 3 | X7: =IF($D7="","",IF(OR($H7="",$H7="Credit"),0,Q7)) -> 0
A8: 46120 | B8: INV-0004 | C8: Delhi Hardware Mart | D8: Cement 50kg | E8: 25 | H8: Bank | I8: Delivered | J8: =IF($D8="","",IFERROR(INDEX(Items!$D$5:$D$504,U8),"")) -> Bag | K8: =IF($D8="","",IF($F8="",IFERROR(INDEX(Items!$H$5:$H$504,U8),0),$F8)) -> 427 | L8: =IF($D8="","",ROUND(N($E8)*K8*(1-N($G8)),2)) -> 10675 | M8: =IF($D8="","",IFERROR(INDEX(Items!$F$5:$F$504,U8),0)) -> 0.18 | N8: =IF($D8="","",IF(AND(V8<>"",INDEX(Parties!$E$5:$E$304,V8)<>"",INDEX(Parties!$E$5:$E$304,V8)<>HomeState),0,ROUND(L8*M8/2,2))) -> 0 | O8: =IF($D8="","",N8) -> 0 | P8: =IF($D8="","",IF(AND(V8<>"",INDEX(Parties!$E$5:$E$304,V8)<>"",INDEX(Parties!$E$5:$E$304,V8)<>HomeState),ROUND(L8*M8,2),0)) -> 1921.5 | Q8: =IF($D8="","",L8+N8+O8+P8) -> 12596.5 | R8: =IF($D8="","",ROUND(N($E8)*IFERROR(INDEX(Items!$P$5:$P$504,U8),0),2)) -> 8504.36 | S8: =IF($D8="","",L8-R8) -> 2170.64 | T8: =IF($D8="","",IF(U8="","UNKNOWN ITEM",IF(INDEX(Items!$O$5:$O$504,U8)<0,"NEG STOCK",IF(K8<INDEX(Items!$P$5:$P$504,U8),"BELOW COST","OK")))) -> OK | U8: =IF($D8="","",IFERROR(MATCH($D8,Items!$A$5:$A$504,0),"")) -> 10 | V8: =IF($C8="","",IFERROR(MATCH($C8,Parties!$A$5:$A$304,0),"")) -> 3 | W8: =IF($B8="","",IFERROR(VALUE(SUBSTITUTE($B8,InvPrefix,"")),0)) -> 4 | X8: =IF($D8="","",IF(OR($H8="",$H8="Credit"),0,Q8)) -> 12596.5
A9: 46122 | B9: INV-0005 | C9: FMCG Distributors | D9: Ceiling Fan 1200mm | E9: 3 | G9: 0.05 | I9: Delivered | J9: =IF($D9="","",IFERROR(INDEX(Items!$D$5:$D$504,U9),"")) -> Pcs | K9: =IF($D9="","",IF($F9="",IFERROR(INDEX(Items!$H$5:$H$504,U9),0),$F9)) -> 2322 | L9: =IF($D9="","",ROUND(N($E9)*K9*(1-N($G9)),2)) -> 6617.7 | M9: =IF($D9="","",IFERROR(INDEX(Items!$F$5:$F$504,U9),0)) -> 0.18 | N9: =IF($D9="","",IF(AND(V9<>"",INDEX(Parties!$E$5:$E$304,V9)<>"",INDEX(Parties!$E$5:$E$304,V9)<>HomeState),0,ROUND(L9*M9/2,2))) -> 595.59 | O9: =IF($D9="","",N9) -> 595.59 | P9: =IF($D9="","",IF(AND(V9<>"",INDEX(Parties!$E$5:$E$304,V9)<>"",INDEX(Parties!$E$5:$E$304,V9)<>HomeState),ROUND(L9*M9,2),0)) -> 0 | Q9: =IF($D9="","",L9+N9+O9+P9) -> 7808.88 | R9: =IF($D9="","",ROUND(N($E9)*IFERROR(INDEX(Items!$P$5:$P$504,U9),0),2)) -> 4931.4 | S9: =IF($D9="","",L9-R9) -> 1686.3 | T9: =IF($D9="","",IF(U9="","UNKNOWN ITEM",IF(INDEX(Items!$O$5:$O$504,U9)<0,"NEG STOCK",IF(K9<INDEX(Items!$P$5:$P$504,U9),"BELOW COST","OK")))) -> OK | U9: =IF($D9="","",IFERROR(MATCH($D9,Items!$A$5:$A$504,0),"")) -> 12 | V9: =IF($C9="","",IFERROR(MATCH($C9,Parties!$A$5:$A$304,0),"")) -> 9 | W9: =IF($B9="","",IFERROR(VALUE(SUBSTITUTE($B9,InvPrefix,"")),0)) -> 5 | X9: =IF($D9="","",IF(OR($H9="",$H9="Credit"),0,Q9)) -> 0
A10: 46122 | B10: INV-0005 | C10: FMCG Distributors | D10: Sugar 50kg | E10: 3 | G10: 0.05 | I10: Delivered | J10: =IF($D10="","",IFERROR(INDEX(Items!$D$5:$D$504,U10),"")) -> Bag | K10: =IF($D10="","",IF($F10="",IFERROR(INDEX(Items!$H$5:$H$504,U10),0),$F10)) -> 2462 | L10: =IF($D10="","",ROUND(N($E10)*K10*(1-N($G10)),2)) -> 7016.7 | M10: =IF($D10="","",IFERROR(INDEX(Items!$F$5:$F$504,U10),0)) -> 0.05 | N10: =IF($D10="","",IF(AND(V10<>"",INDEX(Parties!$E$5:$E$304,V10)<>"",INDEX(Parties!$E$5:$E$304,V10)<>HomeState),0,ROUND(L10*M10/2,2))) -> 175.42 | O10: =IF($D10="","",N10) -> 175.42 | P10: =IF($D10="","",IF(AND(V10<>"",INDEX(Parties!$E$5:$E$304,V10)<>"",INDEX(Parties!$E$5:$E$304,V10)<>HomeState),ROUND(L10*M10,2),0)) -> 0 | Q10: =IF($D10="","",L10+N10+O10+P10) -> 7367.54 | R10: =IF($D10="","",ROUND(N($E10)*IFERROR(INDEX(Items!$P$5:$P$504,U10),0),2)) -> 6113.19 | S10: =IF($D10="","",L10-R10) -> 903.51 | T10: =IF($D10="","",IF(U10="","UNKNOWN ITEM",IF(INDEX(Items!$O$5:$O$504,U10)<0,"NEG STOCK",IF(K10<INDEX(Items!$P$5:$P$504,U10),"BELOW COST","OK")))) -> OK | U10: =IF($D10="","",IFERROR(MATCH($D10,Items!$A$5:$A$504,0),"")) -> 2 | V10: =IF($C10="","",IFERROR(MATCH($C10,Parties!$A$5:$A$304,0),"")) -> 9 | W10: =IF($B10="","",IFERROR(VALUE(SUBSTITUTE($B10,InvPrefix,"")),0)) -> 5 | X10: =IF($D10="","",IF(OR($H10="",$H10="Credit"),0,Q10)) -> 0
A11: 46123 | B11: INV-0006 | C11: Mehta Constructions | D11: Sugar 50kg | E11: 5 | H11: Bank | I11: Delivered | J11: =IF($D11="","",IFERROR(INDEX(Items!$D$5:$D$504,U11),"")) -> Bag | K11: =IF($D11="","",IF($F11="",IFERROR(INDEX(Items!$H$5:$H$504,U11),0),$F11)) -> 2462 | L11: =IF($D11="","",ROUND(N($E11)*K11*(1-N($G11)),2)) -> 12310 | M11: =IF($D11="","",IFERROR(INDEX(Items!$F$5:$F$504,U11),0)) -> 0.05 | N11: =IF($D11="","",IF(AND(V11<>"",INDEX(Parties!$E$5:$E$304,V11)<>"",INDEX(Parties!$E$5:$E$304,V11)<>HomeState),0,ROUND(L11*M11/2,2))) -> 307.75 | O11: =IF($D11="","",N11) -> 307.75 | P11: =IF($D11="","",IF(AND(V11<>"",INDEX(Parties!$E$5:$E$304,V11)<>"",INDEX(Parties!$E$5:$E$304,V11)<>HomeState),ROUND(L11*M11,2),0)) -> 0 | Q11: =IF($D11="","",L11+N11+O11+P11) -> 12925.5 | R11: =IF($D11="","",ROUND(N($E11)*IFERROR(INDEX(Items!$P$5:$P$504,U11),0),2)) -> 10188.64 | S11: =IF($D11="","",L11-R11) -> 2121.36 | T11: =IF($D11="","",IF(U11="","UNKNOWN ITEM",IF(INDEX(Items!$O$5:$O$504,U11)<0,"NEG STOCK",IF(K11<INDEX(Items!$P$5:$P$504,U11),"BELOW COST","OK")))) -> OK | U11: =IF($D11="","",IFERROR(MATCH($D11,Items!$A$5:$A$504,0),"")) -> 2 | V11: =IF($C11="","",IFERROR(MATCH($C11,Parties!$A$5:$A$304,0),"")) -> 5 | W11: =IF($B11="","",IFERROR(VALUE(SUBSTITUTE($B11,InvPrefix,"")),0)) -> 6 | X11: =IF($D11="","",IF(OR($H11="",$H11="Credit"),0,Q11)) -> 12925.5
A12: 46125 | B12: INV-0007 | C12: Delhi Hardware Mart | D12: Basmati Rice 25kg | E12: 8 | H12: UPI | I12: Delivered | J12: =IF($D12="","",IFERROR(INDEX(Items!$D$5:$D$504,U12),"")) -> Bag | K12: =IF($D12="","",IF($F12="",IFERROR(INDEX(Items!$H$5:$H$504,U12),0),$F12)) -> 2106 | L12: =IF($D12="","",ROUND(N($E12)*K12*(1-N($G12)),2)) -> 16848 | M12: =IF($D12="","",IFERROR(INDEX(Items!$F$5:$F$504,U12),0)) -> 0.05 | N12: =IF($D12="","",IF(AND(V12<>"",INDEX(Parties!$E$5:$E$304,V12)<>"",INDEX(Parties!$E$5:$E$304,V12)<>HomeState),0,ROUND(L12*M12/2,2))) -> 0 | O12: =IF($D12="","",N12) -> 0 | P12: =IF($D12="","",IF(AND(V12<>"",INDEX(Parties!$E$5:$E$304,V12)<>"",INDEX(Parties!$E$5:$E$304,V12)<>HomeState),ROUND(L12*M12,2),0)) -> 842.4 | Q12: =IF($D12="","",L12+N12+O12+P12) -> 17690.4 | R12: =IF($D12="","",ROUND(N($E12)*IFERROR(INDEX(Items!$P$5:$P$504,U12),0),2)) -> 13179.44 | S12: =IF($D12="","",L12-R12) -> 3668.56 | T12: =IF($D12="","",IF(U12="","UNKNOWN ITEM",IF(INDEX(Items!$O$5:$O$504,U12)<0,"NEG STOCK",IF(K12<INDEX(Items!$P$5:$P$504,U12),"BELOW COST","OK")))) -> OK | U12: =IF($D12="","",IFERROR(MATCH($D12,Items!$A$5:$A$504,0),"")) -> 1 | V12: =IF($C12="","",IFERROR(MATCH($C12,Parties!$A$5:$A$304,0),"")) -> 3 | W12: =IF($B12="","",IFERROR(VALUE(SUBSTITUTE($B12,InvPrefix,"")),0)) -> 7 | X12: =IF($D12="","",IF(OR($H12="",$H12="Credit"),0,Q12)) -> 17690.4
A13: 46126 | B13: INV-0008 | C13: FMCG Distributors | D13: Copper Wire 90m | E13: 3 | I13: Delivered | J13: =IF($D13="","",IFERROR(INDEX(Items!$D$5:$D$504,U13),"")) -> Pcs | K13: =IF($D13="","",IF($F13="",IFERROR(INDEX(Items!$H$5:$H$504,U13),0),$F13)) -> 3132 | L13: =IF($D13="","",ROUND(N($E13)*K13*(1-N($G13)),2)) -> 9396 | M13: =IF($D13="","",IFERROR(INDEX(Items!$F$5:$F$504,U13),0)) -> 0.18 | N13: =IF($D13="","",IF(AND(V13<>"",INDEX(Parties!$E$5:$E$304,V13)<>"",INDEX(Parties!$E$5:$E$304,V13)<>HomeState),0,ROUND(L13*M13/2,2))) -> 845.64 | O13: =IF($D13="","",N13) -> 845.64 | P13: =IF($D13="","",IF(AND(V13<>"",INDEX(Parties!$E$5:$E$304,V13)<>"",INDEX(Parties!$E$5:$E$304,V13)<>HomeState),ROUND(L13*M13,2),0)) -> 0 | Q13: =IF($D13="","",L13+N13+O13+P13) -> 11087.28 | R13: =IF($D13="","",ROUND(N($E13)*IFERROR(INDEX(Items!$P$5:$P$504,U13),0),2)) -> 7354.45 | S13: =IF($D13="","",L13-R13) -> 2041.55 | T13: =IF($D13="","",IF(U13="","UNKNOWN ITEM",IF(INDEX(Items!$O$5:$O$504,U13)<0,"NEG STOCK",IF(K13<INDEX(Items!$P$5:$P$504,U13),"BELOW COST","OK")))) -> OK | U13: =IF($D13="","",IFERROR(MATCH($D13,Items!$A$5:$A$504,0),"")) -> 8 | V13: =IF($C13="","",IFERROR(MATCH($C13,Parties!$A$5:$A$304,0),"")) -> 9 | W13: =IF($B13="","",IFERROR(VALUE(SUBSTITUTE($B13,InvPrefix,"")),0)) -> 8 | X13: =IF($D13="","",IF(OR($H13="",$H13="Credit"),0,Q13)) -> 0
A14: 46126 | B14: INV-0008 | C14: FMCG Distributors | D14: Cement 50kg | E14: 40 | I14: Delivered | J14: =IF($D14="","",IFERROR(INDEX(Items!$D$5:$D$504,U14),"")) -> Bag | K14: =IF($D14="","",IF($F14="",IFERROR(INDEX(Items!$H$5:$H$504,U14),0),$F14)) -> 427 | L14: =IF($D14="","",ROUND(N($E14)*K14*(1-N($G14)),2)) -> 17080 | M14: =IF($D14="","",IFERROR(INDEX(Items!$F$5:$F$504,U14),0)) -> 0.18 | N14: =IF($D14="","",IF(AND(V14<>"",INDEX(Parties!$E$5:$E$304,V14)<>"",INDEX(Parties!$E$5:$E$304,V14)<>HomeState),0,ROUND(L14*M14/2,2))) -> 1537.2 | O14: =IF($D14="","",N14) -> 1537.2 | P14: =IF($D14="","",IF(AND(V14<>"",INDEX(Parties!$E$5:$E$304,V14)<>"",INDEX(Parties!$E$5:$E$304,V14)<>HomeState),ROUND(L14*M14,2),0)) -> 0 | Q14: =IF($D14="","",L14+N14+O14+P14) -> 20154.4 | R14: =IF($D14="","",ROUND(N($E14)*IFERROR(INDEX(Items!$P$5:$P$504,U14),0),2)) -> 13606.97 | S14: =IF($D14="","",L14-R14) -> 3473.03 | T14: =IF($D14="","",IF(U14="","UNKNOWN ITEM",IF(INDEX(Items!$O$5:$O$504,U14)<0,"NEG STOCK",IF(K14<INDEX(Items!$P$5:$P$504,U14),"BELOW COST","OK")))) -> OK | U14: =IF($D14="","",IFERROR(MATCH($D14,Items!$A$5:$A$504,0),"")) -> 10 | V14: =IF($C14="","",IFERROR(MATCH($C14,Parties!$A$5:$A$304,0),"")) -> 9 | W14: =IF($B14="","",IFERROR(VALUE(SUBSTITUTE($B14,InvPrefix,"")),0)) -> 8 | X14: =IF($D14="","",IF(OR($H14="",$H14="Credit"),0,Q14)) -> 0
A15: 46127 | B15: INV-0009 | C15: Gupta Electricals | D15: Ceiling Fan 1200mm | E15: 3 | G15: 0.02 | I15: Delivered | J15: =IF($D15="","",IFERROR(INDEX(Items!$D$5:$D$504,U15),"")) -> Pcs | K15: =IF($D15="","",IF($F15="",IFERROR(INDEX(Items!$H$5:$H$504,U15),0),$F15)) -> 2322 | L15: =IF($D15="","",ROUND(N($E15)*K15*(1-N($G15)),2)) -> 6826.68 | M15: =IF($D15="","",IFERROR(INDEX(Items!$F$5:$F$504,U15),0)) -> 0.18 | N15: =IF($D15="","",IF(AND(V15<>"",INDEX(Parties!$E$5:$E$304,V15)<>"",INDEX(Parties!$E$5:$E$304,V15)<>HomeState),0,ROUND(L15*M15/2,2))) -> 614.4 | O15: =IF($D15="","",N15) -> 614.4 | P15: =IF($D15="","",IF(AND(V15<>"",INDEX(Parties!$E$5:$E$304,V15)<>"",INDEX(Parties!$E$5:$E$304,V15)<>HomeState),ROUND(L15*M15,2),0)) -> 0 | Q15: =IF($D15="","",L15+N15+O15+P15) -> 8055.48 | R15: =IF($D15="","",ROUND(N($E15)*IFERROR(INDEX(Items!$P$5:$P$504,U15),0),2)) -> 4931.4 | S15: =IF($D15="","",L15-R15) -> 1895.28 | T15: =IF($D15="","",IF(U15="","UNKNOWN ITEM",IF(INDEX(Items!$O$5:$O$504,U15)<0,"NEG STOCK",IF(K15<INDEX(Items!$P$5:$P$504,U15),"BELOW COST","OK")))) -> OK | U15: =IF($D15="","",IFERROR(MATCH($D15,Items!$A$5:$A$504,0),"")) -> 12 | V15: =IF($C15="","",IFERROR(MATCH($C15,Parties!$A$5:$A$304,0),"")) -> 2 | W15: =IF($B15="","",IFERROR(VALUE(SUBSTITUTE($B15,InvPrefix,"")),0)) -> 9 | X15: =IF($D15="","",IF(OR($H15="",$H15="Credit"),0,Q15)) -> 0
A16: 46127 | B16: INV-0009 | C16: Gupta Electricals | D16: Detergent 5kg | E16: 7 | G16: 0.02 | I16: Delivered | J16: =IF($D16="","",IFERROR(INDEX(Items!$D$5:$D$504,U16),"")) -> Pack | K16: =IF($D16="","",IF($F16="",IFERROR(INDEX(Items!$H$5:$H$504,U16),0),$F16)) -> 691 | L16: =IF($D16="","",ROUND(N($E16)*K16*(1-N($G16)),2)) -> 4740.26 | M16: =IF($D16="","",IFERROR(INDEX(Items!$F$5:$F$504,U16),0)) -> 0.18 | N16: =IF($D16="","",IF(AND(V16<>"",INDEX(Parties!$E$5:$E$304,V16)<>"",INDEX(Parties!$E$5:$E$304,V16)<>HomeState),0,ROUND(L16*M16/2,2))) -> 426.62 | O16: =IF($D16="","",N16) -> 426.62 | P16: =IF($D16="","",IF(AND(V16<>"",INDEX(Parties!$E$5:$E$304,V16)<>"",INDEX(Parties!$E$5:$E$304,V16)<>HomeState),ROUND(L16*M16,2),0)) -> 0 | Q16: =IF($D16="","",L16+N16+O16+P16) -> 5593.5 | R16: =IF($D16="","",ROUND(N($E16)*IFERROR(INDEX(Items!$P$5:$P$504,U16),0),2)) -> 3623.85 | S16: =IF($D16="","",L16-R16) -> 1116.41 | T16: =IF($D16="","",IF(U16="","UNKNOWN ITEM",IF(INDEX(Items!$O$5:$O$504,U16)<0,"NEG STOCK",IF(K16<INDEX(Items!$P$5:$P$504,U16),"BELOW COST","OK")))) -> OK | U16: =IF($D16="","",IFERROR(MATCH($D16,Items!$A$5:$A$504,0),"")) -> 5 | V16: =IF($C16="","",IFERROR(MATCH($C16,Parties!$A$5:$A$304,0),"")) -> 2 | W16: =IF($B16="","",IFERROR(VALUE(SUBSTITUTE($B16,InvPrefix,"")),0)) -> 9 | X16: =IF($D16="","",IF(OR($H16="",$H16="Credit"),0,Q16)) -> 0
A17: 46128 | B17: INV-0010 | C17: Sharma Kirana Store | D17: Refined Oil 15L | E17: 6 | G17: 0.02 | H17: UPI | I17: Delivered | J17: =IF($D17="","",IFERROR(INDEX(Items!$D$5:$D$504,U17),"")) -> Box | K17: =IF($D17="","",IF($F17="",IFERROR(INDEX(Items!$H$5:$H$504,U17),0),$F17)) -> 2290 | L17: =IF($D17="","",ROUND(N($E17)*K17*(1-N($G17)),2)) -> 13465.2 | M17: =IF($D17="","",IFERROR(INDEX(Items!$F$5:$F$504,U17),0)) -> 0.05 | N17: =IF($D17="","",IF(AND(V17<>"",INDEX(Parties!$E$5:$E$304,V17)<>"",INDEX(Parties!$E$5:$E$304,V17)<>HomeState),0,ROUND(L17*M17/2,2))) -> 336.63 | O17: =IF($D17="","",N17) -> 336.63 | P17: =IF($D17="","",IF(AND(V17<>"",INDEX(Parties!$E$5:$E$304,V17)<>"",INDEX(Parties!$E$5:$E$304,V17)<>HomeState),ROUND(L17*M17,2),0)) -> 0 | Q17: =IF($D17="","",L17+N17+O17+P17) -> 14138.46 | R17: =IF($D17="","",ROUND(N($E17)*IFERROR(INDEX(Items!$P$5:$P$504,U17),0),2)) -> 11426.18 | S17: =IF($D17="","",L17-R17) -> 2039.02 | T17: =IF($D17="","",IF(U17="","UNKNOWN ITEM",IF(INDEX(Items!$O$5:$O$504,U17)<0,"NEG STOCK",IF(K17<INDEX(Items!$P$5:$P$504,U17),"BELOW COST","OK")))) -> OK | U17: =IF($D17="","",IFERROR(MATCH($D17,Items!$A$5:$A$504,0),"")) -> 3 | V17: =IF($C17="","",IFERROR(MATCH($C17,Parties!$A$5:$A$304,0),"")) -> 1 | W17: =IF($B17="","",IFERROR(VALUE(SUBSTITUTE($B17,InvPrefix,"")),0)) -> 10 | X17: =IF($D17="","",IF(OR($H17="",$H17="Credit"),0,Q17)) -> 14138.46
A18: 46130 | B18: INV-0011 | C18: Mehta Constructions | D18: Tea Premium 1kg | E18: 11 | G18: 0.02 | I18: Delivered | J18: =IF($D18="","",IFERROR(INDEX(Items!$D$5:$D$504,U18),"")) -> Pack | K18: =IF($D18="","",IF($F18="",IFERROR(INDEX(Items!$H$5:$H$504,U18),0),$F18)) -> 508 | L18: =IF($D18="","",ROUND(N($E18)*K18*(1-N($G18)),2)) -> 5476.24 | M18: =IF($D18="","",IFERROR(INDEX(Items!$F$5:$F$504,U18),0)) -> 0.05 | N18: =IF($D18="","",IF(AND(V18<>"",INDEX(Parties!$E$5:$E$304,V18)<>"",INDEX(Parties!$E$5:$E$304,V18)<>HomeState),0,ROUND(L18*M18/2,2))) -> 136.91 | O18: =IF($D18="","",N18) -> 136.91 | P18: =IF($D18="","",IF(AND(V18<>"",INDEX(Parties!$E$5:$E$304,V18)<>"",INDEX(Parties!$E$5:$E$304,V18)<>HomeState),ROUND(L18*M18,2),0)) -> 0 | Q18: =IF($D18="","",L18+N18+O18+P18) -> 5750.06 | R18: =IF($D18="","",ROUND(N($E18)*IFERROR(INDEX(Items!$P$5:$P$504,U18),0),2)) -> 4147.87 | S18: =IF($D18="","",L18-R18) -> 1328.37 | T18: =IF($D18="","",IF(U18="","UNKNOWN ITEM",IF(INDEX(Items!$O$5:$O$504,U18)<0,"NEG STOCK",IF(K18<INDEX(Items!$P$5:$P$504,U18),"BELOW COST","OK")))) -> OK | U18: =IF($D18="","",IFERROR(MATCH($D18,Items!$A$5:$A$504,0),"")) -> 4 | V18: =IF($C18="","",IFERROR(MATCH($C18,Parties!$A$5:$A$304,0),"")) -> 5 | W18: =IF($B18="","",IFERROR(VALUE(SUBSTITUTE($B18,InvPrefix,"")),0)) -> 11 | X18: =IF($D18="","",IF(OR($H18="",$H18="Credit"),0,Q18)) -> 0
A19: 46130 | B19: INV-0011 | C19: Mehta Constructions | D19: LED Bulb 9W | E19: 39 | G19: 0.02 | I19: Delivered | J19: =IF($D19="","",IFERROR(INDEX(Items!$D$5:$D$504,U19),"")) -> Pcs | K19: =IF($D19="","",IF($F19="",IFERROR(INDEX(Items!$H$5:$H$504,U19),0),$F19)) -> 107 | L19: =IF($D19="","",ROUND(N($E19)*K19*(1-N($G19)),2)) -> 4089.54 | M19: =IF($D19="","",IFERROR(INDEX(Items!$F$5:$F$504,U19),0)) -> 0.18 | N19: =IF($D19="","",IF(AND(V19<>"",INDEX(Parties!$E$5:$E$304,V19)<>"",INDEX(Parties!$E$5:$E$304,V19)<>HomeState),0,ROUND(L19*M19/2,2))) -> 368.06 | O19: =IF($D19="","",N19) -> 368.06 | P19: =IF($D19="","",IF(AND(V19<>"",INDEX(Parties!$E$5:$E$304,V19)<>"",INDEX(Parties!$E$5:$E$304,V19)<>HomeState),ROUND(L19*M19,2),0)) -> 0 | Q19: =IF($D19="","",L19+N19+O19+P19) -> 4825.66 | R19: =IF($D19="","",ROUND(N($E19)*IFERROR(INDEX(Items!$P$5:$P$504,U19),0),2)) -> 2395.27 | S19: =IF($D19="","",L19-R19) -> 1694.27 | T19: =IF($D19="","",IF(U19="","UNKNOWN ITEM",IF(INDEX(Items!$O$5:$O$504,U19)<0,"NEG STOCK",IF(K19<INDEX(Items!$P$5:$P$504,U19),"BELOW COST","OK")))) -> OK | U19: =IF($D19="","",IFERROR(MATCH($D19,Items!$A$5:$A$504,0),"")) -> 7 | V19: =IF($C19="","",IFERROR(MATCH($C19,Parties!$A$5:$A$304,0),"")) -> 5 | W19: =IF($B19="","",IFERROR(VALUE(SUBSTITUTE($B19,InvPrefix,"")),0)) -> 11 | X19: =IF($D19="","",IF(OR($H19="",$H19="Credit"),0,Q19)) -> 0
A20: 46132 | B20: INV-0012 | C20: Mehta Constructions | D20: PVC Pipe 1in 6m | E20: 20 | G20: 0.02 | I20: Delivered | J20: =IF($D20="","",IFERROR(INDEX(Items!$D$5:$D$504,U20),"")) -> Pcs | K20: =IF($D20="","",IF($F20="",IFERROR(INDEX(Items!$H$5:$H$504,U20),0),$F20)) -> 297 | L20: =IF($D20="","",ROUND(N($E20)*K20*(1-N($G20)),2)) -> 5821.2 | M20: =IF($D20="","",IFERROR(INDEX(Items!$F$5:$F$504,U20),0)) -> 0.18 | N20: =IF($D20="","",IF(AND(V20<>"",INDEX(Parties!$E$5:$E$304,V20)<>"",INDEX(Parties!$E$5:$E$304,V20)<>HomeState),0,ROUND(L20*M20/2,2))) -> 523.91 | O20: =IF($D20="","",N20) -> 523.91 | P20: =IF($D20="","",IF(AND(V20<>"",INDEX(Parties!$E$5:$E$304,V20)<>"",INDEX(Parties!$E$5:$E$304,V20)<>HomeState),ROUND(L20*M20,2),0)) -> 0 | Q20: =IF($D20="","",L20+N20+O20+P20) -> 6869.02 | R20: =IF($D20="","",ROUND(N($E20)*IFERROR(INDEX(Items!$P$5:$P$504,U20),0),2)) -> 4192.67 | S20: =IF($D20="","",L20-R20) -> 1628.53 | T20: =IF($D20="","",IF(U20="","UNKNOWN ITEM",IF(INDEX(Items!$O$5:$O$504,U20)<0,"NEG STOCK",IF(K20<INDEX(Items!$P$5:$P$504,U20),"BELOW COST","OK")))) -> OK | U20: =IF($D20="","",IFERROR(MATCH($D20,Items!$A$5:$A$504,0),"")) -> 9 | V20: =IF($C20="","",IFERROR(MATCH($C20,Parties!$A$5:$A$304,0),"")) -> 5 | W20: =IF($B20="","",IFERROR(VALUE(SUBSTITUTE($B20,InvPrefix,"")),0)) -> 12 | X20: =IF($D20="","",IF(OR($H20="",$H20="Credit"),0,Q20)) -> 0
A21: 46133 | B21: INV-0013 | C21: Walk-in Customer | D21: Refined Oil 15L | E21: 3 | H21: Cash | I21: Delivered | J21: =IF($D21="","",IFERROR(INDEX(Items!$D$5:$D$504,U21),"")) -> Box | K21: =IF($D21="","",IF($F21="",IFERROR(INDEX(Items!$H$5:$H$504,U21),0),$F21)) -> 2290 | L21: =IF($D21="","",ROUND(N($E21)*K21*(1-N($G21)),2)) -> 6870 | M21: =IF($D21="","",IFERROR(INDEX(Items!$F$5:$F$504,U21),0)) -> 0.05 | N21: =IF($D21="","",IF(AND(V21<>"",INDEX(Parties!$E$5:$E$304,V21)<>"",INDEX(Parties!$E$5:$E$304,V21)<>HomeState),0,ROUND(L21*M21/2,2))) -> 171.75 | O21: =IF($D21="","",N21) -> 171.75 | P21: =IF($D21="","",IF(AND(V21<>"",INDEX(Parties!$E$5:$E$304,V21)<>"",INDEX(Parties!$E$5:$E$304,V21)<>HomeState),ROUND(L21*M21,2),0)) -> 0 | Q21: =IF($D21="","",L21+N21+O21+P21) -> 7213.5 | R21: =IF($D21="","",ROUND(N($E21)*IFERROR(INDEX(Items!$P$5:$P$504,U21),0),2)) -> 5713.09 | S21: =IF($D21="","",L21-R21) -> 1156.91 | T21: =IF($D21="","",IF(U21="","UNKNOWN ITEM",IF(INDEX(Items!$O$5:$O$504,U21)<0,"NEG STOCK",IF(K21<INDEX(Items!$P$5:$P$504,U21),"BELOW COST","OK")))) -> OK | U21: =IF($D21="","",IFERROR(MATCH($D21,Items!$A$5:$A$504,0),"")) -> 3 | V21: =IF($C21="","",IFERROR(MATCH($C21,Parties!$A$5:$A$304,0),"")) -> 4 | W21: =IF($B21="","",IFERROR(VALUE(SUBSTITUTE($B21,InvPrefix,"")),0)) -> 13 | X21: =IF($D21="","",IF(OR($H21="",$H21="Credit"),0,Q21)) -> 7213.5
A22: 46134 | B22: INV-0014 | C22: Walk-in Customer | D22: Copper Wire 90m | E22: 4 | H22: Cash | I22: Delivered | J22: =IF($D22="","",IFERROR(INDEX(Items!$D$5:$D$504,U22),"")) -> Pcs | K22: =IF($D22="","",IF($F22="",IFERROR(INDEX(Items!$H$5:$H$504,U22),0),$F22)) -> 3132 | L22: =IF($D22="","",ROUND(N($E22)*K22*(1-N($G22)),2)) -> 12528 | M22: =IF($D22="","",IFERROR(INDEX(Items!$F$5:$F$504,U22),0)) -> 0.18 | N22: =IF($D22="","",IF(AND(V22<>"",INDEX(Parties!$E$5:$E$304,V22)<>"",INDEX(Parties!$E$5:$E$304,V22)<>HomeState),0,ROUND(L22*M22/2,2))) -> 1127.52 | O22: =IF($D22="","",N22) -> 1127.52 | P22: =IF($D22="","",IF(AND(V22<>"",INDEX(Parties!$E$5:$E$304,V22)<>"",INDEX(Parties!$E$5:$E$304,V22)<>HomeState),ROUND(L22*M22,2),0)) -> 0 | Q22: =IF($D22="","",L22+N22+O22+P22) -> 14783.04 | R22: =IF($D22="","",ROUND(N($E22)*IFERROR(INDEX(Items!$P$5:$P$504,U22),0),2)) -> 9805.93 | S22: =IF($D22="","",L22-R22) -> 2722.07 | T22: =IF($D22="","",IF(U22="","UNKNOWN ITEM",IF(INDEX(Items!$O$5:$O$504,U22)<0,"NEG STOCK",IF(K22<INDEX(Items!$P$5:$P$504,U22),"BELOW COST","OK")))) -> OK | U22: =IF($D22="","",IFERROR(MATCH($D22,Items!$A$5:$A$504,0),"")) -> 8 | V22: =IF($C22="","",IFERROR(MATCH($C22,Parties!$A$5:$A$304,0),"")) -> 4 | W22: =IF($B22="","",IFERROR(VALUE(SUBSTITUTE($B22,InvPrefix,"")),0)) -> 14 | X22: =IF($D22="","",IF(OR($H22="",$H22="Credit"),0,Q22)) -> 14783.04
A23: 46135 | B23: INV-0015 | C23: Mehta Constructions | D23: LED Bulb 9W | E23: 64 | G23: 0.05 | I23: Delivered | J23: =IF($D23="","",IFERROR(INDEX(Items!$D$5:$D$504,U23),"")) -> Pcs | K23: =IF($D23="","",IF($F23="",IFERROR(INDEX(Items!$H$5:$H$504,U23),0),$F23)) -> 107 | L23: =IF($D23="","",ROUND(N($E23)*K23*(1-N($G23)),2)) -> 6505.6 | M23: =IF($D23="","",IFERROR(INDEX(Items!$F$5:$F$504,U23),0)) -> 0.18 | N23: =IF($D23="","",IF(AND(V23<>"",INDEX(Parties!$E$5:$E$304,V23)<>"",INDEX(Parties!$E$5:$E$304,V23)<>HomeState),0,ROUND(L23*M23/2,2))) -> 585.5 | O23: =IF($D23="","",N23) -> 585.5 | P23: =IF($D23="","",IF(AND(V23<>"",INDEX(Parties!$E$5:$E$304,V23)<>"",INDEX(Parties!$E$5:$E$304,V23)<>HomeState),ROUND(L23*M23,2),0)) -> 0 | Q23: =IF($D23="","",L23+N23+O23+P23) -> 7676.6 | R23: =IF($D23="","",ROUND(N($E23)*IFERROR(INDEX(Items!$P$5:$P$504,U23),0),2)) -> 3930.69 | S23: =IF($D23="","",L23-R23) -> 2574.91 | T23: =IF($D23="","",IF(U23="","UNKNOWN ITEM",IF(INDEX(Items!$O$5:$O$504,U23)<0,"NEG STOCK",IF(K23<INDEX(Items!$P$5:$P$504,U23),"BELOW COST","OK")))) -> OK | U23: =IF($D23="","",IFERROR(MATCH($D23,Items!$A$5:$A$504,0),"")) -> 7 | V23: =IF($C23="","",IFERROR(MATCH($C23,Parties!$A$5:$A$304,0),"")) -> 5 | W23: =IF($B23="","",IFERROR(VALUE(SUBSTITUTE($B23,InvPrefix,"")),0)) -> 15 | X23: =IF($D23="","",IF(OR($H23="",$H23="Credit"),0,Q23)) -> 0
A24: 46136 | B24: INV-0016 | C24: Delhi Hardware Mart | D24: A4 Paper Ream | E24: 22 | G24: 0.02 | H24: Bank | I24: Delivered | J24: =IF($D24="","",IFERROR(INDEX(Items!$D$5:$D$504,U24),"")) -> Pack | K24: =IF($D24="","",IF($F24="",IFERROR(INDEX(Items!$H$5:$H$504,U24),0),$F24)) -> 335 | L24: =IF($D24="","",ROUND(N($E24)*K24*(1-N($G24)),2)) -> 7222.6 | M24: =IF($D24="","",IFERROR(INDEX(Items!$F$5:$F$504,U24),0)) -> 0.12 | N24: =IF($D24="","",IF(AND(V24<>"",INDEX(Parties!$E$5:$E$304,V24)<>"",INDEX(Parties!$E$5:$E$304,V24)<>HomeState),0,ROUND(L24*M24/2,2))) -> 0 | O24: =IF($D24="","",N24) -> 0 | P24: =IF($D24="","",IF(AND(V24<>"",INDEX(Parties!$E$5:$E$304,V24)<>"",INDEX(Parties!$E$5:$E$304,V24)<>HomeState),ROUND(L24*M24,2),0)) -> 866.71 | Q24: =IF($D24="","",L24+N24+O24+P24) -> 8089.31 | R24: =IF($D24="","",ROUND(N($E24)*IFERROR(INDEX(Items!$P$5:$P$504,U24),0),2)) -> 5280 | S24: =IF($D24="","",L24-R24) -> 1942.6 | T24: =IF($D24="","",IF(U24="","UNKNOWN ITEM",IF(INDEX(Items!$O$5:$O$504,U24)<0,"NEG STOCK",IF(K24<INDEX(Items!$P$5:$P$504,U24),"BELOW COST","OK")))) -> OK | U24: =IF($D24="","",IFERROR(MATCH($D24,Items!$A$5:$A$504,0),"")) -> 11 | V24: =IF($C24="","",IFERROR(MATCH($C24,Parties!$A$5:$A$304,0),"")) -> 3 | W24: =IF($B24="","",IFERROR(VALUE(SUBSTITUTE($B24,InvPrefix,"")),0)) -> 16 | X24: =IF($D24="","",IF(OR($H24="",$H24="Credit"),0,Q24)) -> 8089.31
A25: 46136 | B25: INV-0016 | C25: Delhi Hardware Mart | D25: Ceiling Fan 1200mm | E25: 4 | G25: 0.05 | H25: Bank | I25: Delivered | J25: =IF($D25="","",IFERROR(INDEX(Items!$D$5:$D$504,U25),"")) -> Pcs | K25: =IF($D25="","",IF($F25="",IFERROR(INDEX(Items!$H$5:$H$504,U25),0),$F25)) -> 2322 | L25: =IF($D25="","",ROUND(N($E25)*K25*(1-N($G25)),2)) -> 8823.6 | M25: =IF($D25="","",IFERROR(INDEX(Items!$F$5:$F$504,U25),0)) -> 0.18 | N25: =IF($D25="","",IF(AND(V25<>"",INDEX(Parties!$E$5:$E$304,V25)<>"",INDEX(Parties!$E$5:$E$304,V25)<>HomeState),0,ROUND(L25*M25/2,2))) -> 0 | O25: =IF($D25="","",N25) -> 0 | P25: =IF($D25="","",IF(AND(V25<>"",INDEX(Parties!$E$5:$E$304,V25)<>"",INDEX(Parties!$E$5:$E$304,V25)<>HomeState),ROUND(L25*M25,2),0)) -> 1588.25 | Q25: =IF($D25="","",L25+N25+O25+P25) -> 10411.85 | R25: =IF($D25="","",ROUND(N($E25)*IFERROR(INDEX(Items!$P$5:$P$504,U25),0),2)) -> 6575.2 | S25: =IF($D25="","",L25-R25) -> 2248.4 | T25: =IF($D25="","",IF(U25="","UNKNOWN ITEM",IF(INDEX(Items!$O$5:$O$504,U25)<0,"NEG STOCK",IF(K25<INDEX(Items!$P$5:$P$504,U25),"BELOW COST","OK")))) -> OK | U25: =IF($D25="","",IFERROR(MATCH($D25,Items!$A$5:$A$504,0),"")) -> 12 | V25: =IF($C25="","",IFERROR(MATCH($C25,Parties!$A$5:$A$304,0),"")) -> 3 | W25: =IF($B25="","",IFERROR(VALUE(SUBSTITUTE($B25,InvPrefix,"")),0)) -> 16 | X25: =IF($D25="","",IF(OR($H25="",$H25="Credit"),0,Q25)) -> 10411.85
A26: 46137 | B26: INV-0017 | C26: Walk-in Customer | D26: LED Bulb 9W | E26: 40 | G26: 0.02 | H26: Cash | I26: Delivered | J26: =IF($D26="","",IFERROR(INDEX(Items!$D$5:$D$504,U26),"")) -> Pcs | K26: =IF($D26="","",IF($F26="",IFERROR(INDEX(Items!$H$5:$H$504,U26),0),$F26)) -> 107 | L26: =IF($D26="","",ROUND(N($E26)*K26*(1-N($G26)),2)) -> 4194.4 | M26: =IF($D26="","",IFERROR(INDEX(Items!$F$5:$F$504,U26),0)) -> 0.18 | N26: =IF($D26="","",IF(AND(V26<>"",INDEX(Parties!$E$5:$E$304,V26)<>"",INDEX(Parties!$E$5:$E$304,V26)<>HomeState),0,ROUND(L26*M26/2,2))) -> 377.5 | O26: =IF($D26="","",N26) -> 377.5 | P26: =IF($D26="","",IF(AND(V26<>"",INDEX(Parties!$E$5:$E$304,V26)<>"",INDEX(Parties!$E$5:$E$304,V26)<>HomeState),ROUND(L26*M26,2),0)) -> 0 | Q26: =IF($D26="","",L26+N26+O26+P26) -> 4949.4 | R26: =IF($D26="","",ROUND(N($E26)*IFERROR(INDEX(Items!$P$5:$P$504,U26),0),2)) -> 2456.68 | S26: =IF($D26="","",L26-R26) -> 1737.72 | T26: =IF($D26="","",IF(U26="","UNKNOWN ITEM",IF(INDEX(Items!$O$5:$O$504,U26)<0,"NEG STOCK",IF(K26<INDEX(Items!$P$5:$P$504,U26),"BELOW COST","OK")))) -> OK | U26: =IF($D26="","",IFERROR(MATCH($D26,Items!$A$5:$A$504,0),"")) -> 7 | V26: =IF($C26="","",IFERROR(MATCH($C26,Parties!$A$5:$A$304,0),"")) -> 4 | W26: =IF($B26="","",IFERROR(VALUE(SUBSTITUTE($B26,InvPrefix,"")),0)) -> 17 | X26: =IF($D26="","",IF(OR($H26="",$H26="Credit"),0,Q26)) -> 4949.4
A27: 46140 | B27: INV-0018 | C27: Gupta Electricals | D27: Refined Oil 15L | E27: 4 | G27: 0.05 | I27: Delivered | J27: =IF($D27="","",IFERROR(INDEX(Items!$D$5:$D$504,U27),"")) -> Box | K27: =IF($D27="","",IF($F27="",IFERROR(INDEX(Items!$H$5:$H$504,U27),0),$F27)) -> 2290 | L27: =IF($D27="","",ROUND(N($E27)*K27*(1-N($G27)),2)) -> 8702 | M27: =IF($D27="","",IFERROR(INDEX(Items!$F$5:$F$504,U27),0)) -> 0.05 | N27: =IF($D27="","",IF(AND(V27<>"",INDEX(Parties!$E$5:$E$304,V27)<>"",INDEX(Parties!$E$5:$E$304,V27)<>HomeState),0,ROUND(L27*M27/2,2))) -> 217.55 | O27: =IF($D27="","",N27) -> 217.55 | P27: =IF($D27="","",IF(AND(V27<>"",INDEX(Parties!$E$5:$E$304,V27)<>"",INDEX(Parties!$E$5:$E$304,V27)<>HomeState),ROUND(L27*M27,2),0)) -> 0 | Q27: =IF($D27="","",L27+N27+O27+P27) -> 9137.1 | R27: =IF($D27="","",ROUND(N($E27)*IFERROR(INDEX(Items!$P$5:$P$504,U27),0),2)) -> 7617.45 | S27: =IF($D27="","",L27-R27) -> 1084.55 | T27: =IF($D27="","",IF(U27="","UNKNOWN ITEM",IF(INDEX(Items!$O$5:$O$504,U27)<0,"NEG STOCK",IF(K27<INDEX(Items!$P$5:$P$504,U27),"BELOW COST","OK")))) -> OK | U27: =IF($D27="","",IFERROR(MATCH($D27,Items!$A$5:$A$504,0),"")) -> 3 | V27: =IF($C27="","",IFERROR(MATCH($C27,Parties!$A$5:$A$304,0),"")) -> 2 | W27: =IF($B27="","",IFERROR(VALUE(SUBSTITUTE($B27,InvPrefix,"")),0)) -> 18 | X27: =IF($D27="","",IF(OR($H27="",$H27="Credit"),0,Q27)) -> 0
A28: 46143 | B28: INV-0019 | C28: Gupta Electricals | D28: Copper Wire 90m | E28: 3 | I28: Delivered | J28: =IF($D28="","",IFERROR(INDEX(Items!$D$5:$D$504,U28),"")) -> Pcs | K28: =IF($D28="","",IF($F28="",IFERROR(INDEX(Items!$H$5:$H$504,U28),0),$F28)) -> 3132 | L28: =IF($D28="","",ROUND(N($E28)*K28*(1-N($G28)),2)) -> 9396 | M28: =IF($D28="","",IFERROR(INDEX(Items!$F$5:$F$504,U28),0)) -> 0.18 | N28: =IF($D28="","",IF(AND(V28<>"",INDEX(Parties!$E$5:$E$304,V28)<>"",INDEX(Parties!$E$5:$E$304,V28)<>HomeState),0,ROUND(L28*M28/2,2))) -> 845.64 | O28: =IF($D28="","",N28) -> 845.64 | P28: =IF($D28="","",IF(AND(V28<>"",INDEX(Parties!$E$5:$E$304,V28)<>"",INDEX(Parties!$E$5:$E$304,V28)<>HomeState),ROUND(L28*M28,2),0)) -> 0 | Q28: =IF($D28="","",L28+N28+O28+P28) -> 11087.28 | R28: =IF($D28="","",ROUND(N($E28)*IFERROR(INDEX(Items!$P$5:$P$504,U28),0),2)) -> 7354.45 | S28: =IF($D28="","",L28-R28) -> 2041.55 | T28: =IF($D28="","",IF(U28="","UNKNOWN ITEM",IF(INDEX(Items!$O$5:$O$504,U28)<0,"NEG STOCK",IF(K28<INDEX(Items!$P$5:$P$504,U28),"BELOW COST","OK")))) -> OK | U28: =IF($D28="","",IFERROR(MATCH($D28,Items!$A$5:$A$504,0),"")) -> 8 | V28: =IF($C28="","",IFERROR(MATCH($C28,Parties!$A$5:$A$304,0),"")) -> 2 | W28: =IF($B28="","",IFERROR(VALUE(SUBSTITUTE($B28,InvPrefix,"")),0)) -> 19 | X28: =IF($D28="","",IF(OR($H28="",$H28="Credit"),0,Q28)) -> 0
A29: 46146 | B29: INV-0020 | C29: Gupta Electricals | D29: Detergent 5kg | E29: 12 | I29: Delivered | J29: =IF($D29="","",IFERROR(INDEX(Items!$D$5:$D$504,U29),"")) -> Pack | K29: =IF($D29="","",IF($F29="",IFERROR(INDEX(Items!$H$5:$H$504,U29),0),$F29)) -> 691 | L29: =IF($D29="","",ROUND(N($E29)*K29*(1-N($G29)),2)) -> 8292 | M29: =IF($D29="","",IFERROR(INDEX(Items!$F$5:$F$504,U29),0)) -> 0.18 | N29: =IF($D29="","",IF(AND(V29<>"",INDEX(Parties!$E$5:$E$304,V29)<>"",INDEX(Parties!$E$5:$E$304,V29)<>HomeState),0,ROUND(L29*M29/2,2))) -> 746.28 | O29: =IF($D29="","",N29) -> 746.28 | P29: =IF($D29="","",IF(AND(V29<>"",INDEX(Parties!$E$5:$E$304,V29)<>"",INDEX(Parties!$E$5:$E$304,V29)<>HomeState),ROUND(L29*M29,2),0)) -> 0 | Q29: =IF($D29="","",L29+N29+O29+P29) -> 9784.56 | R29: =IF($D29="","",ROUND(N($E29)*IFERROR(INDEX(Items!$P$5:$P$504,U29),0),2)) -> 6212.31 | S29: =IF($D29="","",L29-R29) -> 2079.69 | T29: =IF($D29="","",IF(U29="","UNKNOWN ITEM",IF(INDEX(Items!$O$5:$O$504,U29)<0,"NEG STOCK",IF(K29<INDEX(Items!$P$5:$P$504,U29),"BELOW COST","OK")))) -> OK | U29: =IF($D29="","",IFERROR(MATCH($D29,Items!$A$5:$A$504,0),"")) -> 5 | V29: =IF($C29="","",IFERROR(MATCH($C29,Parties!$A$5:$A$304,0),"")) -> 2 | W29: =IF($B29="","",IFERROR(VALUE(SUBSTITUTE($B29,InvPrefix,"")),0)) -> 20 | X29: =IF($D29="","",IF(OR($H29="",$H29="Credit"),0,Q29)) -> 0
A30: 46146 | B30: INV-0020 | C30: Gupta Electricals | D30: Copper Wire 90m | E30: 3 | I30: Delivered | J30: =IF($D30="","",IFERROR(INDEX(Items!$D$5:$D$504,U30),"")) -> Pcs | K30: =IF($D30="","",IF($F30="",IFERROR(INDEX(Items!$H$5:$H$504,U30),0),$F30)) -> 3132 | L30: =IF($D30="","",ROUND(N($E30)*K30*(1-N($G30)),2)) -> 9396 | M30: =IF($D30="","",IFERROR(INDEX(Items!$F$5:$F$504,U30),0)) -> 0.18 | N30: =IF($D30="","",IF(AND(V30<>"",INDEX(Parties!$E$5:$E$304,V30)<>"",INDEX(Parties!$E$5:$E$304,V30)<>HomeState),0,ROUND(L30*M30/2,2))) -> 845.64 | O30: =IF($D30="","",N30) -> 845.64 | P30: =IF($D30="","",IF(AND(V30<>"",INDEX(Parties!$E$5:$E$304,V30)<>"",INDEX(Parties!$E$5:$E$304,V30)<>HomeState),ROUND(L30*M30,2),0)) -> 0 | Q30: =IF($D30="","",L30+N30+O30+P30) -> 11087.28 | R30: =IF($D30="","",ROUND(N($E30)*IFERROR(INDEX(Items!$P$5:$P$504,U30),0),2)) -> 7354.45 | S30: =IF($D30="","",L30-R30) -> 2041.55 | T30: =IF($D30="","",IF(U30="","UNKNOWN ITEM",IF(INDEX(Items!$O$5:$O$504,U30)<0,"NEG STOCK",IF(K30<INDEX(Items!$P$5:$P$504,U30),"BELOW COST","OK")))) -> OK | U30: =IF($D30="","",IFERROR(MATCH($D30,Items!$A$5:$A$504,0),"")) -> 8 | V30: =IF($C30="","",IFERROR(MATCH($C30,Parties!$A$5:$A$304,0),"")) -> 2 | W30: =IF($B30="","",IFERROR(VALUE(SUBSTITUTE($B30,InvPrefix,"")),0)) -> 20 | X30: =IF($D30="","",IF(OR($H30="",$H30="Credit"),0,Q30)) -> 0
A31: 46147 | B31: INV-0021 | C31: Delhi Hardware Mart | D31: PVC Pipe 1in 6m | E31: 20 | H31: Bank | I31: Delivered | J31: =IF($D31="","",IFERROR(INDEX(Items!$D$5:$D$504,U31),"")) -> Pcs | K31: =IF($D31="","",IF($F31="",IFERROR(INDEX(Items!$H$5:$H$504,U31),0),$F31)) -> 297 | L31: =IF($D31="","",ROUND(N($E31)*K31*(1-N($G31)),2)) -> 5940 | M31: =IF($D31="","",IFERROR(INDEX(Items!$F$5:$F$504,U31),0)) -> 0.18 | N31: =IF($D31="","",IF(AND(V31<>"",INDEX(Parties!$E$5:$E$304,V31)<>"",INDEX(Parties!$E$5:$E$304,V31)<>HomeState),0,ROUND(L31*M31/2,2))) -> 0 | O31: =IF($D31="","",N31) -> 0 | P31: =IF($D31="","",IF(AND(V31<>"",INDEX(Parties!$E$5:$E$304,V31)<>"",INDEX(Parties!$E$5:$E$304,V31)<>HomeState),ROUND(L31*M31,2),0)) -> 1069.2 | Q31: =IF($D31="","",L31+N31+O31+P31) -> 7009.2 | R31: =IF($D31="","",ROUND(N($E31)*IFERROR(INDEX(Items!$P$5:$P$504,U31),0),2)) -> 4192.67 | S31: =IF($D31="","",L31-R31) -> 1747.33 | T31: =IF($D31="","",IF(U31="","UNKNOWN ITEM",IF(INDEX(Items!$O$5:$O$504,U31)<0,"NEG STOCK",IF(K31<INDEX(Items!$P$5:$P$504,U31),"BELOW COST","OK")))) -> OK | U31: =IF($D31="","",IFERROR(MATCH($D31,Items!$A$5:$A$504,0),"")) -> 9 | V31: =IF($C31="","",IFERROR(MATCH($C31,Parties!$A$5:$A$304,0),"")) -> 3 | W31: =IF($B31="","",IFERROR(VALUE(SUBSTITUTE($B31,InvPrefix,"")),0)) -> 21 | X31: =IF($D31="","",IF(OR($H31="",$H31="Credit"),0,Q31)) -> 7009.2
A32: 46148 | B32: INV-0022 | C32: Delhi Hardware Mart | D32: PVC Pipe 1in 6m | E32: 25 | G32: 0.05 | I32: Delivered | J32: =IF($D32="","",IFERROR(INDEX(Items!$D$5:$D$504,U32),"")) -> Pcs | K32: =IF($D32="","",IF($F32="",IFERROR(INDEX(Items!$H$5:$H$504,U32),0),$F32)) -> 297 | L32: =IF($D32="","",ROUND(N($E32)*K32*(1-N($G32)),2)) -> 7053.75 | M32: =IF($D32="","",IFERROR(INDEX(Items!$F$5:$F$504,U32),0)) -> 0.18 | N32: =IF($D32="","",IF(AND(V32<>"",INDEX(Parties!$E$5:$E$304,V32)<>"",INDEX(Parties!$E$5:$E$304,V32)<>HomeState),0,ROUND(L32*M32/2,2))) -> 0 | O32: =IF($D32="","",N32) -> 0 | P32: =IF($D32="","",IF(AND(V32<>"",INDEX(Parties!$E$5:$E$304,V32)<>"",INDEX(Parties!$E$5:$E$304,V32)<>HomeState),ROUND(L32*M32,2),0)) -> 1269.68 | Q32: =IF($D32="","",L32+N32+O32+P32) -> 8323.43 | R32: =IF($D32="","",ROUND(N($E32)*IFERROR(INDEX(Items!$P$5:$P$504,U32),0),2)) -> 5240.83 | S32: =IF($D32="","",L32-R32) -> 1812.92 | T32: =IF($D32="","",IF(U32="","UNKNOWN ITEM",IF(INDEX(Items!$O$5:$O$504,U32)<0,"NEG STOCK",IF(K32<INDEX(Items!$P$5:$P$504,U32),"BELOW COST","OK")))) -> OK | U32: =IF($D32="","",IFERROR(MATCH($D32,Items!$A$5:$A$504,0),"")) -> 9 | V32: =IF($C32="","",IFERROR(MATCH($C32,Parties!$A$5:$A$304,0),"")) -> 3 | W32: =IF($B32="","",IFERROR(VALUE(SUBSTITUTE($B32,InvPrefix,"")),0)) -> 22 | X32: =IF($D32="","",IF(OR($H32="",$H32="Credit"),0,Q32)) -> 0
A33: 46149 | B33: INV-0023 | C33: Walk-in Customer | D33: Tea Premium 1kg | E33: 16 | H33: Cash | I33: Delivered | J33: =IF($D33="","",IFERROR(INDEX(Items!$D$5:$D$504,U33),"")) -> Pack | K33: =IF($D33="","",IF($F33="",IFERROR(INDEX(Items!$H$5:$H$504,U33),0),$F33)) -> 508 | L33: =IF($D33="","",ROUND(N($E33)*K33*(1-N($G33)),2)) -> 8128 | M33: =IF($D33="","",IFERROR(INDEX(Items!$F$5:$F$504,U33),0)) -> 0.05 | N33: =IF($D33="","",IF(AND(V33<>"",INDEX(Parties!$E$5:$E$304,V33)<>"",INDEX(Parties!$E$5:$E$304,V33)<>HomeState),0,ROUND(L33*M33/2,2))) -> 203.2 | O33: =IF($D33="","",N33) -> 203.2 | P33: =IF($D33="","",IF(AND(V33<>"",INDEX(Parties!$E$5:$E$304,V33)<>"",INDEX(Parties!$E$5:$E$304,V33)<>HomeState),ROUND(L33*M33,2),0)) -> 0 | Q33: =IF($D33="","",L33+N33+O33+P33) -> 8534.4 | R33: =IF($D33="","",ROUND(N($E33)*IFERROR(INDEX(Items!$P$5:$P$504,U33),0),2)) -> 6033.27 | S33: =IF($D33="","",L33-R33) -> 2094.73 | T33: =IF($D33="","",IF(U33="","UNKNOWN ITEM",IF(INDEX(Items!$O$5:$O$504,U33)<0,"NEG STOCK",IF(K33<INDEX(Items!$P$5:$P$504,U33),"BELOW COST","OK")))) -> OK | U33: =IF($D33="","",IFERROR(MATCH($D33,Items!$A$5:$A$504,0),"")) -> 4 | V33: =IF($C33="","",IFERROR(MATCH($C33,Parties!$A$5:$A$304,0),"")) -> 4 | W33: =IF($B33="","",IFERROR(VALUE(SUBSTITUTE($B33,InvPrefix,"")),0)) -> 23 | X33: =IF($D33="","",IF(OR($H33="",$H33="Credit"),0,Q33)) -> 8534.4
A34: 46149 | B34: INV-0023 | C34: Walk-in Customer | D34: Ceiling Fan 1200mm | E34: 2 | G34: 0.02 | H34: Cash | I34: Delivered | J34: =IF($D34="","",IFERROR(INDEX(Items!$D$5:$D$504,U34),"")) -> Pcs | K34: =IF($D34="","",IF($F34="",IFERROR(INDEX(Items!$H$5:$H$504,U34),0),$F34)) -> 2322 | L34: =IF($D34="","",ROUND(N($E34)*K34*(1-N($G34)),2)) -> 4551.12 | M34: =IF($D34="","",IFERROR(INDEX(Items!$F$5:$F$504,U34),0)) -> 0.18 | N34: =IF($D34="","",IF(AND(V34<>"",INDEX(Parties!$E$5:$E$304,V34)<>"",INDEX(Parties!$E$5:$E$304,V34)<>HomeState),0,ROUND(L34*M34/2,2))) -> 409.6 | O34: =IF($D34="","",N34) -> 409.6 | P34: =IF($D34="","",IF(AND(V34<>"",INDEX(Parties!$E$5:$E$304,V34)<>"",INDEX(Parties!$E$5:$E$304,V34)<>HomeState),ROUND(L34*M34,2),0)) -> 0 | Q34: =IF($D34="","",L34+N34+O34+P34) -> 5370.32 | R34: =IF($D34="","",ROUND(N($E34)*IFERROR(INDEX(Items!$P$5:$P$504,U34),0),2)) -> 3287.6 | S34: =IF($D34="","",L34-R34) -> 1263.52 | T34: =IF($D34="","",IF(U34="","UNKNOWN ITEM",IF(INDEX(Items!$O$5:$O$504,U34)<0,"NEG STOCK",IF(K34<INDEX(Items!$P$5:$P$504,U34),"BELOW COST","OK")))) -> OK | U34: =IF($D34="","",IFERROR(MATCH($D34,Items!$A$5:$A$504,0),"")) -> 12 | V34: =IF($C34="","",IFERROR(MATCH($C34,Parties!$A$5:$A$304,0),"")) -> 4 | W34: =IF($B34="","",IFERROR(VALUE(SUBSTITUTE($B34,InvPrefix,"")),0)) -> 23 | X34: =IF($D34="","",IF(OR($H34="",$H34="Credit"),0,Q34)) -> 5370.32
A35: 46150 | B35: INV-0024 | C35: Sharma Kirana Store | D35: Copper Wire 90m | E35: 2 | G35: 0.05 | I35: Delivered | J35: =IF($D35="","",IFERROR(INDEX(Items!$D$5:$D$504,U35),"")) -> Pcs | K35: =IF($D35="","",IF($F35="",IFERROR(INDEX(Items!$H$5:$H$504,U35),0),$F35)) -> 3132 | L35: =IF($D35="","",ROUND(N($E35)*K35*(1-N($G35)),2)) -> 5950.8 | M35: =IF($D35="","",IFERROR(INDEX(Items!$F$5:$F$504,U35),0)) -> 0.18 | N35: =IF($D35="","",IF(AND(V35<>"",INDEX(Parties!$E$5:$E$304,V35)<>"",INDEX(Parties!$E$5:$E$304,V35)<>HomeState),0,ROUND(L35*M35/2,2))) -> 535.57 | O35: =IF($D35="","",N35) -> 535.57 | P35: =IF($D35="","",IF(AND(V35<>"",INDEX(Parties!$E$5:$E$304,V35)<>"",INDEX(Parties!$E$5:$E$304,V35)<>HomeState),ROUND(L35*M35,2),0)) -> 0 | Q35: =IF($D35="","",L35+N35+O35+P35) -> 7021.94 | R35: =IF($D35="","",ROUND(N($E35)*IFERROR(INDEX(Items!$P$5:$P$504,U35),0),2)) -> 4902.96 | S35: =IF($D35="","",L35-R35) -> 1047.84 | T35: =IF($D35="","",IF(U35="","UNKNOWN ITEM",IF(INDEX(Items!$O$5:$O$504,U35)<0,"NEG STOCK",IF(K35<INDEX(Items!$P$5:$P$504,U35),"BELOW COST","OK")))) -> OK | U35: =IF($D35="","",IFERROR(MATCH($D35,Items!$A$5:$A$504,0),"")) -> 8 | V35: =IF($C35="","",IFERROR(MATCH($C35,Parties!$A$5:$A$304,0),"")) -> 1 | W35: =IF($B35="","",IFERROR(VALUE(SUBSTITUTE($B35,InvPrefix,"")),0)) -> 24 | X35: =IF($D35="","",IF(OR($H35="",$H35="Credit"),0,Q35)) -> 0
A36: 46151 | B36: INV-0025 | C36: Walk-in Customer | D36: Toothpaste 150g x12 | E36: 3 | H36: Cash | I36: Delivered | J36: =IF($D36="","",IFERROR(INDEX(Items!$D$5:$D$504,U36),"")) -> Box | K36: =IF($D36="","",IF($F36="",IFERROR(INDEX(Items!$H$5:$H$504,U36),0),$F36)) -> 1166 | L36: =IF($D36="","",ROUND(N($E36)*K36*(1-N($G36)),2)) -> 3498 | M36: =IF($D36="","",IFERROR(INDEX(Items!$F$5:$F$504,U36),0)) -> 0.05 | N36: =IF($D36="","",IF(AND(V36<>"",INDEX(Parties!$E$5:$E$304,V36)<>"",INDEX(Parties!$E$5:$E$304,V36)<>HomeState),0,ROUND(L36*M36/2,2))) -> 87.45 | O36: =IF($D36="","",N36) -> 87.45 | P36: =IF($D36="","",IF(AND(V36<>"",INDEX(Parties!$E$5:$E$304,V36)<>"",INDEX(Parties!$E$5:$E$304,V36)<>HomeState),ROUND(L36*M36,2),0)) -> 0 | Q36: =IF($D36="","",L36+N36+O36+P36) -> 3672.9 | R36: =IF($D36="","",ROUND(N($E36)*IFERROR(INDEX(Items!$P$5:$P$504,U36),0),2)) -> 2665.44 | S36: =IF($D36="","",L36-R36) -> 832.56 | T36: =IF($D36="","",IF(U36="","UNKNOWN ITEM",IF(INDEX(Items!$O$5:$O$504,U36)<0,"NEG STOCK",IF(K36<INDEX(Items!$P$5:$P$504,U36),"BELOW COST","OK")))) -> OK | U36: =IF($D36="","",IFERROR(MATCH($D36,Items!$A$5:$A$504,0),"")) -> 6 | V36: =IF($C36="","",IFERROR(MATCH($C36,Parties!$A$5:$A$304,0),"")) -> 4 | W36: =IF($B36="","",IFERROR(VALUE(SUBSTITUTE($B36,InvPrefix,"")),0)) -> 25 | X36: =IF($D36="","",IF(OR($H36="",$H36="Credit"),0,Q36)) -> 3672.9
A37: 46151 | B37: INV-0025 | C37: Walk-in Customer | D37: Ceiling Fan 1200mm | E37: 2 | H37: Cash | I37: Delivered | J37: =IF($D37="","",IFERROR(INDEX(Items!$D$5:$D$504,U37),"")) -> Pcs | K37: =IF($D37="","",IF($F37="",IFERROR(INDEX(Items!$H$5:$H$504,U37),0),$F37)) -> 2322 | L37: =IF($D37="","",ROUND(N($E37)*K37*(1-N($G37)),2)) -> 4644 | M37: =IF($D37="","",IFERROR(INDEX(Items!$F$5:$F$504,U37),0)) -> 0.18 | N37: =IF($D37="","",IF(AND(V37<>"",INDEX(Parties!$E$5:$E$304,V37)<>"",INDEX(Parties!$E$5:$E$304,V37)<>HomeState),0,ROUND(L37*M37/2,2))) -> 417.96 | O37: =IF($D37="","",N37) -> 417.96 | P37: =IF($D37="","",IF(AND(V37<>"",INDEX(Parties!$E$5:$E$304,V37)<>"",INDEX(Parties!$E$5:$E$304,V37)<>HomeState),ROUND(L37*M37,2),0)) -> 0 | Q37: =IF($D37="","",L37+N37+O37+P37) -> 5479.92 | R37: =IF($D37="","",ROUND(N($E37)*IFERROR(INDEX(Items!$P$5:$P$504,U37),0),2)) -> 3287.6 | S37: =IF($D37="","",L37-R37) -> 1356.4 | T37: =IF($D37="","",IF(U37="","UNKNOWN ITEM",IF(INDEX(Items!$O$5:$O$504,U37)<0,"NEG STOCK",IF(K37<INDEX(Items!$P$5:$P$504,U37),"BELOW COST","OK")))) -> OK | U37: =IF($D37="","",IFERROR(MATCH($D37,Items!$A$5:$A$504,0),"")) -> 12 | V37: =IF($C37="","",IFERROR(MATCH($C37,Parties!$A$5:$A$304,0),"")) -> 4 | W37: =IF($B37="","",IFERROR(VALUE(SUBSTITUTE($B37,InvPrefix,"")),0)) -> 25 | X37: =IF($D37="","",IF(OR($H37="",$H37="Credit"),0,Q37)) -> 5479.92
A38: 46153 | B38: INV-0026 | C38: Gupta Electricals | D38: LED Bulb 9W | E38: 75 | H38: UPI | I38: Delivered | J38: =IF($D38="","",IFERROR(INDEX(Items!$D$5:$D$504,U38),"")) -> Pcs | K38: =IF($D38="","",IF($F38="",IFERROR(INDEX(Items!$H$5:$H$504,U38),0),$F38)) -> 107 | L38: =IF($D38="","",ROUND(N($E38)*K38*(1-N($G38)),2)) -> 8025 | M38: =IF($D38="","",IFERROR(INDEX(Items!$F$5:$F$504,U38),0)) -> 0.18 | N38: =IF($D38="","",IF(AND(V38<>"",INDEX(Parties!$E$5:$E$304,V38)<>"",INDEX(Parties!$E$5:$E$304,V38)<>HomeState),0,ROUND(L38*M38/2,2))) -> 722.25 | O38: =IF($D38="","",N38) -> 722.25 | P38: =IF($D38="","",IF(AND(V38<>"",INDEX(Parties!$E$5:$E$304,V38)<>"",INDEX(Parties!$E$5:$E$304,V38)<>HomeState),ROUND(L38*M38,2),0)) -> 0 | Q38: =IF($D38="","",L38+N38+O38+P38) -> 9469.5 | R38: =IF($D38="","",ROUND(N($E38)*IFERROR(INDEX(Items!$P$5:$P$504,U38),0),2)) -> 4606.28 | S38: =IF($D38="","",L38-R38) -> 3418.72 | T38: =IF($D38="","",IF(U38="","UNKNOWN ITEM",IF(INDEX(Items!$O$5:$O$504,U38)<0,"NEG STOCK",IF(K38<INDEX(Items!$P$5:$P$504,U38),"BELOW COST","OK")))) -> OK | U38: =IF($D38="","",IFERROR(MATCH($D38,Items!$A$5:$A$504,0),"")) -> 7 | V38: =IF($C38="","",IFERROR(MATCH($C38,Parties!$A$5:$A$304,0),"")) -> 2 | W38: =IF($B38="","",IFERROR(VALUE(SUBSTITUTE($B38,InvPrefix,"")),0)) -> 26 | X38: =IF($D38="","",IF(OR($H38="",$H38="Credit"),0,Q38)) -> 9469.5
A39: 46154 | B39: INV-0027 | C39: Delhi Hardware Mart | D39: Refined Oil 15L | E39: 6 | G39: 0.02 | I39: Delivered | J39: =IF($D39="","",IFERROR(INDEX(Items!$D$5:$D$504,U39),"")) -> Box | K39: =IF($D39="","",IF($F39="",IFERROR(INDEX(Items!$H$5:$H$504,U39),0),$F39)) -> 2290 | L39: =IF($D39="","",ROUND(N($E39)*K39*(1-N($G39)),2)) -> 13465.2 | M39: =IF($D39="","",IFERROR(INDEX(Items!$F$5:$F$504,U39),0)) -> 0.05 | N39: =IF($D39="","",IF(AND(V39<>"",INDEX(Parties!$E$5:$E$304,V39)<>"",INDEX(Parties!$E$5:$E$304,V39)<>HomeState),0,ROUND(L39*M39/2,2))) -> 0 | O39: =IF($D39="","",N39) -> 0 | P39: =IF($D39="","",IF(AND(V39<>"",INDEX(Parties!$E$5:$E$304,V39)<>"",INDEX(Parties!$E$5:$E$304,V39)<>HomeState),ROUND(L39*M39,2),0)) -> 673.26 | Q39: =IF($D39="","",L39+N39+O39+P39) -> 14138.46 | R39: =IF($D39="","",ROUND(N($E39)*IFERROR(INDEX(Items!$P$5:$P$504,U39),0),2)) -> 11426.18 | S39: =IF($D39="","",L39-R39) -> 2039.02 | T39: =IF($D39="","",IF(U39="","UNKNOWN ITEM",IF(INDEX(Items!$O$5:$O$504,U39)<0,"NEG STOCK",IF(K39<INDEX(Items!$P$5:$P$504,U39),"BELOW COST","OK")))) -> OK | U39: =IF($D39="","",IFERROR(MATCH($D39,Items!$A$5:$A$504,0),"")) -> 3 | V39: =IF($C39="","",IFERROR(MATCH($C39,Parties!$A$5:$A$304,0),"")) -> 3 | W39: =IF($B39="","",IFERROR(VALUE(SUBSTITUTE($B39,InvPrefix,"")),0)) -> 27 | X39: =IF($D39="","",IF(OR($H39="",$H39="Credit"),0,Q39)) -> 0
A40: 46155 | B40: INV-0028 | C40: Walk-in Customer | D40: Toothpaste 150g x12 | E40: 6 | H40: Cash | I40: Delivered | J40: =IF($D40="","",IFERROR(INDEX(Items!$D$5:$D$504,U40),"")) -> Box | K40: =IF($D40="","",IF($F40="",IFERROR(INDEX(Items!$H$5:$H$504,U40),0),$F40)) -> 1166 | L40: =IF($D40="","",ROUND(N($E40)*K40*(1-N($G40)),2)) -> 6996 | M40: =IF($D40="","",IFERROR(INDEX(Items!$F$5:$F$504,U40),0)) -> 0.05 | N40: =IF($D40="","",IF(AND(V40<>"",INDEX(Parties!$E$5:$E$304,V40)<>"",INDEX(Parties!$E$5:$E$304,V40)<>HomeState),0,ROUND(L40*M40/2,2))) -> 174.9 | O40: =IF($D40="","",N40) -> 174.9 | P40: =IF($D40="","",IF(AND(V40<>"",INDEX(Parties!$E$5:$E$304,V40)<>"",INDEX(Parties!$E$5:$E$304,V40)<>HomeState),ROUND(L40*M40,2),0)) -> 0 | Q40: =IF($D40="","",L40+N40+O40+P40) -> 7345.8 | R40: =IF($D40="","",ROUND(N($E40)*IFERROR(INDEX(Items!$P$5:$P$504,U40),0),2)) -> 5330.88 | S40: =IF($D40="","",L40-R40) -> 1665.12 | T40: =IF($D40="","",IF(U40="","UNKNOWN ITEM",IF(INDEX(Items!$O$5:$O$504,U40)<0,"NEG STOCK",IF(K40<INDEX(Items!$P$5:$P$504,U40),"BELOW COST","OK")))) -> OK | U40: =IF($D40="","",IFERROR(MATCH($D40,Items!$A$5:$A$504,0),"")) -> 6 | V40: =IF($C40="","",IFERROR(MATCH($C40,Parties!$A$5:$A$304,0),"")) -> 4 | W40: =IF($B40="","",IFERROR(VALUE(SUBSTITUTE($B40,InvPrefix,"")),0)) -> 28 | X40: =IF($D40="","",IF(OR($H40="",$H40="Credit"),0,Q40)) -> 7345.8
A41: 46155 | B41: INV-0028 | C41: Walk-in Customer | D41: Refined Oil 15L | E41: 3 | H41: Cash | I41: Delivered | J41: =IF($D41="","",IFERROR(INDEX(Items!$D$5:$D$504,U41),"")) -> Box | K41: =IF($D41="","",IF($F41="",IFERROR(INDEX(Items!$H$5:$H$504,U41),0),$F41)) -> 2290 | L41: =IF($D41="","",ROUND(N($E41)*K41*(1-N($G41)),2)) -> 6870 | M41: =IF($D41="","",IFERROR(INDEX(Items!$F$5:$F$504,U41),0)) -> 0.05 | N41: =IF($D41="","",IF(AND(V41<>"",INDEX(Parties!$E$5:$E$304,V41)<>"",INDEX(Parties!$E$5:$E$304,V41)<>HomeState),0,ROUND(L41*M41/2,2))) -> 171.75 | O41: =IF($D41="","",N41) -> 171.75 | P41: =IF($D41="","",IF(AND(V41<>"",INDEX(Parties!$E$5:$E$304,V41)<>"",INDEX(Parties!$E$5:$E$304,V41)<>HomeState),ROUND(L41*M41,2),0)) -> 0 | Q41: =IF($D41="","",L41+N41+O41+P41) -> 7213.5 | R41: =IF($D41="","",ROUND(N($E41)*IFERROR(INDEX(Items!$P$5:$P$504,U41),0),2)) -> 5713.09 | S41: =IF($D41="","",L41-R41) -> 1156.91 | T41: =IF($D41="","",IF(U41="","UNKNOWN ITEM",IF(INDEX(Items!$O$5:$O$504,U41)<0,"NEG STOCK",IF(K41<INDEX(Items!$P$5:$P$504,U41),"BELOW COST","OK")))) -> OK | U41: =IF($D41="","",IFERROR(MATCH($D41,Items!$A$5:$A$504,0),"")) -> 3 | V41: =IF($C41="","",IFERROR(MATCH($C41,Parties!$A$5:$A$304,0),"")) -> 4 | W41: =IF($B41="","",IFERROR(VALUE(SUBSTITUTE($B41,InvPrefix,"")),0)) -> 28 | X41: =IF($D41="","",IF(OR($H41="",$H41="Credit"),0,Q41)) -> 7213.5
A42: 46156 | B42: INV-0029 | C42: Walk-in Customer | D42: Tea Premium 1kg | E42: 7 | H42: Cash | I42: Delivered | J42: =IF($D42="","",IFERROR(INDEX(Items!$D$5:$D$504,U42),"")) -> Pack | K42: =IF($D42="","",IF($F42="",IFERROR(INDEX(Items!$H$5:$H$504,U42),0),$F42)) -> 508 | L42: =IF($D42="","",ROUND(N($E42)*K42*(1-N($G42)),2)) -> 3556 | M42: =IF($D42="","",IFERROR(INDEX(Items!$F$5:$F$504,U42),0)) -> 0.05 | N42: =IF($D42="","",IF(AND(V42<>"",INDEX(Parties!$E$5:$E$304,V42)<>"",INDEX(Parties!$E$5:$E$304,V42)<>HomeState),0,ROUND(L42*M42/2,2))) -> 88.9 | O42: =IF($D42="","",N42) -> 88.9 | P42: =IF($D42="","",IF(AND(V42<>"",INDEX(Parties!$E$5:$E$304,V42)<>"",INDEX(Parties!$E$5:$E$304,V42)<>HomeState),ROUND(L42*M42,2),0)) -> 0 | Q42: =IF($D42="","",L42+N42+O42+P42) -> 3733.8 | R42: =IF($D42="","",ROUND(N($E42)*IFERROR(INDEX(Items!$P$5:$P$504,U42),0),2)) -> 2639.55 | S42: =IF($D42="","",L42-R42) -> 916.45 | T42: =IF($D42="","",IF(U42="","UNKNOWN ITEM",IF(INDEX(Items!$O$5:$O$504,U42)<0,"NEG STOCK",IF(K42<INDEX(Items!$P$5:$P$504,U42),"BELOW COST","OK")))) -> OK | U42: =IF($D42="","",IFERROR(MATCH($D42,Items!$A$5:$A$504,0),"")) -> 4 | V42: =IF($C42="","",IFERROR(MATCH($C42,Parties!$A$5:$A$304,0),"")) -> 4 | W42: =IF($B42="","",IFERROR(VALUE(SUBSTITUTE($B42,InvPrefix,"")),0)) -> 29 | X42: =IF($D42="","",IF(OR($H42="",$H42="Credit"),0,Q42)) -> 3733.8
A43: 46157 | B43: INV-0030 | C43: Walk-in Customer | D43: Toothpaste 150g x12 | E43: 6 | H43: Cash | I43: Delivered | J43: =IF($D43="","",IFERROR(INDEX(Items!$D$5:$D$504,U43),"")) -> Box | K43: =IF($D43="","",IF($F43="",IFERROR(INDEX(Items!$H$5:$H$504,U43),0),$F43)) -> 1166 | L43: =IF($D43="","",ROUND(N($E43)*K43*(1-N($G43)),2)) -> 6996 | M43: =IF($D43="","",IFERROR(INDEX(Items!$F$5:$F$504,U43),0)) -> 0.05 | N43: =IF($D43="","",IF(AND(V43<>"",INDEX(Parties!$E$5:$E$304,V43)<>"",INDEX(Parties!$E$5:$E$304,V43)<>HomeState),0,ROUND(L43*M43/2,2))) -> 174.9 | O43: =IF($D43="","",N43) -> 174.9 | P43: =IF($D43="","",IF(AND(V43<>"",INDEX(Parties!$E$5:$E$304,V43)<>"",INDEX(Parties!$E$5:$E$304,V43)<>HomeState),ROUND(L43*M43,2),0)) -> 0 | Q43: =IF($D43="","",L43+N43+O43+P43) -> 7345.8 | R43: =IF($D43="","",ROUND(N($E43)*IFERROR(INDEX(Items!$P$5:$P$504,U43),0),2)) -> 5330.88 | S43: =IF($D43="","",L43-R43) -> 1665.12 | T43: =IF($D43="","",IF(U43="","UNKNOWN ITEM",IF(INDEX(Items!$O$5:$O$504,U43)<0,"NEG STOCK",IF(K43<INDEX(Items!$P$5:$P$504,U43),"BELOW COST","OK")))) -> OK | U43: =IF($D43="","",IFERROR(MATCH($D43,Items!$A$5:$A$504,0),"")) -> 6 | V43: =IF($C43="","",IFERROR(MATCH($C43,Parties!$A$5:$A$304,0),"")) -> 4 | W43: =IF($B43="","",IFERROR(VALUE(SUBSTITUTE($B43,InvPrefix,"")),0)) -> 30 | X43: =IF($D43="","",IF(OR($H43="",$H43="Credit"),0,Q43)) -> 7345.8
A44: 46157 | B44: INV-0030 | C44: Walk-in Customer | D44: Detergent 5kg | E44: 5 | H44: Cash | I44: Delivered | J44: =IF($D44="","",IFERROR(INDEX(Items!$D$5:$D$504,U44),"")) -> Pack | K44: =IF($D44="","",IF($F44="",IFERROR(INDEX(Items!$H$5:$H$504,U44),0),$F44)) -> 691 | L44: =IF($D44="","",ROUND(N($E44)*K44*(1-N($G44)),2)) -> 3455 | M44: =IF($D44="","",IFERROR(INDEX(Items!$F$5:$F$504,U44),0)) -> 0.18 | N44: =IF($D44="","",IF(AND(V44<>"",INDEX(Parties!$E$5:$E$304,V44)<>"",INDEX(Parties!$E$5:$E$304,V44)<>HomeState),0,ROUND(L44*M44/2,2))) -> 310.95 | O44: =IF($D44="","",N44) -> 310.95 | P44: =IF($D44="","",IF(AND(V44<>"",INDEX(Parties!$E$5:$E$304,V44)<>"",INDEX(Parties!$E$5:$E$304,V44)<>HomeState),ROUND(L44*M44,2),0)) -> 0 | Q44: =IF($D44="","",L44+N44+O44+P44) -> 4076.9 | R44: =IF($D44="","",ROUND(N($E44)*IFERROR(INDEX(Items!$P$5:$P$504,U44),0),2)) -> 2588.46 | S44: =IF($D44="","",L44-R44) -> 866.54 | T44: =IF($D44="","",IF(U44="","UNKNOWN ITEM",IF(INDEX(Items!$O$5:$O$504,U44)<0,"NEG STOCK",IF(K44<INDEX(Items!$P$5:$P$504,U44),"BELOW COST","OK")))) -> OK | U44: =IF($D44="","",IFERROR(MATCH($D44,Items!$A$5:$A$504,0),"")) -> 5 | V44: =IF($C44="","",IFERROR(MATCH($C44,Parties!$A$5:$A$304,0),"")) -> 4 | W44: =IF($B44="","",IFERROR(VALUE(SUBSTITUTE($B44,InvPrefix,"")),0)) -> 30 | X44: =IF($D44="","",IF(OR($H44="",$H44="Credit"),0,Q44)) -> 4076.9
A45: 46158 | B45: INV-0031 | C45: Walk-in Customer | D45: Refined Oil 15L | E45: 4 | G45: 0.05 | H45: Cash | I45: Delivered | J45: =IF($D45="","",IFERROR(INDEX(Items!$D$5:$D$504,U45),"")) -> Box | K45: =IF($D45="","",IF($F45="",IFERROR(INDEX(Items!$H$5:$H$504,U45),0),$F45)) -> 2290 | L45: =IF($D45="","",ROUND(N($E45)*K45*(1-N($G45)),2)) -> 8702 | M45: =IF($D45="","",IFERROR(INDEX(Items!$F$5:$F$504,U45),0)) -> 0.05 | N45: =IF($D45="","",IF(AND(V45<>"",INDEX(Parties!$E$5:$E$304,V45)<>"",INDEX(Parties!$E$5:$E$304,V45)<>HomeState),0,ROUND(L45*M45/2,2))) -> 217.55 | O45: =IF($D45="","",N45) -> 217.55 | P45: =IF($D45="","",IF(AND(V45<>"",INDEX(Parties!$E$5:$E$304,V45)<>"",INDEX(Parties!$E$5:$E$304,V45)<>HomeState),ROUND(L45*M45,2),0)) -> 0 | Q45: =IF($D45="","",L45+N45+O45+P45) -> 9137.1 | R45: =IF($D45="","",ROUND(N($E45)*IFERROR(INDEX(Items!$P$5:$P$504,U45),0),2)) -> 7617.45 | S45: =IF($D45="","",L45-R45) -> 1084.55 | T45: =IF($D45="","",IF(U45="","UNKNOWN ITEM",IF(INDEX(Items!$O$5:$O$504,U45)<0,"NEG STOCK",IF(K45<INDEX(Items!$P$5:$P$504,U45),"BELOW COST","OK")))) -> OK | U45: =IF($D45="","",IFERROR(MATCH($D45,Items!$A$5:$A$504,0),"")) -> 3 | V45: =IF($C45="","",IFERROR(MATCH($C45,Parties!$A$5:$A$304,0),"")) -> 4 | W45: =IF($B45="","",IFERROR(VALUE(SUBSTITUTE($B45,InvPrefix,"")),0)) -> 31 | X45: =IF($D45="","",IF(OR($H45="",$H45="Credit"),0,Q45)) -> 9137.1
A46: 46158 | B46: INV-0031 | C46: Walk-in Customer | D46: PVC Pipe 1in 6m | E46: 14 | G46: 0.02 | H46: Cash | I46: Delivered | J46: =IF($D46="","",IFERROR(INDEX(Items!$D$5:$D$504,U46),"")) -> Pcs | K46: =IF($D46="","",IF($F46="",IFERROR(INDEX(Items!$H$5:$H$504,U46),0),$F46)) -> 297 | L46: =IF($D46="","",ROUND(N($E46)*K46*(1-N($G46)),2)) -> 4074.84 | M46: =IF($D46="","",IFERROR(INDEX(Items!$F$5:$F$504,U46),0)) -> 0.18 | N46: =IF($D46="","",IF(AND(V46<>"",INDEX(Parties!$E$5:$E$304,V46)<>"",INDEX(Parties!$E$5:$E$304,V46)<>HomeState),0,ROUND(L46*M46/2,2))) -> 366.74 | O46: =IF($D46="","",N46) -> 366.74 | P46: =IF($D46="","",IF(AND(V46<>"",INDEX(Parties!$E$5:$E$304,V46)<>"",INDEX(Parties!$E$5:$E$304,V46)<>HomeState),ROUND(L46*M46,2),0)) -> 0 | Q46: =IF($D46="","",L46+N46+O46+P46) -> 4808.32 | R46: =IF($D46="","",ROUND(N($E46)*IFERROR(INDEX(Items!$P$5:$P$504,U46),0),2)) -> 2934.87 | S46: =IF($D46="","",L46-R46) -> 1139.97 | T46: =IF($D46="","",IF(U46="","UNKNOWN ITEM",IF(INDEX(Items!$O$5:$O$504,U46)<0,"NEG STOCK",IF(K46<INDEX(Items!$P$5:$P$504,U46),"BELOW COST","OK")))) -> OK | U46: =IF($D46="","",IFERROR(MATCH($D46,Items!$A$5:$A$504,0),"")) -> 9 | V46: =IF($C46="","",IFERROR(MATCH($C46,Parties!$A$5:$A$304,0),"")) -> 4 | W46: =IF($B46="","",IFERROR(VALUE(SUBSTITUTE($B46,InvPrefix,"")),0)) -> 31 | X46: =IF($D46="","",IF(OR($H46="",$H46="Credit"),0,Q46)) -> 4808.32
A47: 46160 | B47: INV-0032 | C47: Sharma Kirana Store | D47: Refined Oil 15L | E47: 6 | I47: Delivered | J47: =IF($D47="","",IFERROR(INDEX(Items!$D$5:$D$504,U47),"")) -> Box | K47: =IF($D47="","",IF($F47="",IFERROR(INDEX(Items!$H$5:$H$504,U47),0),$F47)) -> 2290 | L47: =IF($D47="","",ROUND(N($E47)*K47*(1-N($G47)),2)) -> 13740 | M47: =IF($D47="","",IFERROR(INDEX(Items!$F$5:$F$504,U47),0)) -> 0.05 | N47: =IF($D47="","",IF(AND(V47<>"",INDEX(Parties!$E$5:$E$304,V47)<>"",INDEX(Parties!$E$5:$E$304,V47)<>HomeState),0,ROUND(L47*M47/2,2))) -> 343.5 | O47: =IF($D47="","",N47) -> 343.5 | P47: =IF($D47="","",IF(AND(V47<>"",INDEX(Parties!$E$5:$E$304,V47)<>"",INDEX(Parties!$E$5:$E$304,V47)<>HomeState),ROUND(L47*M47,2),0)) -> 0 | Q47: =IF($D47="","",L47+N47+O47+P47) -> 14427 | R47: =IF($D47="","",ROUND(N($E47)*IFERROR(INDEX(Items!$P$5:$P$504,U47),0),2)) -> 11426.18 | S47: =IF($D47="","",L47-R47) -> 2313.82 | T47: =IF($D47="","",IF(U47="","UNKNOWN ITEM",IF(INDEX(Items!$O$5:$O$504,U47)<0,"NEG STOCK",IF(K47<INDEX(Items!$P$5:$P$504,U47),"BELOW COST","OK")))) -> OK | U47: =IF($D47="","",IFERROR(MATCH($D47,Items!$A$5:$A$504,0),"")) -> 3 | V47: =IF($C47="","",IFERROR(MATCH($C47,Parties!$A$5:$A$304,0),"")) -> 1 | W47: =IF($B47="","",IFERROR(VALUE(SUBSTITUTE($B47,InvPrefix,"")),0)) -> 32 | X47: =IF($D47="","",IF(OR($H47="",$H47="Credit"),0,Q47)) -> 0
A48: 46162 | B48: INV-0033 | C48: Walk-in Customer | D48: PVC Pipe 1in 6m | E48: 15 | H48: Cash | I48: Delivered | J48: =IF($D48="","",IFERROR(INDEX(Items!$D$5:$D$504,U48),"")) -> Pcs | K48: =IF($D48="","",IF($F48="",IFERROR(INDEX(Items!$H$5:$H$504,U48),0),$F48)) -> 297 | L48: =IF($D48="","",ROUND(N($E48)*K48*(1-N($G48)),2)) -> 4455 | M48: =IF($D48="","",IFERROR(INDEX(Items!$F$5:$F$504,U48),0)) -> 0.18 | N48: =IF($D48="","",IF(AND(V48<>"",INDEX(Parties!$E$5:$E$304,V48)<>"",INDEX(Parties!$E$5:$E$304,V48)<>HomeState),0,ROUND(L48*M48/2,2))) -> 400.95 | O48: =IF($D48="","",N48) -> 400.95 | P48: =IF($D48="","",IF(AND(V48<>"",INDEX(Parties!$E$5:$E$304,V48)<>"",INDEX(Parties!$E$5:$E$304,V48)<>HomeState),ROUND(L48*M48,2),0)) -> 0 | Q48: =IF($D48="","",L48+N48+O48+P48) -> 5256.9 | R48: =IF($D48="","",ROUND(N($E48)*IFERROR(INDEX(Items!$P$5:$P$504,U48),0),2)) -> 3144.5 | S48: =IF($D48="","",L48-R48) -> 1310.5 | T48: =IF($D48="","",IF(U48="","UNKNOWN ITEM",IF(INDEX(Items!$O$5:$O$504,U48)<0,"NEG STOCK",IF(K48<INDEX(Items!$P$5:$P$504,U48),"BELOW COST","OK")))) -> OK | U48: =IF($D48="","",IFERROR(MATCH($D48,Items!$A$5:$A$504,0),"")) -> 9 | V48: =IF($C48="","",IFERROR(MATCH($C48,Parties!$A$5:$A$304,0),"")) -> 4 | W48: =IF($B48="","",IFERROR(VALUE(SUBSTITUTE($B48,InvPrefix,"")),0)) -> 33 | X48: =IF($D48="","",IF(OR($H48="",$H48="Credit"),0,Q48)) -> 5256.9
A49: 46163 | B49: INV-0034 | C49: Sharma Kirana Store | D49: Copper Wire 90m | E49: 1 | I49: Delivered | J49: =IF($D49="","",IFERROR(INDEX(Items!$D$5:$D$504,U49),"")) -> Pcs | K49: =IF($D49="","",IF($F49="",IFERROR(INDEX(Items!$H$5:$H$504,U49),0),$F49)) -> 3132 | L49: =IF($D49="","",ROUND(N($E49)*K49*(1-N($G49)),2)) -> 3132 | M49: =IF($D49="","",IFERROR(INDEX(Items!$F$5:$F$504,U49),0)) -> 0.18 | N49: =IF($D49="","",IF(AND(V49<>"",INDEX(Parties!$E$5:$E$304,V49)<>"",INDEX(Parties!$E$5:$E$304,V49)<>HomeState),0,ROUND(L49*M49/2,2))) -> 281.88 | O49: =IF($D49="","",N49) -> 281.88 | P49: =IF($D49="","",IF(AND(V49<>"",INDEX(Parties!$E$5:$E$304,V49)<>"",INDEX(Parties!$E$5:$E$304,V49)<>HomeState),ROUND(L49*M49,2),0)) -> 0 | Q49: =IF($D49="","",L49+N49+O49+P49) -> 3695.76 | R49: =IF($D49="","",ROUND(N($E49)*IFERROR(INDEX(Items!$P$5:$P$504,U49),0),2)) -> 2451.48 | S49: =IF($D49="","",L49-R49) -> 680.52 | T49: =IF($D49="","",IF(U49="","UNKNOWN ITEM",IF(INDEX(Items!$O$5:$O$504,U49)<0,"NEG STOCK",IF(K49<INDEX(Items!$P$5:$P$504,U49),"BELOW COST","OK")))) -> OK | U49: =IF($D49="","",IFERROR(MATCH($D49,Items!$A$5:$A$504,0),"")) -> 8 | V49: =IF($C49="","",IFERROR(MATCH($C49,Parties!$A$5:$A$304,0),"")) -> 1 | W49: =IF($B49="","",IFERROR(VALUE(SUBSTITUTE($B49,InvPrefix,"")),0)) -> 34 | X49: =IF($D49="","",IF(OR($H49="",$H49="Credit"),0,Q49)) -> 0
A50: 46163 | B50: INV-0034 | C50: Sharma Kirana Store | D50: PVC Pipe 1in 6m | E50: 23 | G50: 0.05 | I50: Delivered | J50: =IF($D50="","",IFERROR(INDEX(Items!$D$5:$D$504,U50),"")) -> Pcs | K50: =IF($D50="","",IF($F50="",IFERROR(INDEX(Items!$H$5:$H$504,U50),0),$F50)) -> 297 | L50: =IF($D50="","",ROUND(N($E50)*K50*(1-N($G50)),2)) -> 6489.45 | M50: =IF($D50="","",IFERROR(INDEX(Items!$F$5:$F$504,U50),0)) -> 0.18 | N50: =IF($D50="","",IF(AND(V50<>"",INDEX(Parties!$E$5:$E$304,V50)<>"",INDEX(Parties!$E$5:$E$304,V50)<>HomeState),0,ROUND(L50*M50/2,2))) -> 584.05 | O50: =IF($D50="","",N50) -> 584.05 | P50: =IF($D50="","",IF(AND(V50<>"",INDEX(Parties!$E$5:$E$304,V50)<>"",INDEX(Parties!$E$5:$E$304,V50)<>HomeState),ROUND(L50*M50,2),0)) -> 0 | Q50: =IF($D50="","",L50+N50+O50+P50) -> 7657.55 | R50: =IF($D50="","",ROUND(N($E50)*IFERROR(INDEX(Items!$P$5:$P$504,U50),0),2)) -> 4821.57 | S50: =IF($D50="","",L50-R50) -> 1667.88 | T50: =IF($D50="","",IF(U50="","UNKNOWN ITEM",IF(INDEX(Items!$O$5:$O$504,U50)<0,"NEG STOCK",IF(K50<INDEX(Items!$P$5:$P$504,U50),"BELOW COST","OK")))) -> OK | U50: =IF($D50="","",IFERROR(MATCH($D50,Items!$A$5:$A$504,0),"")) -> 9 | V50: =IF($C50="","",IFERROR(MATCH($C50,Parties!$A$5:$A$304,0),"")) -> 1 | W50: =IF($B50="","",IFERROR(VALUE(SUBSTITUTE($B50,InvPrefix,"")),0)) -> 34 | X50: =IF($D50="","",IF(OR($H50="",$H50="Credit"),0,Q50)) -> 0
A51: 46164 | B51: INV-0035 | C51: Mehta Constructions | D51: PVC Pipe 1in 6m | E51: 25 | H51: UPI | I51: Delivered | J51: =IF($D51="","",IFERROR(INDEX(Items!$D$5:$D$504,U51),"")) -> Pcs | K51: =IF($D51="","",IF($F51="",IFERROR(INDEX(Items!$H$5:$H$504,U51),0),$F51)) -> 297 | L51: =IF($D51="","",ROUND(N($E51)*K51*(1-N($G51)),2)) -> 7425 | M51: =IF($D51="","",IFERROR(INDEX(Items!$F$5:$F$504,U51),0)) -> 0.18 | N51: =IF($D51="","",IF(AND(V51<>"",INDEX(Parties!$E$5:$E$304,V51)<>"",INDEX(Parties!$E$5:$E$304,V51)<>HomeState),0,ROUND(L51*M51/2,2))) -> 668.25 | O51: =IF($D51="","",N51) -> 668.25 | P51: =IF($D51="","",IF(AND(V51<>"",INDEX(Parties!$E$5:$E$304,V51)<>"",INDEX(Parties!$E$5:$E$304,V51)<>HomeState),ROUND(L51*M51,2),0)) -> 0 | Q51: =IF($D51="","",L51+N51+O51+P51) -> 8761.5 | R51: =IF($D51="","",ROUND(N($E51)*IFERROR(INDEX(Items!$P$5:$P$504,U51),0),2)) -> 5240.83 | S51: =IF($D51="","",L51-R51) -> 2184.17 | T51: =IF($D51="","",IF(U51="","UNKNOWN ITEM",IF(INDEX(Items!$O$5:$O$504,U51)<0,"NEG STOCK",IF(K51<INDEX(Items!$P$5:$P$504,U51),"BELOW COST","OK")))) -> OK | U51: =IF($D51="","",IFERROR(MATCH($D51,Items!$A$5:$A$504,0),"")) -> 9 | V51: =IF($C51="","",IFERROR(MATCH($C51,Parties!$A$5:$A$304,0),"")) -> 5 | W51: =IF($B51="","",IFERROR(VALUE(SUBSTITUTE($B51,InvPrefix,"")),0)) -> 35 | X51: =IF($D51="","",IF(OR($H51="",$H51="Credit"),0,Q51)) -> 8761.5
A52: 46164 | B52: INV-0035 | C52: Mehta Constructions | D52: Copper Wire 90m | E52: 3 | H52: UPI | I52: Delivered | J52: =IF($D52="","",IFERROR(INDEX(Items!$D$5:$D$504,U52),"")) -> Pcs | K52: =IF($D52="","",IF($F52="",IFERROR(INDEX(Items!$H$5:$H$504,U52),0),$F52)) -> 3132 | L52: =IF($D52="","",ROUND(N($E52)*K52*(1-N($G52)),2)) -> 9396 | M52: =IF($D52="","",IFERROR(INDEX(Items!$F$5:$F$504,U52),0)) -> 0.18 | N52: =IF($D52="","",IF(AND(V52<>"",INDEX(Parties!$E$5:$E$304,V52)<>"",INDEX(Parties!$E$5:$E$304,V52)<>HomeState),0,ROUND(L52*M52/2,2))) -> 845.64 | O52: =IF($D52="","",N52) -> 845.64 | P52: =IF($D52="","",IF(AND(V52<>"",INDEX(Parties!$E$5:$E$304,V52)<>"",INDEX(Parties!$E$5:$E$304,V52)<>HomeState),ROUND(L52*M52,2),0)) -> 0 | Q52: =IF($D52="","",L52+N52+O52+P52) -> 11087.28 | R52: =IF($D52="","",ROUND(N($E52)*IFERROR(INDEX(Items!$P$5:$P$504,U52),0),2)) -> 7354.45 | S52: =IF($D52="","",L52-R52) -> 2041.55 | T52: =IF($D52="","",IF(U52="","UNKNOWN ITEM",IF(INDEX(Items!$O$5:$O$504,U52)<0,"NEG STOCK",IF(K52<INDEX(Items!$P$5:$P$504,U52),"BELOW COST","OK")))) -> OK | U52: =IF($D52="","",IFERROR(MATCH($D52,Items!$A$5:$A$504,0),"")) -> 8 | V52: =IF($C52="","",IFERROR(MATCH($C52,Parties!$A$5:$A$304,0),"")) -> 5 | W52: =IF($B52="","",IFERROR(VALUE(SUBSTITUTE($B52,InvPrefix,"")),0)) -> 35 | X52: =IF($D52="","",IF(OR($H52="",$H52="Credit"),0,Q52)) -> 11087.28
A53: 46165 | B53: INV-0036 | C53: Walk-in Customer | D53: LED Bulb 9W | E53: 41 | G53: 0.02 | H53: Cash | I53: Delivered | J53: =IF($D53="","",IFERROR(INDEX(Items!$D$5:$D$504,U53),"")) -> Pcs | K53: =IF($D53="","",IF($F53="",IFERROR(INDEX(Items!$H$5:$H$504,U53),0),$F53)) -> 107 | L53: =IF($D53="","",ROUND(N($E53)*K53*(1-N($G53)),2)) -> 4299.26 | M53: =IF($D53="","",IFERROR(INDEX(Items!$F$5:$F$504,U53),0)) -> 0.18 | N53: =IF($D53="","",IF(AND(V53<>"",INDEX(Parties!$E$5:$E$304,V53)<>"",INDEX(Parties!$E$5:$E$304,V53)<>HomeState),0,ROUND(L53*M53/2,2))) -> 386.93 | O53: =IF($D53="","",N53) -> 386.93 | P53: =IF($D53="","",IF(AND(V53<>"",INDEX(Parties!$E$5:$E$304,V53)<>"",INDEX(Parties!$E$5:$E$304,V53)<>HomeState),ROUND(L53*M53,2),0)) -> 0 | Q53: =IF($D53="","",L53+N53+O53+P53) -> 5073.12 | R53: =IF($D53="","",ROUND(N($E53)*IFERROR(INDEX(Items!$P$5:$P$504,U53),0),2)) -> 2518.1 | S53: =IF($D53="","",L53-R53) -> 1781.16 | T53: =IF($D53="","",IF(U53="","UNKNOWN ITEM",IF(INDEX(Items!$O$5:$O$504,U53)<0,"NEG STOCK",IF(K53<INDEX(Items!$P$5:$P$504,U53),"BELOW COST","OK")))) -> OK | U53: =IF($D53="","",IFERROR(MATCH($D53,Items!$A$5:$A$504,0),"")) -> 7 | V53: =IF($C53="","",IFERROR(MATCH($C53,Parties!$A$5:$A$304,0),"")) -> 4 | W53: =IF($B53="","",IFERROR(VALUE(SUBSTITUTE($B53,InvPrefix,"")),0)) -> 36 | X53: =IF($D53="","",IF(OR($H53="",$H53="Credit"),0,Q53)) -> 5073.12
A54: 46167 | B54: INV-0037 | C54: Gupta Electricals | D54: Sugar 50kg | E54: 3 | I54: Delivered | J54: =IF($D54="","",IFERROR(INDEX(Items!$D$5:$D$504,U54),"")) -> Bag | K54: =IF($D54="","",IF($F54="",IFERROR(INDEX(Items!$H$5:$H$504,U54),0),$F54)) -> 2462 | L54: =IF($D54="","",ROUND(N($E54)*K54*(1-N($G54)),2)) -> 7386 | M54: =IF($D54="","",IFERROR(INDEX(Items!$F$5:$F$504,U54),0)) -> 0.05 | N54: =IF($D54="","",IF(AND(V54<>"",INDEX(Parties!$E$5:$E$304,V54)<>"",INDEX(Parties!$E$5:$E$304,V54)<>HomeState),0,ROUND(L54*M54/2,2))) -> 184.65 | O54: =IF($D54="","",N54) -> 184.65 | P54: =IF($D54="","",IF(AND(V54<>"",INDEX(Parties!$E$5:$E$304,V54)<>"",INDEX(Parties!$E$5:$E$304,V54)<>HomeState),ROUND(L54*M54,2),0)) -> 0 | Q54: =IF($D54="","",L54+N54+O54+P54) -> 7755.3 | R54: =IF($D54="","",ROUND(N($E54)*IFERROR(INDEX(Items!$P$5:$P$504,U54),0),2)) -> 6113.19 | S54: =IF($D54="","",L54-R54) -> 1272.81 | T54: =IF($D54="","",IF(U54="","UNKNOWN ITEM",IF(INDEX(Items!$O$5:$O$504,U54)<0,"NEG STOCK",IF(K54<INDEX(Items!$P$5:$P$504,U54),"BELOW COST","OK")))) -> OK | U54: =IF($D54="","",IFERROR(MATCH($D54,Items!$A$5:$A$504,0),"")) -> 2 | V54: =IF($C54="","",IFERROR(MATCH($C54,Parties!$A$5:$A$304,0),"")) -> 2 | W54: =IF($B54="","",IFERROR(VALUE(SUBSTITUTE($B54,InvPrefix,"")),0)) -> 37 | X54: =IF($D54="","",IF(OR($H54="",$H54="Credit"),0,Q54)) -> 0
A55: 46169 | B55: INV-0038 | C55: FMCG Distributors | D55: Refined Oil 15L | E55: 8 | I55: Delivered | J55: =IF($D55="","",IFERROR(INDEX(Items!$D$5:$D$504,U55),"")) -> Box | K55: =IF($D55="","",IF($F55="",IFERROR(INDEX(Items!$H$5:$H$504,U55),0),$F55)) -> 2290 | L55: =IF($D55="","",ROUND(N($E55)*K55*(1-N($G55)),2)) -> 18320 | M55: =IF($D55="","",IFERROR(INDEX(Items!$F$5:$F$504,U55),0)) -> 0.05 | N55: =IF($D55="","",IF(AND(V55<>"",INDEX(Parties!$E$5:$E$304,V55)<>"",INDEX(Parties!$E$5:$E$304,V55)<>HomeState),0,ROUND(L55*M55/2,2))) -> 458 | O55: =IF($D55="","",N55) -> 458 | P55: =IF($D55="","",IF(AND(V55<>"",INDEX(Parties!$E$5:$E$304,V55)<>"",INDEX(Parties!$E$5:$E$304,V55)<>HomeState),ROUND(L55*M55,2),0)) -> 0 | Q55: =IF($D55="","",L55+N55+O55+P55) -> 19236 | R55: =IF($D55="","",ROUND(N($E55)*IFERROR(INDEX(Items!$P$5:$P$504,U55),0),2)) -> 15234.9 | S55: =IF($D55="","",L55-R55) -> 3085.1 | T55: =IF($D55="","",IF(U55="","UNKNOWN ITEM",IF(INDEX(Items!$O$5:$O$504,U55)<0,"NEG STOCK",IF(K55<INDEX(Items!$P$5:$P$504,U55),"BELOW COST","OK")))) -> OK | U55: =IF($D55="","",IFERROR(MATCH($D55,Items!$A$5:$A$504,0),"")) -> 3 | V55: =IF($C55="","",IFERROR(MATCH($C55,Parties!$A$5:$A$304,0),"")) -> 9 | W55: =IF($B55="","",IFERROR(VALUE(SUBSTITUTE($B55,InvPrefix,"")),0)) -> 38 | X55: =IF($D55="","",IF(OR($H55="",$H55="Credit"),0,Q55)) -> 0
A56: 46171 | B56: INV-0039 | C56: Walk-in Customer | D56: A4 Paper Ream | E56: 24 | H56: Cash | I56: Delivered | J56: =IF($D56="","",IFERROR(INDEX(Items!$D$5:$D$504,U56),"")) -> Pack | K56: =IF($D56="","",IF($F56="",IFERROR(INDEX(Items!$H$5:$H$504,U56),0),$F56)) -> 335 | L56: =IF($D56="","",ROUND(N($E56)*K56*(1-N($G56)),2)) -> 8040 | M56: =IF($D56="","",IFERROR(INDEX(Items!$F$5:$F$504,U56),0)) -> 0.12 | N56: =IF($D56="","",IF(AND(V56<>"",INDEX(Parties!$E$5:$E$304,V56)<>"",INDEX(Parties!$E$5:$E$304,V56)<>HomeState),0,ROUND(L56*M56/2,2))) -> 482.4 | O56: =IF($D56="","",N56) -> 482.4 | P56: =IF($D56="","",IF(AND(V56<>"",INDEX(Parties!$E$5:$E$304,V56)<>"",INDEX(Parties!$E$5:$E$304,V56)<>HomeState),ROUND(L56*M56,2),0)) -> 0 | Q56: =IF($D56="","",L56+N56+O56+P56) -> 9004.8 | R56: =IF($D56="","",ROUND(N($E56)*IFERROR(INDEX(Items!$P$5:$P$504,U56),0),2)) -> 5760 | S56: =IF($D56="","",L56-R56) -> 2280 | T56: =IF($D56="","",IF(U56="","UNKNOWN ITEM",IF(INDEX(Items!$O$5:$O$504,U56)<0,"NEG STOCK",IF(K56<INDEX(Items!$P$5:$P$504,U56),"BELOW COST","OK")))) -> OK | U56: =IF($D56="","",IFERROR(MATCH($D56,Items!$A$5:$A$504,0),"")) -> 11 | V56: =IF($C56="","",IFERROR(MATCH($C56,Parties!$A$5:$A$304,0),"")) -> 4 | W56: =IF($B56="","",IFERROR(VALUE(SUBSTITUTE($B56,InvPrefix,"")),0)) -> 39 | X56: =IF($D56="","",IF(OR($H56="",$H56="Credit"),0,Q56)) -> 9004.8
A57: 46172 | B57: INV-0040 | C57: Walk-in Customer | D57: LED Bulb 9W | E57: 45 | H57: Cash | I57: Delivered | J57: =IF($D57="","",IFERROR(INDEX(Items!$D$5:$D$504,U57),"")) -> Pcs | K57: =IF($D57="","",IF($F57="",IFERROR(INDEX(Items!$H$5:$H$504,U57),0),$F57)) -> 107 | L57: =IF($D57="","",ROUND(N($E57)*K57*(1-N($G57)),2)) -> 4815 | M57: =IF($D57="","",IFERROR(INDEX(Items!$F$5:$F$504,U57),0)) -> 0.18 | N57: =IF($D57="","",IF(AND(V57<>"",INDEX(Parties!$E$5:$E$304,V57)<>"",INDEX(Parties!$E$5:$E$304,V57)<>HomeState),0,ROUND(L57*M57/2,2))) -> 433.35 | O57: =IF($D57="","",N57) -> 433.35 | P57: =IF($D57="","",IF(AND(V57<>"",INDEX(Parties!$E$5:$E$304,V57)<>"",INDEX(Parties!$E$5:$E$304,V57)<>HomeState),ROUND(L57*M57,2),0)) -> 0 | Q57: =IF($D57="","",L57+N57+O57+P57) -> 5681.7 | R57: =IF($D57="","",ROUND(N($E57)*IFERROR(INDEX(Items!$P$5:$P$504,U57),0),2)) -> 2763.77 | S57: =IF($D57="","",L57-R57) -> 2051.23 | T57: =IF($D57="","",IF(U57="","UNKNOWN ITEM",IF(INDEX(Items!$O$5:$O$504,U57)<0,"NEG STOCK",IF(K57<INDEX(Items!$P$5:$P$504,U57),"BELOW COST","OK")))) -> OK | U57: =IF($D57="","",IFERROR(MATCH($D57,Items!$A$5:$A$504,0),"")) -> 7 | V57: =IF($C57="","",IFERROR(MATCH($C57,Parties!$A$5:$A$304,0),"")) -> 4 | W57: =IF($B57="","",IFERROR(VALUE(SUBSTITUTE($B57,InvPrefix,"")),0)) -> 40 | X57: =IF($D57="","",IF(OR($H57="",$H57="Credit"),0,Q57)) -> 5681.7
A58: 46174 | B58: INV-0041 | C58: Gupta Electricals | D58: Sugar 50kg | E58: 3 | I58: Delivered | J58: =IF($D58="","",IFERROR(INDEX(Items!$D$5:$D$504,U58),"")) -> Bag | K58: =IF($D58="","",IF($F58="",IFERROR(INDEX(Items!$H$5:$H$504,U58),0),$F58)) -> 2462 | L58: =IF($D58="","",ROUND(N($E58)*K58*(1-N($G58)),2)) -> 7386 | M58: =IF($D58="","",IFERROR(INDEX(Items!$F$5:$F$504,U58),0)) -> 0.05 | N58: =IF($D58="","",IF(AND(V58<>"",INDEX(Parties!$E$5:$E$304,V58)<>"",INDEX(Parties!$E$5:$E$304,V58)<>HomeState),0,ROUND(L58*M58/2,2))) -> 184.65 | O58: =IF($D58="","",N58) -> 184.65 | P58: =IF($D58="","",IF(AND(V58<>"",INDEX(Parties!$E$5:$E$304,V58)<>"",INDEX(Parties!$E$5:$E$304,V58)<>HomeState),ROUND(L58*M58,2),0)) -> 0 | Q58: =IF($D58="","",L58+N58+O58+P58) -> 7755.3 | R58: =IF($D58="","",ROUND(N($E58)*IFERROR(INDEX(Items!$P$5:$P$504,U58),0),2)) -> 6113.19 | S58: =IF($D58="","",L58-R58) -> 1272.81 | T58: =IF($D58="","",IF(U58="","UNKNOWN ITEM",IF(INDEX(Items!$O$5:$O$504,U58)<0,"NEG STOCK",IF(K58<INDEX(Items!$P$5:$P$504,U58),"BELOW COST","OK")))) -> OK | U58: =IF($D58="","",IFERROR(MATCH($D58,Items!$A$5:$A$504,0),"")) -> 2 | V58: =IF($C58="","",IFERROR(MATCH($C58,Parties!$A$5:$A$304,0),"")) -> 2 | W58: =IF($B58="","",IFERROR(VALUE(SUBSTITUTE($B58,InvPrefix,"")),0)) -> 41 | X58: =IF($D58="","",IF(OR($H58="",$H58="Credit"),0,Q58)) -> 0
A59: 46176 | B59: INV-0042 | C59: Mehta Constructions | D59: A4 Paper Ream | E59: 24 | I59: Delivered | J59: =IF($D59="","",IFERROR(INDEX(Items!$D$5:$D$504,U59),"")) -> Pack | K59: =IF($D59="","",IF($F59="",IFERROR(INDEX(Items!$H$5:$H$504,U59),0),$F59)) -> 335 | L59: =IF($D59="","",ROUND(N($E59)*K59*(1-N($G59)),2)) -> 8040 | M59: =IF($D59="","",IFERROR(INDEX(Items!$F$5:$F$504,U59),0)) -> 0.12 | N59: =IF($D59="","",IF(AND(V59<>"",INDEX(Parties!$E$5:$E$304,V59)<>"",INDEX(Parties!$E$5:$E$304,V59)<>HomeState),0,ROUND(L59*M59/2,2))) -> 482.4 | O59: =IF($D59="","",N59) -> 482.4 | P59: =IF($D59="","",IF(AND(V59<>"",INDEX(Parties!$E$5:$E$304,V59)<>"",INDEX(Parties!$E$5:$E$304,V59)<>HomeState),ROUND(L59*M59,2),0)) -> 0 | Q59: =IF($D59="","",L59+N59+O59+P59) -> 9004.8 | R59: =IF($D59="","",ROUND(N($E59)*IFERROR(INDEX(Items!$P$5:$P$504,U59),0),2)) -> 5760 | S59: =IF($D59="","",L59-R59) -> 2280 | T59: =IF($D59="","",IF(U59="","UNKNOWN ITEM",IF(INDEX(Items!$O$5:$O$504,U59)<0,"NEG STOCK",IF(K59<INDEX(Items!$P$5:$P$504,U59),"BELOW COST","OK")))) -> OK | U59: =IF($D59="","",IFERROR(MATCH($D59,Items!$A$5:$A$504,0),"")) -> 11 | V59: =IF($C59="","",IFERROR(MATCH($C59,Parties!$A$5:$A$304,0),"")) -> 5 | W59: =IF($B59="","",IFERROR(VALUE(SUBSTITUTE($B59,InvPrefix,"")),0)) -> 42 | X59: =IF($D59="","",IF(OR($H59="",$H59="Credit"),0,Q59)) -> 0
A60: 46177 | B60: INV-0043 | C60: Delhi Hardware Mart | D60: Cement 50kg | E60: 36 | H60: Bank | I60: Delivered | J60: =IF($D60="","",IFERROR(INDEX(Items!$D$5:$D$504,U60),"")) -> Bag | K60: =IF($D60="","",IF($F60="",IFERROR(INDEX(Items!$H$5:$H$504,U60),0),$F60)) -> 427 | L60: =IF($D60="","",ROUND(N($E60)*K60*(1-N($G60)),2)) -> 15372 | M60: =IF($D60="","",IFERROR(INDEX(Items!$F$5:$F$504,U60),0)) -> 0.18 | N60: =IF($D60="","",IF(AND(V60<>"",INDEX(Parties!$E$5:$E$304,V60)<>"",INDEX(Parties!$E$5:$E$304,V60)<>HomeState),0,ROUND(L60*M60/2,2))) -> 0 | O60: =IF($D60="","",N60) -> 0 | P60: =IF($D60="","",IF(AND(V60<>"",INDEX(Parties!$E$5:$E$304,V60)<>"",INDEX(Parties!$E$5:$E$304,V60)<>HomeState),ROUND(L60*M60,2),0)) -> 2766.96 | Q60: =IF($D60="","",L60+N60+O60+P60) -> 18138.96 | R60: =IF($D60="","",ROUND(N($E60)*IFERROR(INDEX(Items!$P$5:$P$504,U60),0),2)) -> 12246.27 | S60: =IF($D60="","",L60-R60) -> 3125.73 | T60: =IF($D60="","",IF(U60="","UNKNOWN ITEM",IF(INDEX(Items!$O$5:$O$504,U60)<0,"NEG STOCK",IF(K60<INDEX(Items!$P$5:$P$504,U60),"BELOW COST","OK")))) -> OK | U60: =IF($D60="","",IFERROR(MATCH($D60,Items!$A$5:$A$504,0),"")) -> 10 | V60: =IF($C60="","",IFERROR(MATCH($C60,Parties!$A$5:$A$304,0),"")) -> 3 | W60: =IF($B60="","",IFERROR(VALUE(SUBSTITUTE($B60,InvPrefix,"")),0)) -> 43 | X60: =IF($D60="","",IF(OR($H60="",$H60="Credit"),0,Q60)) -> 18138.96
A61: 46177 | B61: INV-0043 | C61: Delhi Hardware Mart | D61: Copper Wire 90m | E61: 2 | H61: Bank | I61: Delivered | J61: =IF($D61="","",IFERROR(INDEX(Items!$D$5:$D$504,U61),"")) -> Pcs | K61: =IF($D61="","",IF($F61="",IFERROR(INDEX(Items!$H$5:$H$504,U61),0),$F61)) -> 3132 | L61: =IF($D61="","",ROUND(N($E61)*K61*(1-N($G61)),2)) -> 6264 | M61: =IF($D61="","",IFERROR(INDEX(Items!$F$5:$F$504,U61),0)) -> 0.18 | N61: =IF($D61="","",IF(AND(V61<>"",INDEX(Parties!$E$5:$E$304,V61)<>"",INDEX(Parties!$E$5:$E$304,V61)<>HomeState),0,ROUND(L61*M61/2,2))) -> 0 | O61: =IF($D61="","",N61) -> 0 | P61: =IF($D61="","",IF(AND(V61<>"",INDEX(Parties!$E$5:$E$304,V61)<>"",INDEX(Parties!$E$5:$E$304,V61)<>HomeState),ROUND(L61*M61,2),0)) -> 1127.52 | Q61: =IF($D61="","",L61+N61+O61+P61) -> 7391.52 | R61: =IF($D61="","",ROUND(N($E61)*IFERROR(INDEX(Items!$P$5:$P$504,U61),0),2)) -> 4902.96 | S61: =IF($D61="","",L61-R61) -> 1361.04 | T61: =IF($D61="","",IF(U61="","UNKNOWN ITEM",IF(INDEX(Items!$O$5:$O$504,U61)<0,"NEG STOCK",IF(K61<INDEX(Items!$P$5:$P$504,U61),"BELOW COST","OK")))) -> OK | U61: =IF($D61="","",IFERROR(MATCH($D61,Items!$A$5:$A$504,0),"")) -> 8 | V61: =IF($C61="","",IFERROR(MATCH($C61,Parties!$A$5:$A$304,0),"")) -> 3 | W61: =IF($B61="","",IFERROR(VALUE(SUBSTITUTE($B61,InvPrefix,"")),0)) -> 43 | X61: =IF($D61="","",IF(OR($H61="",$H61="Credit"),0,Q61)) -> 7391.52
A62: 46179 | B62: INV-0045 | C62: Gupta Electricals | D62: Copper Wire 90m | E62: 1 | G62: 0.05 | I62: Delivered | J62: =IF($D62="","",IFERROR(INDEX(Items!$D$5:$D$504,U62),"")) -> Pcs | K62: =IF($D62="","",IF($F62="",IFERROR(INDEX(Items!$H$5:$H$504,U62),0),$F62)) -> 3132 | L62: =IF($D62="","",ROUND(N($E62)*K62*(1-N($G62)),2)) -> 2975.4 | M62: =IF($D62="","",IFERROR(INDEX(Items!$F$5:$F$504,U62),0)) -> 0.18 | N62: =IF($D62="","",IF(AND(V62<>"",INDEX(Parties!$E$5:$E$304,V62)<>"",INDEX(Parties!$E$5:$E$304,V62)<>HomeState),0,ROUND(L62*M62/2,2))) -> 267.79 | O62: =IF($D62="","",N62) -> 267.79 | P62: =IF($D62="","",IF(AND(V62<>"",INDEX(Parties!$E$5:$E$304,V62)<>"",INDEX(Parties!$E$5:$E$304,V62)<>HomeState),ROUND(L62*M62,2),0)) -> 0 | Q62: =IF($D62="","",L62+N62+O62+P62) -> 3510.98 | R62: =IF($D62="","",ROUND(N($E62)*IFERROR(INDEX(Items!$P$5:$P$504,U62),0),2)) -> 2451.48 | S62: =IF($D62="","",L62-R62) -> 523.92 | T62: =IF($D62="","",IF(U62="","UNKNOWN ITEM",IF(INDEX(Items!$O$5:$O$504,U62)<0,"NEG STOCK",IF(K62<INDEX(Items!$P$5:$P$504,U62),"BELOW COST","OK")))) -> OK | U62: =IF($D62="","",IFERROR(MATCH($D62,Items!$A$5:$A$504,0),"")) -> 8 | V62: =IF($C62="","",IFERROR(MATCH($C62,Parties!$A$5:$A$304,0),"")) -> 2 | W62: =IF($B62="","",IFERROR(VALUE(SUBSTITUTE($B62,InvPrefix,"")),0)) -> 45 | X62: =IF($D62="","",IF(OR($H62="",$H62="Credit"),0,Q62)) -> 0
A63: 46181 | B63: INV-0046 | C63: Mehta Constructions | D63: Basmati Rice 25kg | E63: 6 | H63: Bank | I63: Delivered | J63: =IF($D63="","",IFERROR(INDEX(Items!$D$5:$D$504,U63),"")) -> Bag | K63: =IF($D63="","",IF($F63="",IFERROR(INDEX(Items!$H$5:$H$504,U63),0),$F63)) -> 2106 | L63: =IF($D63="","",ROUND(N($E63)*K63*(1-N($G63)),2)) -> 12636 | M63: =IF($D63="","",IFERROR(INDEX(Items!$F$5:$F$504,U63),0)) -> 0.05 | N63: =IF($D63="","",IF(AND(V63<>"",INDEX(Parties!$E$5:$E$304,V63)<>"",INDEX(Parties!$E$5:$E$304,V63)<>HomeState),0,ROUND(L63*M63/2,2))) -> 315.9 | O63: =IF($D63="","",N63) -> 315.9 | P63: =IF($D63="","",IF(AND(V63<>"",INDEX(Parties!$E$5:$E$304,V63)<>"",INDEX(Parties!$E$5:$E$304,V63)<>HomeState),ROUND(L63*M63,2),0)) -> 0 | Q63: =IF($D63="","",L63+N63+O63+P63) -> 13267.8 | R63: =IF($D63="","",ROUND(N($E63)*IFERROR(INDEX(Items!$P$5:$P$504,U63),0),2)) -> 9884.58 | S63: =IF($D63="","",L63-R63) -> 2751.42 | T63: =IF($D63="","",IF(U63="","UNKNOWN ITEM",IF(INDEX(Items!$O$5:$O$504,U63)<0,"NEG STOCK",IF(K63<INDEX(Items!$P$5:$P$504,U63),"BELOW COST","OK")))) -> OK | U63: =IF($D63="","",IFERROR(MATCH($D63,Items!$A$5:$A$504,0),"")) -> 1 | V63: =IF($C63="","",IFERROR(MATCH($C63,Parties!$A$5:$A$304,0),"")) -> 5 | W63: =IF($B63="","",IFERROR(VALUE(SUBSTITUTE($B63,InvPrefix,"")),0)) -> 46 | X63: =IF($D63="","",IF(OR($H63="",$H63="Credit"),0,Q63)) -> 13267.8
A64: 46183 | B64: INV-0047 | C64: Mehta Constructions | D64: Tea Premium 1kg | E64: 17 | I64: Delivered | J64: =IF($D64="","",IFERROR(INDEX(Items!$D$5:$D$504,U64),"")) -> Pack | K64: =IF($D64="","",IF($F64="",IFERROR(INDEX(Items!$H$5:$H$504,U64),0),$F64)) -> 508 | L64: =IF($D64="","",ROUND(N($E64)*K64*(1-N($G64)),2)) -> 8636 | M64: =IF($D64="","",IFERROR(INDEX(Items!$F$5:$F$504,U64),0)) -> 0.05 | N64: =IF($D64="","",IF(AND(V64<>"",INDEX(Parties!$E$5:$E$304,V64)<>"",INDEX(Parties!$E$5:$E$304,V64)<>HomeState),0,ROUND(L64*M64/2,2))) -> 215.9 | O64: =IF($D64="","",N64) -> 215.9 | P64: =IF($D64="","",IF(AND(V64<>"",INDEX(Parties!$E$5:$E$304,V64)<>"",INDEX(Parties!$E$5:$E$304,V64)<>HomeState),ROUND(L64*M64,2),0)) -> 0 | Q64: =IF($D64="","",L64+N64+O64+P64) -> 9067.8 | R64: =IF($D64="","",ROUND(N($E64)*IFERROR(INDEX(Items!$P$5:$P$504,U64),0),2)) -> 6410.34 | S64: =IF($D64="","",L64-R64) -> 2225.66 | T64: =IF($D64="","",IF(U64="","UNKNOWN ITEM",IF(INDEX(Items!$O$5:$O$504,U64)<0,"NEG STOCK",IF(K64<INDEX(Items!$P$5:$P$504,U64),"BELOW COST","OK")))) -> OK | U64: =IF($D64="","",IFERROR(MATCH($D64,Items!$A$5:$A$504,0),"")) -> 4 | V64: =IF($C64="","",IFERROR(MATCH($C64,Parties!$A$5:$A$304,0),"")) -> 5 | W64: =IF($B64="","",IFERROR(VALUE(SUBSTITUTE($B64,InvPrefix,"")),0)) -> 47 | X64: =IF($D64="","",IF(OR($H64="",$H64="Credit"),0,Q64)) -> 0
A65: 46184 | B65: INV-0048 | C65: Walk-in Customer | D65: LED Bulb 9W | E65: 51 | H65: Cash | I65: Delivered | J65: =IF($D65="","",IFERROR(INDEX(Items!$D$5:$D$504,U65),"")) -> Pcs | K65: =IF($D65="","",IF($F65="",IFERROR(INDEX(Items!$H$5:$H$504,U65),0),$F65)) -> 107 | L65: =IF($D65="","",ROUND(N($E65)*K65*(1-N($G65)),2)) -> 5457 | M65: =IF($D65="","",IFERROR(INDEX(Items!$F$5:$F$504,U65),0)) -> 0.18 | N65: =IF($D65="","",IF(AND(V65<>"",INDEX(Parties!$E$5:$E$304,V65)<>"",INDEX(Parties!$E$5:$E$304,V65)<>HomeState),0,ROUND(L65*M65/2,2))) -> 491.13 | O65: =IF($D65="","",N65) -> 491.13 | P65: =IF($D65="","",IF(AND(V65<>"",INDEX(Parties!$E$5:$E$304,V65)<>"",INDEX(Parties!$E$5:$E$304,V65)<>HomeState),ROUND(L65*M65,2),0)) -> 0 | Q65: =IF($D65="","",L65+N65+O65+P65) -> 6439.26 | R65: =IF($D65="","",ROUND(N($E65)*IFERROR(INDEX(Items!$P$5:$P$504,U65),0),2)) -> 3132.27 | S65: =IF($D65="","",L65-R65) -> 2324.73 | T65: =IF($D65="","",IF(U65="","UNKNOWN ITEM",IF(INDEX(Items!$O$5:$O$504,U65)<0,"NEG STOCK",IF(K65<INDEX(Items!$P$5:$P$504,U65),"BELOW COST","OK")))) -> OK | U65: =IF($D65="","",IFERROR(MATCH($D65,Items!$A$5:$A$504,0),"")) -> 7 | V65: =IF($C65="","",IFERROR(MATCH($C65,Parties!$A$5:$A$304,0),"")) -> 4 | W65: =IF($B65="","",IFERROR(VALUE(SUBSTITUTE($B65,InvPrefix,"")),0)) -> 48 | X65: =IF($D65="","",IF(OR($H65="",$H65="Credit"),0,Q65)) -> 6439.26
A66: 46184 | B66: INV-0048 | C66: Walk-in Customer | D66: PVC Pipe 1in 6m | E66: 35 | H66: Cash | I66: Delivered | J66: =IF($D66="","",IFERROR(INDEX(Items!$D$5:$D$504,U66),"")) -> Pcs | K66: =IF($D66="","",IF($F66="",IFERROR(INDEX(Items!$H$5:$H$504,U66),0),$F66)) -> 297 | L66: =IF($D66="","",ROUND(N($E66)*K66*(1-N($G66)),2)) -> 10395 | M66: =IF($D66="","",IFERROR(INDEX(Items!$F$5:$F$504,U66),0)) -> 0.18 | N66: =IF($D66="","",IF(AND(V66<>"",INDEX(Parties!$E$5:$E$304,V66)<>"",INDEX(Parties!$E$5:$E$304,V66)<>HomeState),0,ROUND(L66*M66/2,2))) -> 935.55 | O66: =IF($D66="","",N66) -> 935.55 | P66: =IF($D66="","",IF(AND(V66<>"",INDEX(Parties!$E$5:$E$304,V66)<>"",INDEX(Parties!$E$5:$E$304,V66)<>HomeState),ROUND(L66*M66,2),0)) -> 0 | Q66: =IF($D66="","",L66+N66+O66+P66) -> 12266.1 | R66: =IF($D66="","",ROUND(N($E66)*IFERROR(INDEX(Items!$P$5:$P$504,U66),0),2)) -> 7337.16 | S66: =IF($D66="","",L66-R66) -> 3057.84 | T66: =IF($D66="","",IF(U66="","UNKNOWN ITEM",IF(INDEX(Items!$O$5:$O$504,U66)<0,"NEG STOCK",IF(K66<INDEX(Items!$P$5:$P$504,U66),"BELOW COST","OK")))) -> OK | U66: =IF($D66="","",IFERROR(MATCH($D66,Items!$A$5:$A$504,0),"")) -> 9 | V66: =IF($C66="","",IFERROR(MATCH($C66,Parties!$A$5:$A$304,0),"")) -> 4 | W66: =IF($B66="","",IFERROR(VALUE(SUBSTITUTE($B66,InvPrefix,"")),0)) -> 48 | X66: =IF($D66="","",IF(OR($H66="",$H66="Credit"),0,Q66)) -> 12266.1
A67: 46185 | B67: INV-0049 | C67: Delhi Hardware Mart | D67: Basmati Rice 25kg | E67: 8 | H67: UPI | I67: Delivered | J67: =IF($D67="","",IFERROR(INDEX(Items!$D$5:$D$504,U67),"")) -> Bag | K67: =IF($D67="","",IF($F67="",IFERROR(INDEX(Items!$H$5:$H$504,U67),0),$F67)) -> 2106 | L67: =IF($D67="","",ROUND(N($E67)*K67*(1-N($G67)),2)) -> 16848 | M67: =IF($D67="","",IFERROR(INDEX(Items!$F$5:$F$504,U67),0)) -> 0.05 | N67: =IF($D67="","",IF(AND(V67<>"",INDEX(Parties!$E$5:$E$304,V67)<>"",INDEX(Parties!$E$5:$E$304,V67)<>HomeState),0,ROUND(L67*M67/2,2))) -> 0 | O67: =IF($D67="","",N67) -> 0 | P67: =IF($D67="","",IF(AND(V67<>"",INDEX(Parties!$E$5:$E$304,V67)<>"",INDEX(Parties!$E$5:$E$304,V67)<>HomeState),ROUND(L67*M67,2),0)) -> 842.4 | Q67: =IF($D67="","",L67+N67+O67+P67) -> 17690.4 | R67: =IF($D67="","",ROUND(N($E67)*IFERROR(INDEX(Items!$P$5:$P$504,U67),0),2)) -> 13179.44 | S67: =IF($D67="","",L67-R67) -> 3668.56 | T67: =IF($D67="","",IF(U67="","UNKNOWN ITEM",IF(INDEX(Items!$O$5:$O$504,U67)<0,"NEG STOCK",IF(K67<INDEX(Items!$P$5:$P$504,U67),"BELOW COST","OK")))) -> OK | U67: =IF($D67="","",IFERROR(MATCH($D67,Items!$A$5:$A$504,0),"")) -> 1 | V67: =IF($C67="","",IFERROR(MATCH($C67,Parties!$A$5:$A$304,0),"")) -> 3 | W67: =IF($B67="","",IFERROR(VALUE(SUBSTITUTE($B67,InvPrefix,"")),0)) -> 49 | X67: =IF($D67="","",IF(OR($H67="",$H67="Credit"),0,Q67)) -> 17690.4
A68: 46188 | B68: INV-0050 | C68: Walk-in Customer | D68: Basmati Rice 25kg | E68: 3 | G68: 0.02 | H68: Cash | I68: Delivered | J68: =IF($D68="","",IFERROR(INDEX(Items!$D$5:$D$504,U68),"")) -> Bag | K68: =IF($D68="","",IF($F68="",IFERROR(INDEX(Items!$H$5:$H$504,U68),0),$F68)) -> 2106 | L68: =IF($D68="","",ROUND(N($E68)*K68*(1-N($G68)),2)) -> 6191.64 | M68: =IF($D68="","",IFERROR(INDEX(Items!$F$5:$F$504,U68),0)) -> 0.05 | N68: =IF($D68="","",IF(AND(V68<>"",INDEX(Parties!$E$5:$E$304,V68)<>"",INDEX(Parties!$E$5:$E$304,V68)<>HomeState),0,ROUND(L68*M68/2,2))) -> 154.79 | O68: =IF($D68="","",N68) -> 154.79 | P68: =IF($D68="","",IF(AND(V68<>"",INDEX(Parties!$E$5:$E$304,V68)<>"",INDEX(Parties!$E$5:$E$304,V68)<>HomeState),ROUND(L68*M68,2),0)) -> 0 | Q68: =IF($D68="","",L68+N68+O68+P68) -> 6501.22 | R68: =IF($D68="","",ROUND(N($E68)*IFERROR(INDEX(Items!$P$5:$P$504,U68),0),2)) -> 4942.29 | S68: =IF($D68="","",L68-R68) -> 1249.35 | T68: =IF($D68="","",IF(U68="","UNKNOWN ITEM",IF(INDEX(Items!$O$5:$O$504,U68)<0,"NEG STOCK",IF(K68<INDEX(Items!$P$5:$P$504,U68),"BELOW COST","OK")))) -> OK | U68: =IF($D68="","",IFERROR(MATCH($D68,Items!$A$5:$A$504,0),"")) -> 1 | V68: =IF($C68="","",IFERROR(MATCH($C68,Parties!$A$5:$A$304,0),"")) -> 4 | W68: =IF($B68="","",IFERROR(VALUE(SUBSTITUTE($B68,InvPrefix,"")),0)) -> 50 | X68: =IF($D68="","",IF(OR($H68="",$H68="Credit"),0,Q68)) -> 6501.22
A69: 46189 | B69: INV-0051 | C69: Walk-in Customer | D69: Detergent 5kg | E69: 9 | H69: Cash | I69: Delivered | J69: =IF($D69="","",IFERROR(INDEX(Items!$D$5:$D$504,U69),"")) -> Pack | K69: =IF($D69="","",IF($F69="",IFERROR(INDEX(Items!$H$5:$H$504,U69),0),$F69)) -> 691 | L69: =IF($D69="","",ROUND(N($E69)*K69*(1-N($G69)),2)) -> 6219 | M69: =IF($D69="","",IFERROR(INDEX(Items!$F$5:$F$504,U69),0)) -> 0.18 | N69: =IF($D69="","",IF(AND(V69<>"",INDEX(Parties!$E$5:$E$304,V69)<>"",INDEX(Parties!$E$5:$E$304,V69)<>HomeState),0,ROUND(L69*M69/2,2))) -> 559.71 | O69: =IF($D69="","",N69) -> 559.71 | P69: =IF($D69="","",IF(AND(V69<>"",INDEX(Parties!$E$5:$E$304,V69)<>"",INDEX(Parties!$E$5:$E$304,V69)<>HomeState),ROUND(L69*M69,2),0)) -> 0 | Q69: =IF($D69="","",L69+N69+O69+P69) -> 7338.42 | R69: =IF($D69="","",ROUND(N($E69)*IFERROR(INDEX(Items!$P$5:$P$504,U69),0),2)) -> 4659.23 | S69: =IF($D69="","",L69-R69) -> 1559.77 | T69: =IF($D69="","",IF(U69="","UNKNOWN ITEM",IF(INDEX(Items!$O$5:$O$504,U69)<0,"NEG STOCK",IF(K69<INDEX(Items!$P$5:$P$504,U69),"BELOW COST","OK")))) -> OK | U69: =IF($D69="","",IFERROR(MATCH($D69,Items!$A$5:$A$504,0),"")) -> 5 | V69: =IF($C69="","",IFERROR(MATCH($C69,Parties!$A$5:$A$304,0),"")) -> 4 | W69: =IF($B69="","",IFERROR(VALUE(SUBSTITUTE($B69,InvPrefix,"")),0)) -> 51 | X69: =IF($D69="","",IF(OR($H69="",$H69="Credit"),0,Q69)) -> 7338.42
A70: 46189 | B70: INV-0051 | C70: Walk-in Customer | D70: Basmati Rice 25kg | E70: 4 | H70: Cash | I70: Delivered | J70: =IF($D70="","",IFERROR(INDEX(Items!$D$5:$D$504,U70),"")) -> Bag | K70: =IF($D70="","",IF($F70="",IFERROR(INDEX(Items!$H$5:$H$504,U70),0),$F70)) -> 2106 | L70: =IF($D70="","",ROUND(N($E70)*K70*(1-N($G70)),2)) -> 8424 | M70: =IF($D70="","",IFERROR(INDEX(Items!$F$5:$F$504,U70),0)) -> 0.05 | N70: =IF($D70="","",IF(AND(V70<>"",INDEX(Parties!$E$5:$E$304,V70)<>"",INDEX(Parties!$E$5:$E$304,V70)<>HomeState),0,ROUND(L70*M70/2,2))) -> 210.6 | O70: =IF($D70="","",N70) -> 210.6 | P70: =IF($D70="","",IF(AND(V70<>"",INDEX(Parties!$E$5:$E$304,V70)<>"",INDEX(Parties!$E$5:$E$304,V70)<>HomeState),ROUND(L70*M70,2),0)) -> 0 | Q70: =IF($D70="","",L70+N70+O70+P70) -> 8845.2 | R70: =IF($D70="","",ROUND(N($E70)*IFERROR(INDEX(Items!$P$5:$P$504,U70),0),2)) -> 6589.72 | S70: =IF($D70="","",L70-R70) -> 1834.28 | T70: =IF($D70="","",IF(U70="","UNKNOWN ITEM",IF(INDEX(Items!$O$5:$O$504,U70)<0,"NEG STOCK",IF(K70<INDEX(Items!$P$5:$P$504,U70),"BELOW COST","OK")))) -> OK | U70: =IF($D70="","",IFERROR(MATCH($D70,Items!$A$5:$A$504,0),"")) -> 1 | V70: =IF($C70="","",IFERROR(MATCH($C70,Parties!$A$5:$A$304,0),"")) -> 4 | W70: =IF($B70="","",IFERROR(VALUE(SUBSTITUTE($B70,InvPrefix,"")),0)) -> 51 | X70: =IF($D70="","",IF(OR($H70="",$H70="Credit"),0,Q70)) -> 8845.2
A71: 46190 | B71: INV-0052 | C71: FMCG Distributors | D71: Toothpaste 150g x12 | E71: 3 | I71: Delivered | J71: =IF($D71="","",IFERROR(INDEX(Items!$D$5:$D$504,U71),"")) -> Box | K71: =IF($D71="","",IF($F71="",IFERROR(INDEX(Items!$H$5:$H$504,U71),0),$F71)) -> 1166 | L71: =IF($D71="","",ROUND(N($E71)*K71*(1-N($G71)),2)) -> 3498 | M71: =IF($D71="","",IFERROR(INDEX(Items!$F$5:$F$504,U71),0)) -> 0.05 | N71: =IF($D71="","",IF(AND(V71<>"",INDEX(Parties!$E$5:$E$304,V71)<>"",INDEX(Parties!$E$5:$E$304,V71)<>HomeState),0,ROUND(L71*M71/2,2))) -> 87.45 | O71: =IF($D71="","",N71) -> 87.45 | P71: =IF($D71="","",IF(AND(V71<>"",INDEX(Parties!$E$5:$E$304,V71)<>"",INDEX(Parties!$E$5:$E$304,V71)<>HomeState),ROUND(L71*M71,2),0)) -> 0 | Q71: =IF($D71="","",L71+N71+O71+P71) -> 3672.9 | R71: =IF($D71="","",ROUND(N($E71)*IFERROR(INDEX(Items!$P$5:$P$504,U71),0),2)) -> 2665.44 | S71: =IF($D71="","",L71-R71) -> 832.56 | T71: =IF($D71="","",IF(U71="","UNKNOWN ITEM",IF(INDEX(Items!$O$5:$O$504,U71)<0,"NEG STOCK",IF(K71<INDEX(Items!$P$5:$P$504,U71),"BELOW COST","OK")))) -> OK | U71: =IF($D71="","",IFERROR(MATCH($D71,Items!$A$5:$A$504,0),"")) -> 6 | V71: =IF($C71="","",IFERROR(MATCH($C71,Parties!$A$5:$A$304,0),"")) -> 9 | W71: =IF($B71="","",IFERROR(VALUE(SUBSTITUTE($B71,InvPrefix,"")),0)) -> 52 | X71: =IF($D71="","",IF(OR($H71="",$H71="Credit"),0,Q71)) -> 0
A72: 46190 | B72: INV-0052 | C72: FMCG Distributors | D72: Tea Premium 1kg | E72: 9 | I72: Delivered | J72: =IF($D72="","",IFERROR(INDEX(Items!$D$5:$D$504,U72),"")) -> Pack | K72: =IF($D72="","",IF($F72="",IFERROR(INDEX(Items!$H$5:$H$504,U72),0),$F72)) -> 508 | L72: =IF($D72="","",ROUND(N($E72)*K72*(1-N($G72)),2)) -> 4572 | M72: =IF($D72="","",IFERROR(INDEX(Items!$F$5:$F$504,U72),0)) -> 0.05 | N72: =IF($D72="","",IF(AND(V72<>"",INDEX(Parties!$E$5:$E$304,V72)<>"",INDEX(Parties!$E$5:$E$304,V72)<>HomeState),0,ROUND(L72*M72/2,2))) -> 114.3 | O72: =IF($D72="","",N72) -> 114.3 | P72: =IF($D72="","",IF(AND(V72<>"",INDEX(Parties!$E$5:$E$304,V72)<>"",INDEX(Parties!$E$5:$E$304,V72)<>HomeState),ROUND(L72*M72,2),0)) -> 0 | Q72: =IF($D72="","",L72+N72+O72+P72) -> 4800.6 | R72: =IF($D72="","",ROUND(N($E72)*IFERROR(INDEX(Items!$P$5:$P$504,U72),0),2)) -> 3393.71 | S72: =IF($D72="","",L72-R72) -> 1178.29 | T72: =IF($D72="","",IF(U72="","UNKNOWN ITEM",IF(INDEX(Items!$O$5:$O$504,U72)<0,"NEG STOCK",IF(K72<INDEX(Items!$P$5:$P$504,U72),"BELOW COST","OK")))) -> OK | U72: =IF($D72="","",IFERROR(MATCH($D72,Items!$A$5:$A$504,0),"")) -> 4 | V72: =IF($C72="","",IFERROR(MATCH($C72,Parties!$A$5:$A$304,0),"")) -> 9 | W72: =IF($B72="","",IFERROR(VALUE(SUBSTITUTE($B72,InvPrefix,"")),0)) -> 52 | X72: =IF($D72="","",IF(OR($H72="",$H72="Credit"),0,Q72)) -> 0
A73: 46192 | B73: INV-0053 | C73: Walk-in Customer | D73: Copper Wire 90m | E73: 2 | H73: Cash | I73: Delivered | J73: =IF($D73="","",IFERROR(INDEX(Items!$D$5:$D$504,U73),"")) -> Pcs | K73: =IF($D73="","",IF($F73="",IFERROR(INDEX(Items!$H$5:$H$504,U73),0),$F73)) -> 3132 | L73: =IF($D73="","",ROUND(N($E73)*K73*(1-N($G73)),2)) -> 6264 | M73: =IF($D73="","",IFERROR(INDEX(Items!$F$5:$F$504,U73),0)) -> 0.18 | N73: =IF($D73="","",IF(AND(V73<>"",INDEX(Parties!$E$5:$E$304,V73)<>"",INDEX(Parties!$E$5:$E$304,V73)<>HomeState),0,ROUND(L73*M73/2,2))) -> 563.76 | O73: =IF($D73="","",N73) -> 563.76 | P73: =IF($D73="","",IF(AND(V73<>"",INDEX(Parties!$E$5:$E$304,V73)<>"",INDEX(Parties!$E$5:$E$304,V73)<>HomeState),ROUND(L73*M73,2),0)) -> 0 | Q73: =IF($D73="","",L73+N73+O73+P73) -> 7391.52 | R73: =IF($D73="","",ROUND(N($E73)*IFERROR(INDEX(Items!$P$5:$P$504,U73),0),2)) -> 4902.96 | S73: =IF($D73="","",L73-R73) -> 1361.04 | T73: =IF($D73="","",IF(U73="","UNKNOWN ITEM",IF(INDEX(Items!$O$5:$O$504,U73)<0,"NEG STOCK",IF(K73<INDEX(Items!$P$5:$P$504,U73),"BELOW COST","OK")))) -> OK | U73: =IF($D73="","",IFERROR(MATCH($D73,Items!$A$5:$A$504,0),"")) -> 8 | V73: =IF($C73="","",IFERROR(MATCH($C73,Parties!$A$5:$A$304,0),"")) -> 4 | W73: =IF($B73="","",IFERROR(VALUE(SUBSTITUTE($B73,InvPrefix,"")),0)) -> 53 | X73: =IF($D73="","",IF(OR($H73="",$H73="Credit"),0,Q73)) -> 7391.52
A74: 46193 | B74: INV-0054 | C74: Sharma Kirana Store | D74: Sugar 50kg | E74: 3 | G74: 0.05 | I74: Delivered | J74: =IF($D74="","",IFERROR(INDEX(Items!$D$5:$D$504,U74),"")) -> Bag | K74: =IF($D74="","",IF($F74="",IFERROR(INDEX(Items!$H$5:$H$504,U74),0),$F74)) -> 2462 | L74: =IF($D74="","",ROUND(N($E74)*K74*(1-N($G74)),2)) -> 7016.7 | M74: =IF($D74="","",IFERROR(INDEX(Items!$F$5:$F$504,U74),0)) -> 0.05 | N74: =IF($D74="","",IF(AND(V74<>"",INDEX(Parties!$E$5:$E$304,V74)<>"",INDEX(Parties!$E$5:$E$304,V74)<>HomeState),0,ROUND(L74*M74/2,2))) -> 175.42 | O74: =IF($D74="","",N74) -> 175.42 | P74: =IF($D74="","",IF(AND(V74<>"",INDEX(Parties!$E$5:$E$304,V74)<>"",INDEX(Parties!$E$5:$E$304,V74)<>HomeState),ROUND(L74*M74,2),0)) -> 0 | Q74: =IF($D74="","",L74+N74+O74+P74) -> 7367.54 | R74: =IF($D74="","",ROUND(N($E74)*IFERROR(INDEX(Items!$P$5:$P$504,U74),0),2)) -> 6113.19 | S74: =IF($D74="","",L74-R74) -> 903.51 | T74: =IF($D74="","",IF(U74="","UNKNOWN ITEM",IF(INDEX(Items!$O$5:$O$504,U74)<0,"NEG STOCK",IF(K74<INDEX(Items!$P$5:$P$504,U74),"BELOW COST","OK")))) -> OK | U74: =IF($D74="","",IFERROR(MATCH($D74,Items!$A$5:$A$504,0),"")) -> 2 | V74: =IF($C74="","",IFERROR(MATCH($C74,Parties!$A$5:$A$304,0),"")) -> 1 | W74: =IF($B74="","",IFERROR(VALUE(SUBSTITUTE($B74,InvPrefix,"")),0)) -> 54 | X74: =IF($D74="","",IF(OR($H74="",$H74="Credit"),0,Q74)) -> 0
A75: 46197 | B75: INV-0056 | C75: Walk-in Customer | D75: Ceiling Fan 1200mm | E75: 4 | H75: Cash | I75: Delivered | J75: =IF($D75="","",IFERROR(INDEX(Items!$D$5:$D$504,U75),"")) -> Pcs | K75: =IF($D75="","",IF($F75="",IFERROR(INDEX(Items!$H$5:$H$504,U75),0),$F75)) -> 2322 | L75: =IF($D75="","",ROUND(N($E75)*K75*(1-N($G75)),2)) -> 9288 | M75: =IF($D75="","",IFERROR(INDEX(Items!$F$5:$F$504,U75),0)) -> 0.18 | N75: =IF($D75="","",IF(AND(V75<>"",INDEX(Parties!$E$5:$E$304,V75)<>"",INDEX(Parties!$E$5:$E$304,V75)<>HomeState),0,ROUND(L75*M75/2,2))) -> 835.92 | O75: =IF($D75="","",N75) -> 835.92 | P75: =IF($D75="","",IF(AND(V75<>"",INDEX(Parties!$E$5:$E$304,V75)<>"",INDEX(Parties!$E$5:$E$304,V75)<>HomeState),ROUND(L75*M75,2),0)) -> 0 | Q75: =IF($D75="","",L75+N75+O75+P75) -> 10959.84 | R75: =IF($D75="","",ROUND(N($E75)*IFERROR(INDEX(Items!$P$5:$P$504,U75),0),2)) -> 6575.2 | S75: =IF($D75="","",L75-R75) -> 2712.8 | T75: =IF($D75="","",IF(U75="","UNKNOWN ITEM",IF(INDEX(Items!$O$5:$O$504,U75)<0,"NEG STOCK",IF(K75<INDEX(Items!$P$5:$P$504,U75),"BELOW COST","OK")))) -> OK | U75: =IF($D75="","",IFERROR(MATCH($D75,Items!$A$5:$A$504,0),"")) -> 12 | V75: =IF($C75="","",IFERROR(MATCH($C75,Parties!$A$5:$A$304,0),"")) -> 4 | W75: =IF($B75="","",IFERROR(VALUE(SUBSTITUTE($B75,InvPrefix,"")),0)) -> 56 | X75: =IF($D75="","",IF(OR($H75="",$H75="Credit"),0,Q75)) -> 10959.84
A76: 46198 | B76: INV-0057 | C76: Delhi Hardware Mart | D76: PVC Pipe 1in 6m | E76: 23 | G76: 0.05 | I76: Delivered | J76: =IF($D76="","",IFERROR(INDEX(Items!$D$5:$D$504,U76),"")) -> Pcs | K76: =IF($D76="","",IF($F76="",IFERROR(INDEX(Items!$H$5:$H$504,U76),0),$F76)) -> 297 | L76: =IF($D76="","",ROUND(N($E76)*K76*(1-N($G76)),2)) -> 6489.45 | M76: =IF($D76="","",IFERROR(INDEX(Items!$F$5:$F$504,U76),0)) -> 0.18 | N76: =IF($D76="","",IF(AND(V76<>"",INDEX(Parties!$E$5:$E$304,V76)<>"",INDEX(Parties!$E$5:$E$304,V76)<>HomeState),0,ROUND(L76*M76/2,2))) -> 0 | O76: =IF($D76="","",N76) -> 0 | P76: =IF($D76="","",IF(AND(V76<>"",INDEX(Parties!$E$5:$E$304,V76)<>"",INDEX(Parties!$E$5:$E$304,V76)<>HomeState),ROUND(L76*M76,2),0)) -> 1168.1 | Q76: =IF($D76="","",L76+N76+O76+P76) -> 7657.55 | R76: =IF($D76="","",ROUND(N($E76)*IFERROR(INDEX(Items!$P$5:$P$504,U76),0),2)) -> 4821.57 | S76: =IF($D76="","",L76-R76) -> 1667.88 | T76: =IF($D76="","",IF(U76="","UNKNOWN ITEM",IF(INDEX(Items!$O$5:$O$504,U76)<0,"NEG STOCK",IF(K76<INDEX(Items!$P$5:$P$504,U76),"BELOW COST","OK")))) -> OK | U76: =IF($D76="","",IFERROR(MATCH($D76,Items!$A$5:$A$504,0),"")) -> 9 | V76: =IF($C76="","",IFERROR(MATCH($C76,Parties!$A$5:$A$304,0),"")) -> 3 | W76: =IF($B76="","",IFERROR(VALUE(SUBSTITUTE($B76,InvPrefix,"")),0)) -> 57 | X76: =IF($D76="","",IF(OR($H76="",$H76="Credit"),0,Q76)) -> 0
A77: 46200 | B77: INV-0058 | C77: Gupta Electricals | D77: Refined Oil 15L | E77: 7 | I77: Delivered | J77: =IF($D77="","",IFERROR(INDEX(Items!$D$5:$D$504,U77),"")) -> Box | K77: =IF($D77="","",IF($F77="",IFERROR(INDEX(Items!$H$5:$H$504,U77),0),$F77)) -> 2290 | L77: =IF($D77="","",ROUND(N($E77)*K77*(1-N($G77)),2)) -> 16030 | M77: =IF($D77="","",IFERROR(INDEX(Items!$F$5:$F$504,U77),0)) -> 0.05 | N77: =IF($D77="","",IF(AND(V77<>"",INDEX(Parties!$E$5:$E$304,V77)<>"",INDEX(Parties!$E$5:$E$304,V77)<>HomeState),0,ROUND(L77*M77/2,2))) -> 400.75 | O77: =IF($D77="","",N77) -> 400.75 | P77: =IF($D77="","",IF(AND(V77<>"",INDEX(Parties!$E$5:$E$304,V77)<>"",INDEX(Parties!$E$5:$E$304,V77)<>HomeState),ROUND(L77*M77,2),0)) -> 0 | Q77: =IF($D77="","",L77+N77+O77+P77) -> 16831.5 | R77: =IF($D77="","",ROUND(N($E77)*IFERROR(INDEX(Items!$P$5:$P$504,U77),0),2)) -> 13330.54 | S77: =IF($D77="","",L77-R77) -> 2699.46 | T77: =IF($D77="","",IF(U77="","UNKNOWN ITEM",IF(INDEX(Items!$O$5:$O$504,U77)<0,"NEG STOCK",IF(K77<INDEX(Items!$P$5:$P$504,U77),"BELOW COST","OK")))) -> OK | U77: =IF($D77="","",IFERROR(MATCH($D77,Items!$A$5:$A$504,0),"")) -> 3 | V77: =IF($C77="","",IFERROR(MATCH($C77,Parties!$A$5:$A$304,0),"")) -> 2 | W77: =IF($B77="","",IFERROR(VALUE(SUBSTITUTE($B77,InvPrefix,"")),0)) -> 58 | X77: =IF($D77="","",IF(OR($H77="",$H77="Credit"),0,Q77)) -> 0
A78: 46202 | B78: INV-0059 | C78: Walk-in Customer | D78: Basmati Rice 25kg | E78: 3 | G78: 0.05 | H78: Cash | I78: Delivered | J78: =IF($D78="","",IFERROR(INDEX(Items!$D$5:$D$504,U78),"")) -> Bag | K78: =IF($D78="","",IF($F78="",IFERROR(INDEX(Items!$H$5:$H$504,U78),0),$F78)) -> 2106 | L78: =IF($D78="","",ROUND(N($E78)*K78*(1-N($G78)),2)) -> 6002.1 | M78: =IF($D78="","",IFERROR(INDEX(Items!$F$5:$F$504,U78),0)) -> 0.05 | N78: =IF($D78="","",IF(AND(V78<>"",INDEX(Parties!$E$5:$E$304,V78)<>"",INDEX(Parties!$E$5:$E$304,V78)<>HomeState),0,ROUND(L78*M78/2,2))) -> 150.05 | O78: =IF($D78="","",N78) -> 150.05 | P78: =IF($D78="","",IF(AND(V78<>"",INDEX(Parties!$E$5:$E$304,V78)<>"",INDEX(Parties!$E$5:$E$304,V78)<>HomeState),ROUND(L78*M78,2),0)) -> 0 | Q78: =IF($D78="","",L78+N78+O78+P78) -> 6302.2 | R78: =IF($D78="","",ROUND(N($E78)*IFERROR(INDEX(Items!$P$5:$P$504,U78),0),2)) -> 4942.29 | S78: =IF($D78="","",L78-R78) -> 1059.81 | T78: =IF($D78="","",IF(U78="","UNKNOWN ITEM",IF(INDEX(Items!$O$5:$O$504,U78)<0,"NEG STOCK",IF(K78<INDEX(Items!$P$5:$P$504,U78),"BELOW COST","OK")))) -> OK | U78: =IF($D78="","",IFERROR(MATCH($D78,Items!$A$5:$A$504,0),"")) -> 1 | V78: =IF($C78="","",IFERROR(MATCH($C78,Parties!$A$5:$A$304,0),"")) -> 4 | W78: =IF($B78="","",IFERROR(VALUE(SUBSTITUTE($B78,InvPrefix,"")),0)) -> 59 | X78: =IF($D78="","",IF(OR($H78="",$H78="Credit"),0,Q78)) -> 6302.2
A79: 46203 | B79: INV-0060 | C79: Mehta Constructions | D79: Sugar 50kg | E79: 6 | G79: 0.05 | I79: Delivered | J79: =IF($D79="","",IFERROR(INDEX(Items!$D$5:$D$504,U79),"")) -> Bag | K79: =IF($D79="","",IF($F79="",IFERROR(INDEX(Items!$H$5:$H$504,U79),0),$F79)) -> 2462 | L79: =IF($D79="","",ROUND(N($E79)*K79*(1-N($G79)),2)) -> 14033.4 | M79: =IF($D79="","",IFERROR(INDEX(Items!$F$5:$F$504,U79),0)) -> 0.05 | N79: =IF($D79="","",IF(AND(V79<>"",INDEX(Parties!$E$5:$E$304,V79)<>"",INDEX(Parties!$E$5:$E$304,V79)<>HomeState),0,ROUND(L79*M79/2,2))) -> 350.84 | O79: =IF($D79="","",N79) -> 350.84 | P79: =IF($D79="","",IF(AND(V79<>"",INDEX(Parties!$E$5:$E$304,V79)<>"",INDEX(Parties!$E$5:$E$304,V79)<>HomeState),ROUND(L79*M79,2),0)) -> 0 | Q79: =IF($D79="","",L79+N79+O79+P79) -> 14735.08 | R79: =IF($D79="","",ROUND(N($E79)*IFERROR(INDEX(Items!$P$5:$P$504,U79),0),2)) -> 12226.37 | S79: =IF($D79="","",L79-R79) -> 1807.03 | T79: =IF($D79="","",IF(U79="","UNKNOWN ITEM",IF(INDEX(Items!$O$5:$O$504,U79)<0,"NEG STOCK",IF(K79<INDEX(Items!$P$5:$P$504,U79),"BELOW COST","OK")))) -> OK | U79: =IF($D79="","",IFERROR(MATCH($D79,Items!$A$5:$A$504,0),"")) -> 2 | V79: =IF($C79="","",IFERROR(MATCH($C79,Parties!$A$5:$A$304,0),"")) -> 5 | W79: =IF($B79="","",IFERROR(VALUE(SUBSTITUTE($B79,InvPrefix,"")),0)) -> 60 | X79: =IF($D79="","",IF(OR($H79="",$H79="Credit"),0,Q79)) -> 0
A80: 46205 | B80: INV-0061 | C80: Walk-in Customer | D80: Tea Premium 1kg | E80: 15 | G80: 0.02 | H80: Cash | I80: Delivered | J80: =IF($D80="","",IFERROR(INDEX(Items!$D$5:$D$504,U80),"")) -> Pack | K80: =IF($D80="","",IF($F80="",IFERROR(INDEX(Items!$H$5:$H$504,U80),0),$F80)) -> 508 | L80: =IF($D80="","",ROUND(N($E80)*K80*(1-N($G80)),2)) -> 7467.6 | M80: =IF($D80="","",IFERROR(INDEX(Items!$F$5:$F$504,U80),0)) -> 0.05 | N80: =IF($D80="","",IF(AND(V80<>"",INDEX(Parties!$E$5:$E$304,V80)<>"",INDEX(Parties!$E$5:$E$304,V80)<>HomeState),0,ROUND(L80*M80/2,2))) -> 186.69 | O80: =IF($D80="","",N80) -> 186.69 | P80: =IF($D80="","",IF(AND(V80<>"",INDEX(Parties!$E$5:$E$304,V80)<>"",INDEX(Parties!$E$5:$E$304,V80)<>HomeState),ROUND(L80*M80,2),0)) -> 0 | Q80: =IF($D80="","",L80+N80+O80+P80) -> 7840.98 | R80: =IF($D80="","",ROUND(N($E80)*IFERROR(INDEX(Items!$P$5:$P$504,U80),0),2)) -> 5656.19 | S80: =IF($D80="","",L80-R80) -> 1811.41 | T80: =IF($D80="","",IF(U80="","UNKNOWN ITEM",IF(INDEX(Items!$O$5:$O$504,U80)<0,"NEG STOCK",IF(K80<INDEX(Items!$P$5:$P$504,U80),"BELOW COST","OK")))) -> OK | U80: =IF($D80="","",IFERROR(MATCH($D80,Items!$A$5:$A$504,0),"")) -> 4 | V80: =IF($C80="","",IFERROR(MATCH($C80,Parties!$A$5:$A$304,0),"")) -> 4 | W80: =IF($B80="","",IFERROR(VALUE(SUBSTITUTE($B80,InvPrefix,"")),0)) -> 61 | X80: =IF($D80="","",IF(OR($H80="",$H80="Credit"),0,Q80)) -> 7840.98
A81: 46205 | B81: INV-0061 | C81: Walk-in Customer | D81: Ceiling Fan 1200mm | E81: 3 | G81: 0.02 | H81: Cash | I81: Delivered | J81: =IF($D81="","",IFERROR(INDEX(Items!$D$5:$D$504,U81),"")) -> Pcs | K81: =IF($D81="","",IF($F81="",IFERROR(INDEX(Items!$H$5:$H$504,U81),0),$F81)) -> 2322 | L81: =IF($D81="","",ROUND(N($E81)*K81*(1-N($G81)),2)) -> 6826.68 | M81: =IF($D81="","",IFERROR(INDEX(Items!$F$5:$F$504,U81),0)) -> 0.18 | N81: =IF($D81="","",IF(AND(V81<>"",INDEX(Parties!$E$5:$E$304,V81)<>"",INDEX(Parties!$E$5:$E$304,V81)<>HomeState),0,ROUND(L81*M81/2,2))) -> 614.4 | O81: =IF($D81="","",N81) -> 614.4 | P81: =IF($D81="","",IF(AND(V81<>"",INDEX(Parties!$E$5:$E$304,V81)<>"",INDEX(Parties!$E$5:$E$304,V81)<>HomeState),ROUND(L81*M81,2),0)) -> 0 | Q81: =IF($D81="","",L81+N81+O81+P81) -> 8055.48 | R81: =IF($D81="","",ROUND(N($E81)*IFERROR(INDEX(Items!$P$5:$P$504,U81),0),2)) -> 4931.4 | S81: =IF($D81="","",L81-R81) -> 1895.28 | T81: =IF($D81="","",IF(U81="","UNKNOWN ITEM",IF(INDEX(Items!$O$5:$O$504,U81)<0,"NEG STOCK",IF(K81<INDEX(Items!$P$5:$P$504,U81),"BELOW COST","OK")))) -> OK | U81: =IF($D81="","",IFERROR(MATCH($D81,Items!$A$5:$A$504,0),"")) -> 12 | V81: =IF($C81="","",IFERROR(MATCH($C81,Parties!$A$5:$A$304,0),"")) -> 4 | W81: =IF($B81="","",IFERROR(VALUE(SUBSTITUTE($B81,InvPrefix,"")),0)) -> 61 | X81: =IF($D81="","",IF(OR($H81="",$H81="Credit"),0,Q81)) -> 8055.48
A82: 46207 | B82: INV-0062 | C82: Mehta Constructions | D82: Ceiling Fan 1200mm | E82: 3 | I82: Delivered | J82: =IF($D82="","",IFERROR(INDEX(Items!$D$5:$D$504,U82),"")) -> Pcs | K82: =IF($D82="","",IF($F82="",IFERROR(INDEX(Items!$H$5:$H$504,U82),0),$F82)) -> 2322 | L82: =IF($D82="","",ROUND(N($E82)*K82*(1-N($G82)),2)) -> 6966 | M82: =IF($D82="","",IFERROR(INDEX(Items!$F$5:$F$504,U82),0)) -> 0.18 | N82: =IF($D82="","",IF(AND(V82<>"",INDEX(Parties!$E$5:$E$304,V82)<>"",INDEX(Parties!$E$5:$E$304,V82)<>HomeState),0,ROUND(L82*M82/2,2))) -> 626.94 | O82: =IF($D82="","",N82) -> 626.94 | P82: =IF($D82="","",IF(AND(V82<>"",INDEX(Parties!$E$5:$E$304,V82)<>"",INDEX(Parties!$E$5:$E$304,V82)<>HomeState),ROUND(L82*M82,2),0)) -> 0 | Q82: =IF($D82="","",L82+N82+O82+P82) -> 8219.88 | R82: =IF($D82="","",ROUND(N($E82)*IFERROR(INDEX(Items!$P$5:$P$504,U82),0),2)) -> 4931.4 | S82: =IF($D82="","",L82-R82) -> 2034.6 | T82: =IF($D82="","",IF(U82="","UNKNOWN ITEM",IF(INDEX(Items!$O$5:$O$504,U82)<0,"NEG STOCK",IF(K82<INDEX(Items!$P$5:$P$504,U82),"BELOW COST","OK")))) -> OK | U82: =IF($D82="","",IFERROR(MATCH($D82,Items!$A$5:$A$504,0),"")) -> 12 | V82: =IF($C82="","",IFERROR(MATCH($C82,Parties!$A$5:$A$304,0),"")) -> 5 | W82: =IF($B82="","",IFERROR(VALUE(SUBSTITUTE($B82,InvPrefix,"")),0)) -> 62 | X82: =IF($D82="","",IF(OR($H82="",$H82="Credit"),0,Q82)) -> 0
A83: 46209 | B83: INV-0063 | C83: Sharma Kirana Store | D83: Copper Wire 90m | E83: 2 | H83: UPI | I83: Delivered | J83: =IF($D83="","",IFERROR(INDEX(Items!$D$5:$D$504,U83),"")) -> Pcs | K83: =IF($D83="","",IF($F83="",IFERROR(INDEX(Items!$H$5:$H$504,U83),0),$F83)) -> 3132 | L83: =IF($D83="","",ROUND(N($E83)*K83*(1-N($G83)),2)) -> 6264 | M83: =IF($D83="","",IFERROR(INDEX(Items!$F$5:$F$504,U83),0)) -> 0.18 | N83: =IF($D83="","",IF(AND(V83<>"",INDEX(Parties!$E$5:$E$304,V83)<>"",INDEX(Parties!$E$5:$E$304,V83)<>HomeState),0,ROUND(L83*M83/2,2))) -> 563.76 | O83: =IF($D83="","",N83) -> 563.76 | P83: =IF($D83="","",IF(AND(V83<>"",INDEX(Parties!$E$5:$E$304,V83)<>"",INDEX(Parties!$E$5:$E$304,V83)<>HomeState),ROUND(L83*M83,2),0)) -> 0 | Q83: =IF($D83="","",L83+N83+O83+P83) -> 7391.52 | R83: =IF($D83="","",ROUND(N($E83)*IFERROR(INDEX(Items!$P$5:$P$504,U83),0),2)) -> 4902.96 | S83: =IF($D83="","",L83-R83) -> 1361.04 | T83: =IF($D83="","",IF(U83="","UNKNOWN ITEM",IF(INDEX(Items!$O$5:$O$504,U83)<0,"NEG STOCK",IF(K83<INDEX(Items!$P$5:$P$504,U83),"BELOW COST","OK")))) -> OK | U83: =IF($D83="","",IFERROR(MATCH($D83,Items!$A$5:$A$504,0),"")) -> 8 | V83: =IF($C83="","",IFERROR(MATCH($C83,Parties!$A$5:$A$304,0),"")) -> 1 | W83: =IF($B83="","",IFERROR(VALUE(SUBSTITUTE($B83,InvPrefix,"")),0)) -> 63 | X83: =IF($D83="","",IF(OR($H83="",$H83="Credit"),0,Q83)) -> 7391.52
A84: 46210 | B84: INV-0064 | C84: Walk-in Customer | D84: Ceiling Fan 1200mm | E84: 3 | G84: 0.02 | H84: Cash | I84: Delivered | J84: =IF($D84="","",IFERROR(INDEX(Items!$D$5:$D$504,U84),"")) -> Pcs | K84: =IF($D84="","",IF($F84="",IFERROR(INDEX(Items!$H$5:$H$504,U84),0),$F84)) -> 2322 | L84: =IF($D84="","",ROUND(N($E84)*K84*(1-N($G84)),2)) -> 6826.68 | M84: =IF($D84="","",IFERROR(INDEX(Items!$F$5:$F$504,U84),0)) -> 0.18 | N84: =IF($D84="","",IF(AND(V84<>"",INDEX(Parties!$E$5:$E$304,V84)<>"",INDEX(Parties!$E$5:$E$304,V84)<>HomeState),0,ROUND(L84*M84/2,2))) -> 614.4 | O84: =IF($D84="","",N84) -> 614.4 | P84: =IF($D84="","",IF(AND(V84<>"",INDEX(Parties!$E$5:$E$304,V84)<>"",INDEX(Parties!$E$5:$E$304,V84)<>HomeState),ROUND(L84*M84,2),0)) -> 0 | Q84: =IF($D84="","",L84+N84+O84+P84) -> 8055.48 | R84: =IF($D84="","",ROUND(N($E84)*IFERROR(INDEX(Items!$P$5:$P$504,U84),0),2)) -> 4931.4 | S84: =IF($D84="","",L84-R84) -> 1895.28 | T84: =IF($D84="","",IF(U84="","UNKNOWN ITEM",IF(INDEX(Items!$O$5:$O$504,U84)<0,"NEG STOCK",IF(K84<INDEX(Items!$P$5:$P$504,U84),"BELOW COST","OK")))) -> OK | U84: =IF($D84="","",IFERROR(MATCH($D84,Items!$A$5:$A$504,0),"")) -> 12 | V84: =IF($C84="","",IFERROR(MATCH($C84,Parties!$A$5:$A$304,0),"")) -> 4 | W84: =IF($B84="","",IFERROR(VALUE(SUBSTITUTE($B84,InvPrefix,"")),0)) -> 64 | X84: =IF($D84="","",IF(OR($H84="",$H84="Credit"),0,Q84)) -> 8055.48
A85: 46211 | B85: INV-0065 | C85: Walk-in Customer | D85: PVC Pipe 1in 6m | E85: 18 | H85: Cash | I85: Delivered | J85: =IF($D85="","",IFERROR(INDEX(Items!$D$5:$D$504,U85),"")) -> Pcs | K85: =IF($D85="","",IF($F85="",IFERROR(INDEX(Items!$H$5:$H$504,U85),0),$F85)) -> 297 | L85: =IF($D85="","",ROUND(N($E85)*K85*(1-N($G85)),2)) -> 5346 | M85: =IF($D85="","",IFERROR(INDEX(Items!$F$5:$F$504,U85),0)) -> 0.18 | N85: =IF($D85="","",IF(AND(V85<>"",INDEX(Parties!$E$5:$E$304,V85)<>"",INDEX(Parties!$E$5:$E$304,V85)<>HomeState),0,ROUND(L85*M85/2,2))) -> 481.14 | O85: =IF($D85="","",N85) -> 481.14 | P85: =IF($D85="","",IF(AND(V85<>"",INDEX(Parties!$E$5:$E$304,V85)<>"",INDEX(Parties!$E$5:$E$304,V85)<>HomeState),ROUND(L85*M85,2),0)) -> 0 | Q85: =IF($D85="","",L85+N85+O85+P85) -> 6308.28 | R85: =IF($D85="","",ROUND(N($E85)*IFERROR(INDEX(Items!$P$5:$P$504,U85),0),2)) -> 3773.4 | S85: =IF($D85="","",L85-R85) -> 1572.6 | T85: =IF($D85="","",IF(U85="","UNKNOWN ITEM",IF(INDEX(Items!$O$5:$O$504,U85)<0,"NEG STOCK",IF(K85<INDEX(Items!$P$5:$P$504,U85),"BELOW COST","OK")))) -> OK | U85: =IF($D85="","",IFERROR(MATCH($D85,Items!$A$5:$A$504,0),"")) -> 9 | V85: =IF($C85="","",IFERROR(MATCH($C85,Parties!$A$5:$A$304,0),"")) -> 4 | W85: =IF($B85="","",IFERROR(VALUE(SUBSTITUTE($B85,InvPrefix,"")),0)) -> 65 | X85: =IF($D85="","",IF(OR($H85="",$H85="Credit"),0,Q85)) -> 6308.28
A86: 46212 | B86: INV-0066 | C86: Sharma Kirana Store | D86: Sugar 50kg | E86: 6 | G86: 0.02 | I86: Delivered | J86: =IF($D86="","",IFERROR(INDEX(Items!$D$5:$D$504,U86),"")) -> Bag | K86: =IF($D86="","",IF($F86="",IFERROR(INDEX(Items!$H$5:$H$504,U86),0),$F86)) -> 2462 | L86: =IF($D86="","",ROUND(N($E86)*K86*(1-N($G86)),2)) -> 14476.56 | M86: =IF($D86="","",IFERROR(INDEX(Items!$F$5:$F$504,U86),0)) -> 0.05 | N86: =IF($D86="","",IF(AND(V86<>"",INDEX(Parties!$E$5:$E$304,V86)<>"",INDEX(Parties!$E$5:$E$304,V86)<>HomeState),0,ROUND(L86*M86/2,2))) -> 361.91 | O86: =IF($D86="","",N86) -> 361.91 | P86: =IF($D86="","",IF(AND(V86<>"",INDEX(Parties!$E$5:$E$304,V86)<>"",INDEX(Parties!$E$5:$E$304,V86)<>HomeState),ROUND(L86*M86,2),0)) -> 0 | Q86: =IF($D86="","",L86+N86+O86+P86) -> 15200.38 | R86: =IF($D86="","",ROUND(N($E86)*IFERROR(INDEX(Items!$P$5:$P$504,U86),0),2)) -> 12226.37 | S86: =IF($D86="","",L86-R86) -> 2250.19 | T86: =IF($D86="","",IF(U86="","UNKNOWN ITEM",IF(INDEX(Items!$O$5:$O$504,U86)<0,"NEG STOCK",IF(K86<INDEX(Items!$P$5:$P$504,U86),"BELOW COST","OK")))) -> OK | U86: =IF($D86="","",IFERROR(MATCH($D86,Items!$A$5:$A$504,0),"")) -> 2 | V86: =IF($C86="","",IFERROR(MATCH($C86,Parties!$A$5:$A$304,0),"")) -> 1 | W86: =IF($B86="","",IFERROR(VALUE(SUBSTITUTE($B86,InvPrefix,"")),0)) -> 66 | X86: =IF($D86="","",IF(OR($H86="",$H86="Credit"),0,Q86)) -> 0
A87: 46213 | B87: INV-0067 | C87: Walk-in Customer | D87: Tea Premium 1kg | E87: 7 | H87: Cash | I87: Delivered | J87: =IF($D87="","",IFERROR(INDEX(Items!$D$5:$D$504,U87),"")) -> Pack | K87: =IF($D87="","",IF($F87="",IFERROR(INDEX(Items!$H$5:$H$504,U87),0),$F87)) -> 508 | L87: =IF($D87="","",ROUND(N($E87)*K87*(1-N($G87)),2)) -> 3556 | M87: =IF($D87="","",IFERROR(INDEX(Items!$F$5:$F$504,U87),0)) -> 0.05 | N87: =IF($D87="","",IF(AND(V87<>"",INDEX(Parties!$E$5:$E$304,V87)<>"",INDEX(Parties!$E$5:$E$304,V87)<>HomeState),0,ROUND(L87*M87/2,2))) -> 88.9 | O87: =IF($D87="","",N87) -> 88.9 | P87: =IF($D87="","",IF(AND(V87<>"",INDEX(Parties!$E$5:$E$304,V87)<>"",INDEX(Parties!$E$5:$E$304,V87)<>HomeState),ROUND(L87*M87,2),0)) -> 0 | Q87: =IF($D87="","",L87+N87+O87+P87) -> 3733.8 | R87: =IF($D87="","",ROUND(N($E87)*IFERROR(INDEX(Items!$P$5:$P$504,U87),0),2)) -> 2639.55 | S87: =IF($D87="","",L87-R87) -> 916.45 | T87: =IF($D87="","",IF(U87="","UNKNOWN ITEM",IF(INDEX(Items!$O$5:$O$504,U87)<0,"NEG STOCK",IF(K87<INDEX(Items!$P$5:$P$504,U87),"BELOW COST","OK")))) -> OK | U87: =IF($D87="","",IFERROR(MATCH($D87,Items!$A$5:$A$504,0),"")) -> 4 | V87: =IF($C87="","",IFERROR(MATCH($C87,Parties!$A$5:$A$304,0),"")) -> 4 | W87: =IF($B87="","",IFERROR(VALUE(SUBSTITUTE($B87,InvPrefix,"")),0)) -> 67 | X87: =IF($D87="","",IF(OR($H87="",$H87="Credit"),0,Q87)) -> 3733.8
A88: 46214 | B88: INV-0068 | C88: Walk-in Customer | D88: Detergent 5kg | E88: 11 | G88: 0.02 | H88: Cash | I88: Delivered | J88: =IF($D88="","",IFERROR(INDEX(Items!$D$5:$D$504,U88),"")) -> Pack | K88: =IF($D88="","",IF($F88="",IFERROR(INDEX(Items!$H$5:$H$504,U88),0),$F88)) -> 691 | L88: =IF($D88="","",ROUND(N($E88)*K88*(1-N($G88)),2)) -> 7448.98 | M88: =IF($D88="","",IFERROR(INDEX(Items!$F$5:$F$504,U88),0)) -> 0.18 | N88: =IF($D88="","",IF(AND(V88<>"",INDEX(Parties!$E$5:$E$304,V88)<>"",INDEX(Parties!$E$5:$E$304,V88)<>HomeState),0,ROUND(L88*M88/2,2))) -> 670.41 | O88: =IF($D88="","",N88) -> 670.41 | P88: =IF($D88="","",IF(AND(V88<>"",INDEX(Parties!$E$5:$E$304,V88)<>"",INDEX(Parties!$E$5:$E$304,V88)<>HomeState),ROUND(L88*M88,2),0)) -> 0 | Q88: =IF($D88="","",L88+N88+O88+P88) -> 8789.8 | R88: =IF($D88="","",ROUND(N($E88)*IFERROR(INDEX(Items!$P$5:$P$504,U88),0),2)) -> 5694.62 | S88: =IF($D88="","",L88-R88) -> 1754.36 | T88: =IF($D88="","",IF(U88="","UNKNOWN ITEM",IF(INDEX(Items!$O$5:$O$504,U88)<0,"NEG STOCK",IF(K88<INDEX(Items!$P$5:$P$504,U88),"BELOW COST","OK")))) -> OK | U88: =IF($D88="","",IFERROR(MATCH($D88,Items!$A$5:$A$504,0),"")) -> 5 | V88: =IF($C88="","",IFERROR(MATCH($C88,Parties!$A$5:$A$304,0),"")) -> 4 | W88: =IF($B88="","",IFERROR(VALUE(SUBSTITUTE($B88,InvPrefix,"")),0)) -> 68 | X88: =IF($D88="","",IF(OR($H88="",$H88="Credit"),0,Q88)) -> 8789.8
A89: 46216 | B89: INV-0069 | C89: Walk-in Customer | D89: Sugar 50kg | E89: 6 | H89: Cash | I89: Delivered | J89: =IF($D89="","",IFERROR(INDEX(Items!$D$5:$D$504,U89),"")) -> Bag | K89: =IF($D89="","",IF($F89="",IFERROR(INDEX(Items!$H$5:$H$504,U89),0),$F89)) -> 2462 | L89: =IF($D89="","",ROUND(N($E89)*K89*(1-N($G89)),2)) -> 14772 | M89: =IF($D89="","",IFERROR(INDEX(Items!$F$5:$F$504,U89),0)) -> 0.05 | N89: =IF($D89="","",IF(AND(V89<>"",INDEX(Parties!$E$5:$E$304,V89)<>"",INDEX(Parties!$E$5:$E$304,V89)<>HomeState),0,ROUND(L89*M89/2,2))) -> 369.3 | O89: =IF($D89="","",N89) -> 369.3 | P89: =IF($D89="","",IF(AND(V89<>"",INDEX(Parties!$E$5:$E$304,V89)<>"",INDEX(Parties!$E$5:$E$304,V89)<>HomeState),ROUND(L89*M89,2),0)) -> 0 | Q89: =IF($D89="","",L89+N89+O89+P89) -> 15510.6 | R89: =IF($D89="","",ROUND(N($E89)*IFERROR(INDEX(Items!$P$5:$P$504,U89),0),2)) -> 12226.37 | S89: =IF($D89="","",L89-R89) -> 2545.63 | T89: =IF($D89="","",IF(U89="","UNKNOWN ITEM",IF(INDEX(Items!$O$5:$O$504,U89)<0,"NEG STOCK",IF(K89<INDEX(Items!$P$5:$P$504,U89),"BELOW COST","OK")))) -> OK | U89: =IF($D89="","",IFERROR(MATCH($D89,Items!$A$5:$A$504,0),"")) -> 2 | V89: =IF($C89="","",IFERROR(MATCH($C89,Parties!$A$5:$A$304,0),"")) -> 4 | W89: =IF($B89="","",IFERROR(VALUE(SUBSTITUTE($B89,InvPrefix,"")),0)) -> 69 | X89: =IF($D89="","",IF(OR($H89="",$H89="Credit"),0,Q89)) -> 15510.6
A90: 46217 | B90: INV-0070 | C90: FMCG Distributors | D90: Tea Premium 1kg | E90: 14 | H90: UPI | I90: Delivered | J90: =IF($D90="","",IFERROR(INDEX(Items!$D$5:$D$504,U90),"")) -> Pack | K90: =IF($D90="","",IF($F90="",IFERROR(INDEX(Items!$H$5:$H$504,U90),0),$F90)) -> 508 | L90: =IF($D90="","",ROUND(N($E90)*K90*(1-N($G90)),2)) -> 7112 | M90: =IF($D90="","",IFERROR(INDEX(Items!$F$5:$F$504,U90),0)) -> 0.05 | N90: =IF($D90="","",IF(AND(V90<>"",INDEX(Parties!$E$5:$E$304,V90)<>"",INDEX(Parties!$E$5:$E$304,V90)<>HomeState),0,ROUND(L90*M90/2,2))) -> 177.8 | O90: =IF($D90="","",N90) -> 177.8 | P90: =IF($D90="","",IF(AND(V90<>"",INDEX(Parties!$E$5:$E$304,V90)<>"",INDEX(Parties!$E$5:$E$304,V90)<>HomeState),ROUND(L90*M90,2),0)) -> 0 | Q90: =IF($D90="","",L90+N90+O90+P90) -> 7467.6 | R90: =IF($D90="","",ROUND(N($E90)*IFERROR(INDEX(Items!$P$5:$P$504,U90),0),2)) -> 5279.11 | S90: =IF($D90="","",L90-R90) -> 1832.89 | T90: =IF($D90="","",IF(U90="","UNKNOWN ITEM",IF(INDEX(Items!$O$5:$O$504,U90)<0,"NEG STOCK",IF(K90<INDEX(Items!$P$5:$P$504,U90),"BELOW COST","OK")))) -> OK | U90: =IF($D90="","",IFERROR(MATCH($D90,Items!$A$5:$A$504,0),"")) -> 4 | V90: =IF($C90="","",IFERROR(MATCH($C90,Parties!$A$5:$A$304,0),"")) -> 9 | W90: =IF($B90="","",IFERROR(VALUE(SUBSTITUTE($B90,InvPrefix,"")),0)) -> 70 | X90: =IF($D90="","",IF(OR($H90="",$H90="Credit"),0,Q90)) -> 7467.6
A91: 46218 | B91: INV-0071 | C91: FMCG Distributors | D91: LED Bulb 9W | E91: 89 | G91: 0.05 | I91: Delivered | J91: =IF($D91="","",IFERROR(INDEX(Items!$D$5:$D$504,U91),"")) -> Pcs | K91: =IF($D91="","",IF($F91="",IFERROR(INDEX(Items!$H$5:$H$504,U91),0),$F91)) -> 107 | L91: =IF($D91="","",ROUND(N($E91)*K91*(1-N($G91)),2)) -> 9046.85 | M91: =IF($D91="","",IFERROR(INDEX(Items!$F$5:$F$504,U91),0)) -> 0.18 | N91: =IF($D91="","",IF(AND(V91<>"",INDEX(Parties!$E$5:$E$304,V91)<>"",INDEX(Parties!$E$5:$E$304,V91)<>HomeState),0,ROUND(L91*M91/2,2))) -> 814.22 | O91: =IF($D91="","",N91) -> 814.22 | P91: =IF($D91="","",IF(AND(V91<>"",INDEX(Parties!$E$5:$E$304,V91)<>"",INDEX(Parties!$E$5:$E$304,V91)<>HomeState),ROUND(L91*M91,2),0)) -> 0 | Q91: =IF($D91="","",L91+N91+O91+P91) -> 10675.29 | R91: =IF($D91="","",ROUND(N($E91)*IFERROR(INDEX(Items!$P$5:$P$504,U91),0),2)) -> 5466.12 | S91: =IF($D91="","",L91-R91) -> 3580.73 | T91: =IF($D91="","",IF(U91="","UNKNOWN ITEM",IF(INDEX(Items!$O$5:$O$504,U91)<0,"NEG STOCK",IF(K91<INDEX(Items!$P$5:$P$504,U91),"BELOW COST","OK")))) -> OK | U91: =IF($D91="","",IFERROR(MATCH($D91,Items!$A$5:$A$504,0),"")) -> 7 | V91: =IF($C91="","",IFERROR(MATCH($C91,Parties!$A$5:$A$304,0),"")) -> 9 | W91: =IF($B91="","",IFERROR(VALUE(SUBSTITUTE($B91,InvPrefix,"")),0)) -> 71 | X91: =IF($D91="","",IF(OR($H91="",$H91="Credit"),0,Q91)) -> 0
A92: 46220 | B92: INV-0072 | C92: Walk-in Customer | D92: Basmati Rice 25kg | E92: 5 | H92: Cash | I92: Delivered | J92: =IF($D92="","",IFERROR(INDEX(Items!$D$5:$D$504,U92),"")) -> Bag | K92: =IF($D92="","",IF($F92="",IFERROR(INDEX(Items!$H$5:$H$504,U92),0),$F92)) -> 2106 | L92: =IF($D92="","",ROUND(N($E92)*K92*(1-N($G92)),2)) -> 10530 | M92: =IF($D92="","",IFERROR(INDEX(Items!$F$5:$F$504,U92),0)) -> 0.05 | N92: =IF($D92="","",IF(AND(V92<>"",INDEX(Parties!$E$5:$E$304,V92)<>"",INDEX(Parties!$E$5:$E$304,V92)<>HomeState),0,ROUND(L92*M92/2,2))) -> 263.25 | O92: =IF($D92="","",N92) -> 263.25 | P92: =IF($D92="","",IF(AND(V92<>"",INDEX(Parties!$E$5:$E$304,V92)<>"",INDEX(Parties!$E$5:$E$304,V92)<>HomeState),ROUND(L92*M92,2),0)) -> 0 | Q92: =IF($D92="","",L92+N92+O92+P92) -> 11056.5 | R92: =IF($D92="","",ROUND(N($E92)*IFERROR(INDEX(Items!$P$5:$P$504,U92),0),2)) -> 8237.15 | S92: =IF($D92="","",L92-R92) -> 2292.85 | T92: =IF($D92="","",IF(U92="","UNKNOWN ITEM",IF(INDEX(Items!$O$5:$O$504,U92)<0,"NEG STOCK",IF(K92<INDEX(Items!$P$5:$P$504,U92),"BELOW COST","OK")))) -> OK | U92: =IF($D92="","",IFERROR(MATCH($D92,Items!$A$5:$A$504,0),"")) -> 1 | V92: =IF($C92="","",IFERROR(MATCH($C92,Parties!$A$5:$A$304,0),"")) -> 4 | W92: =IF($B92="","",IFERROR(VALUE(SUBSTITUTE($B92,InvPrefix,"")),0)) -> 72 | X92: =IF($D92="","",IF(OR($H92="",$H92="Credit"),0,Q92)) -> 11056.5
A93: 46221 | B93: INV-0073 | C93: Delhi Hardware Mart | D93: LED Bulb 9W | E93: 63 | I93: Delivered | J93: =IF($D93="","",IFERROR(INDEX(Items!$D$5:$D$504,U93),"")) -> Pcs | K93: =IF($D93="","",IF($F93="",IFERROR(INDEX(Items!$H$5:$H$504,U93),0),$F93)) -> 107 | L93: =IF($D93="","",ROUND(N($E93)*K93*(1-N($G93)),2)) -> 6741 | M93: =IF($D93="","",IFERROR(INDEX(Items!$F$5:$F$504,U93),0)) -> 0.18 | N93: =IF($D93="","",IF(AND(V93<>"",INDEX(Parties!$E$5:$E$304,V93)<>"",INDEX(Parties!$E$5:$E$304,V93)<>HomeState),0,ROUND(L93*M93/2,2))) -> 0 | O93: =IF($D93="","",N93) -> 0 | P93: =IF($D93="","",IF(AND(V93<>"",INDEX(Parties!$E$5:$E$304,V93)<>"",INDEX(Parties!$E$5:$E$304,V93)<>HomeState),ROUND(L93*M93,2),0)) -> 1213.38 | Q93: =IF($D93="","",L93+N93+O93+P93) -> 7954.38 | R93: =IF($D93="","",ROUND(N($E93)*IFERROR(INDEX(Items!$P$5:$P$504,U93),0),2)) -> 3869.28 | S93: =IF($D93="","",L93-R93) -> 2871.72 | T93: =IF($D93="","",IF(U93="","UNKNOWN ITEM",IF(INDEX(Items!$O$5:$O$504,U93)<0,"NEG STOCK",IF(K93<INDEX(Items!$P$5:$P$504,U93),"BELOW COST","OK")))) -> OK | U93: =IF($D93="","",IFERROR(MATCH($D93,Items!$A$5:$A$504,0),"")) -> 7 | V93: =IF($C93="","",IFERROR(MATCH($C93,Parties!$A$5:$A$304,0),"")) -> 3 | W93: =IF($B93="","",IFERROR(VALUE(SUBSTITUTE($B93,InvPrefix,"")),0)) -> 73 | X93: =IF($D93="","",IF(OR($H93="",$H93="Credit"),0,Q93)) -> 0
A94: 46224 | B94: INV-0075 | C94: Walk-in Customer | D94: Sugar 50kg | E94: 6 | G94: 0.02 | H94: Cash | I94: Delivered | J94: =IF($D94="","",IFERROR(INDEX(Items!$D$5:$D$504,U94),"")) -> Bag | K94: =IF($D94="","",IF($F94="",IFERROR(INDEX(Items!$H$5:$H$504,U94),0),$F94)) -> 2462 | L94: =IF($D94="","",ROUND(N($E94)*K94*(1-N($G94)),2)) -> 14476.56 | M94: =IF($D94="","",IFERROR(INDEX(Items!$F$5:$F$504,U94),0)) -> 0.05 | N94: =IF($D94="","",IF(AND(V94<>"",INDEX(Parties!$E$5:$E$304,V94)<>"",INDEX(Parties!$E$5:$E$304,V94)<>HomeState),0,ROUND(L94*M94/2,2))) -> 361.91 | O94: =IF($D94="","",N94) -> 361.91 | P94: =IF($D94="","",IF(AND(V94<>"",INDEX(Parties!$E$5:$E$304,V94)<>"",INDEX(Parties!$E$5:$E$304,V94)<>HomeState),ROUND(L94*M94,2),0)) -> 0 | Q94: =IF($D94="","",L94+N94+O94+P94) -> 15200.38 | R94: =IF($D94="","",ROUND(N($E94)*IFERROR(INDEX(Items!$P$5:$P$504,U94),0),2)) -> 12226.37 | S94: =IF($D94="","",L94-R94) -> 2250.19 | T94: =IF($D94="","",IF(U94="","UNKNOWN ITEM",IF(INDEX(Items!$O$5:$O$504,U94)<0,"NEG STOCK",IF(K94<INDEX(Items!$P$5:$P$504,U94),"BELOW COST","OK")))) -> OK | U94: =IF($D94="","",IFERROR(MATCH($D94,Items!$A$5:$A$504,0),"")) -> 2 | V94: =IF($C94="","",IFERROR(MATCH($C94,Parties!$A$5:$A$304,0),"")) -> 4 | W94: =IF($B94="","",IFERROR(VALUE(SUBSTITUTE($B94,InvPrefix,"")),0)) -> 75 | X94: =IF($D94="","",IF(OR($H94="",$H94="Credit"),0,Q94)) -> 15200.38
A95: 46224 | B95: INV-0075 | C95: Walk-in Customer | D95: Basmati Rice 25kg | E95: 5 | H95: Cash | I95: Delivered | J95: =IF($D95="","",IFERROR(INDEX(Items!$D$5:$D$504,U95),"")) -> Bag | K95: =IF($D95="","",IF($F95="",IFERROR(INDEX(Items!$H$5:$H$504,U95),0),$F95)) -> 2106 | L95: =IF($D95="","",ROUND(N($E95)*K95*(1-N($G95)),2)) -> 10530 | M95: =IF($D95="","",IFERROR(INDEX(Items!$F$5:$F$504,U95),0)) -> 0.05 | N95: =IF($D95="","",IF(AND(V95<>"",INDEX(Parties!$E$5:$E$304,V95)<>"",INDEX(Parties!$E$5:$E$304,V95)<>HomeState),0,ROUND(L95*M95/2,2))) -> 263.25 | O95: =IF($D95="","",N95) -> 263.25 | P95: =IF($D95="","",IF(AND(V95<>"",INDEX(Parties!$E$5:$E$304,V95)<>"",INDEX(Parties!$E$5:$E$304,V95)<>HomeState),ROUND(L95*M95,2),0)) -> 0 | Q95: =IF($D95="","",L95+N95+O95+P95) -> 11056.5 | R95: =IF($D95="","",ROUND(N($E95)*IFERROR(INDEX(Items!$P$5:$P$504,U95),0),2)) -> 8237.15 | S95: =IF($D95="","",L95-R95) -> 2292.85 | T95: =IF($D95="","",IF(U95="","UNKNOWN ITEM",IF(INDEX(Items!$O$5:$O$504,U95)<0,"NEG STOCK",IF(K95<INDEX(Items!$P$5:$P$504,U95),"BELOW COST","OK")))) -> OK | U95: =IF($D95="","",IFERROR(MATCH($D95,Items!$A$5:$A$504,0),"")) -> 1 | V95: =IF($C95="","",IFERROR(MATCH($C95,Parties!$A$5:$A$304,0),"")) -> 4 | W95: =IF($B95="","",IFERROR(VALUE(SUBSTITUTE($B95,InvPrefix,"")),0)) -> 75 | X95: =IF($D95="","",IF(OR($H95="",$H95="Credit"),0,Q95)) -> 11056.5
A96: 46225 | B96: INV-0076 | C96: Walk-in Customer | D96: PVC Pipe 1in 6m | E96: 16 | G96: 0.02 | H96: Cash | I96: Delivered | J96: =IF($D96="","",IFERROR(INDEX(Items!$D$5:$D$504,U96),"")) -> Pcs | K96: =IF($D96="","",IF($F96="",IFERROR(INDEX(Items!$H$5:$H$504,U96),0),$F96)) -> 297 | L96: =IF($D96="","",ROUND(N($E96)*K96*(1-N($G96)),2)) -> 4656.96 | M96: =IF($D96="","",IFERROR(INDEX(Items!$F$5:$F$504,U96),0)) -> 0.18 | N96: =IF($D96="","",IF(AND(V96<>"",INDEX(Parties!$E$5:$E$304,V96)<>"",INDEX(Parties!$E$5:$E$304,V96)<>HomeState),0,ROUND(L96*M96/2,2))) -> 419.13 | O96: =IF($D96="","",N96) -> 419.13 | P96: =IF($D96="","",IF(AND(V96<>"",INDEX(Parties!$E$5:$E$304,V96)<>"",INDEX(Parties!$E$5:$E$304,V96)<>HomeState),ROUND(L96*M96,2),0)) -> 0 | Q96: =IF($D96="","",L96+N96+O96+P96) -> 5495.22 | R96: =IF($D96="","",ROUND(N($E96)*IFERROR(INDEX(Items!$P$5:$P$504,U96),0),2)) -> 3354.13 | S96: =IF($D96="","",L96-R96) -> 1302.83 | T96: =IF($D96="","",IF(U96="","UNKNOWN ITEM",IF(INDEX(Items!$O$5:$O$504,U96)<0,"NEG STOCK",IF(K96<INDEX(Items!$P$5:$P$504,U96),"BELOW COST","OK")))) -> OK | U96: =IF($D96="","",IFERROR(MATCH($D96,Items!$A$5:$A$504,0),"")) -> 9 | V96: =IF($C96="","",IFERROR(MATCH($C96,Parties!$A$5:$A$304,0),"")) -> 4 | W96: =IF($B96="","",IFERROR(VALUE(SUBSTITUTE($B96,InvPrefix,"")),0)) -> 76 | X96: =IF($D96="","",IF(OR($H96="",$H96="Credit"),0,Q96)) -> 5495.22
A97: 46226 | B97: INV-0077 | C97: FMCG Distributors | D97: Detergent 5kg | E97: 11 | I97: Delivered | J97: =IF($D97="","",IFERROR(INDEX(Items!$D$5:$D$504,U97),"")) -> Pack | K97: =IF($D97="","",IF($F97="",IFERROR(INDEX(Items!$H$5:$H$504,U97),0),$F97)) -> 691 | L97: =IF($D97="","",ROUND(N($E97)*K97*(1-N($G97)),2)) -> 7601 | M97: =IF($D97="","",IFERROR(INDEX(Items!$F$5:$F$504,U97),0)) -> 0.18 | N97: =IF($D97="","",IF(AND(V97<>"",INDEX(Parties!$E$5:$E$304,V97)<>"",INDEX(Parties!$E$5:$E$304,V97)<>HomeState),0,ROUND(L97*M97/2,2))) -> 684.09 | O97: =IF($D97="","",N97) -> 684.09 | P97: =IF($D97="","",IF(AND(V97<>"",INDEX(Parties!$E$5:$E$304,V97)<>"",INDEX(Parties!$E$5:$E$304,V97)<>HomeState),ROUND(L97*M97,2),0)) -> 0 | Q97: =IF($D97="","",L97+N97+O97+P97) -> 8969.18 | R97: =IF($D97="","",ROUND(N($E97)*IFERROR(INDEX(Items!$P$5:$P$504,U97),0),2)) -> 5694.62 | S97: =IF($D97="","",L97-R97) -> 1906.38 | T97: =IF($D97="","",IF(U97="","UNKNOWN ITEM",IF(INDEX(Items!$O$5:$O$504,U97)<0,"NEG STOCK",IF(K97<INDEX(Items!$P$5:$P$504,U97),"BELOW COST","OK")))) -> OK | U97: =IF($D97="","",IFERROR(MATCH($D97,Items!$A$5:$A$504,0),"")) -> 5 | V97: =IF($C97="","",IFERROR(MATCH($C97,Parties!$A$5:$A$304,0),"")) -> 9 | W97: =IF($B97="","",IFERROR(VALUE(SUBSTITUTE($B97,InvPrefix,"")),0)) -> 77 | X97: =IF($D97="","",IF(OR($H97="",$H97="Credit"),0,Q97)) -> 0
A98: 46227 | B98: INV-0078 | C98: Walk-in Customer | D98: Copper Wire 90m | E98: 3 | G98: 0.02 | H98: Cash | I98: Delivered | J98: =IF($D98="","",IFERROR(INDEX(Items!$D$5:$D$504,U98),"")) -> Pcs | K98: =IF($D98="","",IF($F98="",IFERROR(INDEX(Items!$H$5:$H$504,U98),0),$F98)) -> 3132 | L98: =IF($D98="","",ROUND(N($E98)*K98*(1-N($G98)),2)) -> 9208.08 | M98: =IF($D98="","",IFERROR(INDEX(Items!$F$5:$F$504,U98),0)) -> 0.18 | N98: =IF($D98="","",IF(AND(V98<>"",INDEX(Parties!$E$5:$E$304,V98)<>"",INDEX(Parties!$E$5:$E$304,V98)<>HomeState),0,ROUND(L98*M98/2,2))) -> 828.73 | O98: =IF($D98="","",N98) -> 828.73 | P98: =IF($D98="","",IF(AND(V98<>"",INDEX(Parties!$E$5:$E$304,V98)<>"",INDEX(Parties!$E$5:$E$304,V98)<>HomeState),ROUND(L98*M98,2),0)) -> 0 | Q98: =IF($D98="","",L98+N98+O98+P98) -> 10865.54 | R98: =IF($D98="","",ROUND(N($E98)*IFERROR(INDEX(Items!$P$5:$P$504,U98),0),2)) -> 7354.45 | S98: =IF($D98="","",L98-R98) -> 1853.63 | T98: =IF($D98="","",IF(U98="","UNKNOWN ITEM",IF(INDEX(Items!$O$5:$O$504,U98)<0,"NEG STOCK",IF(K98<INDEX(Items!$P$5:$P$504,U98),"BELOW COST","OK")))) -> OK | U98: =IF($D98="","",IFERROR(MATCH($D98,Items!$A$5:$A$504,0),"")) -> 8 | V98: =IF($C98="","",IFERROR(MATCH($C98,Parties!$A$5:$A$304,0),"")) -> 4 | W98: =IF($B98="","",IFERROR(VALUE(SUBSTITUTE($B98,InvPrefix,"")),0)) -> 78 | X98: =IF($D98="","",IF(OR($H98="",$H98="Credit"),0,Q98)) -> 10865.54
A99: 46230 | B99: INV-0079 | C99: Delhi Hardware Mart | D99: PVC Pipe 1in 6m | E99: 33 | G99: 0.02 | I99: Delivered | J99: =IF($D99="","",IFERROR(INDEX(Items!$D$5:$D$504,U99),"")) -> Pcs | K99: =IF($D99="","",IF($F99="",IFERROR(INDEX(Items!$H$5:$H$504,U99),0),$F99)) -> 297 | L99: =IF($D99="","",ROUND(N($E99)*K99*(1-N($G99)),2)) -> 9604.98 | M99: =IF($D99="","",IFERROR(INDEX(Items!$F$5:$F$504,U99),0)) -> 0.18 | N99: =IF($D99="","",IF(AND(V99<>"",INDEX(Parties!$E$5:$E$304,V99)<>"",INDEX(Parties!$E$5:$E$304,V99)<>HomeState),0,ROUND(L99*M99/2,2))) -> 0 | O99: =IF($D99="","",N99) -> 0 | P99: =IF($D99="","",IF(AND(V99<>"",INDEX(Parties!$E$5:$E$304,V99)<>"",INDEX(Parties!$E$5:$E$304,V99)<>HomeState),ROUND(L99*M99,2),0)) -> 1728.9 | Q99: =IF($D99="","",L99+N99+O99+P99) -> 11333.88 | R99: =IF($D99="","",ROUND(N($E99)*IFERROR(INDEX(Items!$P$5:$P$504,U99),0),2)) -> 6917.9 | S99: =IF($D99="","",L99-R99) -> 2687.08 | T99: =IF($D99="","",IF(U99="","UNKNOWN ITEM",IF(INDEX(Items!$O$5:$O$504,U99)<0,"NEG STOCK",IF(K99<INDEX(Items!$P$5:$P$504,U99),"BELOW COST","OK")))) -> OK | U99: =IF($D99="","",IFERROR(MATCH($D99,Items!$A$5:$A$504,0),"")) -> 9 | V99: =IF($C99="","",IFERROR(MATCH($C99,Parties!$A$5:$A$304,0),"")) -> 3 | W99: =IF($B99="","",IFERROR(VALUE(SUBSTITUTE($B99,InvPrefix,"")),0)) -> 79 | X99: =IF($D99="","",IF(OR($H99="",$H99="Credit"),0,Q99)) -> 0
A100: 46231 | B100: INV-0080 | C100: Walk-in Customer | D100: Copper Wire 90m | E100: 2 | G100: 0.05 | H100: Cash | I100: Delivered | J100: =IF($D100="","",IFERROR(INDEX(Items!$D$5:$D$504,U100),"")) -> Pcs | K100: =IF($D100="","",IF($F100="",IFERROR(INDEX(Items!$H$5:$H$504,U100),0),$F100)) -> 3132 | L100: =IF($D100="","",ROUND(N($E100)*K100*(1-N($G100)),2)) -> 5950.8 | M100: =IF($D100="","",IFERROR(INDEX(Items!$F$5:$F$504,U100),0)) -> 0.18 | N100: =IF($D100="","",IF(AND(V100<>"",INDEX(Parties!$E$5:$E$304,V100)<>"",INDEX(Parties!$E$5:$E$304,V100)<>HomeState),0,ROUND(L100*M100/2,2))) -> 535.57 | O100: =IF($D100="","",N100) -> 535.57 | P100: =IF($D100="","",IF(AND(V100<>"",INDEX(Parties!$E$5:$E$304,V100)<>"",INDEX(Parties!$E$5:$E$304,V100)<>HomeState),ROUND(L100*M100,2),0)) -> 0 | Q100: =IF($D100="","",L100+N100+O100+P100) -> 7021.94 | R100: =IF($D100="","",ROUND(N($E100)*IFERROR(INDEX(Items!$P$5:$P$504,U100),0),2)) -> 4902.96 | S100: =IF($D100="","",L100-R100) -> 1047.84 | T100: =IF($D100="","",IF(U100="","UNKNOWN ITEM",IF(INDEX(Items!$O$5:$O$504,U100)<0,"NEG STOCK",IF(K100<INDEX(Items!$P$5:$P$504,U100),"BELOW COST","OK")))) -> OK | U100: =IF($D100="","",IFERROR(MATCH($D100,Items!$A$5:$A$504,0),"")) -> 8 | V100: =IF($C100="","",IFERROR(MATCH($C100,Parties!$A$5:$A$304,0),"")) -> 4 | W100: =IF($B100="","",IFERROR(VALUE(SUBSTITUTE($B100,InvPrefix,"")),0)) -> 80 | X100: =IF($D100="","",IF(OR($H100="",$H100="Credit"),0,Q100)) -> 7021.94
...

Sheet Purchases
A1: PURCHASES / GOODS RECEIVED (PROCURE) | U1: « Home
A2: One line per item received. Stock, average cost, supplier payable and GST input credit update instantly.
A3: Blue / cream = type here | I3: Grey = automatic (do not type)
A4: Date * | B4: Bill No * | C4: Supplier * | D4: Item * | E4: Qty * | F4: Rate (₹) blank=std | G4: Disc % | H4: Paid Via (blank=Credit) | I4: Unit | J4: Rate Used (₹) | K4: Taxable (₹) | L4: GST % | M4: CGST (₹) | N4: SGST (₹) | O4: IGST (₹) | P4: Bill Total (₹) | Q4: itemRow | R4: partyRow | S4: Paid Now (₹)
A5: 46113 | B5: B-0001 | C5: Bharat Electric Co | D5: Copper Wire 90m | E5: 13 | F5: 2517 | I5: =IF($D5="","",IFERROR(INDEX(Items!$D$5:$D$504,Q5),"")) -> Pcs | J5: =IF($D5="","",IF($F5="",IFERROR(INDEX(Items!$G$5:$G$504,Q5),0),$F5)) -> 2517 | K5: =IF($D5="","",ROUND(N($E5)*J5*(1-N($G5)),2)) -> 32721 | L5: =IF($D5="","",IFERROR(INDEX(Items!$F$5:$F$504,Q5),0)) -> 0.18 | M5: =IF($D5="","",IF(AND(R5<>"",INDEX(Parties!$E$5:$E$304,R5)<>"",INDEX(Parties!$E$5:$E$304,R5)<>HomeState),0,ROUND(K5*L5/2,2))) -> 0 | N5: =IF($D5="","",M5) -> 0 | O5: =IF($D5="","",IF(AND(R5<>"",INDEX(Parties!$E$5:$E$304,R5)<>"",INDEX(Parties!$E$5:$E$304,R5)<>HomeState),ROUND(K5*L5,2),0)) -> 5889.78 | P5: =IF($D5="","",K5+M5+N5+O5) -> 38610.78 | Q5: =IF($D5="","",IFERROR(MATCH($D5,Items!$A$5:$A$504,0),"")) -> 8 | R5: =IF($C5="","",IFERROR(MATCH($C5,Parties!$A$5:$A$304,0),"")) -> 7 | S5: =IF($D5="","",IF(OR($H5="",$H5="Credit"),0,P5)) -> 0
A6: 46113 | B6: B-0001 | C6: Bharat Electric Co | D6: Ceiling Fan 1200mm | E6: 21 | F6: 1650 | I6: =IF($D6="","",IFERROR(INDEX(Items!$D$5:$D$504,Q6),"")) -> Pcs | J6: =IF($D6="","",IF($F6="",IFERROR(INDEX(Items!$G$5:$G$504,Q6),0),$F6)) -> 1650 | K6: =IF($D6="","",ROUND(N($E6)*J6*(1-N($G6)),2)) -> 34650 | L6: =IF($D6="","",IFERROR(INDEX(Items!$F$5:$F$504,Q6),0)) -> 0.18 | M6: =IF($D6="","",IF(AND(R6<>"",INDEX(Parties!$E$5:$E$304,R6)<>"",INDEX(Parties!$E$5:$E$304,R6)<>HomeState),0,ROUND(K6*L6/2,2))) -> 0 | N6: =IF($D6="","",M6) -> 0 | O6: =IF($D6="","",IF(AND(R6<>"",INDEX(Parties!$E$5:$E$304,R6)<>"",INDEX(Parties!$E$5:$E$304,R6)<>HomeState),ROUND(K6*L6,2),0)) -> 6237 | P6: =IF($D6="","",K6+M6+N6+O6) -> 40887 | Q6: =IF($D6="","",IFERROR(MATCH($D6,Items!$A$5:$A$504,0),"")) -> 12 | R6: =IF($C6="","",IFERROR(MATCH($C6,Parties!$A$5:$A$304,0),"")) -> 7 | S6: =IF($D6="","",IF(OR($H6="",$H6="Credit"),0,P6)) -> 0
A7: 46113 | B7: B-0002 | C7: FMCG Distributors | D7: Toothpaste 150g x12 | E7: 25 | F7: 885 | I7: =IF($D7="","",IFERROR(INDEX(Items!$D$5:$D$504,Q7),"")) -> Box | J7: =IF($D7="","",IF($F7="",IFERROR(INDEX(Items!$G$5:$G$504,Q7),0),$F7)) -> 885 | K7: =IF($D7="","",ROUND(N($E7)*J7*(1-N($G7)),2)) -> 22125 | L7: =IF($D7="","",IFERROR(INDEX(Items!$F$5:$F$504,Q7),0)) -> 0.05 | M7: =IF($D7="","",IF(AND(R7<>"",INDEX(Parties!$E$5:$E$304,R7)<>"",INDEX(Parties!$E$5:$E$304,R7)<>HomeState),0,ROUND(K7*L7/2,2))) -> 553.13 | N7: =IF($D7="","",M7) -> 553.13 | O7: =IF($D7="","",IF(AND(R7<>"",INDEX(Parties!$E$5:$E$304,R7)<>"",INDEX(Parties!$E$5:$E$304,R7)<>HomeState),ROUND(K7*L7,2),0)) -> 0 | P7: =IF($D7="","",K7+M7+N7+O7) -> 23231.26 | Q7: =IF($D7="","",IFERROR(MATCH($D7,Items!$A$5:$A$504,0),"")) -> 6 | R7: =IF($C7="","",IFERROR(MATCH($C7,Parties!$A$5:$A$304,0),"")) -> 9 | S7: =IF($D7="","",IF(OR($H7="",$H7="Credit"),0,P7)) -> 0
A8: 46144 | B8: B-0003 | C8: Agro Foods Pvt Ltd | D8: Basmati Rice 25kg | E8: 29 | F8: 1664 | I8: =IF($D8="","",IFERROR(INDEX(Items!$D$5:$D$504,Q8),"")) -> Bag | J8: =IF($D8="","",IF($F8="",IFERROR(INDEX(Items!$G$5:$G$504,Q8),0),$F8)) -> 1664 | K8: =IF($D8="","",ROUND(N($E8)*J8*(1-N($G8)),2)) -> 48256 | L8: =IF($D8="","",IFERROR(INDEX(Items!$F$5:$F$504,Q8),0)) -> 0.05 | M8: =IF($D8="","",IF(AND(R8<>"",INDEX(Parties!$E$5:$E$304,R8)<>"",INDEX(Parties!$E$5:$E$304,R8)<>HomeState),0,ROUND(K8*L8/2,2))) -> 1206.4 | N8: =IF($D8="","",M8) -> 1206.4 | O8: =IF($D8="","",IF(AND(R8<>"",INDEX(Parties!$E$5:$E$304,R8)<>"",INDEX(Parties!$E$5:$E$304,R8)<>HomeState),ROUND(K8*L8,2),0)) -> 0 | P8: =IF($D8="","",K8+M8+N8+O8) -> 50668.8 | Q8: =IF($D8="","",IFERROR(MATCH($D8,Items!$A$5:$A$504,0),"")) -> 1 | R8: =IF($C8="","",IFERROR(MATCH($C8,Parties!$A$5:$A$304,0),"")) -> 6 | S8: =IF($D8="","",IF(OR($H8="",$H8="Credit"),0,P8)) -> 0
A9: 46144 | B9: B-0003 | C9: Agro Foods Pvt Ltd | D9: Sugar 50kg | E9: 23 | F9: 2064 | I9: =IF($D9="","",IFERROR(INDEX(Items!$D$5:$D$504,Q9),"")) -> Bag | J9: =IF($D9="","",IF($F9="",IFERROR(INDEX(Items!$G$5:$G$504,Q9),0),$F9)) -> 2064 | K9: =IF($D9="","",ROUND(N($E9)*J9*(1-N($G9)),2)) -> 47472 | L9: =IF($D9="","",IFERROR(INDEX(Items!$F$5:$F$504,Q9),0)) -> 0.05 | M9: =IF($D9="","",IF(AND(R9<>"",INDEX(Parties!$E$5:$E$304,R9)<>"",INDEX(Parties!$E$5:$E$304,R9)<>HomeState),0,ROUND(K9*L9/2,2))) -> 1186.8 | N9: =IF($D9="","",M9) -> 1186.8 | O9: =IF($D9="","",IF(AND(R9<>"",INDEX(Parties!$E$5:$E$304,R9)<>"",INDEX(Parties!$E$5:$E$304,R9)<>HomeState),ROUND(K9*L9,2),0)) -> 0 | P9: =IF($D9="","",K9+M9+N9+O9) -> 49845.6 | Q9: =IF($D9="","",IFERROR(MATCH($D9,Items!$A$5:$A$504,0),"")) -> 2 | R9: =IF($C9="","",IFERROR(MATCH($C9,Parties!$A$5:$A$304,0),"")) -> 6 | S9: =IF($D9="","",IF(OR($H9="",$H9="Credit"),0,P9)) -> 0
A10: 46144 | B10: B-0003 | C10: Agro Foods Pvt Ltd | D10: Refined Oil 15L | E10: 33 | F10: 1932 | I10: =IF($D10="","",IFERROR(INDEX(Items!$D$5:$D$504,Q10),"")) -> Box | J10: =IF($D10="","",IF($F10="",IFERROR(INDEX(Items!$G$5:$G$504,Q10),0),$F10)) -> 1932 | K10: =IF($D10="","",ROUND(N($E10)*J10*(1-N($G10)),2)) -> 63756 | L10: =IF($D10="","",IFERROR(INDEX(Items!$F$5:$F$504,Q10),0)) -> 0.05 | M10: =IF($D10="","",IF(AND(R10<>"",INDEX(Parties!$E$5:$E$304,R10)<>"",INDEX(Parties!$E$5:$E$304,R10)<>HomeState),0,ROUND(K10*L10/2,2))) -> 1593.9 | N10: =IF($D10="","",M10) -> 1593.9 | O10: =IF($D10="","",IF(AND(R10<>"",INDEX(Parties!$E$5:$E$304,R10)<>"",INDEX(Parties!$E$5:$E$304,R10)<>HomeState),ROUND(K10*L10,2),0)) -> 0 | P10: =IF($D10="","",K10+M10+N10+O10) -> 66943.8 | Q10: =IF($D10="","",IFERROR(MATCH($D10,Items!$A$5:$A$504,0),"")) -> 3 | R10: =IF($C10="","",IFERROR(MATCH($C10,Parties!$A$5:$A$304,0),"")) -> 6 | S10: =IF($D10="","",IF(OR($H10="",$H10="Credit"),0,P10)) -> 0
A11: 46144 | B11: B-0004 | C11: Bharat Electric Co | D11: LED Bulb 9W | E11: 343 | F11: 61 | I11: =IF($D11="","",IFERROR(INDEX(Items!$D$5:$D$504,Q11),"")) -> Pcs | J11: =IF($D11="","",IF($F11="",IFERROR(INDEX(Items!$G$5:$G$504,Q11),0),$F11)) -> 61 | K11: =IF($D11="","",ROUND(N($E11)*J11*(1-N($G11)),2)) -> 20923 | L11: =IF($D11="","",IFERROR(INDEX(Items!$F$5:$F$504,Q11),0)) -> 0.18 | M11: =IF($D11="","",IF(AND(R11<>"",INDEX(Parties!$E$5:$E$304,R11)<>"",INDEX(Parties!$E$5:$E$304,R11)<>HomeState),0,ROUND(K11*L11/2,2))) -> 0 | N11: =IF($D11="","",M11) -> 0 | O11: =IF($D11="","",IF(AND(R11<>"",INDEX(Parties!$E$5:$E$304,R11)<>"",INDEX(Parties!$E$5:$E$304,R11)<>HomeState),ROUND(K11*L11,2),0)) -> 3766.14 | P11: =IF($D11="","",K11+M11+N11+O11) -> 24689.14 | Q11: =IF($D11="","",IFERROR(MATCH($D11,Items!$A$5:$A$504,0),"")) -> 7 | R11: =IF($C11="","",IFERROR(MATCH($C11,Parties!$A$5:$A$304,0),"")) -> 7 | S11: =IF($D11="","",IF(OR($H11="",$H11="Credit"),0,P11)) -> 0
A12: 46144 | B12: B-0005 | C12: FMCG Distributors | D12: Tea Premium 1kg | E12: 51 | F12: 384 | I12: =IF($D12="","",IFERROR(INDEX(Items!$D$5:$D$504,Q12),"")) -> Pack | J12: =IF($D12="","",IF($F12="",IFERROR(INDEX(Items!$G$5:$G$504,Q12),0),$F12)) -> 384 | K12: =IF($D12="","",ROUND(N($E12)*J12*(1-N($G12)),2)) -> 19584 | L12: =IF($D12="","",IFERROR(INDEX(Items!$F$5:$F$504,Q12),0)) -> 0.05 | M12: =IF($D12="","",IF(AND(R12<>"",INDEX(Parties!$E$5:$E$304,R12)<>"",INDEX(Parties!$E$5:$E$304,R12)<>HomeState),0,ROUND(K12*L12/2,2))) -> 489.6 | N12: =IF($D12="","",M12) -> 489.6 | O12: =IF($D12="","",IF(AND(R12<>"",INDEX(Parties!$E$5:$E$304,R12)<>"",INDEX(Parties!$E$5:$E$304,R12)<>HomeState),ROUND(K12*L12,2),0)) -> 0 | P12: =IF($D12="","",K12+M12+N12+O12) -> 20563.2 | Q12: =IF($D12="","",IFERROR(MATCH($D12,Items!$A$5:$A$504,0),"")) -> 4 | R12: =IF($C12="","",IFERROR(MATCH($C12,Parties!$A$5:$A$304,0),"")) -> 9 | S12: =IF($D12="","",IF(OR($H12="",$H12="Credit"),0,P12)) -> 0
A13: 46144 | B13: B-0005 | C13: FMCG Distributors | D13: Detergent 5kg | E13: 32 | F13: 513 | I13: =IF($D13="","",IFERROR(INDEX(Items!$D$5:$D$504,Q13),"")) -> Pack | J13: =IF($D13="","",IF($F13="",IFERROR(INDEX(Items!$G$5:$G$504,Q13),0),$F13)) -> 513 | K13: =IF($D13="","",ROUND(N($E13)*J13*(1-N($G13)),2)) -> 16416 | L13: =IF($D13="","",IFERROR(INDEX(Items!$F$5:$F$504,Q13),0)) -> 0.18 | M13: =IF($D13="","",IF(AND(R13<>"",INDEX(Parties!$E$5:$E$304,R13)<>"",INDEX(Parties!$E$5:$E$304,R13)<>HomeState),0,ROUND(K13*L13/2,2))) -> 1477.44 | N13: =IF($D13="","",M13) -> 1477.44 | O13: =IF($D13="","",IF(AND(R13<>"",INDEX(Parties!$E$5:$E$304,R13)<>"",INDEX(Parties!$E$5:$E$304,R13)<>HomeState),ROUND(K13*L13,2),0)) -> 0 | P13: =IF($D13="","",K13+M13+N13+O13) -> 19370.88 | Q13: =IF($D13="","",IFERROR(MATCH($D13,Items!$A$5:$A$504,0),"")) -> 5 | R13: =IF($C13="","",IFERROR(MATCH($C13,Parties!$A$5:$A$304,0),"")) -> 9 | S13: =IF($D13="","",IF(OR($H13="",$H13="Credit"),0,P13)) -> 0
A14: 46144 | B14: B-0006 | C14: National Hardware Supply | D14: PVC Pipe 1in 6m | E14: 132 | F14: 216 | I14: =IF($D14="","",IFERROR(INDEX(Items!$D$5:$D$504,Q14),"")) -> Pcs | J14: =IF($D14="","",IF($F14="",IFERROR(INDEX(Items!$G$5:$G$504,Q14),0),$F14)) -> 216 | K14: =IF($D14="","",ROUND(N($E14)*J14*(1-N($G14)),2)) -> 28512 | L14: =IF($D14="","",IFERROR(INDEX(Items!$F$5:$F$504,Q14),0)) -> 0.18 | M14: =IF($D14="","",IF(AND(R14<>"",INDEX(Parties!$E$5:$E$304,R14)<>"",INDEX(Parties!$E$5:$E$304,R14)<>HomeState),0,ROUND(K14*L14/2,2))) -> 2566.08 | N14: =IF($D14="","",M14) -> 2566.08 | O14: =IF($D14="","",IF(AND(R14<>"",INDEX(Parties!$E$5:$E$304,R14)<>"",INDEX(Parties!$E$5:$E$304,R14)<>HomeState),ROUND(K14*L14,2),0)) -> 0 | P14: =IF($D14="","",K14+M14+N14+O14) -> 33644.16 | Q14: =IF($D14="","",IFERROR(MATCH($D14,Items!$A$5:$A$504,0),"")) -> 9 | R14: =IF($C14="","",IFERROR(MATCH($C14,Parties!$A$5:$A$304,0),"")) -> 8 | S14: =IF($D14="","",IF(OR($H14="",$H14="Credit"),0,P14)) -> 0
A15: 46144 | B15: B-0006 | C15: National Hardware Supply | D15: Cement 50kg | E15: 115 | F15: 343 | I15: =IF($D15="","",IFERROR(INDEX(Items!$D$5:$D$504,Q15),"")) -> Bag | J15: =IF($D15="","",IF($F15="",IFERROR(INDEX(Items!$G$5:$G$504,Q15),0),$F15)) -> 343 | K15: =IF($D15="","",ROUND(N($E15)*J15*(1-N($G15)),2)) -> 39445 | L15: =IF($D15="","",IFERROR(INDEX(Items!$F$5:$F$504,Q15),0)) -> 0.18 | M15: =IF($D15="","",IF(AND(R15<>"",INDEX(Parties!$E$5:$E$304,R15)<>"",INDEX(Parties!$E$5:$E$304,R15)<>HomeState),0,ROUND(K15*L15/2,2))) -> 3550.05 | N15: =IF($D15="","",M15) -> 3550.05 | O15: =IF($D15="","",IF(AND(R15<>"",INDEX(Parties!$E$5:$E$304,R15)<>"",INDEX(Parties!$E$5:$E$304,R15)<>HomeState),ROUND(K15*L15,2),0)) -> 0 | P15: =IF($D15="","",K15+M15+N15+O15) -> 46545.1 | Q15: =IF($D15="","",IFERROR(MATCH($D15,Items!$A$5:$A$504,0),"")) -> 10 | R15: =IF($C15="","",IFERROR(MATCH($C15,Parties!$A$5:$A$304,0),"")) -> 8 | S15: =IF($D15="","",IF(OR($H15="",$H15="Credit"),0,P15)) -> 0
A16: 46175 | B16: B-0007 | C16: Agro Foods Pvt Ltd | D16: Refined Oil 15L | E16: 27 | F16: 1910 | I16: =IF($D16="","",IFERROR(INDEX(Items!$D$5:$D$504,Q16),"")) -> Box | J16: =IF($D16="","",IF($F16="",IFERROR(INDEX(Items!$G$5:$G$504,Q16),0),$F16)) -> 1910 | K16: =IF($D16="","",ROUND(N($E16)*J16*(1-N($G16)),2)) -> 51570 | L16: =IF($D16="","",IFERROR(INDEX(Items!$F$5:$F$504,Q16),0)) -> 0.05 | M16: =IF($D16="","",IF(AND(R16<>"",INDEX(Parties!$E$5:$E$304,R16)<>"",INDEX(Parties!$E$5:$E$304,R16)<>HomeState),0,ROUND(K16*L16/2,2))) -> 1289.25 | N16: =IF($D16="","",M16) -> 1289.25 | O16: =IF($D16="","",IF(AND(R16<>"",INDEX(Parties!$E$5:$E$304,R16)<>"",INDEX(Parties!$E$5:$E$304,R16)<>HomeState),ROUND(K16*L16,2),0)) -> 0 | P16: =IF($D16="","",K16+M16+N16+O16) -> 54148.5 | Q16: =IF($D16="","",IFERROR(MATCH($D16,Items!$A$5:$A$504,0),"")) -> 3 | R16: =IF($C16="","",IFERROR(MATCH($C16,Parties!$A$5:$A$304,0),"")) -> 6 | S16: =IF($D16="","",IF(OR($H16="",$H16="Credit"),0,P16)) -> 0
... A21: 46205 | B21: B-0011 | C21: Bharat Electric Co | D21: LED Bulb 9W | E21: 212 | F21: 63 | I21: =IF($D21="","",IFERROR(INDEX(Items!$D$5:$D$504,Q21),"")) -> Pcs | J21: =IF($D21="","",IF($F21="",IFERROR(INDEX(Items!$G$5:$G$504,Q21),0),$F21)) -> 63 | K21: =IF($D21="","",ROUND(N($E21)*J21*(1-N($G21)),2)) -> 13356 | L21: =IF($D21="","",IFERROR(INDEX(Items!$F$5:$F$504,Q21),0)) -> 0.18 | M21: =IF($D21="","",IF(AND(R21<>"",INDEX(Parties!$E$5:$E$304,R21)<>"",INDEX(Parties!$E$5:$E$304,R21)<>HomeState),0,ROUND(K21*L21/2,2))) -> 0 | N21: =IF($D21="","",M21) -> 0 | O21: =IF($D21="","",IF(AND(R21<>"",INDEX(Parties!$E$5:$E$304,R21)<>"",INDEX(Parties!$E$5:$E$304,R21)<>HomeState),ROUND(K21*L21,2),0)) -> 2404.08 | P21: =IF($D21="","",K21+M21+N21+O21) -> 15760.08 | Q21: =IF($D21="","",IFERROR(MATCH($D21,Items!$A$5:$A$504,0),"")) -> 7 | R21: =IF($C21="","",IFERROR(MATCH($C21,Parties!$A$5:$A$304,0),"")) -> 7 | S21: =IF($D21="","",IF(OR($H21="",$H21="Credit"),0,P21)) -> 0
A22: 46205 | B22: B-0012 | C22: FMCG Distributors | D22: Tea Premium 1kg | E22: 49 | F22: 377 | H22: Bank | I22: =IF($D22="","",IFERROR(INDEX(Items!$D$5:$D$504,Q22),"")) -> Pack | J22: =IF($D22="","",IF($F22="",IFERROR(INDEX(Items!$G$5:$G$504,Q22),0),$F22)) -> 377 | K22: =IF($D22="","",ROUND(N($E22)*J22*(1-N($G22)),2)) -> 18473 | L22: =IF($D22="","",IFERROR(INDEX(Items!$F$5:$F$504,Q22),0)) -> 0.05 | M22: =IF($D22="","",IF(AND(R22<>"",INDEX(Parties!$E$5:$E$304,R22)<>"",INDEX(Parties!$E$5:$E$304,R22)<>HomeState),0,ROUND(K22*L22/2,2))) -> 461.83 | N22: =IF($D22="","",M22) -> 461.83 | O22: =IF($D22="","",IF(AND(R22<>"",INDEX(Parties!$E$5:$E$304,R22)<>"",INDEX(Parties!$E$5:$E$304,R22)<>HomeState),ROUND(K22*L22,2),0)) -> 0 | P22: =IF($D22="","",K22+M22+N22+O22) -> 19396.66 | Q22: =IF($D22="","",IFERROR(MATCH($D22,Items!$A$5:$A$504,0),"")) -> 4 | R22: =IF($C22="","",IFERROR(MATCH($C22,Parties!$A$5:$A$304,0),"")) -> 9 | S22: =IF($D22="","",IF(OR($H22="",$H22="Credit"),0,P22)) -> 19396.66
A23: 46236 | B23: B-0013 | C23: Agro Foods Pvt Ltd | D23: Sugar 50kg | E23: 33 | F23: 2048 | H23: Bank | I23: =IF($D23="","",IFERROR(INDEX(Items!$D$5:$D$504,Q23),"")) -> Bag | J23: =IF($D23="","",IF($F23="",IFERROR(INDEX(Items!$G$5:$G$504,Q23),0),$F23)) -> 2048 | K23: =IF($D23="","",ROUND(N($E23)*J23*(1-N($G23)),2)) -> 67584 | L23: =IF($D23="","",IFERROR(INDEX(Items!$F$5:$F$504,Q23),0)) -> 0.05 | M23: =IF($D23="","",IF(AND(R23<>"",INDEX(Parties!$E$5:$E$304,R23)<>"",INDEX(Parties!$E$5:$E$304,R23)<>HomeState),0,ROUND(K23*L23/2,2))) -> 1689.6 | N23: =IF($D23="","",M23) -> 1689.6 | O23: =IF($D23="","",IF(AND(R23<>"",INDEX(Parties!$E$5:$E$304,R23)<>"",INDEX(Parties!$E$5:$E$304,R23)<>HomeState),ROUND(K23*L23,2),0)) -> 0 | P23: =IF($D23="","",K23+M23+N23+O23) -> 70963.2 | Q23: =IF($D23="","",IFERROR(MATCH($D23,Items!$A$5:$A$504,0),"")) -> 2 | R23: =IF($C23="","",IFERROR(MATCH($C23,Parties!$A$5:$A$304,0),"")) -> 6 | S23: =IF($D23="","",IF(OR($H23="",$H23="Credit"),0,P23)) -> 70963.2
A24: 46236 | B24: B-0014 | C24: Bharat Electric Co | D24: Copper Wire 90m | E24: 12 | F24: 2447 | I24: =IF($D24="","",IFERROR(INDEX(Items!$D$5:$D$504,Q24),"")) -> Pcs | J24: =IF($D24="","",IF($F24="",IFERROR(INDEX(Items!$G$5:$G$504,Q24),0),$F24)) -> 2447 | K24: =IF($D24="","",ROUND(N($E24)*J24*(1-N($G24)),2)) -> 29364 | L24: =IF($D24="","",IFERROR(INDEX(Items!$F$5:$F$504,Q24),0)) -> 0.18 | M24: =IF($D24="","",IF(AND(R24<>"",INDEX(Parties!$E$5:$E$304,R24)<>"",INDEX(Parties!$E$5:$E$304,R24)<>HomeState),0,ROUND(K24*L24/2,2))) -> 0 | N24: =IF($D24="","",M24) -> 0 | O24: =IF($D24="","",IF(AND(R24<>"",INDEX(Parties!$E$5:$E$304,R24)<>"",INDEX(Parties!$E$5:$E$304,R24)<>HomeState),ROUND(K24*L24,2),0)) -> 5285.52 | P24: =IF($D24="","",K24+M24+N24+O24) -> 34649.52 | Q24: =IF($D24="","",IFERROR(MATCH($D24,Items!$A$5:$A$504,0),"")) -> 8 | R24: =IF($C24="","",IFERROR(MATCH($C24,Parties!$A$5:$A$304,0),"")) -> 7 | S24: =IF($D24="","",IF(OR($H24="",$H24="Credit"),0,P24)) -> 0
A25: 46236 | B25: B-0014 | C25: Bharat Electric Co | D25: Ceiling Fan 1200mm | E25: 13 | F25: 1645 | I25: =IF($D25="","",IFERROR(INDEX(Items!$D$5:$D$504,Q25),"")) -> Pcs | J25: =IF($D25="","",IF($F25="",IFERROR(INDEX(Items!$G$5:$G$504,Q25),0),$F25)) -> 1645 | K25: =IF($D25="","",ROUND(N($E25)*J25*(1-N($G25)),2)) -> 21385 | L25: =IF($D25="","",IFERROR(INDEX(Items!$F$5:$F$504,Q25),0)) -> 0.18 | M25: =IF($D25="","",IF(AND(R25<>"",INDEX(Parties!$E$5:$E$304,R25)<>"",INDEX(Parties!$E$5:$E$304,R25)<>HomeState),0,ROUND(K25*L25/2,2))) -> 0 | N25: =IF($D25="","",M25) -> 0 | O25: =IF($D25="","",IF(AND(R25<>"",INDEX(Parties!$E$5:$E$304,R25)<>"",INDEX(Parties!$E$5:$E$304,R25)<>HomeState),ROUND(K25*L25,2),0)) -> 3849.3 | P25: =IF($D25="","",K25+M25+N25+O25) -> 25234.3 | Q25: =IF($D25="","",IFERROR(MATCH($D25,Items!$A$5:$A$504,0),"")) -> 12 | R25: =IF($C25="","",IFERROR(MATCH($C25,Parties!$A$5:$A$304,0),"")) -> 7 | S25: =IF($D25="","",IF(OR($H25="",$H25="Credit"),0,P25)) -> 0
A26: 46236 | B26: B-0015 | C26: FMCG Distributors | D26: Detergent 5kg | E26: 59 | F26: 523 | I26: =IF($D26="","",IFERROR(INDEX(Items!$D$5:$D$504,Q26),"")) -> Pack | J26: =IF($D26="","",IF($F26="",IFERROR(INDEX(Items!$G$5:$G$504,Q26),0),$F26)) -> 523 | K26: =IF($D26="","",ROUND(N($E26)*J26*(1-N($G26)),2)) -> 30857 | L26: =IF($D26="","",IFERROR(INDEX(Items!$F$5:$F$504,Q26),0)) -> 0.18 | M26: =IF($D26="","",IF(AND(R26<>"",INDEX(Parties!$E$5:$E$304,R26)<>"",INDEX(Parties!$E$5:$E$304,R26)<>HomeState),0,ROUND(K26*L26/2,2))) -> 2777.13 | N26: =IF($D26="","",M26) -> 2777.13 | O26: =IF($D26="","",IF(AND(R26<>"",INDEX(Parties!$E$5:$E$304,R26)<>"",INDEX(Parties!$E$5:$E$304,R26)<>HomeState),ROUND(K26*L26,2),0)) -> 0 | P26: =IF($D26="","",K26+M26+N26+O26) -> 36411.26 | Q26: =IF($D26="","",IFERROR(MATCH($D26,Items!$A$5:$A$504,0),"")) -> 5 | R26: =IF($C26="","",IFERROR(MATCH($C26,Parties!$A$5:$A$304,0),"")) -> 9 | S26: =IF($D26="","",IF(OR($H26="",$H26="Credit"),0,P26)) -> 0
A27: 46236 | B27: B-0016 | C27: National Hardware Supply | D27: PVC Pipe 1in 6m | E27: 125 | F27: 207 | I27: =IF($D27="","",IFERROR(INDEX(Items!$D$5:$D$504,Q27),"")) -> Pcs | J27: =IF($D27="","",IF($F27="",IFERROR(INDEX(Items!$G$5:$G$504,Q27),0),$F27)) -> 207 | K27: =IF($D27="","",ROUND(N($E27)*J27*(1-N($G27)),2)) -> 25875 | L27: =IF($D27="","",IFERROR(INDEX(Items!$F$5:$F$504,Q27),0)) -> 0.18 | M27: =IF($D27="","",IF(AND(R27<>"",INDEX(Parties!$E$5:$E$304,R27)<>"",INDEX(Parties!$E$5:$E$304,R27)<>HomeState),0,ROUND(K27*L27/2,2))) -> 2328.75 | N27: =IF($D27="","",M27) -> 2328.75 | O27: =IF($D27="","",IF(AND(R27<>"",INDEX(Parties!$E$5:$E$304,R27)<>"",INDEX(Parties!$E$5:$E$304,R27)<>HomeState),ROUND(K27*L27,2),0)) -> 0 | P27: =IF($D27="","",K27+M27+N27+O27) -> 30532.5 | Q27: =IF($D27="","",IFERROR(MATCH($D27,Items!$A$5:$A$504,0),"")) -> 9 | R27: =IF($C27="","",IFERROR(MATCH($C27,Parties!$A$5:$A$304,0),"")) -> 8 | S27: =IF($D27="","",IF(OR($H27="",$H27="Credit"),0,P27)) -> 0
A28: 46267 | B28: B-0017 | C28: Agro Foods Pvt Ltd | D28: Basmati Rice 25kg | E28: 29 | F28: 1648 | I28: =IF($D28="","",IFERROR(INDEX(Items!$D$5:$D$504,Q28),"")) -> Bag | J28: =IF($D28="","",IF($F28="",IFERROR(INDEX(Items!$G$5:$G$504,Q28),0),$F28)) -> 1648 | K28: =IF($D28="","",ROUND(N($E28)*J28*(1-N($G28)),2)) -> 47792 | L28: =IF($D28="","",IFERROR(INDEX(Items!$F$5:$F$504,Q28),0)) -> 0.05 | M28: =IF($D28="","",IF(AND(R28<>"",INDEX(Parties!$E$5:$E$304,R28)<>"",INDEX(Parties!$E$5:$E$304,R28)<>HomeState),0,ROUND(K28*L28/2,2))) -> 1194.8 | N28: =IF($D28="","",M28) -> 1194.8 | O28: =IF($D28="","",IF(AND(R28<>"",INDEX(Parties!$E$5:$E$304,R28)<>"",INDEX(Parties!$E$5:$E$304,R28)<>HomeState),ROUND(K28*L28,2),0)) -> 0 | P28: =IF($D28="","",K28+M28+N28+O28) -> 50181.6 | Q28: =IF($D28="","",IFERROR(MATCH($D28,Items!$A$5:$A$504,0),"")) -> 1 | R28: =IF($C28="","",IFERROR(MATCH($C28,Parties!$A$5:$A$304,0),"")) -> 6 | S28: =IF($D28="","",IF(OR($H28="",$H28="Credit"),0,P28)) -> 0
A29: 46267 | B29: B-0017 | C29: Agro Foods Pvt Ltd | D29: Refined Oil 15L | E29: 23 | F29: 1929 | I29: =IF($D29="","",IFERROR(INDEX(Items!$D$5:$D$504,Q29),"")) -> Box | J29: =IF($D29="","",IF($F29="",IFERROR(INDEX(Items!$G$5:$G$504,Q29),0),$F29)) -> 1929 | K29: =IF($D29="","",ROUND(N($E29)*J29*(1-N($G29)),2)) -> 44367 | L29: =IF($D29="","",IFERROR(INDEX(Items!$F$5:$F$504,Q29),0)) -> 0.05 | M29: =IF($D29="","",IF(AND(R29<>"",INDEX(Parties!$E$5:$E$304,R29)<>"",INDEX(Parties!$E$5:$E$304,R29)<>HomeState),0,ROUND(K29*L29/2,2))) -> 1109.18 | N29: =IF($D29="","",M29) -> 1109.18 | O29: =IF($D29="","",IF(AND(R29<>"",INDEX(Parties!$E$5:$E$304,R29)<>"",INDEX(Parties!$E$5:$E$304,R29)<>HomeState),ROUND(K29*L29,2),0)) -> 0 | P29: =IF($D29="","",K29+M29+N29+O29) -> 46585.36 | Q29: =IF($D29="","",IFERROR(MATCH($D29,Items!$A$5:$A$504,0),"")) -> 3 | R29: =IF($C29="","",IFERROR(MATCH($C29,Parties!$A$5:$A$304,0),"")) -> 6 | S29: =IF($D29="","",IF(OR($H29="",$H29="Credit"),0,P29)) -> 0
A30: 46267 | B30: B-0018 | C30: Bharat Electric Co | D30: LED Bulb 9W | E30: 399 | F30: 62 | I30: =IF($D30="","",IFERROR(INDEX(Items!$D$5:$D$504,Q30),"")) -> Pcs | J30: =IF($D30="","",IF($F30="",IFERROR(INDEX(Items!$G$5:$G$504,Q30),0),$F30)) -> 62 | K30: =IF($D30="","",ROUND(N($E30)*J30*(1-N($G30)),2)) -> 24738 | L30: =IF($D30="","",IFERROR(INDEX(Items!$F$5:$F$504,Q30),0)) -> 0.18 | M30: =IF($D30="","",IF(AND(R30<>"",INDEX(Parties!$E$5:$E$304,R30)<>"",INDEX(Parties!$E$5:$E$304,R30)<>HomeState),0,ROUND(K30*L30/2,2))) -> 0 | N30: =IF($D30="","",M30) -> 0 | O30: =IF($D30="","",IF(AND(R30<>"",INDEX(Parties!$E$5:$E$304,R30)<>"",INDEX(Parties!$E$5:$E$304,R30)<>HomeState),ROUND(K30*L30,2),0)) -> 4452.84 | P30: =IF($D30="","",K30+M30+N30+O30) -> 29190.84 | Q30: =IF($D30="","",IFERROR(MATCH($D30,Items!$A$5:$A$504,0),"")) -> 7 | R30: =IF($C30="","",IFERROR(MATCH($C30,Parties!$A$5:$A$304,0),"")) -> 7 | S30: =IF($D30="","",IF(OR($H30="",$H30="Credit"),0,P30)) -> 0
A31: 46267 | B31: B-0019 | C31: FMCG Distributors | D31: Tea Premium 1kg | E31: 55 | F31: 373 | H31: Bank | I31: =IF($D31="","",IFERROR(INDEX(Items!$D$5:$D$504,Q31),"")) -> Pack | J31: =IF($D31="","",IF($F31="",IFERROR(INDEX(Items!$G$5:$G$504,Q31),0),$F31)) -> 373 | K31: =IF($D31="","",ROUND(N($E31)*J31*(1-N($G31)),2)) -> 20515 | L31: =IF($D31="","",IFERROR(INDEX(Items!$F$5:$F$504,Q31),0)) -> 0.05 | M31: =IF($D31="","",IF(AND(R31<>"",INDEX(Parties!$E$5:$E$304,R31)<>"",INDEX(Parties!$E$5:$E$304,R31)<>HomeState),0,ROUND(K31*L31/2,2))) -> 512.88 | N31: =IF($D31="","",M31) -> 512.88 | O31: =IF($D31="","",IF(AND(R31<>"",INDEX(Parties!$E$5:$E$304,R31)<>"",INDEX(Parties!$E$5:$E$304,R31)<>HomeState),ROUND(K31*L31,2),0)) -> 0 | P31: =IF($D31="","",K31+M31+N31+O31) -> 21540.76 | Q31: =IF($D31="","",IFERROR(MATCH($D31,Items!$A$5:$A$504,0),"")) -> 4 | R31: =IF($C31="","",IFERROR(MATCH($C31,Parties!$A$5:$A$304,0),"")) -> 9 | S31: =IF($D31="","",IF(OR($H31="",$H31="Credit"),0,P31)) -> 21540.76
A32: 46267 | B32: B-0019 | C32: FMCG Distributors | D32: Toothpaste 150g x12 | E32: 25 | F32: 900 | H32: Bank | I32: =IF($D32="","",IFERROR(INDEX(Items!$D$5:$D$504,Q32),"")) -> Box | J32: =IF($D32="","",IF($F32="",IFERROR(INDEX(Items!$G$5:$G$504,Q32),0),$F32)) -> 900 | K32: =IF($D32="","",ROUND(N($E32)*J32*(1-N($G32)),2)) -> 22500 | L32: =IF($D32="","",IFERROR(INDEX(Items!$F$5:$F$504,Q32),0)) -> 0.05 | M32: =IF($D32="","",IF(AND(R32<>"",INDEX(Parties!$E$5:$E$304,R32)<>"",INDEX(Parties!$E$5:$E$304,R32)<>HomeState),0,ROUND(K32*L32/2,2))) -> 562.5 | N32: =IF($D32="","",M32) -> 562.5 | O32: =IF($D32="","",IF(AND(R32<>"",INDEX(Parties!$E$5:$E$304,R32)<>"",INDEX(Parties!$E$5:$E$304,R32)<>HomeState),ROUND(K32*L32,2),0)) -> 0 | P32: =IF($D32="","",K32+M32+N32+O32) -> 23625 | Q32: =IF($D32="","",IFERROR(MATCH($D32,Items!$A$5:$A$504,0),"")) -> 6 | R32: =IF($C32="","",IFERROR(MATCH($C32,Parties!$A$5:$A$304,0),"")) -> 9 | S32: =IF($D32="","",IF(OR($H32="",$H32="Credit"),0,P32)) -> 23625
A33: 46297 | B33: B-0020 | C33: Agro Foods Pvt Ltd | D33: Basmati Rice 25kg | E33: 22 | F33: 1649 | I33: =IF($D33="","",IFERROR(INDEX(Items!$D$5:$D$504,Q33),"")) -> Bag | J33: =IF($D33="","",IF($F33="",IFERROR(INDEX(Items!$G$5:$G$504,Q33),0),$F33)) -> 1649 | K33: =IF($D33="","",ROUND(N($E33)*J33*(1-N($G33)),2)) -> 36278 | L33: =IF($D33="","",IFERROR(INDEX(Items!$F$5:$F$504,Q33),0)) -> 0.05 | M33: =IF($D33="","",IF(AND(R33<>"",INDEX(Parties!$E$5:$E$304,R33)<>"",INDEX(Parties!$E$5:$E$304,R33)<>HomeState),0,ROUND(K33*L33/2,2))) -> 906.95 | N33: =IF($D33="","",M33) -> 906.95 | O33: =IF($D33="","",IF(AND(R33<>"",INDEX(Parties!$E$5:$E$304,R33)<>"",INDEX(Parties!$E$5:$E$304,R33)<>HomeState),ROUND(K33*L33,2),0)) -> 0 | P33: =IF($D33="","",K33+M33+N33+O33) -> 38091.9 | Q33: =IF($D33="","",IFERROR(MATCH($D33,Items!$A$5:$A$504,0),"")) -> 1 | R33: =IF($C33="","",IFERROR(MATCH($C33,Parties!$A$5:$A$304,0),"")) -> 6 | S33: =IF($D33="","",IF(OR($H33="",$H33="Credit"),0,P33)) -> 0
A34: 46297 | B34: B-0021 | C34: Bharat Electric Co | D34: Ceiling Fan 1200mm | E34: 13 | F34: 1634 | H34: Bank | I34: =IF($D34="","",IFERROR(INDEX(Items!$D$5:$D$504,Q34),"")) -> Pcs | J34: =IF($D34="","",IF($F34="",IFERROR(INDEX(Items!$G$5:$G$504,Q34),0),$F34)) -> 1634 | K34: =IF($D34="","",ROUND(N($E34)*J34*(1-N($G34)),2)) -> 21242 | L34: =IF($D34="","",IFERROR(INDEX(Items!$F$5:$F$504,Q34),0)) -> 0.18 | M34: =IF($D34="","",IF(AND(R34<>"",INDEX(Parties!$E$5:$E$304,R34)<>"",INDEX(Parties!$E$5:$E$304,R34)<>HomeState),0,ROUND(K34*L34/2,2))) -> 0 | N34: =IF($D34="","",M34) -> 0 | O34: =IF($D34="","",IF(AND(R34<>"",INDEX(Parties!$E$5:$E$304,R34)<>"",INDEX(Parties!$E$5:$E$304,R34)<>HomeState),ROUND(K34*L34,2),0)) -> 3823.56 | P34: =IF($D34="","",K34+M34+N34+O34) -> 25065.56 | Q34: =IF($D34="","",IFERROR(MATCH($D34,Items!$A$5:$A$504,0),"")) -> 12 | R34: =IF($C34="","",IFERROR(MATCH($C34,Parties!$A$5:$A$304,0),"")) -> 7 | S34: =IF($D34="","",IF(OR($H34="",$H34="Credit"),0,P34)) -> 25065.56
A35: 46297 | B35: B-0022 | C35: FMCG Distributors | D35: Detergent 5kg | E35: 67 | F35: 521 | I35: =IF($D35="","",IFERROR(INDEX(Items!$D$5:$D$504,Q35),"")) -> Pack | J35: =IF($D35="","",IF($F35="",IFERROR(INDEX(Items!$G$5:$G$504,Q35),0),$F35)) -> 521 | K35: =IF($D35="","",ROUND(N($E35)*J35*(1-N($G35)),2)) -> 34907 | L35: =IF($D35="","",IFERROR(INDEX(Items!$F$5:$F$504,Q35),0)) -> 0.18 | M35: =IF($D35="","",IF(AND(R35<>"",INDEX(Parties!$E$5:$E$304,R35)<>"",INDEX(Parties!$E$5:$E$304,R35)<>HomeState),0,ROUND(K35*L35/2,2))) -> 3141.63 | N35: =IF($D35="","",M35) -> 3141.63 | O35: =IF($D35="","",IF(AND(R35<>"",INDEX(Parties!$E$5:$E$304,R35)<>"",INDEX(Parties!$E$5:$E$304,R35)<>HomeState),ROUND(K35*L35,2),0)) -> 0 | P35: =IF($D35="","",K35+M35+N35+O35) -> 41190.26 | Q35: =IF($D35="","",IFERROR(MATCH($D35,Items!$A$5:$A$504,0),"")) -> 5 | R35: =IF($C35="","",IFERROR(MATCH($C35,Parties!$A$5:$A$304,0),"")) -> 9 | S35: =IF($D35="","",IF(OR($H35="",$H35="Credit"),0,P35)) -> 0
A36: 46297 | B36: B-0022 | C36: FMCG Distributors | D36: Toothpaste 150g x12 | E36: 21 | F36: 889 | I36: =IF($D36="","",IFERROR(INDEX(Items!$D$5:$D$504,Q36),"")) -> Box | J36: =IF($D36="","",IF($F36="",IFERROR(INDEX(Items!$G$5:$G$504,Q36),0),$F36)) -> 889 | K36: =IF($D36="","",ROUND(N($E36)*J36*(1-N($G36)),2)) -> 18669 | L36: =IF($D36="","",IFERROR(INDEX(Items!$F$5:$F$504,Q36),0)) -> 0.05 | M36: =IF($D36="","",IF(AND(R36<>"",INDEX(Parties!$E$5:$E$304,R36)<>"",INDEX(Parties!$E$5:$E$304,R36)<>HomeState),0,ROUND(K36*L36/2,2))) -> 466.73 | N36: =IF($D36="","",M36) -> 466.73 | O36: =IF($D36="","",IF(AND(R36<>"",INDEX(Parties!$E$5:$E$304,R36)<>"",INDEX(Parties!$E$5:$E$304,R36)<>HomeState),ROUND(K36*L36,2),0)) -> 0 | P36: =IF($D36="","",K36+M36+N36+O36) -> 19602.46 | Q36: =IF($D36="","",IFERROR(MATCH($D36,Items!$A$5:$A$504,0),"")) -> 6 | R36: =IF($C36="","",IFERROR(MATCH($C36,Parties!$A$5:$A$304,0),"")) -> 9 | S36: =IF($D36="","",IF(OR($H36="",$H36="Credit"),0,P36)) -> 0
A37: 46297 | B37: B-0023 | C37: National Hardware Supply | D37: Cement 50kg | E37: 104 | F37: 347 | I37: =IF($D37="","",IFERROR(INDEX(Items!$D$5:$D$504,Q37),"")) -> Bag | J37: =IF($D37="","",IF($F37="",IFERROR(INDEX(Items!$G$5:$G$504,Q37),0),$F37)) -> 347 | K37: =IF($D37="","",ROUND(N($E37)*J37*(1-N($G37)),2)) -> 36088 | L37: =IF($D37="","",IFERROR(INDEX(Items!$F$5:$F$504,Q37),0)) -> 0.18 | M37: =IF($D37="","",IF(AND(R37<>"",INDEX(Parties!$E$5:$E$304,R37)<>"",INDEX(Parties!$E$5:$E$304,R37)<>HomeState),0,ROUND(K37*L37/2,2))) -> 3247.92 | N37: =IF($D37="","",M37) -> 3247.92 | O37: =IF($D37="","",IF(AND(R37<>"",INDEX(Parties!$E$5:$E$304,R37)<>"",INDEX(Parties!$E$5:$E$304,R37)<>HomeState),ROUND(K37*L37,2),0)) -> 0 | P37: =IF($D37="","",K37+M37+N37+O37) -> 42583.84 | Q37: =IF($D37="","",IFERROR(MATCH($D37,Items!$A$5:$A$504,0),"")) -> 10 | R37: =IF($C37="","",IFERROR(MATCH($C37,Parties!$A$5:$A$304,0),"")) -> 8 | S37: =IF($D37="","",IF(OR($H37="",$H37="Credit"),0,P37)) -> 0
I38: =IF($D38="","",IFERROR(INDEX(Items!$D$5:$D$504,Q38),"")) | J38: =IF($D38="","",IF($F38="",IFERROR(INDEX(Items!$G$5:$G$504,Q38),0),$F38)) | K38: =IF($D38="","",ROUND(N($E38)*J38*(1-N($G38)),2)) | L38: =IF($D38="","",IFERROR(INDEX(Items!$F$5:$F$504,Q38),0)) | M38: =IF($D38="","",IF(AND(R38<>"",INDEX(Parties!$E$5:$E$304,R38)<>"",INDEX(Parties!$E$5:$E$304,R38)<>HomeState),0,ROUND(K38*L38/2,2))) | N38: =IF($D38="","",M38) | O38: =IF($D38="","",IF(AND(R38<>"",INDEX(Parties!$E$5:$E$304,R38)<>"",INDEX(Parties!$E$5:$E$304,R38)<>HomeState),ROUND(K38*L38,2),0)) | P38: =IF($D38="","",K38+M38+N38+O38) | Q38: =IF($D38="","",IFERROR(MATCH($D38,Items!$A$5:$A$504,0),"")) | R38: =IF($C38="","",IFERROR(MATCH($C38,Parties!$A$5:$A$304,0),"")) | S38: =IF($D38="","",IF(OR($H38="",$H38="Credit"),0,P38))
I39: =IF($D39="","",IFERROR(INDEX(Items!$D$5:$D$504,Q39),"")) | J39: =IF($D39="","",IF($F39="",IFERROR(INDEX(Items!$G$5:$G$504,Q39),0),$F39)) | K39: =IF($D39="","",ROUND(N($E39)*J39*(1-N($G39)),2)) | L39: =IF($D39="","",IFERROR(INDEX(Items!$F$5:$F$504,Q39),0)) | M39: =IF($D39="","",IF(AND(R39<>"",INDEX(Parties!$E$5:$E$304,R39)<>"",INDEX(Parties!$E$5:$E$304,R39)<>HomeState),0,ROUND(K39*L39/2,2))) | N39: =IF($D39="","",M39) | O39: =IF($D39="","",IF(AND(R39<>"",INDEX(Parties!$E$5:$E$304,R39)<>"",INDEX(Parties!$E$5:$E$304,R39)<>HomeState),ROUND(K39*L39,2),0)) | P39: =IF($D39="","",K39+M39+N39+O39) | Q39: =IF($D39="","",IFERROR(MATCH($D39,Items!$A$5:$A$504,0),"")) | R39: =IF($C39="","",IFERROR(MATCH($C39,Parties!$A$5:$A$304,0),"")) | S39: =IF($D39="","",IF(OR($H39="",$H39="Credit"),0,P39))
I40: =IF($D40="","",IFERROR(INDEX(Items!$D$5:$D$504,Q40),"")) | J40: =IF($D40="","",IF($F40="",IFERROR(INDEX(Items!$G$5:$G$504,Q40),0),$F40)) | K40: =IF($D40="","",ROUND(N($E40)*J40*(1-N($G40)),2)) | L40: =IF($D40="","",IFERROR(INDEX(Items!$F$5:$F$504,Q40),0)) | M40: =IF($D40="","",IF(AND(R40<>"",INDEX(Parties!$E$5:$E$304,R40)<>"",INDEX(Parties!$E$5:$E$304,R40)<>HomeState),0,ROUND(K40*L40/2,2))) | N40: =IF($D40="","",M40) | O40: =IF($D40="","",IF(AND(R40<>"",INDEX(Parties!$E$5:$E$304,R40)<>"",INDEX(Parties!$E$5:$E$304,R40)<>HomeState),ROUND(K40*L40,2),0)) | P40: =IF($D40="","",K40+M40+N40+O40) | Q40: =IF($D40="","",IFERROR(MATCH($D40,Items!$A$5:$A$504,0),"")) | R40: =IF($C40="","",IFERROR(MATCH($C40,Parties!$A$5:$A$304,0),"")) | S40: =IF($D40="","",IF(OR($H40="",$H40="Credit"),0,P40))
I41: =IF($D41="","",IFERROR(INDEX(Items!$D$5:$D$504,Q41),"")) | J41: =IF($D41="","",IF($F41="",IFERROR(INDEX(Items!$G$5:$G$504,Q41),0),$F41)) | K41: =IF($D41="","",ROUND(N($E41)*J41*(1-N($G41)),2)) | L41: =IF($D41="","",IFERROR(INDEX(Items!$F$5:$F$504,Q41),0)) | M41: =IF($D41="","",IF(AND(R41<>"",INDEX(Parties!$E$5:$E$304,R41)<>"",INDEX(Parties!$E$5:$E$304,R41)<>HomeState),0,ROUND(K41*L41/2,2))) | N41: =IF($D41="","",M41) | O41: =IF($D41="","",IF(AND(R41<>"",INDEX(Parties!$E$5:$E$304,R41)<>"",INDEX(Parties!$E$5:$E$304,R41)<>HomeState),ROUND(K41*L41,2),0)) | P41: =IF($D41="","",K41+M41+N41+O41) | Q41: =IF($D41="","",IFERROR(MATCH($D41,Items!$A$5:$A$504,0),"")) | R41: =IF($C41="","",IFERROR(MATCH($C41,Parties!$A$5:$A$304,0),"")) | S41: =IF($D41="","",IF(OR($H41="",$H41="Credit"),0,P41))
I42: =IF($D42="","",IFERROR(INDEX(Items!$D$5:$D$504,Q42),"")) | J42: =IF($D42="","",IF($F42="",IFERROR(INDEX(Items!$G$5:$G$504,Q42),0),$F42)) | K42: =IF($D42="","",ROUND(N($E42)*J42*(1-N($G42)),2)) | L42: =IF($D42="","",IFERROR(INDEX(Items!$F$5:$F$504,Q42),0)) | M42: =IF($D42="","",IF(AND(R42<>"",INDEX(Parties!$E$5:$E$304,R42)<>"",INDEX(Parties!$E$5:$E$304,R42)<>HomeState),0,ROUND(K42*L42/2,2))) | N42: =IF($D42="","",M42) | O42: =IF($D42="","",IF(AND(R42<>"",INDEX(Parties!$E$5:$E$304,R42)<>"",INDEX(Parties!$E$5:$E$304,R42)<>HomeState),ROUND(K42*L42,2),0)) | P42: =IF($D42="","",K42+M42+N42+O42) | Q42: =IF($D42="","",IFERROR(MATCH($D42,Items!$A$5:$A$504,0),"")) | R42: =IF($C42="","",IFERROR(MATCH($C42,Parties!$A$5:$A$304,0),"")) | S42: =IF($D42="","",IF(OR($H42="",$H42="Credit"),0,P42))
I43: =IF($D43="","",IFERROR(INDEX(Items!$D$5:$D$504,Q43),"")) | J43: =IF($D43="","",IF($F43="",IFERROR(INDEX(Items!$G$5:$G$504,Q43),0),$F43)) | K43: =IF($D43="","",ROUND(N($E43)*J43*(1-N($G43)),2)) | L43: =IF($D43="","",IFERROR(INDEX(Items!$F$5:$F$504,Q43),0)) | M43: =IF($D43="","",IF(AND(R43<>"",INDEX(Parties!$E$5:$E$304,R43)<>"",INDEX(Parties!$E$5:$E$304,R43)<>HomeState),0,ROUND(K43*L43/2,2))) | N43: =IF($D43="","",M43) | O43: =IF($D43="","",IF(AND(R43<>"",INDEX(Parties!$E$5:$E$304,R43)<>"",INDEX(Parties!$E$5:$E$304,R43)<>HomeState),ROUND(K43*L43,2),0)) | P43: =IF($D43="","",K43+M43+N43+O43) | Q43: =IF($D43="","",IFERROR(MATCH($D43,Items!$A$5:$A$504,0),"")) | R43: =IF($C43="","",IFERROR(MATCH($C43,Parties!$A$5:$A$304,0),"")) | S43: =IF($D43="","",IF(OR($H43="",$H43="Credit"),0,P43))
I44: =IF($D44="","",IFERROR(INDEX(Items!$D$5:$D$504,Q44),"")) | J44: =IF($D44="","",IF($F44="",IFERROR(INDEX(Items!$G$5:$G$504,Q44),0),$F44)) | K44: =IF($D44="","",ROUND(N($E44)*J44*(1-N($G44)),2)) | L44: =IF($D44="","",IFERROR(INDEX(Items!$F$5:$F$504,Q44),0)) | M44: =IF($D44="","",IF(AND(R44<>"",INDEX(Parties!$E$5:$E$304,R44)<>"",INDEX(Parties!$E$5:$E$304,R44)<>HomeState),0,ROUND(K44*L44/2,2))) | N44: =IF($D44="","",M44) | O44: =IF($D44="","",IF(AND(R44<>"",INDEX(Parties!$E$5:$E$304,R44)<>"",INDEX(Parties!$E$5:$E$304,R44)<>HomeState),ROUND(K44*L44,2),0)) | P44: =IF($D44="","",K44+M44+N44+O44) | Q44: =IF($D44="","",IFERROR(MATCH($D44,Items!$A$5:$A$504,0),"")) | R44: =IF($C44="","",IFERROR(MATCH($C44,Parties!$A$5:$A$304,0),"")) | S44: =IF($D44="","",IF(OR($H44="",$H44="Credit"),0,P44))
I45: =IF($D45="","",IFERROR(INDEX(Items!$D$5:$D$504,Q45),"")) | J45: =IF($D45="","",IF($F45="",IFERROR(INDEX(Items!$G$5:$G$504,Q45),0),$F45)) | K45: =IF($D45="","",ROUND(N($E45)*J45*(1-N($G45)),2)) | L45: =IF($D45="","",IFERROR(INDEX(Items!$F$5:$F$504,Q45),0)) | M45: =IF($D45="","",IF(AND(R45<>"",INDEX(Parties!$E$5:$E$304,R45)<>"",INDEX(Parties!$E$5:$E$304,R45)<>HomeState),0,ROUND(K45*L45/2,2))) | N45: =IF($D45="","",M45) | O45: =IF($D45="","",IF(AND(R45<>"",INDEX(Parties!$E$5:$E$304,R45)<>"",INDEX(Parties!$E$5:$E$304,R45)<>HomeState),ROUND(K45*L45,2),0)) | P45: =IF($D45="","",K45+M45+N45+O45) | Q45: =IF($D45="","",IFERROR(MATCH($D45,Items!$A$5:$A$504,0),"")) | R45: =IF($C45="","",IFERROR(MATCH($C45,Parties!$A$5:$A$304,0),"")) | S45: =IF($D45="","",IF(OR($H45="",$H45="Credit"),0,P45))
I46: =IF($D46="","",IFERROR(INDEX(Items!$D$5:$D$504,Q46),"")) | J46: =IF($D46="","",IF($F46="",IFERROR(INDEX(Items!$G$5:$G$504,Q46),0),$F46)) | K46: =IF($D46="","",ROUND(N($E46)*J46*(1-N($G46)),2)) | L46: =IF($D46="","",IFERROR(INDEX(Items!$F$5:$F$504,Q46),0)) | M46: =IF($D46="","",IF(AND(R46<>"",INDEX(Parties!$E$5:$E$304,R46)<>"",INDEX(Parties!$E$5:$E$304,R46)<>HomeState),0,ROUND(K46*L46/2,2))) | N46: =IF($D46="","",M46) | O46: =IF($D46="","",IF(AND(R46<>"",INDEX(Parties!$E$5:$E$304,R46)<>"",INDEX(Parties!$E$5:$E$304,R46)<>HomeState),ROUND(K46*L46,2),0)) | P46: =IF($D46="","",K46+M46+N46+O46) | Q46: =IF($D46="","",IFERROR(MATCH($D46,Items!$A$5:$A$504,0),"")) | R46: =IF($C46="","",IFERROR(MATCH($C46,Parties!$A$5:$A$304,0),"")) | S46: =IF($D46="","",IF(OR($H46="",$H46="Credit"),0,P46))
I47: =IF($D47="","",IFERROR(INDEX(Items!$D$5:$D$504,Q47),"")) | J47: =IF($D47="","",IF($F47="",IFERROR(INDEX(Items!$G$5:$G$504,Q47),0),$F47)) | K47: =IF($D47="","",ROUND(N($E47)*J47*(1-N($G47)),2)) | L47: =IF($D47="","",IFERROR(INDEX(Items!$F$5:$F$504,Q47),0)) | M47: =IF($D47="","",IF(AND(R47<>"",INDEX(Parties!$E$5:$E$304,R47)<>"",INDEX(Parties!$E$5:$E$304,R47)<>HomeState),0,ROUND(K47*L47/2,2))) | N47: =IF($D47="","",M47) | O47: =IF($D47="","",IF(AND(R47<>"",INDEX(Parties!$E$5:$E$304,R47)<>"",INDEX(Parties!$E$5:$E$304,R47)<>HomeState),ROUND(K47*L47,2),0)) | P47: =IF($D47="","",K47+M47+N47+O47) | Q47: =IF($D47="","",IFERROR(MATCH($D47,Items!$A$5:$A$504,0),"")) | R47: =IF($C47="","",IFERROR(MATCH($C47,Parties!$A$5:$A$304,0),"")) | S47: =IF($D47="","",IF(OR($H47="",$H47="Credit"),0,P47))
I48: =IF($D48="","",IFERROR(INDEX(Items!$D$5:$D$504,Q48),"")) | J48: =IF($D48="","",IF($F48="",IFERROR(INDEX(Items!$G$5:$G$504,Q48),0),$F48)) | K48: =IF($D48="","",ROUND(N($E48)*J48*(1-N($G48)),2)) | L48: =IF($D48="","",IFERROR(INDEX(Items!$F$5:$F$504,Q48),0)) | M48: =IF($D48="","",IF(AND(R48<>"",INDEX(Parties!$E$5:$E$304,R48)<>"",INDEX(Parties!$E$5:$E$304,R48)<>HomeState),0,ROUND(K48*L48/2,2))) | N48: =IF($D48="","",M48) | O48: =IF($D48="","",IF(AND(R48<>"",INDEX(Parties!$E$5:$E$304,R48)<>"",INDEX(Parties!$E$5:$E$304,R48)<>HomeState),ROUND(K48*L48,2),0)) | P48: =IF($D48="","",K48+M48+N48+O48) | Q48: =IF($D48="","",IFERROR(MATCH($D48,Items!$A$5:$A$504,0),"")) | R48: =IF($C48="","",IFERROR(MATCH($C48,Parties!$A$5:$A$304,0),"")) | S48: =IF($D48="","",IF(OR($H48="",$H48="Credit"),0,P48))
I49: =IF($D49="","",IFERROR(INDEX(Items!$D$5:$D$504,Q49),"")) | J49: =IF($D49="","",IF($F49="",IFERROR(INDEX(Items!$G$5:$G$504,Q49),0),$F49)) | K49: =IF($D49="","",ROUND(N($E49)*J49*(1-N($G49)),2)) | L49: =IF($D49="","",IFERROR(INDEX(Items!$F$5:$F$504,Q49),0)) | M49: =IF($D49="","",IF(AND(R49<>"",INDEX(Parties!$E$5:$E$304,R49)<>"",INDEX(Parties!$E$5:$E$304,R49)<>HomeState),0,ROUND(K49*L49/2,2))) | N49: =IF($D49="","",M49) | O49: =IF($D49="","",IF(AND(R49<>"",INDEX(Parties!$E$5:$E$304,R49)<>"",INDEX(Parties!$E$5:$E$304,R49)<>HomeState),ROUND(K49*L49,2),0)) | P49: =IF($D49="","",K49+M49+N49+O49) | Q49: =IF($D49="","",IFERROR(MATCH($D49,Items!$A$5:$A$504,0),"")) | R49: =IF($C49="","",IFERROR(MATCH($C49,Parties!$A$5:$A$304,0),"")) | S49: =IF($D49="","",IF(OR($H49="",$H49="Credit"),0,P49))
... I204: =IF($D204="","",IFERROR(INDEX(Items!$D$5:$D$504,Q204),"")) | J204: =IF($D204="","",IF($F204="",IFERROR(INDEX(Items!$G$5:$G$504,Q204),0),$F204)) | K204: =IF($D204="","",ROUND(N($E204)*J204*(1-N($G204)),2)) | L204: =IF($D204="","",IFERROR(INDEX(Items!$F$5:$F$504,Q204),0)) | M204: =IF($D204="","",IF(AND(R204<>"",INDEX(Parties!$E$5:$E$304,R204)<>"",INDEX(Parties!$E$5:$E$304,R204)<>HomeState),0,ROUND(K204*L204/2,2))) | N204: =IF($D204="","",M204) | O204: =IF($D204="","",IF(AND(R204<>"",INDEX(Parties!$E$5:$E$304,R204)<>"",INDEX(Parties!$E$5:$E$304,R204)<>HomeState),ROUND(K204*L204,2),0)) | P204: =IF($D204="","",K204+M204+N204+O204) | Q204: =IF($D204="","",IFERROR(MATCH($D204,Items!$A$5:$A$504,0),"")) | R204: =IF($C204="","",IFERROR(MATCH($C204,Parties!$A$5:$A$304,0),"")) | S204: =IF($D204="","",IF(OR($H204="",$H204="Credit"),0,P204))
I205: =IF(IsPro,IF($D205="","",IFERROR(INDEX(Items!$D$5:$D$504,Q205),"")),IF($D205="","","PRO PLAN")) | J205: =IF(IsPro,IF($D205="","",IF($F205="",IFERROR(INDEX(Items!$G$5:$G$504,Q205),0),$F205)),"") | K205: =IF(IsPro,IF($D205="","",ROUND(N($E205)*J205*(1-N($G205)),2)),"") | L205: =IF(IsPro,IF($D205="","",IFERROR(INDEX(Items!$F$5:$F$504,Q205),0)),"") | M205: =IF(IsPro,IF($D205="","",IF(AND(R205<>"",INDEX(Parties!$E$5:$E$304,R205)<>"",INDEX(Parties!$E$5:$E$304,R205)<>HomeState),0,ROUND(K205*L205/2,2))),"") | N205: =IF(IsPro,IF($D205="","",M205),"") | O205: =IF(IsPro,IF($D205="","",IF(AND(R205<>"",INDEX(Parties!$E$5:$E$304,R205)<>"",INDEX(Parties!$E$5:$E$304,R205)<>HomeState),ROUND(K205*L205,2),0)),"") | P205: =IF(IsPro,IF($D205="","",K205+M205+N205+O205),"") | Q205: =IF(IsPro,IF($D205="","",IFERROR(MATCH($D205,Items!$A$5:$A$504,0),"")),"") | R205: =IF(IsPro,IF($C205="","",IFERROR(MATCH($C205,Parties!$A$5:$A$304,0),"")),"") | S205: =IF(IsPro,IF($D205="","",IF(OR($H205="",$H205="Credit"),0,P205)),"")
I206: =IF(IsPro,IF($D206="","",IFERROR(INDEX(Items!$D$5:$D$504,Q206),"")),IF($D206="","","PRO PLAN")) | J206: =IF(IsPro,IF($D206="","",IF($F206="",IFERROR(INDEX(Items!$G$5:$G$504,Q206),0),$F206)),"") | K206: =IF(IsPro,IF($D206="","",ROUND(N($E206)*J206*(1-N($G206)),2)),"") | L206: =IF(IsPro,IF($D206="","",IFERROR(INDEX(Items!$F$5:$F$504,Q206),0)),"") | M206: =IF(IsPro,IF($D206="","",IF(AND(R206<>"",INDEX(Parties!$E$5:$E$304,R206)<>"",INDEX(Parties!$E$5:$E$304,R206)<>HomeState),0,ROUND(K206*L206/2,2))),"") | N206: =IF(IsPro,IF($D206="","",M206),"") | O206: =IF(IsPro,IF($D206="","",IF(AND(R206<>"",INDEX(Parties!$E$5:$E$304,R206)<>"",INDEX(Parties!$E$5:$E$304,R206)<>HomeState),ROUND(K206*L206,2),0)),"") | P206: =IF(IsPro,IF($D206="","",K206+M206+N206+O206),"") | Q206: =IF(IsPro,IF($D206="","",IFERROR(MATCH($D206,Items!$A$5:$A$504,0),"")),"") | R206: =IF(IsPro,IF($C206="","",IFERROR(MATCH($C206,Parties!$A$5:$A$304,0),"")),"") | S206: =IF(IsPro,IF($D206="","",IF(OR($H206="",$H206="Credit"),0,P206)),"")
I207: =IF(IsPro,IF($D207="","",IFERROR(INDEX(Items!$D$5:$D$504,Q207),"")),IF($D207="","","PRO PLAN")) | J207: =IF(IsPro,IF($D207="","",IF($F207="",IFERROR(INDEX(Items!$G$5:$G$504,Q207),0),$F207)),"") | K207: =IF(IsPro,IF($D207="","",ROUND(N($E207)*J207*(1-N($G207)),2)),"") | L207: =IF(IsPro,IF($D207="","",IFERROR(INDEX(Items!$F$5:$F$504,Q207),0)),"") | M207: =IF(IsPro,IF($D207="","",IF(AND(R207<>"",INDEX(Parties!$E$5:$E$304,R207)<>"",INDEX(Parties!$E$5:$E$304,R207)<>HomeState),0,ROUND(K207*L207/2,2))),"") | N207: =IF(IsPro,IF($D207="","",M207),"") | O207: =IF(IsPro,IF($D207="","",IF(AND(R207<>"",INDEX(Parties!$E$5:$E$304,R207)<>"",INDEX(Parties!$E$5:$E$304,R207)<>HomeState),ROUND(K207*L207,2),0)),"") | P207: =IF(IsPro,IF($D207="","",K207+M207+N207+O207),"") | Q207: =IF(IsPro,IF($D207="","",IFERROR(MATCH($D207,Items!$A$5:$A$504,0),"")),"") | R207: =IF(IsPro,IF($C207="","",IFERROR(MATCH($C207,Parties!$A$5:$A$304,0),"")),"") | S207: =IF(IsPro,IF($D207="","",IF(OR($H207="",$H207="Credit"),0,P207)),"")
I208: =IF(IsPro,IF($D208="","",IFERROR(INDEX(Items!$D$5:$D$504,Q208),"")),IF($D208="","","PRO PLAN")) | J208: =IF(IsPro,IF($D208="","",IF($F208="",IFERROR(INDEX(Items!$G$5:$G$504,Q208),0),$F208)),"") | K208: =IF(IsPro,IF($D208="","",ROUND(N($E208)*J208*(1-N($G208)),2)),"") | L208: =IF(IsPro,IF($D208="","",IFERROR(INDEX(Items!$F$5:$F$504,Q208),0)),"") | M208: =IF(IsPro,IF($D208="","",IF(AND(R208<>"",INDEX(Parties!$E$5:$E$304,R208)<>"",INDEX(Parties!$E$5:$E$304,R208)<>HomeState),0,ROUND(K208*L208/2,2))),"") | N208: =IF(IsPro,IF($D208="","",M208),"") | O208: =IF(IsPro,IF($D208="","",IF(AND(R208<>"",INDEX(Parties!$E$5:$E$304,R208)<>"",INDEX(Parties!$E$5:$E$304,R208)<>HomeState),ROUND(K208*L208,2),0)),"") | P208: =IF(IsPro,IF($D208="","",K208+M208+N208+O208),"") | Q208: =IF(IsPro,IF($D208="","",IFERROR(MATCH($D208,Items!$A$5:$A$504,0),"")),"") | R208: =IF(IsPro,IF($C208="","",IFERROR(MATCH($C208,Parties!$A$5:$A$304,0),"")),"") | S208: =IF(IsPro,IF($D208="","",IF(OR($H208="",$H208="Credit"),0,P208)),"")
I209: =IF(IsPro,IF($D209="","",IFERROR(INDEX(Items!$D$5:$D$504,Q209),"")),IF($D209="","","PRO PLAN")) | J209: =IF(IsPro,IF($D209="","",IF($F209="",IFERROR(INDEX(Items!$G$5:$G$504,Q209),0),$F209)),"") | K209: =IF(IsPro,IF($D209="","",ROUND(N($E209)*J209*(1-N($G209)),2)),"") | L209: =IF(IsPro,IF($D209="","",IFERROR(INDEX(Items!$F$5:$F$504,Q209),0)),"") | M209: =IF(IsPro,IF($D209="","",IF(AND(R209<>"",INDEX(Parties!$E$5:$E$304,R209)<>"",INDEX(Parties!$E$5:$E$304,R209)<>HomeState),0,ROUND(K209*L209/2,2))),"") | N209: =IF(IsPro,IF($D209="","",M209),"") | O209: =IF(IsPro,IF($D209="","",IF(AND(R209<>"",INDEX(Parties!$E$5:$E$304,R209)<>"",INDEX(Parties!$E$5:$E$304,R209)<>HomeState),ROUND(K209*L209,2),0)),"") | P209: =IF(IsPro,IF($D209="","",K209+M209+N209+O209),"") | Q209: =IF(IsPro,IF($D209="","",IFERROR(MATCH($D209,Items!$A$5:$A$504,0),"")),"") | R209: =IF(IsPro,IF($C209="","",IFERROR(MATCH($C209,Parties!$A$5:$A$304,0),"")),"") | S209: =IF(IsPro,IF($D209="","",IF(OR($H209="",$H209="Credit"),0,P209)),"")
I210: =IF(IsPro,IF($D210="","",IFERROR(INDEX(Items!$D$5:$D$504,Q210),"")),IF($D210="","","PRO PLAN")) | J210: =IF(IsPro,IF($D210="","",IF($F210="",IFERROR(INDEX(Items!$G$5:$G$504,Q210),0),$F210)),"") | K210: =IF(IsPro,IF($D210="","",ROUND(N($E210)*J210*(1-N($G210)),2)),"") | L210: =IF(IsPro,IF($D210="","",IFERROR(INDEX(Items!$F$5:$F$504,Q210),0)),"") | M210: =IF(IsPro,IF($D210="","",IF(AND(R210<>"",INDEX(Parties!$E$5:$E$304,R210)<>"",INDEX(Parties!$E$5:$E$304,R210)<>HomeState),0,ROUND(K210*L210/2,2))),"") | N210: =IF(IsPro,IF($D210="","",M210),"") | O210: =IF(IsPro,IF($D210="","",IF(AND(R210<>"",INDEX(Parties!$E$5:$E$304,R210)<>"",INDEX(Parties!$E$5:$E$304,R210)<>HomeState),ROUND(K210*L210,2),0)),"") | P210: =IF(IsPro,IF($D210="","",K210+M210+N210+O210),"") | Q210: =IF(IsPro,IF($D210="","",IFERROR(MATCH($D210,Items!$A$5:$A$504,0),"")),"") | R210: =IF(IsPro,IF($C210="","",IFERROR(MATCH($C210,Parties!$A$5:$A$304,0),"")),"") | S210: =IF(IsPro,IF($D210="","",IF(OR($H210="",$H210="Credit"),0,P210)),"")
I211: =IF(IsPro,IF($D211="","",IFERROR(INDEX(Items!$D$5:$D$504,Q211),"")),IF($D211="","","PRO PLAN")) | J211: =IF(IsPro,IF($D211="","",IF($F211="",IFERROR(INDEX(Items!$G$5:$G$504,Q211),0),$F211)),"") | K211: =IF(IsPro,IF($D211="","",ROUND(N($E211)*J211*(1-N($G211)),2)),"") | L211: =IF(IsPro,IF($D211="","",IFERROR(INDEX(Items!$F$5:$F$504,Q211),0)),"") | M211: =IF(IsPro,IF($D211="","",IF(AND(R211<>"",INDEX(Parties!$E$5:$E$304,R211)<>"",INDEX(Parties!$E$5:$E$304,R211)<>HomeState),0,ROUND(K211*L211/2,2))),"") | N211: =IF(IsPro,IF($D211="","",M211),"") | O211: =IF(IsPro,IF($D211="","",IF(AND(R211<>"",INDEX(Parties!$E$5:$E$304,R211)<>"",INDEX(Parties!$E$5:$E$304,R211)<>HomeState),ROUND(K211*L211,2),0)),"") | P211: =IF(IsPro,IF($D211="","",K211+M211+N211+O211),"") | Q211: =IF(IsPro,IF($D211="","",IFERROR(MATCH($D211,Items!$A$5:$A$504,0),"")),"") | R211: =IF(IsPro,IF($C211="","",IFERROR(MATCH($C211,Parties!$A$5:$A$304,0),"")),"") | S211: =IF(IsPro,IF($D211="","",IF(OR($H211="",$H211="Credit"),0,P211)),"")
I212: =IF(IsPro,IF($D212="","",IFERROR(INDEX(Items!$D$5:$D$504,Q212),"")),IF($D212="","","PRO PLAN")) | J212: =IF(IsPro,IF($D212="","",IF($F212="",IFERROR(INDEX(Items!$G$5:$G$504,Q212),0),$F212)),"") | K212: =IF(IsPro,IF($D212="","",ROUND(N($E212)*J212*(1-N($G212)),2)),"") | L212: =IF(IsPro,IF($D212="","",IFERROR(INDEX(Items!$F$5:$F$504,Q212),0)),"") | M212: =IF(IsPro,IF($D212="","",IF(AND(R212<>"",INDEX(Parties!$E$5:$E$304,R212)<>"",INDEX(Parties!$E$5:$E$304,R212)<>HomeState),0,ROUND(K212*L212/2,2))),"") | N212: =IF(IsPro,IF($D212="","",M212),"") | O212: =IF(IsPro,IF($D212="","",IF(AND(R212<>"",INDEX(Parties!$E$5:$E$304,R212)<>"",INDEX(Parties!$E$5:$E$304,R212)<>HomeState),ROUND(K212*L212,2),0)),"") | P212: =IF(IsPro,IF($D212="","",K212+M212+N212+O212),"") | Q212: =IF(IsPro,IF($D212="","",IFERROR(MATCH($D212,Items!$A$5:$A$504,0),"")),"") | R212: =IF(IsPro,IF($C212="","",IFERROR(MATCH($C212,Parties!$A$5:$A$304,0),"")),"") | S212: =IF(IsPro,IF($D212="","",IF(OR($H212="",$H212="Credit"),0,P212)),"")
I213: =IF(IsPro,IF($D213="","",IFERROR(INDEX(Items!$D$5:$D$504,Q213),"")),IF($D213="","","PRO PLAN")) | J213: =IF(IsPro,IF($D213="","",IF($F213="",IFERROR(INDEX(Items!$G$5:$G$504,Q213),0),$F213)),"") | K213: =IF(IsPro,IF($D213="","",ROUND(N($E213)*J213*(1-N($G213)),2)),"") | L213: =IF(IsPro,IF($D213="","",IFERROR(INDEX(Items!$F$5:$F$504,Q213),0)),"") | M213: =IF(IsPro,IF($D213="","",IF(AND(R213<>"",INDEX(Parties!$E$5:$E$304,R213)<>"",INDEX(Parties!$E$5:$E$304,R213)<>HomeState),0,ROUND(K213*L213/2,2))),"") | N213: =IF(IsPro,IF($D213="","",M213),"") | O213: =IF(IsPro,IF($D213="","",IF(AND(R213<>"",INDEX(Parties!$E$5:$E$304,R213)<>"",INDEX(Parties!$E$5:$E$304,R213)<>HomeState),ROUND(K213*L213,2),0)),"") | P213: =IF(IsPro,IF($D213="","",K213+M213+N213+O213),"") | Q213: =IF(IsPro,IF($D213="","",IFERROR(MATCH($D213,Items!$A$5:$A$504,0),"")),"") | R213: =IF(IsPro,IF($C213="","",IFERROR(MATCH($C213,Parties!$A$5:$A$304,0),"")),"") | S213: =IF(IsPro,IF($D213="","",IF(OR($H213="",$H213="Credit"),0,P213)),"")
I214: =IF(IsPro,IF($D214="","",IFERROR(INDEX(Items!$D$5:$D$504,Q214),"")),IF($D214="","","PRO PLAN")) | J214: =IF(IsPro,IF($D214="","",IF($F214="",IFERROR(INDEX(Items!$G$5:$G$504,Q214),0),$F214)),"") | K214: =IF(IsPro,IF($D214="","",ROUND(N($E214)*J214*(1-N($G214)),2)),"") | L214: =IF(IsPro,IF($D214="","",IFERROR(INDEX(Items!$F$5:$F$504,Q214),0)),"") | M214: =IF(IsPro,IF($D214="","",IF(AND(R214<>"",INDEX(Parties!$E$5:$E$304,R214)<>"",INDEX(Parties!$E$5:$E$304,R214)<>HomeState),0,ROUND(K214*L214/2,2))),"") | N214: =IF(IsPro,IF($D214="","",M214),"") | O214: =IF(IsPro,IF($D214="","",IF(AND(R214<>"",INDEX(Parties!$E$5:$E$304,R214)<>"",INDEX(Parties!$E$5:$E$304,R214)<>HomeState),ROUND(K214*L214,2),0)),"") | P214: =IF(IsPro,IF($D214="","",K214+M214+N214+O214),"") | Q214: =IF(IsPro,IF($D214="","",IFERROR(MATCH($D214,Items!$A$5:$A$504,0),"")),"") | R214: =IF(IsPro,IF($C214="","",IFERROR(MATCH($C214,Parties!$A$5:$A$304,0),"")),"") | S214: =IF(IsPro,IF($D214="","",IF(OR($H214="",$H214="Credit"),0,P214)),"")
I215: =IF(IsPro,IF($D215="","",IFERROR(INDEX(Items!$D$5:$D$504,Q215),"")),IF($D215="","","PRO PLAN")) | J215: =IF(IsPro,IF($D215="","",IF($F215="",IFERROR(INDEX(Items!$G$5:$G$504,Q215),0),$F215)),"") | K215: =IF(IsPro,IF($D215="","",ROUND(N($E215)*J215*(1-N($G215)),2)),"") | L215: =IF(IsPro,IF($D215="","",IFERROR(INDEX(Items!$F$5:$F$504,Q215),0)),"") | M215: =IF(IsPro,IF($D215="","",IF(AND(R215<>"",INDEX(Parties!$E$5:$E$304,R215)<>"",INDEX(Parties!$E$5:$E$304,R215)<>HomeState),0,ROUND(K215*L215/2,2))),"") | N215: =IF(IsPro,IF($D215="","",M215),"") | O215: =IF(IsPro,IF($D215="","",IF(AND(R215<>"",INDEX(Parties!$E$5:$E$304,R215)<>"",INDEX(Parties!$E$5:$E$304,R215)<>HomeState),ROUND(K215*L215,2),0)),"") | P215: =IF(IsPro,IF($D215="","",K215+M215+N215+O215),"") | Q215: =IF(IsPro,IF($D215="","",IFERROR(MATCH($D215,Items!$A$5:$A$504,0),"")),"") | R215: =IF(IsPro,IF($C215="","",IFERROR(MATCH($C215,Parties!$A$5:$A$304,0),"")),"") | S215: =IF(IsPro,IF($D215="","",IF(OR($H215="",$H215="Credit"),0,P215)),"")
I216: =IF(IsPro,IF($D216="","",IFERROR(INDEX(Items!$D$5:$D$504,Q216),"")),IF($D216="","","PRO PLAN")) | J216: =IF(IsPro,IF($D216="","",IF($F216="",IFERROR(INDEX(Items!$G$5:$G$504,Q216),0),$F216)),"") | K216: =IF(IsPro,IF($D216="","",ROUND(N($E216)*J216*(1-N($G216)),2)),"") | L216: =IF(IsPro,IF($D216="","",IFERROR(INDEX(Items!$F$5:$F$504,Q216),0)),"") | M216: =IF(IsPro,IF($D216="","",IF(AND(R216<>"",INDEX(Parties!$E$5:$E$304,R216)<>"",INDEX(Parties!$E$5:$E$304,R216)<>HomeState),0,ROUND(K216*L216/2,2))),"") | N216: =IF(IsPro,IF($D216="","",M216),"") | O216: =IF(IsPro,IF($D216="","",IF(AND(R216<>"",INDEX(Parties!$E$5:$E$304,R216)<>"",INDEX(Parties!$E$5:$E$304,R216)<>HomeState),ROUND(K216*L216,2),0)),"") | P216: =IF(IsPro,IF($D216="","",K216+M216+N216+O216),"") | Q216: =IF(IsPro,IF($D216="","",IFERROR(MATCH($D216,Items!$A$5:$A$504,0),"")),"") | R216: =IF(IsPro,IF($C216="","",IFERROR(MATCH($C216,Parties!$A$5:$A$304,0),"")),"") | S216: =IF(IsPro,IF($D216="","",IF(OR($H216="",$H216="Credit"),0,P216)),"")
... I3004: =IF(IsPro,IF($D3004="","",IFERROR(INDEX(Items!$D$5:$D$504,Q3004),"")),IF($D3004="","","PRO PLAN")) | J3004: =IF(IsPro,IF($D3004="","",IF($F3004="",IFERROR(INDEX(Items!$G$5:$G$504,Q3004),0),$F3004)),"") | K3004: =IF(IsPro,IF($D3004="","",ROUND(N($E3004)*J3004*(1-N($G3004)),2)),"") | L3004: =IF(IsPro,IF($D3004="","",IFERROR(INDEX(Items!$F$5:$F$504,Q3004),0)),"") | M3004: =IF(IsPro,IF($D3004="","",IF(AND(R3004<>"",INDEX(Parties!$E$5:$E$304,R3004)<>"",INDEX(Parties!$E$5:$E$304,R3004)<>HomeState),0,ROUND(K3004*L3004/2,2))),"") | N3004: =IF(IsPro,IF($D3004="","",M3004),"") | O3004: =IF(IsPro,IF($D3004="","",IF(AND(R3004<>"",INDEX(Parties!$E$5:$E$304,R3004)<>"",INDEX(Parties!$E$5:$E$304,R3004)<>HomeState),ROUND(K3004*L3004,2),0)),"") | P3004: =IF(IsPro,IF($D3004="","",K3004+M3004+N3004+O3004),"") | Q3004: =IF(IsPro,IF($D3004="","",IFERROR(MATCH($D3004,Items!$A$5:$A$504,0),"")),"") | R3004: =IF(IsPro,IF($C3004="","",IFERROR(MATCH($C3004,Parties!$A$5:$A$304,0),"")),"") | S3004: =IF(IsPro,IF($D3004="","",IF(OR($H3004="",$H3004="Credit"),0,P3004)),"")

Sheet CashBook
A1: CASH & BANK BOOK (FINANCE) | M1: « Home
A2: Customer receipts, supplier payments, expenses, owner capital/drawings and transfers between accounts.
A3: Blue / cream = type here | I3: Grey = automatic (do not type)
A4: Date * | B4: Voucher No | C4: Type * | D4: Party (Receipt/Payment) | E4: Expense / Income Head | F4: Account * | G4: Amount (₹) * | H4: Reference / Notes | I4: Money In (₹) | J4: Money Out (₹) | K4: Check
A5: 46117 | B5: V-0001 | C5: Expense | E5: Rent | F5: Bank | G5: 9000 | I5: =IF(OR($C5="",N($G5)=0),"",IF(OR($C5="Receipt",$C5="Other Income",$C5="Capital In",$C5="Transfer In"),$G5,0)) -> 0 | J5: =IF(OR($C5="",N($G5)=0),"",IF(I5=0,$G5,0)) -> 9000 | K5: =IF($C5="","",IF(AND(OR($C5="Receipt",$C5="Payment"),$D5=""),"Party needed",IF(AND(OR($C5="Expense",$C5="Other Income"),$E5=""),"Head needed",IF($F5="","Account needed","OK")))) -> OK
A6: 46117 | B6: V-0002 | C6: Expense | E6: Salary | F6: Bank | G6: 12000 | I6: =IF(OR($C6="",N($G6)=0),"",IF(OR($C6="Receipt",$C6="Other Income",$C6="Capital In",$C6="Transfer In"),$G6,0)) -> 0 | J6: =IF(OR($C6="",N($G6)=0),"",IF(I6=0,$G6,0)) -> 12000 | K6: =IF($C6="","",IF(AND(OR($C6="Receipt",$C6="Payment"),$D6=""),"Party needed",IF(AND(OR($C6="Expense",$C6="Other Income"),$E6=""),"Head needed",IF($F6="","Account needed","OK")))) -> OK
A7: 46117 | B7: V-0003 | C7: Expense | E7: Electricity | F7: UPI | G7: 5140 | I7: =IF(OR($C7="",N($G7)=0),"",IF(OR($C7="Receipt",$C7="Other Income",$C7="Capital In",$C7="Transfer In"),$G7,0)) -> 0 | J7: =IF(OR($C7="",N($G7)=0),"",IF(I7=0,$G7,0)) -> 5140 | K7: =IF($C7="","",IF(AND(OR($C7="Receipt",$C7="Payment"),$D7=""),"Party needed",IF(AND(OR($C7="Expense",$C7="Other Income"),$E7=""),"Head needed",IF($F7="","Account needed","OK")))) -> OK
A8: 46117 | B8: V-0004 | C8: Expense | E8: Transport / Freight | F8: Cash | G8: 6328 | I8: =IF(OR($C8="",N($G8)=0),"",IF(OR($C8="Receipt",$C8="Other Income",$C8="Capital In",$C8="Transfer In"),$G8,0)) -> 0 | J8: =IF(OR($C8="",N($G8)=0),"",IF(I8=0,$G8,0)) -> 6328 | K8: =IF($C8="","",IF(AND(OR($C8="Receipt",$C8="Payment"),$D8=""),"Party needed",IF(AND(OR($C8="Expense",$C8="Other Income"),$E8=""),"Head needed",IF($F8="","Account needed","OK")))) -> OK
A9: 46117 | B9: V-0005 | C9: Expense | E9: Telephone / Internet | F9: UPI | G9: 1199 | I9: =IF(OR($C9="",N($G9)=0),"",IF(OR($C9="Receipt",$C9="Other Income",$C9="Capital In",$C9="Transfer In"),$G9,0)) -> 0 | J9: =IF(OR($C9="",N($G9)=0),"",IF(I9=0,$G9,0)) -> 1199 | K9: =IF($C9="","",IF(AND(OR($C9="Receipt",$C9="Payment"),$D9=""),"Party needed",IF(AND(OR($C9="Expense",$C9="Other Income"),$E9=""),"Head needed",IF($F9="","Account needed","OK")))) -> OK
