Workbook
Name CoName: Settings!$B$4
Name CoAddr: Settings!$B$5
Name CoGSTIN: Settings!$B$6
Name HomeState: Settings!$B$7
Name CoPhone: Settings!$B$8
Name FYStart: Settings!$B$9
Name AsOf: Settings!$B$10
Name InvPrefix: Settings!$B$11
Name DeadDays: Settings!$B$12
Name CoBank: Settings!$B$13
Name L_Categories: OFFSET(Settings!$D$5,0,0,MAX(1,COUNTA(Settings!$D$5:$D$44)),1)
Name L_Units: OFFSET(Settings!$E$5,0,0,MAX(1,COUNTA(Settings!$E$5:$E$44)),1)
Name L_GSTRates: OFFSET(Settings!$F$5,0,0,MAX(1,COUNTA(Settings!$F$5:$F$44)),1)
Name L_PayModes: OFFSET(Settings!$G$5,0,0,MAX(1,COUNTA(Settings!$G$5:$G$44)),1)
Name L_VoucherTypes: OFFSET(Settings!$H$5,0,0,MAX(1,COUNTA(Settings!$H$5:$H$44)),1)
Name L_ExpenseHeads: OFFSET(Settings!$I$5,0,0,MAX(1,COUNTA(Settings!$I$5:$I$44)),1)
Name L_PartyTypes: OFFSET(Settings!$J$5,0,0,MAX(1,COUNTA(Settings!$J$5:$J$44)),1)
Name L_DeliveryStatus: OFFSET(Settings!$K$5,0,0,MAX(1,COUNTA(Settings!$K$5:$K$44)),1)
Name L_AdjReasons: OFFSET(Settings!$L$5,0,0,MAX(1,COUNTA(Settings!$L$5:$L$44)),1)
Name L_States: OFFSET(Settings!$M$5,0,0,MAX(1,COUNTA(Settings!$M$5:$M$44)),1)
Name L_Accounts: OFFSET(Settings!$A$18,0,0,MAX(1,COUNTA(Settings!$A$18:$A$25)),1)
Name L_Items: OFFSET(Items!$A$5,0,0,MAX(1,COUNTA(Items!$A$5:$A$2004)),1)
Name L_Parties: OFFSET(Parties!$A$5,0,0,MAX(1,COUNTA(Parties!$A$5:$A$1004)),1)
Name DFrom: Dashboard!$D$4
Name DTo: Dashboard!$G$4
Name IN_Items: Items!$A$5:$K$2004
Name IN_Parties: Parties!$A$5:$I$1004
Name IN_Purchases: Purchases!$A$5:$H$20004
Name IN_Sales: Sales!$A$5:$I$20004
Name IN_CashBook: CashBook!$A$5:$H$20004
Name IN_Adjust: Adjustments!$A$5:$E$2004
Name IN_Settings: Settings!$B$4:$B$13

Sheet Dashboard
B1: =CoName&" · SmartTrader ERP (C Engine)"
B2: ="Live business cockpit · Period: "&TEXT(D4,"dd-mmm-yy")&" to "&TEXT(G4,"dd-mmm-yy")
B4: From | D4: =FYStart | E4: To | G4: =AsOf | H4: ← overwrite these dates to analyse any period | K4: =IFERROR("✔ "&_xll.ST_VERSION(),"⚠ C engine not loaded - see Guide")
B6: ➕ New Sale | C6: 🛒 Purchase | D6: 💰 Cash Book | E6: 📦 Items | F6: 👥 Parties | G6: 🧾 Invoice | H6: 🔧 Adjust | I6: 📊 Reports | J6: ⚙ Settings | K6: ❓ Guide
B8: SALES (excl. GST) | D8: GROSS PROFIT | F8: NET PROFIT | H8: PURCHASES (excl. GST) | J8: EXPENSES
B9: =SUMIFS(Sales!$L$5:$L$20004,Sales!$A$5:$A$20004,">="&DFrom,Sales!$A$5:$A$20004,"<="&DTo) | D9: =SUMIFS(Sales!$S$5:$S$20004,Sales!$A$5:$A$20004,">="&DFrom,Sales!$A$5:$A$20004,"<="&DTo) | F9: =D9-SUMIFS(CashBook!$G$5:$G$20004,CashBook!$C$5:$C$20004,"Expense",CashBook!$A$5:$A$20004,">="&DFrom,CashBook!$A$5:$A$20004,"<="&DTo)+SUMIFS(CashBook!$G$5:$G$20004,CashBook!$C$5:$C$20004,"Other Income",CashBook!$A$5:$A$20004,">="&DFrom,CashBook!$A$5:$A$20004,"<="&DTo)+SUMIFS(Adjustments!$G$5:$G$2004,Adjustments!$A$5:$A$2004,">="&DFrom,Adjustments!$A$5:$A$2004,"<="&DTo) | H9: =SUMIFS(Purchases!$K$5:$K$20004,Purchases!$A$5:$A$20004,">="&DFrom,Purchases!$A$5:$A$20004,"<="&DTo) | J9: =SUMIFS(CashBook!$G$5:$G$20004,CashBook!$C$5:$C$20004,"Expense",CashBook!$A$5:$A$20004,">="&DFrom,CashBook!$A$5:$A$20004,"<="&DTo)
B11: GP MARGIN | D11: RECEIVABLES (owed to you) | F11: PAYABLES (you owe) | H11: STOCK VALUE (at cost) | J11: NET GST PAYABLE
B12: =IF(B9=0,0,D9/B9) | D12: =SUMIF(Parties!$N$5:$N$1004,">0") | F12: =-SUMIF(Parties!$N$5:$N$1004,"<0") | H12: =SUM(Items!$Q$5:$Q$2004) | J12: =SUMIFS(Sales!$N$5:$N$20004,Sales!$A$5:$A$20004,">="&DFrom,Sales!$A$5:$A$20004,"<="&DTo)+SUMIFS(Sales!$O$5:$O$20004,Sales!$A$5:$A$20004,">="&DFrom,Sales!$A$5:$A$20004,"<="&DTo)+SUMIFS(Sales!$P$5:$P$20004,Sales!$A$5:$A$20004,">="&DFrom,Sales!$A$5:$A$20004,"<="&DTo)-SUMIFS(Purchases!$M$5:$M$20004,Purchases!$A$5:$A$20004,">="&DFrom,Purchases!$A$5:$A$20004,"<="&DTo)-SUMIFS(Purchases!$N$5:$N$20004,Purchases!$A$5:$A$20004,">="&DFrom,Purchases!$A$5:$A$20004,"<="&DTo)-SUMIFS(Purchases!$O$5:$O$20004,Purchases!$A$5:$A$20004,">="&DFrom,Purchases!$A$5:$A$20004,"<="&DTo)
B14: ITEMS TO REORDER | D14: DEAD-STOCK ITEMS | F14: OVERDUE CUSTOMERS | H14: PENDING DELIVERIES (lines) | J14: NEXT INVOICE No.
B15: =COUNTIF(Items!$R$5:$R$2004,"REORDER")+COUNTIF(Items!$R$5:$R$2004,"OUT OF STOCK")+COUNTIF(Items!$R$5:$R$2004,"NEGATIVE") | D15: =COUNTIF(Items!$R$5:$R$2004,"DEAD STOCK") | F15: =COUNTIF(Parties!$S$5:$S$1004,"OVERDUE")+COUNTIF(Parties!$S$5:$S$1004,"OVER LIMIT") | H15: =COUNTIFS(Sales!$I$5:$I$20004,"Pending")+COUNTIFS(Sales!$I$5:$I$20004,"Packed") | J15: =InvPrefix&TEXT(MAX(Sales!$W$5:$W$20004)+1,"0000")
B18: CASH & BANK BALANCES (as of 'To' date) | I18: TOP 10 ITEMS BY SALES (all time)
B19: Account | D19: Opening | E19: In | F19: Out | G19: Balance | I19: # | J19: Item | L19: Sales (₹) | M19: Stock | N19: Status
B20: =IF(Settings!$A$18="","",Settings!$A$18) | D20: =IF(B20="","",N(Settings!$B$18)) | E20: =IF(B20="","",SUMIFS(CashBook!$I$5:$I$20004,CashBook!$F$5:$F$20004,B20,CashBook!$A$5:$A$20004,"<="&DTo)+SUMIFS(Sales!$X$5:$X$20004,Sales!$H$5:$H$20004,B20,Sales!$A$5:$A$20004,"<="&DTo)) | F20: =IF(B20="","",SUMIFS(CashBook!$J$5:$J$20004,CashBook!$F$5:$F$20004,B20,CashBook!$A$5:$A$20004,"<="&DTo)+SUMIFS(Purchases!$S$5:$S$20004,Purchases!$H$5:$H$20004,B20,Purchases!$A$5:$A$20004,"<="&DTo)) | G20: =IF(B20="","",D20+E20-F20) | I20: 1 | J20: =IFERROR(IF(INDEX(Items!$U$5:$U$2004,MATCH(LARGE(Items!$Z$5:$Z$2004,1),Items!$Z$5:$Z$2004,0))=0,"",INDEX(Items!$A$5:$A$2004,MATCH(LARGE(Items!$Z$5:$Z$2004,1),Items!$Z$5:$Z$2004,0))),"") | L20: =IF(J20="","",INDEX(Items!$U$5:$U$2004,MATCH(LARGE(Items!$Z$5:$Z$2004,1),Items!$Z$5:$Z$2004,0))) | M20: =IF(J20="","",INDEX(Items!$O$5:$O$2004,MATCH(LARGE(Items!$Z$5:$Z$2004,1),Items!$Z$5:$Z$2004,0))) | N20: =IF(J20="","",INDEX(Items!$R$5:$R$2004,MATCH(LARGE(Items!$Z$5:$Z$2004,1),Items!$Z$5:$Z$2004,0)))
B21: =IF(Settings!$A$19="","",Settings!$A$19) | D21: =IF(B21="","",N(Settings!$B$19)) | E21: =IF(B21="","",SUMIFS(CashBook!$I$5:$I$20004,CashBook!$F$5:$F$20004,B21,CashBook!$A$5:$A$20004,"<="&DTo)+SUMIFS(Sales!$X$5:$X$20004,Sales!$H$5:$H$20004,B21,Sales!$A$5:$A$20004,"<="&DTo)) | F21: =IF(B21="","",SUMIFS(CashBook!$J$5:$J$20004,CashBook!$F$5:$F$20004,B21,CashBook!$A$5:$A$20004,"<="&DTo)+SUMIFS(Purchases!$S$5:$S$20004,Purchases!$H$5:$H$20004,B21,Purchases!$A$5:$A$20004,"<="&DTo)) | G21: =IF(B21="","",D21+E21-F21) | I21: 2 | J21: =IFERROR(IF(INDEX(Items!$U$5:$U$2004,MATCH(LARGE(Items!$Z$5:$Z$2004,2),Items!$Z$5:$Z$2004,0))=0,"",INDEX(Items!$A$5:$A$2004,MATCH(LARGE(Items!$Z$5:$Z$2004,2),Items!$Z$5:$Z$2004,0))),"") | L21: =IF(J21="","",INDEX(Items!$U$5:$U$2004,MATCH(LARGE(Items!$Z$5:$Z$2004,2),Items!$Z$5:$Z$2004,0))) | M21: =IF(J21="","",INDEX(Items!$O$5:$O$2004,MATCH(LARGE(Items!$Z$5:$Z$2004,2),Items!$Z$5:$Z$2004,0))) | N21: =IF(J21="","",INDEX(Items!$R$5:$R$2004,MATCH(LARGE(Items!$Z$5:$Z$2004,2),Items!$Z$5:$Z$2004,0)))
B22: =IF(Settings!$A$20="","",Settings!$A$20) | D22: =IF(B22="","",N(Settings!$B$20)) | E22: =IF(B22="","",SUMIFS(CashBook!$I$5:$I$20004,CashBook!$F$5:$F$20004,B22,CashBook!$A$5:$A$20004,"<="&DTo)+SUMIFS(Sales!$X$5:$X$20004,Sales!$H$5:$H$20004,B22,Sales!$A$5:$A$20004,"<="&DTo)) | F22: =IF(B22="","",SUMIFS(CashBook!$J$5:$J$20004,CashBook!$F$5:$F$20004,B22,CashBook!$A$5:$A$20004,"<="&DTo)+SUMIFS(Purchases!$S$5:$S$20004,Purchases!$H$5:$H$20004,B22,Purchases!$A$5:$A$20004,"<="&DTo)) | G22: =IF(B22="","",D22+E22-F22) | I22: 3 | J22: =IFERROR(IF(INDEX(Items!$U$5:$U$2004,MATCH(LARGE(Items!$Z$5:$Z$2004,3),Items!$Z$5:$Z$2004,0))=0,"",INDEX(Items!$A$5:$A$2004,MATCH(LARGE(Items!$Z$5:$Z$2004,3),Items!$Z$5:$Z$2004,0))),"") | L22: =IF(J22="","",INDEX(Items!$U$5:$U$2004,MATCH(LARGE(Items!$Z$5:$Z$2004,3),Items!$Z$5:$Z$2004,0))) | M22: =IF(J22="","",INDEX(Items!$O$5:$O$2004,MATCH(LARGE(Items!$Z$5:$Z$2004,3),Items!$Z$5:$Z$2004,0))) | N22: =IF(J22="","",INDEX(Items!$R$5:$R$2004,MATCH(LARGE(Items!$Z$5:$Z$2004,3),Items!$Z$5:$Z$2004,0)))
B23: =IF(Settings!$A$21="","",Settings!$A$21) | D23: =IF(B23="","",N(Settings!$B$21)) | E23: =IF(B23="","",SUMIFS(CashBook!$I$5:$I$20004,CashBook!$F$5:$F$20004,B23,CashBook!$A$5:$A$20004,"<="&DTo)+SUMIFS(Sales!$X$5:$X$20004,Sales!$H$5:$H$20004,B23,Sales!$A$5:$A$20004,"<="&DTo)) | F23: =IF(B23="","",SUMIFS(CashBook!$J$5:$J$20004,CashBook!$F$5:$F$20004,B23,CashBook!$A$5:$A$20004,"<="&DTo)+SUMIFS(Purchases!$S$5:$S$20004,Purchases!$H$5:$H$20004,B23,Purchases!$A$5:$A$20004,"<="&DTo)) | G23: =IF(B23="","",D23+E23-F23) | I23: 4 | J23: =IFERROR(IF(INDEX(Items!$U$5:$U$2004,MATCH(LARGE(Items!$Z$5:$Z$2004,4),Items!$Z$5:$Z$2004,0))=0,"",INDEX(Items!$A$5:$A$2004,MATCH(LARGE(Items!$Z$5:$Z$2004,4),Items!$Z$5:$Z$2004,0))),"") | L23: =IF(J23="","",INDEX(Items!$U$5:$U$2004,MATCH(LARGE(Items!$Z$5:$Z$2004,4),Items!$Z$5:$Z$2004,0))) | M23: =IF(J23="","",INDEX(Items!$O$5:$O$2004,MATCH(LARGE(Items!$Z$5:$Z$2004,4),Items!$Z$5:$Z$2004,0))) | N23: =IF(J23="","",INDEX(Items!$R$5:$R$2004,MATCH(LARGE(Items!$Z$5:$Z$2004,4),Items!$Z$5:$Z$2004,0)))
B24: TOTAL LIQUIDITY | G24: =SUM(G20:G23) | I24: 5 | J24: =IFERROR(IF(INDEX(Items!$U$5:$U$2004,MATCH(LARGE(Items!$Z$5:$Z$2004,5),Items!$Z$5:$Z$2004,0))=0,"",INDEX(Items!$A$5:$A$2004,MATCH(LARGE(Items!$Z$5:$Z$2004,5),Items!$Z$5:$Z$2004,0))),"") | L24: =IF(J24="","",INDEX(Items!$U$5:$U$2004,MATCH(LARGE(Items!$Z$5:$Z$2004,5),Items!$Z$5:$Z$2004,0))) | M24: =IF(J24="","",INDEX(Items!$O$5:$O$2004,MATCH(LARGE(Items!$Z$5:$Z$2004,5),Items!$Z$5:$Z$2004,0))) | N24: =IF(J24="","",INDEX(Items!$R$5:$R$2004,MATCH(LARGE(Items!$Z$5:$Z$2004,5),Items!$Z$5:$Z$2004,0)))
I25: 6 | J25: =IFERROR(IF(INDEX(Items!$U$5:$U$2004,MATCH(LARGE(Items!$Z$5:$Z$2004,6),Items!$Z$5:$Z$2004,0))=0,"",INDEX(Items!$A$5:$A$2004,MATCH(LARGE(Items!$Z$5:$Z$2004,6),Items!$Z$5:$Z$2004,0))),"") | L25: =IF(J25="","",INDEX(Items!$U$5:$U$2004,MATCH(LARGE(Items!$Z$5:$Z$2004,6),Items!$Z$5:$Z$2004,0))) | M25: =IF(J25="","",INDEX(Items!$O$5:$O$2004,MATCH(LARGE(Items!$Z$5:$Z$2004,6),Items!$Z$5:$Z$2004,0))) | N25: =IF(J25="","",INDEX(Items!$R$5:$R$2004,MATCH(LARGE(Items!$Z$5:$Z$2004,6),Items!$Z$5:$Z$2004,0)))
I26: 7 | J26: =IFERROR(IF(INDEX(Items!$U$5:$U$2004,MATCH(LARGE(Items!$Z$5:$Z$2004,7),Items!$Z$5:$Z$2004,0))=0,"",INDEX(Items!$A$5:$A$2004,MATCH(LARGE(Items!$Z$5:$Z$2004,7),Items!$Z$5:$Z$2004,0))),"") | L26: =IF(J26="","",INDEX(Items!$U$5:$U$2004,MATCH(LARGE(Items!$Z$5:$Z$2004,7),Items!$Z$5:$Z$2004,0))) | M26: =IF(J26="","",INDEX(Items!$O$5:$O$2004,MATCH(LARGE(Items!$Z$5:$Z$2004,7),Items!$Z$5:$Z$2004,0))) | N26: =IF(J26="","",INDEX(Items!$R$5:$R$2004,MATCH(LARGE(Items!$Z$5:$Z$2004,7),Items!$Z$5:$Z$2004,0)))
I27: 8 | J27: =IFERROR(IF(INDEX(Items!$U$5:$U$2004,MATCH(LARGE(Items!$Z$5:$Z$2004,8),Items!$Z$5:$Z$2004,0))=0,"",INDEX(Items!$A$5:$A$2004,MATCH(LARGE(Items!$Z$5:$Z$2004,8),Items!$Z$5:$Z$2004,0))),"") | L27: =IF(J27="","",INDEX(Items!$U$5:$U$2004,MATCH(LARGE(Items!$Z$5:$Z$2004,8),Items!$Z$5:$Z$2004,0))) | M27: =IF(J27="","",INDEX(Items!$O$5:$O$2004,MATCH(LARGE(Items!$Z$5:$Z$2004,8),Items!$Z$5:$Z$2004,0))) | N27: =IF(J27="","",INDEX(Items!$R$5:$R$2004,MATCH(LARGE(Items!$Z$5:$Z$2004,8),Items!$Z$5:$Z$2004,0)))
I28: 9 | J28: =IFERROR(IF(INDEX(Items!$U$5:$U$2004,MATCH(LARGE(Items!$Z$5:$Z$2004,9),Items!$Z$5:$Z$2004,0))=0,"",INDEX(Items!$A$5:$A$2004,MATCH(LARGE(Items!$Z$5:$Z$2004,9),Items!$Z$5:$Z$2004,0))),"") | L28: =IF(J28="","",INDEX(Items!$U$5:$U$2004,MATCH(LARGE(Items!$Z$5:$Z$2004,9),Items!$Z$5:$Z$2004,0))) | M28: =IF(J28="","",INDEX(Items!$O$5:$O$2004,MATCH(LARGE(Items!$Z$5:$Z$2004,9),Items!$Z$5:$Z$2004,0))) | N28: =IF(J28="","",INDEX(Items!$R$5:$R$2004,MATCH(LARGE(Items!$Z$5:$Z$2004,9),Items!$Z$5:$Z$2004,0)))
I29: 10 | J29: =IFERROR(IF(INDEX(Items!$U$5:$U$2004,MATCH(LARGE(Items!$Z$5:$Z$2004,10),Items!$Z$5:$Z$2004,0))=0,"",INDEX(Items!$A$5:$A$2004,MATCH(LARGE(Items!$Z$5:$Z$2004,10),Items!$Z$5:$Z$2004,0))),"") | L29: =IF(J29="","",INDEX(Items!$U$5:$U$2004,MATCH(LARGE(Items!$Z$5:$Z$2004,10),Items!$Z$5:$Z$2004,0))) | M29: =IF(J29="","",INDEX(Items!$O$5:$O$2004,MATCH(LARGE(Items!$Z$5:$Z$2004,10),Items!$Z$5:$Z$2004,0))) | N29: =IF(J29="","",INDEX(Items!$R$5:$R$2004,MATCH(LARGE(Items!$Z$5:$Z$2004,10),Items!$Z$5:$Z$2004,0)))

Sheet Sales
A1: 🧾 SALES / INVOICES (DELIVER) | Z1: ◀ Home
A2: One line per item sold. Keep all lines of an invoice together. Leave Rate blank to use the standard sale rate.
A3: Blue / cream = type here | J3: ⚙ C engine: {=_xll.ST_SALES(…)} fills J:X
A4: Date * | B4: Invoice No * | C4: Customer * | D4: Item * | E4: Qty * | F4: Rate (₹) blank=std | G4: Disc % | H4: Paid Via (blank=Credit) | I4: Delivery | J4: Unit | K4: Rate Used (₹) | L4: Taxable (₹) | M4: GST % | N4: CGST (₹) | O4: SGST (₹) | P4: IGST (₹) | Q4: Line Total (₹) | R4: COGS (₹) | S4: Profit (₹) | T4: Stock Check | U4: itemRow | V4: partyRow | W4: invNum | X4: Paid Now (₹)
A5: 46113 | B5: INV-0001 | C5: FMCG Distributors | D5: PVC Pipe 1in 6m | E5: 3 | H5: Bank | I5: Delivered | J5: {=_xll.ST_SALES(IN_Items,IN_Parties,IN_Purchases,IN_Sales,IN_CashBook,IN_Adjust,IN_Settings)}
A6: 46113 | B6: INV-0002 | C6: Walk-in Customer | D6: Sugar 50kg | E6: 1 | H6: Cash | I6: Delivered
A7: 46113 | B7: INV-0002 | C7: Walk-in Customer | D7: Tea Premium 1kg | E7: 4 | H7: Cash | I7: Delivered
A8: 46113 | B8: INV-0002 | C8: Walk-in Customer | D8: Ceiling Fan 1200mm | E8: 1 | G8: 0.05 | H8: Cash | I8: Delivered
A9: 46114 | B9: INV-0003 | C9: Walk-in Customer | D9: Tea Premium 1kg | E9: 1 | H9: Cash | I9: Delivered
A10: 46114 | B10: INV-0004 | C10: Mehta Constructions | D10: PVC Pipe 1in 6m | E10: 6 | G10: 0.05 | H10: UPI | I10: Delivered
A11: 46114 | B11: INV-0004 | C11: Mehta Constructions | D11: Sugar 50kg | E11: 1 | H11: UPI | I11: Delivered
A12: 46115 | B12: INV-0005 | C12: Walk-in Customer | D12: Sugar 50kg | E12: 1 | G12: 0.05 | H12: Cash | I12: Delivered
A13: 46115 | B13: INV-0005 | C13: Walk-in Customer | D13: PVC Pipe 1in 6m | E13: 2 | H13: Cash | I13: Delivered
A14: 46115 | B14: INV-0006 | C14: Walk-in Customer | D14: Toothpaste 150g x12 | E14: 2 | H14: Cash | I14: Delivered
A15: 46115 | B15: INV-0006 | C15: Walk-in Customer | D15: Copper Wire 90m | E15: 1 | H15: Cash | I15: Delivered
A16: 46115 | B16: INV-0006 | C16: Walk-in Customer | D16: Cement 50kg | E16: 9 | H16: Cash | I16: Delivered
A17: 46116 | B17: INV-0007 | C17: Mehta Constructions | D17: Toothpaste 150g x12 | E17: 1 | H17: Bank | I17: Delivered
A18: 46116 | B18: INV-0007 | C18: Mehta Constructions | D18: Copper Wire 90m | E18: 1 | G18: 0.02 | H18: Bank | I18: Delivered
A19: 46116 | B19: INV-0007 | C19: Mehta Constructions | D19: Detergent 5kg | E19: 1 | H19: Bank | I19: Delivered
A20: 46116 | B20: INV-0008 | C20: Delhi Hardware Mart | D20: Basmati Rice 25kg | E20: 2 | G20: 0.05 | H20: UPI | I20: Delivered
A21: 46116 | B21: INV-0008 | C21: Delhi Hardware Mart | D21: A4 Paper Ream | E21: 6 | H21: UPI | I21: Delivered
A22: 46116 | B22: INV-0008 | C22: Delhi Hardware Mart | D22: Sugar 50kg | E22: 1 | H22: UPI | I22: Delivered
A23: 46118 | B23: INV-0009 | C23: Gupta Electricals | D23: Copper Wire 90m | E23: 1 | I23: Delivered
A24: 46118 | B24: INV-0009 | C24: Gupta Electricals | D24: A4 Paper Ream | E24: 5 | G24: 0.02 | I24: Delivered
A25: 46118 | B25: INV-0010 | C25: Mehta Constructions | D25: Basmati Rice 25kg | E25: 1 | G25: 0.05 | H25: UPI | I25: Delivered
A26: 46118 | B26: INV-0010 | C26: Mehta Constructions | D26: Copper Wire 90m | E26: 1 | H26: UPI | I26: Delivered
A27: 46118 | B27: INV-0011 | C27: Walk-in Customer | D27: Refined Oil 15L | E27: 1 | G27: 0.02 | H27: Cash | I27: Delivered
A28: 46118 | B28: INV-0011 | C28: Walk-in Customer | D28: Tea Premium 1kg | E28: 1 | G28: 0.02 | H28: Cash | I28: Delivered
A29: 46118 | B29: INV-0012 | C29: Walk-in Customer | D29: Refined Oil 15L | E29: 2 | H29: Cash | I29: Delivered
A30: 46118 | B30: INV-0012 | C30: Walk-in Customer | D30: LED Bulb 9W | E30: 19 | H30: Cash | I30: Delivered
A31: 46119 | B31: INV-0013 | C31: Walk-in Customer | D31: Sugar 50kg | E31: 1 | H31: Cash | I31: Delivered
A32: 46119 | B32: INV-0013 | C32: Walk-in Customer | D32: Refined Oil 15L | E32: 1 | G32: 0.05 | H32: Cash | I32: Delivered
A33: 46119 | B33: INV-0014 | C33: Delhi Hardware Mart | D33: Basmati Rice 25kg | E33: 1 | I33: Delivered
A34: 46119 | B34: INV-0014 | C34: Delhi Hardware Mart | D34: Refined Oil 15L | E34: 1 | I34: Delivered
A35: 46119 | B35: INV-0015 | C35: Delhi Hardware Mart | D35: Copper Wire 90m | E35: 1 | G35: 0.05 | H35: Bank | I35: Delivered
A36: 46119 | B36: INV-0016 | C36: Walk-in Customer | D36: LED Bulb 9W | E36: 14 | G36: 0.02 | H36: Cash | I36: Delivered
A37: 46119 | B37: INV-0016 | C37: Walk-in Customer | D37: Ceiling Fan 1200mm | E37: 1 | H37: Cash | I37: Delivered
A38: 46119 | B38: INV-0016 | C38: Walk-in Customer | D38: Sugar 50kg | E38: 1 | G38: 0.02 | H38: Cash | I38: Delivered
A39: 46120 | B39: INV-0017 | C39: Gupta Electricals | D39: Sugar 50kg | E39: 1 | I39: Delivered
A40: 46120 | B40: INV-0018 | C40: Gupta Electricals | D40: Sugar 50kg | E40: 1 | G40: 0.05 | I40: Delivered
A41: 46120 | B41: INV-0019 | C41: Walk-in Customer | D41: A4 Paper Ream | E41: 7 | G41: 0.05 | H41: Cash | I41: Delivered
A42: 46120 | B42: INV-0019 | C42: Walk-in Customer | D42: Detergent 5kg | E42: 1 | H42: Cash | I42: Delivered
A43: 46121 | B43: INV-0020 | C43: Walk-in Customer | D43: Copper Wire 90m | E43: 1 | H43: Cash | I43: Delivered
A44: 46121 | B44: INV-0020 | C44: Walk-in Customer | D44: Ceiling Fan 1200mm | E44: 1 | H44: Cash | I44: Delivered
A45: 46121 | B45: INV-0020 | C45: Walk-in Customer | D45: Detergent 5kg | E45: 2 | H45: Cash | I45: Delivered
A46: 46121 | B46: INV-0021 | C46: Sharma Kirana Store | D46: Refined Oil 15L | E46: 2 | G46: 0.05 | I46: Delivered
A47: 46121 | B47: INV-0021 | C47: Sharma Kirana Store | D47: PVC Pipe 1in 6m | E47: 4 | I47: Delivered
A48: 46122 | B48: INV-0022 | C48: FMCG Distributors | D48: Tea Premium 1kg | E48: 3 | G48: 0.05 | I48: Delivered
A49: 46122 | B49: INV-0022 | C49: FMCG Distributors | D49: PVC Pipe 1in 6m | E49: 4 | I49: Delivered
A50: 46122 | B50: INV-0023 | C50: Walk-in Customer | D50: LED Bulb 9W | E50: 8 | G50: 0.02 | H50: Cash | I50: Delivered
A51: 46122 | B51: INV-0023 | C51: Walk-in Customer | D51: Tea Premium 1kg | E51: 2 | H51: Cash | I51: Delivered
A52: 46122 | B52: INV-0024 | C52: Sharma Kirana Store | D52: Detergent 5kg | E52: 3 | G52: 0.02 | I52: Delivered
A53: 46122 | B53: INV-0024 | C53: Sharma Kirana Store | D53: Tea Premium 1kg | E53: 4 | I53: Delivered
A54: 46122 | B54: INV-0024 | C54: Sharma Kirana Store | D54: Cement 50kg | E54: 12 | I54: Delivered
A55: 46123 | B55: INV-0025 | C55: Walk-in Customer | D55: Copper Wire 90m | E55: 1 | H55: Cash | I55: Delivered
A56: 46123 | B56: INV-0025 | C56: Walk-in Customer | D56: Refined Oil 15L | E56: 1 | G56: 0.02 | H56: Cash | I56: Delivered
A57: 46123 | B57: INV-0026 | C57: Walk-in Customer | D57: Ceiling Fan 1200mm | E57: 1 | H57: Cash | I57: Delivered
A58: 46123 | B58: INV-0026 | C58: Walk-in Customer | D58: Sugar 50kg | E58: 1 | G58: 0.05 | H58: Cash | I58: Delivered
A59: 46123 | B59: INV-0026 | C59: Walk-in Customer | D59: Refined Oil 15L | E59: 2 | H59: Cash | I59: Delivered
A60: 46125 | B60: INV-0027 | C60: FMCG Distributors | D60: Basmati Rice 25kg | E60: 2 | I60: Delivered
A61: 46125 | B61: INV-0027 | C61: FMCG Distributors | D61: Ceiling Fan 1200mm | E61: 1 | I61: Delivered
A62: 46125 | B62: INV-0028 | C62: Walk-in Customer | D62: Tea Premium 1kg | E62: 2 | H62: Cash | I62: Delivered
A63: 46125 | B63: INV-0028 | C63: Walk-in Customer | D63: Basmati Rice 25kg | E63: 1 | G63: 0.05 | H63: Cash | I63: Delivered
A64: 46125 | B64: INV-0029 | C64: FMCG Distributors | D64: Refined Oil 15L | E64: 2 | G64: 0.05 | I64: Delivered
A65: 46125 | B65: INV-0029 | C65: FMCG Distributors | D65: Basmati Rice 25kg | E65: 2 | G65: 0.05 | I65: Delivered
A66: 46125 | B66: INV-0029 | C66: FMCG Distributors | D66: Toothpaste 150g x12 | E66: 1 | G66: 0.05 | I66: Delivered
A67: 46125 | B67: INV-0030 | C67: Delhi Hardware Mart | D67: PVC Pipe 1in 6m | E67: 2 | G67: 0.02 | H67: Bank | I67: Delivered
A68: 46125 | B68: INV-0030 | C68: Delhi Hardware Mart | D68: Ceiling Fan 1200mm | E68: 1 | G68: 0.05 | H68: Bank | I68: Delivered
A69: 46126 | B69: INV-0031 | C69: Delhi Hardware Mart | D69: Copper Wire 90m | E69: 1 | G69: 0.05 | I69: Delivered
A70: 46126 | B70: INV-0031 | C70: Delhi Hardware Mart | D70: Cement 50kg | E70: 3 | G70: 0.05 | I70: Delivered
A71: 46126 | B71: INV-0032 | C71: Walk-in Customer | D71: PVC Pipe 1in 6m | E71: 2 | H71: Cash | I71: Delivered
A72: 46127 | B72: INV-0033 | C72: Sharma Kirana Store | D72: PVC Pipe 1in 6m | E72: 5 | G72: 0.05 | I72: Delivered
A73: 46127 | B73: INV-0033 | C73: Sharma Kirana Store | D73: Basmati Rice 25kg | E73: 2 | G73: 0.05 | I73: Delivered
A74: 46127 | B74: INV-0033 | C74: Sharma Kirana Store | D74: Sugar 50kg | E74: 1 | I74: Delivered
A75: 46127 | B75: INV-0034 | C75: Walk-in Customer | D75: PVC Pipe 1in 6m | E75: 9 | H75: Cash | I75: Delivered
A76: 46127 | B76: INV-0034 | C76: Walk-in Customer | D76: Tea Premium 1kg | E76: 4 | H76: Cash | I76: Delivered
A77: 46127 | B77: INV-0034 | C77: Walk-in Customer | D77: Ceiling Fan 1200mm | E77: 1 | H77: Cash | I77: Delivered
A78: 46127 | B78: INV-0035 | C78: Walk-in Customer | D78: LED Bulb 9W | E78: 13 | H78: Cash | I78: Delivered
A79: 46128 | B79: INV-0036 | C79: Walk-in Customer | D79: Tea Premium 1kg | E79: 3 | H79: Cash | I79: Delivered
A80: 46128 | B80: INV-0037 | C80: Delhi Hardware Mart | D80: Detergent 5kg | E80: 3 | I80: Delivered
A81: 46128 | B81: INV-0037 | C81: Delhi Hardware Mart | D81: Refined Oil 15L | E81: 1 | I81: Delivered
A82: 46128 | B82: INV-0038 | C82: Walk-in Customer | D82: Refined Oil 15L | E82: 1 | G82: 0.02 | H82: Cash | I82: Delivered
A83: 46128 | B83: INV-0038 | C83: Walk-in Customer | D83: A4 Paper Ream | E83: 7 | G83: 0.02 | H83: Cash | I83: Delivered
A84: 46128 | B84: INV-0038 | C84: Walk-in Customer | D84: Tea Premium 1kg | E84: 2 | H84: Cash | I84: Delivered
A85: 46129 | B85: INV-0039 | C85: FMCG Distributors | D85: Basmati Rice 25kg | E85: 1 | G85: 0.02 | I85: Delivered
A86: 46129 | B86: INV-0039 | C86: FMCG Distributors | D86: Toothpaste 150g x12 | E86: 1 | G86: 0.02 | I86: Delivered
A87: 46129 | B87: INV-0040 | C87: FMCG Distributors | D87: PVC Pipe 1in 6m | E87: 2 | H87: Bank | I87: Delivered
A88: 46129 | B88: INV-0040 | C88: FMCG Distributors | D88: Sugar 50kg | E88: 1 | H88: Bank | I88: Delivered
A89: 46129 | B89: INV-0041 | C89: Gupta Electricals | D89: Basmati Rice 25kg | E89: 1 | I89: Delivered
A90: 46129 | B90: INV-0041 | C90: Gupta Electricals | D90: Refined Oil 15L | E90: 2 | I90: Delivered
A91: 46130 | B91: INV-0042 | C91: Delhi Hardware Mart | D91: Ceiling Fan 1200mm | E91: 1 | H91: Bank | I91: Delivered
A92: 46130 | B92: INV-0042 | C92: Delhi Hardware Mart | D92: Toothpaste 150g x12 | E92: 1 | H92: Bank | I92: Delivered
A93: 46130 | B93: INV-0042 | C93: Delhi Hardware Mart | D93: Sugar 50kg | E93: 1 | H93: Bank | I93: Delivered
A94: 46130 | B94: INV-0043 | C94: Gupta Electricals | D94: Cement 50kg | E94: 11 | I94: Delivered
A95: 46130 | B95: INV-0044 | C95: Mehta Constructions | D95: Basmati Rice 25kg | E95: 1 | I95: Delivered
A96: 46130 | B96: INV-0044 | C96: Mehta Constructions | D96: Toothpaste 150g x12 | E96: 1 | I96: Delivered
A97: 46130 | B97: INV-0044 | C97: Mehta Constructions | D97: PVC Pipe 1in 6m | E97: 6 | I97: Delivered
A98: 46130 | B98: INV-0045 | C98: Gupta Electricals | D98: Basmati Rice 25kg | E98: 1 | I98: Delivered
A99: 46130 | B99: INV-0045 | C99: Gupta Electricals | D99: Refined Oil 15L | E99: 1 | G99: 0.05 | I99: Delivered
A100: 46132 | B100: INV-0046 | C100: Mehta Constructions | D100: Detergent 5kg | E100: 3 | H100: UPI | I100: Delivered
...

Sheet Purchases
A1: 🛒 PURCHASES / GOODS RECEIVED (PROCURE) | U1: ◀ Home
A2: One line per item received. Stock, average cost, supplier payable and GST input credit update instantly.
A3: Blue / cream = type here | I3: ⚙ C engine: {=_xll.ST_PURCHASES(…)} fills I:S
A4: Date * | B4: Bill No * | C4: Supplier * | D4: Item * | E4: Qty * | F4: Rate (₹) blank=std | G4: Disc % | H4: Paid Via (blank=Credit) | I4: Unit | J4: Rate Used (₹) | K4: Taxable (₹) | L4: GST % | M4: CGST (₹) | N4: SGST (₹) | O4: IGST (₹) | P4: Bill Total (₹) | Q4: itemRow | R4: partyRow | S4: Paid Now (₹)
A5: 46113 | B5: B-0001 | C5: Bharat Electric Co | D5: Copper Wire 90m | E5: 13 | F5: 2517 | I5: {=_xll.ST_PURCHASES(IN_Items,IN_Parties,IN_Purchases,IN_Sales,IN_CashBook,IN_Adjust,IN_Settings)}
A6: 46113 | B6: B-0001 | C6: Bharat Electric Co | D6: Ceiling Fan 1200mm | E6: 21 | F6: 1650
A7: 46113 | B7: B-0002 | C7: FMCG Distributors | D7: Toothpaste 150g x12 | E7: 25 | F7: 885
A8: 46144 | B8: B-0003 | C8: Agro Foods Pvt Ltd | D8: Basmati Rice 25kg | E8: 29 | F8: 1690
A9: 46144 | B9: B-0003 | C9: Agro Foods Pvt Ltd | D9: Sugar 50kg | E9: 34 | F9: 2086
A10: 46144 | B10: B-0003 | C10: Agro Foods Pvt Ltd | D10: Refined Oil 15L | E10: 41 | F10: 1881
A11: 46144 | B11: B-0004 | C11: Bharat Electric Co | D11: LED Bulb 9W | E11: 311 | F11: 63 | H11: Bank
A12: 46144 | B12: B-0004 | C12: Bharat Electric Co | D12: Copper Wire 90m | E12: 13 | F12: 2427 | H12: Bank
A13: 46144 | B13: B-0004 | C13: Bharat Electric Co | D13: Ceiling Fan 1200mm | E13: 13 | F13: 1639 | H13: Bank
A14: 46144 | B14: B-0005 | C14: FMCG Distributors | D14: Tea Premium 1kg | E14: 78 | F14: 382
A15: 46144 | B15: B-0005 | C15: FMCG Distributors | D15: Detergent 5kg | E15: 47 | F15: 525
A16: 46144 | B16: B-0006 | C16: National Hardware Supply | D16: PVC Pipe 1in 6m | E16: 152 | F16: 207
A17: 46144 | B17: B-0006 | C17: National Hardware Supply | D17: Cement 50kg | E17: 111 | F17: 342
A18: 46175 | B18: B-0007 | C18: Bharat Electric Co | D18: LED Bulb 9W | E18: 204 | F18: 64
A19: 46175 | B19: B-0007 | C19: Bharat Electric Co | D19: Copper Wire 90m | E19: 17 | F19: 2490
A20: 46175 | B20: B-0007 | C20: Bharat Electric Co | D20: Ceiling Fan 1200mm | E20: 12 | F20: 1625
A21: 46175 | B21: B-0008 | C21: FMCG Distributors | D21: Detergent 5kg | E21: 31 | F21: 515
A22: 46175 | B22: B-0008 | C22: FMCG Distributors | D22: Toothpaste 150g x12 | E22: 30 | F22: 889
A23: 46205 | B23: B-0009 | C23: Agro Foods Pvt Ltd | D23: Basmati Rice 25kg | E23: 39 | F23: 1687 | H23: Bank
A24: 46205 | B24: B-0009 | C24: Agro Foods Pvt Ltd | D24: Sugar 50kg | E24: 25 | F24: 2067 | H24: Bank
A25: 46205 | B25: B-0009 | C25: Agro Foods Pvt Ltd | D25: Refined Oil 15L | E25: 27 | F25: 1935 | H25: Bank
A26: 46205 | B26: B-0010 | C26: Bharat Electric Co | D26: Copper Wire 90m | E26: 12 | F26: 2501
A27: 46205 | B27: B-0010 | C27: Bharat Electric Co | D27: Ceiling Fan 1200mm | E27: 16 | F27: 1687
A28: 46205 | B28: B-0011 | C28: FMCG Distributors | D28: Tea Premium 1kg | E28: 56 | F28: 379
A29: 46205 | B29: B-0011 | C29: FMCG Distributors | D29: Detergent 5kg | E29: 34 | F29: 513
A30: 46205 | B30: B-0012 | C30: National Hardware Supply | D30: PVC Pipe 1in 6m | E30: 142 | F30: 208
A31: 46205 | B31: B-0012 | C31: National Hardware Supply | D31: Cement 50kg | E31: 216 | F31: 340
A32: 46236 | B32: B-0013 | C32: Agro Foods Pvt Ltd | D32: Basmati Rice 25kg | E32: 25 | F32: 1646
A33: 46236 | B33: B-0014 | C33: Bharat Electric Co | D33: LED Bulb 9W | E33: 392 | F33: 61 | H33: Bank
A34: 46236 | B34: B-0014 | C34: Bharat Electric Co | D34: Copper Wire 90m | E34: 13 | F34: 2522 | H34: Bank
A35: 46236 | B35: B-0014 | C35: Bharat Electric Co | D35: Ceiling Fan 1200mm | E35: 16 | F35: 1653 | H35: Bank
A36: 46236 | B36: B-0015 | C36: FMCG Distributors | D36: Toothpaste 150g x12 | E36: 37 | F36: 904
A37: 46236 | B37: B-0016 | C37: National Hardware Supply | D37: PVC Pipe 1in 6m | E37: 100 | F37: 214
A38: 46267 | B38: B-0017 | C38: Agro Foods Pvt Ltd | D38: Sugar 50kg | E38: 26 | F38: 2081
A39: 46267 | B39: B-0017 | C39: Agro Foods Pvt Ltd | D39: Refined Oil 15L | E39: 29 | F39: 1910
A40: 46267 | B40: B-0018 | C40: Bharat Electric Co | D40: LED Bulb 9W | E40: 253 | F40: 64
A41: 46267 | B41: B-0018 | C41: Bharat Electric Co | D41: Copper Wire 90m | E41: 17 | F41: 2441
A42: 46267 | B42: B-0018 | C42: Bharat Electric Co | D42: Ceiling Fan 1200mm | E42: 14 | F42: 1686
A43: 46267 | B43: B-0019 | C43: FMCG Distributors | D43: Tea Premium 1kg | E43: 57 | F43: 390
A44: 46267 | B44: B-0019 | C44: FMCG Distributors | D44: Detergent 5kg | E44: 39 | F44: 527
A45: 46267 | B45: B-0020 | C45: National Hardware Supply | D45: Cement 50kg | E45: 146 | F45: 340
A46: 46297 | B46: B-0021 | C46: Agro Foods Pvt Ltd | D46: Basmati Rice 25kg | E46: 29 | F46: 1688
A47: 46297 | B47: B-0022 | C47: Bharat Electric Co | D47: Copper Wire 90m | E47: 11 | F47: 2450
A48: 46297 | B48: B-0023 | C48: FMCG Distributors | D48: Toothpaste 150g x12 | E48: 32 | F48: 914
A49: 46297 | B49: B-0024 | C49: National Hardware Supply | D49: PVC Pipe 1in 6m | E49: 114 | F49: 213 | H49: Bank

Sheet CashBook
A1: 💰 CASH & BANK BOOK (FINANCE) | M1: ◀ Home
A2: Customer receipts, supplier payments, expenses, owner capital/drawings and transfers between accounts.
A3: Blue / cream = type here | I3: ⚙ C engine: {=_xll.ST_CASHBOOK(…)} fills I:K
A4: Date * | B4: Voucher No | C4: Type * | D4: Party (Receipt/Payment) | E4: Expense / Income Head | F4: Account * | G4: Amount (₹) * | H4: Reference / Notes | I4: Money In (₹) | J4: Money Out (₹) | K4: Check
A5: 46117 | B5: V-0001 | C5: Expense | E5: Rent | F5: Bank | G5: 18000 | I5: {=_xll.ST_CASHBOOK(IN_Items,IN_Parties,IN_Purchases,IN_Sales,IN_CashBook,IN_Adjust,IN_Settings)}
A6: 46117 | B6: V-0002 | C6: Expense | E6: Salary | F6: Bank | G6: 26000
A7: 46117 | B7: V-0003 | C7: Expense | E7: Electricity | F7: UPI | G7: 4417
A8: 46117 | B8: V-0004 | C8: Expense | E8: Transport / Freight | F8: Cash | G8: 8568
A9: 46117 | B9: V-0005 | C9: Expense | E9: Telephone / Internet | F9: UPI | G9: 1199
A10: 46122 | B10: V-0006 | C10: Receipt | D10: Sharma Kirana Store | F10: Bank | G10: 16500 | H10: NEFT/UPI
A11: 46122 | B11: V-0007 | C11: Receipt | D11: Gupta Electricals | F11: Bank | G11: 6600 | H11: NEFT/UPI
A12: 46122 | B12: V-0008 | C12: Receipt | D12: Delhi Hardware Mart | F12: UPI | G12: 3000 | H12: NEFT/UPI
A13: 46122 | B13: V-0009 | C13: Receipt | D13: Mehta Constructions | F13: Bank | G13: 6900 | H13: NEFT/UPI
A14: 46122 | B14: V-0010 | C14: Receipt | D14: FMCG Distributors | F14: UPI | G14: 700 | H14: NEFT/UPI
A15: 46122 | B15: V-0011 | C15: Payment | D15: Agro Foods Pvt Ltd | F15: Bank | G15: 20000 | H15: RTGS
A16: 46122 | B16: V-0012 | C16: Payment | D16: Bharat Electric Co | F16: Bank | G16: 54000 | H16: RTGS
A17: 46122 | B17: V-0013 | C17: Payment | D17: FMCG Distributors | F17: Bank | G17: 17000 | H17: RTGS
A18: 46137 | B18: V-0014 | C18: Receipt | D18: Sharma Kirana Store | F18: UPI | G18: 18300 | H18: NEFT/UPI
A19: 46137 | B19: V-0015 | C19: Receipt | D19: Gupta Electricals | F19: Bank | G19: 17900 | H19: NEFT/UPI
A20: 46137 | B20: V-0016 | C20: Receipt | D20: Delhi Hardware Mart | F20: Bank | G20: 7300 | H20: NEFT/UPI
A21: 46137 | B21: V-0017 | C21: Receipt | D21: Mehta Constructions | F21: Bank | G21: 19500 | H21: NEFT/UPI
... A25: 46137 | B25: V-0021 | C25: Payment | D25: FMCG Distributors | F25: Bank | G25: 4000 | H25: RTGS
A26: 46138 | B26: V-0022 | C26: Transfer Out | F26: Cash | G26: 145000 | H26: Cash deposited to Bank
A27: 46138 | B27: V-0022 | C27: Transfer In | F27: Bank | G27: 145000 | H27: Cash deposited to Bank
A28: 46138 | B28: V-0023 | C28: Transfer Out | F28: UPI | G28: 29000 | H28: UPI deposited to Bank
A29: 46138 | B29: V-0023 | C29: Transfer In | F29: Bank | G29: 29000 | H29: UPI deposited to Bank
A30: 46147 | B30: V-0024 | C30: Expense | E30: Rent | F30: Bank | G30: 18000
A31: 46147 | B31: V-0025 | C31: Expense | E31: Salary | F31: Bank | G31: 26000
A32: 46147 | B32: V-0026 | C32: Expense | E32: Electricity | F32: UPI | G32: 5088
A33: 46147 | B33: V-0027 | C33: Expense | E33: Transport / Freight | F33: Cash | G33: 7723
A34: 46147 | B34: V-0028 | C34: Expense | E34: Telephone / Internet | F34: UPI | G34: 1199
A35: 46152 | B35: V-0029 | C35: Receipt | D35: Sharma Kirana Store | F35: Bank | G35: 19200 | H35: NEFT/UPI
A36: 46152 | B36: V-0030 | C36: Receipt | D36: Gupta Electricals | F36: Bank | G36: 9900 | H36: NEFT/UPI
A37: 46152 | B37: V-0031 | C37: Receipt | D37: Delhi Hardware Mart | F37: Bank | G37: 20200 | H37: NEFT/UPI
A38: 46152 | B38: V-0032 | C38: Receipt | D38: Mehta Constructions | F38: UPI | G38: 3200 | H38: NEFT/UPI
A39: 46152 | B39: V-0033 | C39: Receipt | D39: FMCG Distributors | F39: UPI | G39: 11300 | H39: NEFT/UPI
A40: 46152 | B40: V-0034 | C40: Payment | D40: Agro Foods Pvt Ltd | F40: Bank | G40: 144000 | H40: RTGS
A41: 46152 | B41: V-0035 | C41: Payment | D41: Bharat Electric Co | F41: Bank | G41: 6000 | H41: RTGS
A42: 46152 | B42: V-0036 | C42: Payment | D42: FMCG Distributors | F42: Bank | G42: 40000 | H42: RTGS
A43: 46152 | B43: V-0037 | C43: Payment | D43: National Hardware Supply | F43: Bank | G43: 54000 | H43: RTGS
A44: 46167 | B44: V-0038 | C44: Receipt | D44: Sharma Kirana Store | F44: Bank | G44: 14200 | H44: NEFT/UPI
A45: 46167 | B45: V-0039 | C45: Receipt | D45: Gupta Electricals | F45: UPI | G45: 20100 | H45: NEFT/UPI
A46: 46167 | B46: V-0040 | C46: Receipt | D46: Delhi Hardware Mart | F46: Bank | G46: 8200 | H46: NEFT/UPI
... A52: 46167 | B52: V-0046 | C52: Payment | D52: National Hardware Supply | F52: Bank | G52: 23000 | H52: RTGS
A53: 46168 | B53: V-0047 | C53: Transfer Out | F53: Cash | G53: 129000 | H53: Cash deposited to Bank
A54: 46168 | B54: V-0047 | C54: Transfer In | F54: Bank | G54: 129000 | H54: Cash deposited to Bank
A55: 46168 | B55: V-0048 | C55: Transfer Out | F55: UPI | G55: 76000 | H55: UPI deposited to Bank
A56: 46168 | B56: V-0048 | C56: Transfer In | F56: Bank | G56: 76000 | H56: UPI deposited to Bank
A57: 46178 | B57: V-0049 | C57: Expense | E57: Rent | F57: Bank | G57: 18000
A58: 46178 | B58: V-0050 | C58: Expense | E58: Salary | F58: Bank | G58: 26000
A59: 46178 | B59: V-0051 | C59: Expense | E59: Electricity | F59: UPI | G59: 3512
A60: 46178 | B60: V-0052 | C60: Expense | E60: Transport / Freight | F60: Cash | G60: 6983
A61: 46178 | B61: V-0053 | C61: Expense | E61: Telephone / Internet | F61: UPI | G61: 1199
A62: 46183 | B62: V-0054 | C62: Receipt | D62: Sharma Kirana Store | F62: Bank | G62: 16200 | H62: NEFT/UPI
A63: 46183 | B63: V-0055 | C63: Receipt | D63: Gupta Electricals | F63: UPI | G63: 16000 | H63: NEFT/UPI
A64: 46183 | B64: V-0056 | C64: Receipt | D64: Delhi Hardware Mart | F64: Bank | G64: 3900 | H64: NEFT/UPI
A65: 46183 | B65: V-0057 | C65: Receipt | D65: Mehta Constructions | F65: UPI | G65: 13300 | H65: NEFT/UPI
A66: 46183 | B66: V-0058 | C66: Receipt | D66: FMCG Distributors | F66: Bank | G66: 11500 | H66: NEFT/UPI
A67: 46183 | B67: V-0059 | C67: Payment | D67: Agro Foods Pvt Ltd | F67: Bank | G67: 14000 | H67: RTGS
A68: 46183 | B68: V-0060 | C68: Payment | D68: Bharat Electric Co | F68: Bank | G68: 57000 | H68: RTGS
A69: 46183 | B69: V-0061 | C69: Payment | D69: FMCG Distributors | F69: Bank | G69: 34000 | H69: RTGS
A70: 46183 | B70: V-0062 | C70: Payment | D70: National Hardware Supply | F70: Bank | G70: 3000 | H70: RTGS
A71: 46198 | B71: V-0063 | C71: Receipt | D71: Sharma Kirana Store | F71: UPI | G71: 12200 | H71: NEFT/UPI
A72: 46198 | B72: V-0064 | C72: Receipt | D72: Gupta Electricals | F72: Bank | G72: 17600 | H72: NEFT/UPI
A73: 46198 | B73: V-0065 | C73: Receipt | D73: Delhi Hardware Mart | F73: Bank | G73: 5100 | H73: NEFT/UPI
... A79: 46198 | B79: V-0071 | C79: Payment | D79: National Hardware Supply | F79: Bank | G79: 1000 | H79: RTGS
A80: 46199 | B80: V-0072 | C80: Transfer Out | F80: Cash | G80: 173000 | H80: Cash deposited to Bank
A81: 46199 | B81: V-0072 | C81: Transfer In | F81: Bank | G81: 173000 | H81: Cash deposited to Bank
A82: 46199 | B82: V-0073 | C82: Transfer Out | F82: UPI | G82: 102000 | H82: UPI deposited to Bank
A83: 46199 | B83: V-0073 | C83: Transfer In | F83: Bank | G83: 102000 | H83: UPI deposited to Bank
A84: 46208 | B84: V-0074 | C84: Expense | E84: Rent | F84: Bank | G84: 18000
A85: 46208 | B85: V-0075 | C85: Expense | E85: Salary | F85: Bank | G85: 26000
A86: 46208 | B86: V-0076 | C86: Expense | E86: Electricity | F86: UPI | G86: 4984
A87: 46208 | B87: V-0077 | C87: Expense | E87: Transport / Freight | F87: Cash | G87: 7350
A88: 46208 | B88: V-0078 | C88: Expense | E88: Telephone / Internet | F88: UPI | G88: 1199
A89: 46213 | B89: V-0079 | C89: Receipt | D89: Sharma Kirana Store | F89: UPI | G89: 20600 | H89: NEFT/UPI
A90: 46213 | B90: V-0080 | C90: Receipt | D90: Gupta Electricals | F90: Bank | G90: 12100 | H90: NEFT/UPI
A91: 46213 | B91: V-0081 | C91: Receipt | D91: Delhi Hardware Mart | F91: UPI | G91: 11700 | H91: NEFT/UPI
A92: 46213 | B92: V-0082 | C92: Receipt | D92: Mehta Constructions | F92: UPI | G92: 12900 | H92: NEFT/UPI
A93: 46213 | B93: V-0083 | C93: Receipt | D93: FMCG Distributors | F93: Bank | G93: 12600 | H93: NEFT/UPI
A94: 46213 | B94: V-0084 | C94: Payment | D94: Agro Foods Pvt Ltd | F94: Bank | G94: 1000 | H94: RTGS
A95: 46213 | B95: V-0085 | C95: Payment | D95: Bharat Electric Co | F95: Bank | G95: 56000 | H95: RTGS
A96: 46213 | B96: V-0086 | C96: Payment | D96: FMCG Distributors | F96: Bank | G96: 38000 | H96: RTGS
A97: 46213 | B97: V-0087 | C97: Payment | D97: National Hardware Supply | F97: Bank | G97: 102000 | H97: RTGS
A98: 46228 | B98: V-0088 | C98: Receipt | D98: Sharma Kirana Store | F98: UPI | G98: 11600 | H98: NEFT/UPI
A99: 46228 | B99: V-0089 | C99: Receipt | D99: Gupta Electricals | F99: UPI | G99: 13400 | H99: NEFT/UPI
A100: 46228 | B100: V-0090 | C100: Receipt | D100: Delhi Hardware Mart | F100: Bank | G100: 11400 | H100: NEFT/UPI
... A106: 46228 | B106: V-0096 | C106: Payment | D106: National Hardware Supply | F106: Bank | G106: 13000 | H106: RTGS
A107: 46229 | B107: V-0097 | C107: Transfer Out | F107: Cash | G107: 103000 | H107: Cash deposited to Bank
A108: 46229 | B108: V-0097 | C108: Transfer In | F108: Bank | G108: 103000 | H108: Cash deposited to Bank
A109: 46229 | B109: V-0098 | C109: Transfer Out | F109: UPI | G109: 122000 | H109: UPI deposited to Bank
A110: 46229 | B110: V-0098 | C110: Transfer In | F110: Bank | G110: 122000 | H110: UPI deposited to Bank
A111: 46235 | B111: V-9002 | C111: Other Income | E111: Misc | F111: Bank | G111: 1500 | H111: Scheme incentive
A112: 46239 | B112: V-0099 | C112: Expense | E112: Rent | F112: Bank | G112: 18000
A113: 46239 | B113: V-0100 | C113: Expense | E113: Salary | F113: Bank | G113: 26000
A114: 46239 | B114: V-0101 | C114: Expense | E114: Electricity | F114: UPI | G114: 4688
A115: 46239 | B115: V-0102 | C115: Expense | E115: Transport / Freight | F115: Cash | G115: 7289
A116: 46239 | B116: V-0103 | C116: Expense | E116: Telephone / Internet | F116: UPI | G116: 1199
A117: 46244 | B117: V-0104 | C117: Receipt | D117: Sharma Kirana Store | F117: Bank | G117: 16500 | H117: NEFT/UPI
A118: 46244 | B118: V-0105 | C118: Receipt | D118: Gupta Electricals | F118: UPI | G118: 20000 | H118: NEFT/UPI
...

Sheet Items
A1: 📦 ITEM MASTER & LIVE STOCK | AB1: ◀ Home
A2: One row per product. Stock, cost, value and reorder alerts update automatically from Purchases, Sales and Adjustments.
A3: Blue / cream = type here | L3: ⚙ C engine: {=_xll.ST_ITEMS(…)} fills L:Z
A4: Item Name * | B4: SKU / Barcode | C4: Category | D4: Unit | E4: HSN | F4: GST % | G4: Std Purchase Rate (₹) | H4: Std Sale Rate (₹) | I4: Reorder Level | J4: Opening Qty | K4: Opening Rate (₹) | L4: Purchased Qty | M4: Sold Qty | N4: Adjust Qty | O4: Closing Stock | P4: Avg Cost (₹) | Q4: Stock Value (₹) | R4: Status | S4: Margin % | T4: Suggested Order Qty | U4: Sales Value (₹) | V4: Gross Profit (₹) | W4: Last Sold | X4: Days Since Sale | Y4: Days of Cover | Z4: rank key
A5: Basmati Rice 25kg | B5: 8901001 | C5: Grocery | D5: Bag | E5: 1006 | F5: 0.05 | G5: 1650 | H5: 2106 | I5: 10 | J5: 40 | K5: 1620 | L5: {=_xll.ST_ITEMS(IN_Items,IN_Parties,IN_Purchases,IN_Sales,IN_CashBook,IN_Adjust,IN_Settings)}
A6: Sugar 50kg | B6: 8901002 | C6: Grocery | D6: Bag | E6: 1701 | F6: 0.05 | G6: 2050 | H6: 2462 | I6: 8 | J6: 25 | K6: 2000
A7: Refined Oil 15L | B7: 8901003 | C7: Grocery | D7: Box | E7: 1512 | F7: 0.05 | G7: 1880 | H7: 2290 | I7: 10 | J7: 30 | K7: 1850
A8: Tea Premium 1kg | B8: 8901004 | C8: FMCG | D8: Pack | E8: 0902 | F8: 0.05 | G8: 380 | H8: 508 | I8: 20 | J8: 60 | K8: 375
A9: Detergent 5kg | B9: 8901005 | C9: FMCG | D9: Pack | E9: 3402 | F9: 0.18 | G9: 520 | H9: 691 | I9: 15 | J9: 50 | K9: 510
A10: Toothpaste 150g x12 | B10: 8901006 | C10: FMCG | D10: Box | E10: 3306 | F10: 0.05 | G10: 900 | H10: 1166 | I10: 10 | J10: 25 | K10: 880
A11: LED Bulb 9W | B11: 8901007 | C11: Electrical | D11: Pcs | E11: 8539 | F11: 0.18 | G11: 62 | H11: 107 | I11: 100 | J11: 300 | K11: 60
A12: Copper Wire 90m | B12: 8901008 | C12: Electrical | D12: Pcs | E12: 8544 | F12: 0.18 | G12: 2450 | H12: 3132 | I12: 5 | J12: 12 | K12: 2400
A13: PVC Pipe 1in 6m | B13: 8901009 | C13: Hardware | D13: Pcs | E13: 3917 | F13: 0.18 | G13: 210 | H13: 297 | I13: 40 | J13: 120 | K13: 205
A14: Cement 50kg | B14: 8901010 | C14: Hardware | D14: Bag | E14: 2523 | F14: 0.18 | G14: 340 | H14: 427 | I14: 50 | J14: 200 | K14: 335
A15: A4 Paper Ream | B15: 8901011 | C15: Stationery | D15: Pack | E15: 4802 | F15: 0.12 | G15: 245 | H15: 335 | I15: 30 | J15: 80 | K15: 240
A16: Ceiling Fan 1200mm | B16: 8901012 | C16: Electrical | D16: Pcs | E16: 8414 | F16: 0.18 | G16: 1650 | H16: 2322 | I16: 5 | J16: 4 | K16: 1600

Sheet Parties
A1: 👥 CUSTOMERS & SUPPLIERS (PARTY LEDGER) | U1: ◀ Home
A2: Balance > 0 means the party owes you (receivable); < 0 means you owe them (payable).
A3: Blue / cream = type here | J3: ⚙ C engine: {=_xll.ST_PARTIES(…)} fills J:S
A4: Party Name * | B4: Type | C4: Phone | D4: GSTIN | E4: State | F4: Address | G4: Credit Limit (₹) | H4: Credit Days | I4: Opening Bal (₹) +recv / -pay | J4: Credit Sales (₹) | K4: Received (₹) | L4: Credit Purchases (₹) | M4: Paid (₹) | N4: Balance (₹) | O4: Position | P4: Last Sale | Q4: Last Receipt | R4: Days Unpaid | S4: Alert
A5: Sharma Kirana Store | B5: Customer | C5: 9810000001 | D5: 08AAAPS1111A1Z1 | E5: Rajasthan | F5: Jaipur | G5: 50000 | H5: 15 | I5: 12000 | J5: {=_xll.ST_PARTIES(IN_Items,IN_Parties,IN_Purchases,IN_Sales,IN_CashBook,IN_Adjust,IN_Settings)}
A6: Gupta Electricals | B6: Customer | C6: 9810000002 | D6: 08AAAPG2222B1Z2 | E6: Rajasthan | F6: Ajmer | G6: 80000 | H6: 30 | I6: 0
A7: Delhi Hardware Mart | B7: Customer | C7: 9810000003 | D7: 07AAAPD3333C1Z3 | E7: Delhi | F7: Karol Bagh, Delhi | G7: 100000 | H7: 30 | I7: 0
A8: Walk-in Customer | B8: Customer | E8: Rajasthan | G8: 0 | H8: 0 | I8: 0
A9: Mehta Constructions | B9: Customer | C9: 9810000005 | D9: 08AAAPM5555E1Z5 | E9: Rajasthan | F9: Jodhpur | G9: 60000 | H9: 21 | I9: 8000
A10: Agro Foods Pvt Ltd | B10: Supplier | C10: 9810000006 | D10: 08AABCA6666F1Z6 | E10: Rajasthan | F10: Kota | G10: 0 | H10: 30 | I10: -25000
A11: Bharat Electric Co | B11: Supplier | C11: 9810000007 | D11: 27AABCB7777G1Z7 | E11: Maharashtra | F11: Mumbai | G11: 0 | H11: 45 | I11: 0
A12: National Hardware Supply | B12: Supplier | C12: 9810000008 | D12: 08AABCN8888H1Z8 | E12: Rajasthan | F12: Jaipur | G12: 0 | H12: 30 | I12: 0
A13: FMCG Distributors | B13: Both | C13: 9810000009 | D13: 08AABCF9999J1Z9 | E13: Rajasthan | F13: Jaipur | G13: 40000 | H13: 15 | I13: 0

Sheet Adjustments
A1: 🔧 STOCK ADJUSTMENTS | I1: ◀ Home
A2: Damage, expiry, physical-count corrections, returns. Negative qty reduces stock and is booked as a loss.
A3: Blue / cream = type here | F3: ⚙ C engine: {=_xll.ST_ADJUST(…)} fills F:G
A4: Date * | B4: Item * | C4: Qty (+in / -out) * | D4: Reason * | E4: Notes | F4: Avg Cost (₹) | G4: Value Impact (₹)
A5: 46162 | B5: Refined Oil 15L | C5: -2 | D5: Damage | E5: Leaking tins | F5: {=_xll.ST_ADJUST(IN_Items,IN_Parties,IN_Purchases,IN_Sales,IN_CashBook,IN_Adjust,IN_Settings)}
A6: 46205 | B6: LED Bulb 9W | C6: -6 | D6: Count Correction | E6: Physical count
A7: 46275 | B7: Basmati Rice 25kg | C7: 1 | D7: Sales Return | E7: Returned by Sharma Kirana

Sheet Invoice
A1: =CoName
A2: =CoAddr&" · "&CoPhone
A3: ="GSTIN: "&CoGSTIN&" · State: "&HomeState | M3: ◀ Home
A5: TAX INVOICE / DELIVERY CHALLAN
B7: Invoice No ▶ (type to reprint) | C7: =IF(COUNTA(Sales!$B$5:$B$20004)=0,"",INDEX(Sales!$B$5:$B$20004,COUNTA(Sales!$B$5:$B$20004))) | G7: Bill To | H7: =IFERROR(INDEX(Sales!$C$5:$C$20004,MATCH($C$7,Sales!$B$5:$B$20004,0)),"")
B8: Invoice Date | C8: =IFERROR(INDEX(Sales!$A$5:$A$20004,MATCH($C$7,Sales!$B$5:$B$20004,0)),"") | G8: GSTIN | H8: =IFERROR(INDEX(Parties!$D$5:$D$1004,MATCH($H$7,Parties!$A$5:$A$1004,0))&"","")
B9: Payment | C9: =IFERROR(IF(INDEX(Sales!$H$5:$H$20004,MATCH($C$7,Sales!$B$5:$B$20004,0))="","Credit",INDEX(Sales!$H$5:$H$20004,MATCH($C$7,Sales!$B$5:$B$20004,0))),"") | G9: State | H9: =IFERROR(INDEX(Parties!$E$5:$E$1004,MATCH($H$7,Parties!$A$5:$A$1004,0))&"","")
G10: Address | H10: =IFERROR(INDEX(Parties!$F$5:$F$1004,MATCH($H$7,Parties!$A$5:$A$1004,0))&"","")
A12: # | B12: Item | C12: HSN | D12: Qty | E12: Unit | F12: Rate (₹) | G12: Disc % | H12: Taxable (₹) | I12: GST % | J12: Tax (₹) | K12: Amount (₹)
A13: =IF(IFERROR(INDEX(Sales!$B$5:$B$20004,(MATCH($C$7,Sales!$B$5:$B$20004,0)+0))=$C$7,FALSE),1,"") | B13: =IF($A13="","",INDEX(Sales!$D$5:$D$20004,(MATCH($C$7,Sales!$B$5:$B$20004,0)+0))) | C13: =IF($A13="","",IFERROR(INDEX(Items!$E$5:$E$2004,INDEX(Sales!$U$5:$U$20004,(MATCH($C$7,Sales!$B$5:$B$20004,0)+0)))&"","")) | D13: =IF($A13="","",INDEX(Sales!$E$5:$E$20004,(MATCH($C$7,Sales!$B$5:$B$20004,0)+0))) | E13: =IF($A13="","",INDEX(Sales!$J$5:$J$20004,(MATCH($C$7,Sales!$B$5:$B$20004,0)+0))) | F13: =IF($A13="","",INDEX(Sales!$K$5:$K$20004,(MATCH($C$7,Sales!$B$5:$B$20004,0)+0))) | G13: =IF($A13="","",N(INDEX(Sales!$G$5:$G$20004,(MATCH($C$7,Sales!$B$5:$B$20004,0)+0)))) | H13: =IF($A13="","",INDEX(Sales!$L$5:$L$20004,(MATCH($C$7,Sales!$B$5:$B$20004,0)+0))) | I13: =IF($A13="","",INDEX(Sales!$M$5:$M$20004,(MATCH($C$7,Sales!$B$5:$B$20004,0)+0))) | J13: =IF($A13="","",INDEX(Sales!$N$5:$N$20004,(MATCH($C$7,Sales!$B$5:$B$20004,0)+0))+INDEX(Sales!$O$5:$O$20004,(MATCH($C$7,Sales!$B$5:$B$20004,0)+0))+INDEX(Sales!$P$5:$P$20004,(MATCH($C$7,Sales!$B$5:$B$20004,0)+0))) | K13: =IF($A13="","",INDEX(Sales!$Q$5:$Q$20004,(MATCH($C$7,Sales!$B$5:$B$20004,0)+0)))
A14: =IF(IFERROR(INDEX(Sales!$B$5:$B$20004,(MATCH($C$7,Sales!$B$5:$B$20004,0)+1))=$C$7,FALSE),2,"") | B14: =IF($A14="","",INDEX(Sales!$D$5:$D$20004,(MATCH($C$7,Sales!$B$5:$B$20004,0)+1))) | C14: =IF($A14="","",IFERROR(INDEX(Items!$E$5:$E$2004,INDEX(Sales!$U$5:$U$20004,(MATCH($C$7,Sales!$B$5:$B$20004,0)+1)))&"","")) | D14: =IF($A14="","",INDEX(Sales!$E$5:$E$20004,(MATCH($C$7,Sales!$B$5:$B$20004,0)+1))) | E14: =IF($A14="","",INDEX(Sales!$J$5:$J$20004,(MATCH($C$7,Sales!$B$5:$B$20004,0)+1))) | F14: =IF($A14="","",INDEX(Sales!$K$5:$K$20004,(MATCH($C$7,Sales!$B$5:$B$20004,0)+1))) | G14: =IF($A14="","",N(INDEX(Sales!$G$5:$G$20004,(MATCH($C$7,Sales!$B$5:$B$20004,0)+1)))) | H14: =IF($A14="","",INDEX(Sales!$L$5:$L$20004,(MATCH($C$7,Sales!$B$5:$B$20004,0)+1))) | I14: =IF($A14="","",INDEX(Sales!$M$5:$M$20004,(MATCH($C$7,Sales!$B$5:$B$20004,0)+1))) | J14: =IF($A14="","",INDEX(Sales!$N$5:$N$20004,(MATCH($C$7,Sales!$B$5:$B$20004,0)+1))+INDEX(Sales!$O$5:$O$20004,(MATCH($C$7,Sales!$B$5:$B$20004,0)+1))+INDEX(Sales!$P$5:$P$20004,(MATCH($C$7,Sales!$B$5:$B$20004,0)+1))) | K14: =IF($A14="","",INDEX(Sales!$Q$5:$Q$20004,(MATCH($C$7,Sales!$B$5:$B$20004,0)+1)))
A15: =IF(IFERROR(INDEX(Sales!$B$5:$B$20004,(MATCH($C$7,Sales!$B$5:$B$20004,0)+2))=$C$7,FALSE),3,"") | B15: =IF($A15="","",INDEX(Sales!$D$5:$D$20004,(MATCH($C$7,Sales!$B$5:$B$20004,0)+2))) | C15: =IF($A15="","",IFERROR(INDEX(Items!$E$5:$E$2004,INDEX(Sales!$U$5:$U$20004,(MATCH($C$7,Sales!$B$5:$B$20004,0)+2)))&"","")) | D15: =IF($A15="","",INDEX(Sales!$E$5:$E$20004,(MATCH($C$7,Sales!$B$5:$B$20004,0)+2))) | E15: =IF($A15="","",INDEX(Sales!$J$5:$J$20004,(MATCH($C$7,Sales!$B$5:$B$20004,0)+2))) | F15: =IF($A15="","",INDEX(Sales!$K$5:$K$20004,(MATCH($C$7,Sales!$B$5:$B$20004,0)+2))) | G15: =IF($A15="","",N(INDEX(Sales!$G$5:$G$20004,(MATCH($C$7,Sales!$B$5:$B$20004,0)+2)))) | H15: =IF($A15="","",INDEX(Sales!$L$5:$L$20004,(MATCH($C$7,Sales!$B$5:$B$20004,0)+2))) | I15: =IF($A15="","",INDEX(Sales!$M$5:$M$20004,(MATCH($C$7,Sales!$B$5:$B$20004,0)+2))) | J15: =IF($A15="","",INDEX(Sales!$N$5:$N$20004,(MATCH($C$7,Sales!$B$5:$B$20004,0)+2))+INDEX(Sales!$O$5:$O$20004,(MATCH($C$7,Sales!$B$5:$B$20004,0)+2))+INDEX(Sales!$P$5:$P$20004,(MATCH($C$7,Sales!$B$5:$B$20004,0)+2))) | K15: =IF($A15="","",INDEX(Sales!$Q$5:$Q$20004,(MATCH($C$7,Sales!$B$5:$B$20004,0)+2)))
A16: =IF(IFERROR(INDEX(Sales!$B$5:$B$20004,(MATCH($C$7,Sales!$B$5:$B$20004,0)+3))=$C$7,FALSE),4,"") | B16: =IF($A16="","",INDEX(Sales!$D$5:$D$20004,(MATCH($C$7,Sales!$B$5:$B$20004,0)+3))) | C16: =IF($A16="","",IFERROR(INDEX(Items!$E$5:$E$2004,INDEX(Sales!$U$5:$U$20004,(MATCH($C$7,Sales!$B$5:$B$20004,0)+3)))&"","")) | D16: =IF($A16="","",INDEX(Sales!$E$5:$E$20004,(MATCH($C$7,Sales!$B$5:$B$20004,0)+3))) | E16: =IF($A16="","",INDEX(Sales!$J$5:$J$20004,(MATCH($C$7,Sales!$B$5:$B$20004,0)+3))) | F16: =IF($A16="","",INDEX(Sales!$K$5:$K$20004,(MATCH($C$7,Sales!$B$5:$B$20004,0)+3))) | G16: =IF($A16="","",N(INDEX(Sales!$G$5:$G$20004,(MATCH($C$7,Sales!$B$5:$B$20004,0)+3)))) | H16: =IF($A16="","",INDEX(Sales!$L$5:$L$20004,(MATCH($C$7,Sales!$B$5:$B$20004,0)+3))) | I16: =IF($A16="","",INDEX(Sales!$M$5:$M$20004,(MATCH($C$7,Sales!$B$5:$B$20004,0)+3))) | J16: =IF($A16="","",INDEX(Sales!$N$5:$N$20004,(MATCH($C$7,Sales!$B$5:$B$20004,0)+3))+INDEX(Sales!$O$5:$O$20004,(MATCH($C$7,Sales!$B$5:$B$20004,0)+3))+INDEX(Sales!$P$5:$P$20004,(MATCH($C$7,Sales!$B$5:$B$20004,0)+3))) | K16: =IF($A16="","",INDEX(Sales!$Q$5:$Q$20004,(MATCH($C$7,Sales!$B$5:$B$20004,0)+3)))
A17: =IF(IFERROR(INDEX(Sales!$B$5:$B$20004,(MATCH($C$7,Sales!$B$5:$B$20004,0)+4))=$C$7,FALSE),5,"") | B17: =IF($A17="","",INDEX(Sales!$D$5:$D$20004,(MATCH($C$7,Sales!$B$5:$B$20004,0)+4))) | C17: =IF($A17="","",IFERROR(INDEX(Items!$E$5:$E$2004,INDEX(Sales!$U$5:$U$20004,(MATCH($C$7,Sales!$B$5:$B$20004,0)+4)))&"","")) | D17: =IF($A17="","",INDEX(Sales!$E$5:$E$20004,(MATCH($C$7,Sales!$B$5:$B$20004,0)+4))) | E17: =IF($A17="","",INDEX(Sales!$J$5:$J$20004,(MATCH($C$7,Sales!$B$5:$B$20004,0)+4))) | F17: =IF($A17="","",INDEX(Sales!$K$5:$K$20004,(MATCH($C$7,Sales!$B$5:$B$20004,0)+4))) | G17: =IF($A17="","",N(INDEX(Sales!$G$5:$G$20004,(MATCH($C$7,Sales!$B$5:$B$20004,0)+4)))) | H17: =IF($A17="","",INDEX(Sales!$L$5:$L$20004,(MATCH($C$7,Sales!$B$5:$B$20004,0)+4))) | I17: =IF($A17="","",INDEX(Sales!$M$5:$M$20004,(MATCH($C$7,Sales!$B$5:$B$20004,0)+4))) | J17: =IF($A17="","",INDEX(Sales!$N$5:$N$20004,(MATCH($C$7,Sales!$B$5:$B$20004,0)+4))+INDEX(Sales!$O$5:$O$20004,(MATCH($C$7,Sales!$B$5:$B$20004,0)+4))+INDEX(Sales!$P$5:$P$20004,(MATCH($C$7,Sales!$B$5:$B$20004,0)+4))) | K17: =IF($A17="","",INDEX(Sales!$Q$5:$Q$20004,(MATCH($C$7,Sales!$B$5:$B$20004,0)+4)))
A18: =IF(IFERROR(INDEX(Sales!$B$5:$B$20004,(MATCH($C$7,Sales!$B$5:$B$20004,0)+5))=$C$7,FALSE),6,"") | B18: =IF($A18="","",INDEX(Sales!$D$5:$D$20004,(MATCH($C$7,Sales!$B$5:$B$20004,0)+5))) | C18: =IF($A18="","",IFERROR(INDEX(Items!$E$5:$E$2004,INDEX(Sales!$U$5:$U$20004,(MATCH($C$7,Sales!$B$5:$B$20004,0)+5)))&"","")) | D18: =IF($A18="","",INDEX(Sales!$E$5:$E$20004,(MATCH($C$7,Sales!$B$5:$B$20004,0)+5))) | E18: =IF($A18="","",INDEX(Sales!$J$5:$J$20004,(MATCH($C$7,Sales!$B$5:$B$20004,0)+5))) | F18: =IF($A18="","",INDEX(Sales!$K$5:$K$20004,(MATCH($C$7,Sales!$B$5:$B$20004,0)+5))) | G18: =IF($A18="","",N(INDEX(Sales!$G$5:$G$20004,(MATCH($C$7,Sales!$B$5:$B$20004,0)+5)))) | H18: =IF($A18="","",INDEX(Sales!$L$5:$L$20004,(MATCH($C$7,Sales!$B$5:$B$20004,0)+5))) | I18: =IF($A18="","",INDEX(Sales!$M$5:$M$20004,(MATCH($C$7,Sales!$B$5:$B$20004,0)+5))) | J18: =IF($A18="","",INDEX(Sales!$N$5:$N$20004,(MATCH($C$7,Sales!$B$5:$B$20004,0)+5))+INDEX(Sales!$O$5:$O$20004,(MATCH($C$7,Sales!$B$5:$B$20004,0)+5))+INDEX(Sales!$P$5:$P$20004,(MATCH($C$7,Sales!$B$5:$B$20004,0)+5))) | K18: =IF($A18="","",INDEX(Sales!$Q$5:$Q$20004,(MATCH($C$7,Sales!$B$5:$B$20004,0)+5)))
A19: =IF(IFERROR(INDEX(Sales!$B$5:$B$20004,(MATCH($C$7,Sales!$B$5:$B$20004,0)+6))=$C$7,FALSE),7,"") | B19: =IF($A19="","",INDEX(Sales!$D$5:$D$20004,(MATCH($C$7,Sales!$B$5:$B$20004,0)+6))) | C19: =IF($A19="","",IFERROR(INDEX(Items!$E$5:$E$2004,INDEX(Sales!$U$5:$U$20004,(MATCH($C$7,Sales!$B$5:$B$20004,0)+6)))&"","")) | D19: =IF($A19="","",INDEX(Sales!$E$5:$E$20004,(MATCH($C$7,Sales!$B$5:$B$20004,0)+6))) | E19: =IF($A19="","",INDEX(Sales!$J$5:$J$20004,(MATCH($C$7,Sales!$B$5:$B$20004,0)+6))) | F19: =IF($A19="","",INDEX(Sales!$K$5:$K$20004,(MATCH($C$7,Sales!$B$5:$B$20004,0)+6))) | G19: =IF($A19="","",N(INDEX(Sales!$G$5:$G$20004,(MATCH($C$7,Sales!$B$5:$B$20004,0)+6)))) | H19: =IF($A19="","",INDEX(Sales!$L$5:$L$20004,(MATCH($C$7,Sales!$B$5:$B$20004,0)+6))) | I19: =IF($A19="","",INDEX(Sales!$M$5:$M$20004,(MATCH($C$7,Sales!$B$5:$B$20004,0)+6))) | J19: =IF($A19="","",INDEX(Sales!$N$5:$N$20004,(MATCH($C$7,Sales!$B$5:$B$20004,0)+6))+INDEX(Sales!$O$5:$O$20004,(MATCH($C$7,Sales!$B$5:$B$20004,0)+6))+INDEX(Sales!$P$5:$P$20004,(MATCH($C$7,Sales!$B$5:$B$20004,0)+6))) | K19: =IF($A19="","",INDEX(Sales!$Q$5:$Q$20004,(MATCH($C$7,Sales!$B$5:$B$20004,0)+6)))
A20: =IF(IFERROR(INDEX(Sales!$B$5:$B$20004,(MATCH($C$7,Sales!$B$5:$B$20004,0)+7))=$C$7,FALSE),8,"") | B20: =IF($A20="","",INDEX(Sales!$D$5:$D$20004,(MATCH($C$7,Sales!$B$5:$B$20004,0)+7))) | C20: =IF($A20="","",IFERROR(INDEX(Items!$E$5:$E$2004,INDEX(Sales!$U$5:$U$20004,(MATCH($C$7,Sales!$B$5:$B$20004,0)+7)))&"","")) | D20: =IF($A20="","",INDEX(Sales!$E$5:$E$20004,(MATCH($C$7,Sales!$B$5:$B$20004,0)+7))) | E20: =IF($A20="","",INDEX(Sales!$J$5:$J$20004,(MATCH($C$7,Sales!$B$5:$B$20004,0)+7))) | F20: =IF($A20="","",INDEX(Sales!$K$5:$K$20004,(MATCH($C$7,Sales!$B$5:$B$20004,0)+7))) | G20: =IF($A20="","",N(INDEX(Sales!$G$5:$G$20004,(MATCH($C$7,Sales!$B$5:$B$20004,0)+7)))) | H20: =IF($A20="","",INDEX(Sales!$L$5:$L$20004,(MATCH($C$7,Sales!$B$5:$B$20004,0)+7))) | I20: =IF($A20="","",INDEX(Sales!$M$5:$M$20004,(MATCH($C$7,Sales!$B$5:$B$20004,0)+7))) | J20: =IF($A20="","",INDEX(Sales!$N$5:$N$20004,(MATCH($C$7,Sales!$B$5:$B$20004,0)+7))+INDEX(Sales!$O$5:$O$20004,(MATCH($C$7,Sales!$B$5:$B$20004,0)+7))+INDEX(Sales!$P$5:$P$20004,(MATCH($C$7,Sales!$B$5:$B$20004,0)+7))) | K20: =IF($A20="","",INDEX(Sales!$Q$5:$Q$20004,(MATCH($C$7,Sales!$B$5:$B$20004,0)+7)))
A21: =IF(IFERROR(INDEX(Sales!$B$5:$B$20004,(MATCH($C$7,Sales!$B$5:$B$20004,0)+8))=$C$7,FALSE),9,"") | B21: =IF($A21="","",INDEX(Sales!$D$5:$D$20004,(MATCH($C$7,Sales!$B$5:$B$20004,0)+8))) | C21: =IF($A21="","",IFERROR(INDEX(Items!$E$5:$E$2004,INDEX(Sales!$U$5:$U$20004,(MATCH($C$7,Sales!$B$5:$B$20004,0)+8)))&"","")) | D21: =IF($A21="","",INDEX(Sales!$E$5:$E$20004,(MATCH($C$7,Sales!$B$5:$B$20004,0)+8))) | E21: =IF($A21="","",INDEX(Sales!$J$5:$J$20004,(MATCH($C$7,Sales!$B$5:$B$20004,0)+8))) | F21: =IF($A21="","",INDEX(Sales!$K$5:$K$20004,(MATCH($C$7,Sales!$B$5:$B$20004,0)+8))) | G21: =IF($A21="","",N(INDEX(Sales!$G$5:$G$20004,(MATCH($C$7,Sales!$B$5:$B$20004,0)+8)))) | H21: =IF($A21="","",INDEX(Sales!$L$5:$L$20004,(MATCH($C$7,Sales!$B$5:$B$20004,0)+8))) | I21: =IF($A21="","",INDEX(Sales!$M$5:$M$20004,(MATCH($C$7,Sales!$B$5:$B$20004,0)+8))) | J21: =IF($A21="","",INDEX(Sales!$N$5:$N$20004,(MATCH($C$7,Sales!$B$5:$B$20004,0)+8))+INDEX(Sales!$O$5:$O$20004,(MATCH($C$7,Sales!$B$5:$B$20004,0)+8))+INDEX(Sales!$P$5:$P$20004,(MATCH($C$7,Sales!$B$5:$B$20004,0)+8))) | K21: =IF($A21="","",INDEX(Sales!$Q$5:$Q$20004,(MATCH($C$7,Sales!$B$5:$B$20004,0)+8)))
A22: =IF(IFERROR(INDEX(Sales!$B$5:$B$20004,(MATCH($C$7,Sales!$B$5:$B$20004,0)+9))=$C$7,FALSE),10,"") | B22: =IF($A22="","",INDEX(Sales!$D$5:$D$20004,(MATCH($C$7,Sales!$B$5:$B$20004,0)+9))) | C22: =IF($A22="","",IFERROR(INDEX(Items!$E$5:$E$2004,INDEX(Sales!$U$5:$U$20004,(MATCH($C$7,Sales!$B$5:$B$20004,0)+9)))&"","")) | D22: =IF($A22="","",INDEX(Sales!$E$5:$E$20004,(MATCH($C$7,Sales!$B$5:$B$20004,0)+9))) | E22: =IF($A22="","",INDEX(Sales!$J$5:$J$20004,(MATCH($C$7,Sales!$B$5:$B$20004,0)+9))) | F22: =IF($A22="","",INDEX(Sales!$K$5:$K$20004,(MATCH($C$7,Sales!$B$5:$B$20004,0)+9))) | G22: =IF($A22="","",N(INDEX(Sales!$G$5:$G$20004,(MATCH($C$7,Sales!$B$5:$B$20004,0)+9)))) | H22: =IF($A22="","",INDEX(Sales!$L$5:$L$20004,(MATCH($C$7,Sales!$B$5:$B$20004,0)+9))) | I22: =IF($A22="","",INDEX(Sales!$M$5:$M$20004,(MATCH($C$7,Sales!$B$5:$B$20004,0)+9))) | J22: =IF($A22="","",INDEX(Sales!$N$5:$N$20004,(MATCH($C$7,Sales!$B$5:$B$20004,0)+9))+INDEX(Sales!$O$5:$O$20004,(MATCH($C$7,Sales!$B$5:$B$20004,0)+9))+INDEX(Sales!$P$5:$P$20004,(MATCH($C$7,Sales!$B$5:$B$20004,0)+9))) | K22: =IF($A22="","",INDEX(Sales!$Q$5:$Q$20004,(MATCH($C$7,Sales!$B$5:$B$20004,0)+9)))
A23: =IF(IFERROR(INDEX(Sales!$B$5:$B$20004,(MATCH($C$7,Sales!$B$5:$B$20004,0)+10))=$C$7,FALSE),11,"") | B23: =IF($A23="","",INDEX(Sales!$D$5:$D$20004,(MATCH($C$7,Sales!$B$5:$B$20004,0)+10))) | C23: =IF($A23="","",IFERROR(INDEX(Items!$E$5:$E$2004,INDEX(Sales!$U$5:$U$20004,(MATCH($C$7,Sales!$B$5:$B$20004,0)+10)))&"","")) | D23: =IF($A23="","",INDEX(Sales!$E$5:$E$20004,(MATCH($C$7,Sales!$B$5:$B$20004,0)+10))) | E23: =IF($A23="","",INDEX(Sales!$J$5:$J$20004,(MATCH($C$7,Sales!$B$5:$B$20004,0)+10))) | F23: =IF($A23="","",INDEX(Sales!$K$5:$K$20004,(MATCH($C$7,Sales!$B$5:$B$20004,0)+10))) | G23: =IF($A23="","",N(INDEX(Sales!$G$5:$G$20004,(MATCH($C$7,Sales!$B$5:$B$20004,0)+10)))) | H23: =IF($A23="","",INDEX(Sales!$L$5:$L$20004,(MATCH($C$7,Sales!$B$5:$B$20004,0)+10))) | I23: =IF($A23="","",INDEX(Sales!$M$5:$M$20004,(MATCH($C$7,Sales!$B$5:$B$20004,0)+10))) | J23: =IF($A23="","",INDEX(Sales!$N$5:$N$20004,(MATCH($C$7,Sales!$B$5:$B$20004,0)+10))+INDEX(Sales!$O$5:$O$20004,(MATCH($C$7,Sales!$B$5:$B$20004,0)+10))+INDEX(Sales!$P$5:$P$20004,(MATCH($C$7,Sales!$B$5:$B$20004,0)+10))) | K23: =IF($A23="","",INDEX(Sales!$Q$5:$Q$20004,(MATCH($C$7,Sales!$B$5:$B$20004,0)+10)))
A24: =IF(IFERROR(INDEX(Sales!$B$5:$B$20004,(MATCH($C$7,Sales!$B$5:$B$20004,0)+11))=$C$7,FALSE),12,"") | B24: =IF($A24="","",INDEX(Sales!$D$5:$D$20004,(MATCH($C$7,Sales!$B$5:$B$20004,0)+11))) | C24: =IF($A24="","",IFERROR(INDEX(Items!$E$5:$E$2004,INDEX(Sales!$U$5:$U$20004,(MATCH($C$7,Sales!$B$5:$B$20004,0)+11)))&"","")) | D24: =IF($A24="","",INDEX(Sales!$E$5:$E$20004,(MATCH($C$7,Sales!$B$5:$B$20004,0)+11))) | E24: =IF($A24="","",INDEX(Sales!$J$5:$J$20004,(MATCH($C$7,Sales!$B$5:$B$20004,0)+11))) | F24: =IF($A24="","",INDEX(Sales!$K$5:$K$20004,(MATCH($C$7,Sales!$B$5:$B$20004,0)+11))) | G24: =IF($A24="","",N(INDEX(Sales!$G$5:$G$20004,(MATCH($C$7,Sales!$B$5:$B$20004,0)+11)))) | H24: =IF($A24="","",INDEX(Sales!$L$5:$L$20004,(MATCH($C$7,Sales!$B$5:$B$20004,0)+11))) | I24: =IF($A24="","",INDEX(Sales!$M$5:$M$20004,(MATCH($C$7,Sales!$B$5:$B$20004,0)+11))) | J24: =IF($A24="","",INDEX(Sales!$N$5:$N$20004,(MATCH($C$7,Sales!$B$5:$B$20004,0)+11))+INDEX(Sales!$O$5:$O$20004,(MATCH($C$7,Sales!$B$5:$B$20004,0)+11))+INDEX(Sales!$P$5:$P$20004,(MATCH($C$7,Sales!$B$5:$B$20004,0)+11))) | K24: =IF($A24="","",INDEX(Sales!$Q$5:$Q$20004,(MATCH($C$7,Sales!$B$5:$B$20004,0)+11)))
A25: =IF(IFERROR(INDEX(Sales!$B$5:$B$20004,(MATCH($C$7,Sales!$B$5:$B$20004,0)+12))=$C$7,FALSE),13,"") | B25: =IF($A25="","",INDEX(Sales!$D$5:$D$20004,(MATCH($C$7,Sales!$B$5:$B$20004,0)+12))) | C25: =IF($A25="","",IFERROR(INDEX(Items!$E$5:$E$2004,INDEX(Sales!$U$5:$U$20004,(MATCH($C$7,Sales!$B$5:$B$20004,0)+12)))&"","")) | D25: =IF($A25="","",INDEX(Sales!$E$5:$E$20004,(MATCH($C$7,Sales!$B$5:$B$20004,0)+12))) | E25: =IF($A25="","",INDEX(Sales!$J$5:$J$20004,(MATCH($C$7,Sales!$B$5:$B$20004,0)+12))) | F25: =IF($A25="","",INDEX(Sales!$K$5:$K$20004,(MATCH($C$7,Sales!$B$5:$B$20004,0)+12))) | G25: =IF($A25="","",N(INDEX(Sales!$G$5:$G$20004,(MATCH($C$7,Sales!$B$5:$B$20004,0)+12)))) | H25: =IF($A25="","",INDEX(Sales!$L$5:$L$20004,(MATCH($C$7,Sales!$B$5:$B$20004,0)+12))) | I25: =IF($A25="","",INDEX(Sales!$M$5:$M$20004,(MATCH($C$7,Sales!$B$5:$B$20004,0)+12))) | J25: =IF($A25="","",INDEX(Sales!$N$5:$N$20004,(MATCH($C$7,Sales!$B$5:$B$20004,0)+12))+INDEX(Sales!$O$5:$O$20004,(MATCH($C$7,Sales!$B$5:$B$20004,0)+12))+INDEX(Sales!$P$5:$P$20004,(MATCH($C$7,Sales!$B$5:$B$20004,0)+12))) | K25: =IF($A25="","",INDEX(Sales!$Q$5:$Q$20004,(MATCH($C$7,Sales!$B$5:$B$20004,0)+12)))
A26: =IF(IFERROR(INDEX(Sales!$B$5:$B$20004,(MATCH($C$7,Sales!$B$5:$B$20004,0)+13))=$C$7,FALSE),14,"") | B26: =IF($A26="","",INDEX(Sales!$D$5:$D$20004,(MATCH($C$7,Sales!$B$5:$B$20004,0)+13))) | C26: =IF($A26="","",IFERROR(INDEX(Items!$E$5:$E$2004,INDEX(Sales!$U$5:$U$20004,(MATCH($C$7,Sales!$B$5:$B$20004,0)+13)))&"","")) | D26: =IF($A26="","",INDEX(Sales!$E$5:$E$20004,(MATCH($C$7,Sales!$B$5:$B$20004,0)+13))) | E26: =IF($A26="","",INDEX(Sales!$J$5:$J$20004,(MATCH($C$7,Sales!$B$5:$B$20004,0)+13))) | F26: =IF($A26="","",INDEX(Sales!$K$5:$K$20004,(MATCH($C$7,Sales!$B$5:$B$20004,0)+13))) | G26: =IF($A26="","",N(INDEX(Sales!$G$5:$G$20004,(MATCH($C$7,Sales!$B$5:$B$20004,0)+13)))) | H26: =IF($A26="","",INDEX(Sales!$L$5:$L$20004,(MATCH($C$7,Sales!$B$5:$B$20004,0)+13))) | I26: =IF($A26="","",INDEX(Sales!$M$5:$M$20004,(MATCH($C$7,Sales!$B$5:$B$20004,0)+13))) | J26: =IF($A26="","",INDEX(Sales!$N$5:$N$20004,(MATCH($C$7,Sales!$B$5:$B$20004,0)+13))+INDEX(Sales!$O$5:$O$20004,(MATCH($C$7,Sales!$B$5:$B$20004,0)+13))+INDEX(Sales!$P$5:$P$20004,(MATCH($C$7,Sales!$B$5:$B$20004,0)+13))) | K26: =IF($A26="","",INDEX(Sales!$Q$5:$Q$20004,(MATCH($C$7,Sales!$B$5:$B$20004,0)+13)))
A27: =IF(IFERROR(INDEX(Sales!$B$5:$B$20004,(MATCH($C$7,Sales!$B$5:$B$20004,0)+14))=$C$7,FALSE),15,"") | B27: =IF($A27="","",INDEX(Sales!$D$5:$D$20004,(MATCH($C$7,Sales!$B$5:$B$20004,0)+14))) | C27: =IF($A27="","",IFERROR(INDEX(Items!$E$5:$E$2004,INDEX(Sales!$U$5:$U$20004,(MATCH($C$7,Sales!$B$5:$B$20004,0)+14)))&"","")) | D27: =IF($A27="","",INDEX(Sales!$E$5:$E$20004,(MATCH($C$7,Sales!$B$5:$B$20004,0)+14))) | E27: =IF($A27="","",INDEX(Sales!$J$5:$J$20004,(MATCH($C$7,Sales!$B$5:$B$20004,0)+14))) | F27: =IF($A27="","",INDEX(Sales!$K$5:$K$20004,(MATCH($C$7,Sales!$B$5:$B$20004,0)+14))) | G27: =IF($A27="","",N(INDEX(Sales!$G$5:$G$20004,(MATCH($C$7,Sales!$B$5:$B$20004,0)+14)))) | H27: =IF($A27="","",INDEX(Sales!$L$5:$L$20004,(MATCH($C$7,Sales!$B$5:$B$20004,0)+14))) | I27: =IF($A27="","",INDEX(Sales!$M$5:$M$20004,(MATCH($C$7,Sales!$B$5:$B$20004,0)+14))) | J27: =IF($A27="","",INDEX(Sales!$N$5:$N$20004,(MATCH($C$7,Sales!$B$5:$B$20004,0)+14))+INDEX(Sales!$O$5:$O$20004,(MATCH($C$7,Sales!$B$5:$B$20004,0)+14))+INDEX(Sales!$P$5:$P$20004,(MATCH($C$7,Sales!$B$5:$B$20004,0)+14))) | K27: =IF($A27="","",INDEX(Sales!$Q$5:$Q$20004,(MATCH($C$7,Sales!$B$5:$B$20004,0)+14)))
A28: =IF(IFERROR(INDEX(Sales!$B$5:$B$20004,(MATCH($C$7,Sales!$B$5:$B$20004,0)+15))=$C$7,FALSE),16,"") | B28: =IF($A28="","",INDEX(Sales!$D$5:$D$20004,(MATCH($C$7,Sales!$B$5:$B$20004,0)+15))) | C28: =IF($A28="","",IFERROR(INDEX(Items!$E$5:$E$2004,INDEX(Sales!$U$5:$U$20004,(MATCH($C$7,Sales!$B$5:$B$20004,0)+15)))&"","")) | D28: =IF($A28="","",INDEX(Sales!$E$5:$E$20004,(MATCH($C$7,Sales!$B$5:$B$20004,0)+15))) | E28: =IF($A28="","",INDEX(Sales!$J$5:$J$20004,(MATCH($C$7,Sales!$B$5:$B$20004,0)+15))) | F28: =IF($A28="","",INDEX(Sales!$K$5:$K$20004,(MATCH($C$7,Sales!$B$5:$B$20004,0)+15))) | G28: =IF($A28="","",N(INDEX(Sales!$G$5:$G$20004,(MATCH($C$7,Sales!$B$5:$B$20004,0)+15)))) | H28: =IF($A28="","",INDEX(Sales!$L$5:$L$20004,(MATCH($C$7,Sales!$B$5:$B$20004,0)+15))) | I28: =IF($A28="","",INDEX(Sales!$M$5:$M$20004,(MATCH($C$7,Sales!$B$5:$B$20004,0)+15))) | J28: =IF($A28="","",INDEX(Sales!$N$5:$N$20004,(MATCH($C$7,Sales!$B$5:$B$20004,0)+15))+INDEX(Sales!$O$5:$O$20004,(MATCH($C$7,Sales!$B$5:$B$20004,0)+15))+INDEX(Sales!$P$5:$P$20004,(MATCH($C$7,Sales!$B$5:$B$20004,0)+15))) | K28: =IF($A28="","",INDEX(Sales!$Q$5:$Q$20004,(MATCH($C$7,Sales!$B$5:$B$20004,0)+15)))
A29: =IF(IFERROR(INDEX(Sales!$B$5:$B$20004,(MATCH($C$7,Sales!$B$5:$B$20004,0)+16))=$C$7,FALSE),17,"") | B29: =IF($A29="","",INDEX(Sales!$D$5:$D$20004,(MATCH($C$7,Sales!$B$5:$B$20004,0)+16))) | C29: =IF($A29="","",IFERROR(INDEX(Items!$E$5:$E$2004,INDEX(Sales!$U$5:$U$20004,(MATCH($C$7,Sales!$B$5:$B$20004,0)+16)))&"","")) | D29: =IF($A29="","",INDEX(Sales!$E$5:$E$20004,(MATCH($C$7,Sales!$B$5:$B$20004,0)+16))) | E29: =IF($A29="","",INDEX(Sales!$J$5:$J$20004,(MATCH($C$7,Sales!$B$5:$B$20004,0)+16))) | F29: =IF($A29="","",INDEX(Sales!$K$5:$K$20004,(MATCH($C$7,Sales!$B$5:$B$20004,0)+16))) | G29: =IF($A29="","",N(INDEX(Sales!$G$5:$G$20004,(MATCH($C$7,Sales!$B$5:$B$20004,0)+16)))) | H29: =IF($A29="","",INDEX(Sales!$L$5:$L$20004,(MATCH($C$7,Sales!$B$5:$B$20004,0)+16))) | I29: =IF($A29="","",INDEX(Sales!$M$5:$M$20004,(MATCH($C$7,Sales!$B$5:$B$20004,0)+16))) | J29: =IF($A29="","",INDEX(Sales!$N$5:$N$20004,(MATCH($C$7,Sales!$B$5:$B$20004,0)+16))+INDEX(Sales!$O$5:$O$20004,(MATCH($C$7,Sales!$B$5:$B$20004,0)+16))+INDEX(Sales!$P$5:$P$20004,(MATCH($C$7,Sales!$B$5:$B$20004,0)+16))) | K29: =IF($A29="","",INDEX(Sales!$Q$5:$Q$20004,(MATCH($C$7,Sales!$B$5:$B$20004,0)+16)))
A30: =IF(IFERROR(INDEX(Sales!$B$5:$B$20004,(MATCH($C$7,Sales!$B$5:$B$20004,0)+17))=$C$7,FALSE),18,"") | B30: =IF($A30="","",INDEX(Sales!$D$5:$D$20004,(MATCH($C$7,Sales!$B$5:$B$20004,0)+17))) | C30: =IF($A30="","",IFERROR(INDEX(Items!$E$5:$E$2004,INDEX(Sales!$U$5:$U$20004,(MATCH($C$7,Sales!$B$5:$B$20004,0)+17)))&"","")) | D30: =IF($A30="","",INDEX(Sales!$E$5:$E$20004,(MATCH($C$7,Sales!$B$5:$B$20004,0)+17))) | E30: =IF($A30="","",INDEX(Sales!$J$5:$J$20004,(MATCH($C$7,Sales!$B$5:$B$20004,0)+17))) | F30: =IF($A30="","",INDEX(Sales!$K$5:$K$20004,(MATCH($C$7,Sales!$B$5:$B$20004,0)+17))) | G30: =IF($A30="","",N(INDEX(Sales!$G$5:$G$20004,(MATCH($C$7,Sales!$B$5:$B$20004,0)+17)))) | H30: =IF($A30="","",INDEX(Sales!$L$5:$L$20004,(MATCH($C$7,Sales!$B$5:$B$20004,0)+17))) | I30: =IF($A30="","",INDEX(Sales!$M$5:$M$20004,(MATCH($C$7,Sales!$B$5:$B$20004,0)+17))) | J30: =IF($A30="","",INDEX(Sales!$N$5:$N$20004,(MATCH($C$7,Sales!$B$5:$B$20004,0)+17))+INDEX(Sales!$O$5:$O$20004,(MATCH($C$7,Sales!$B$5:$B$20004,0)+17))+INDEX(Sales!$P$5:$P$20004,(MATCH($C$7,Sales!$B$5:$B$20004,0)+17))) | K30: =IF($A30="","",INDEX(Sales!$Q$5:$Q$20004,(MATCH($C$7,Sales!$B$5:$B$20004,0)+17)))
A31: =IF(IFERROR(INDEX(Sales!$B$5:$B$20004,(MATCH($C$7,Sales!$B$5:$B$20004,0)+18))=$C$7,FALSE),19,"") | B31: =IF($A31="","",INDEX(Sales!$D$5:$D$20004,(MATCH($C$7,Sales!$B$5:$B$20004,0)+18))) | C31: =IF($A31="","",IFERROR(INDEX(Items!$E$5:$E$2004,INDEX(Sales!$U$5:$U$20004,(MATCH($C$7,Sales!$B$5:$B$20004,0)+18)))&"","")) | D31: =IF($A31="","",INDEX(Sales!$E$5:$E$20004,(MATCH($C$7,Sales!$B$5:$B$20004,0)+18))) | E31: =IF($A31="","",INDEX(Sales!$J$5:$J$20004,(MATCH($C$7,Sales!$B$5:$B$20004,0)+18))) | F31: =IF($A31="","",INDEX(Sales!$K$5:$K$20004,(MATCH($C$7,Sales!$B$5:$B$20004,0)+18))) | G31: =IF($A31="","",N(INDEX(Sales!$G$5:$G$20004,(MATCH($C$7,Sales!$B$5:$B$20004,0)+18)))) | H31: =IF($A31="","",INDEX(Sales!$L$5:$L$20004,(MATCH($C$7,Sales!$B$5:$B$20004,0)+18))) | I31: =IF($A31="","",INDEX(Sales!$M$5:$M$20004,(MATCH($C$7,Sales!$B$5:$B$20004,0)+18))) | J31: =IF($A31="","",INDEX(Sales!$N$5:$N$20004,(MATCH($C$7,Sales!$B$5:$B$20004,0)+18))+INDEX(Sales!$O$5:$O$20004,(MATCH($C$7,Sales!$B$5:$B$20004,0)+18))+INDEX(Sales!$P$5:$P$20004,(MATCH($C$7,Sales!$B$5:$B$20004,0)+18))) | K31: =IF($A31="","",INDEX(Sales!$Q$5:$Q$20004,(MATCH($C$7,Sales!$B$5:$B$20004,0)+18)))
A32: =IF(IFERROR(INDEX(Sales!$B$5:$B$20004,(MATCH($C$7,Sales!$B$5:$B$20004,0)+19))=$C$7,FALSE),20,"") | B32: =IF($A32="","",INDEX(Sales!$D$5:$D$20004,(MATCH($C$7,Sales!$B$5:$B$20004,0)+19))) | C32: =IF($A32="","",IFERROR(INDEX(Items!$E$5:$E$2004,INDEX(Sales!$U$5:$U$20004,(MATCH($C$7,Sales!$B$5:$B$20004,0)+19)))&"","")) | D32: =IF($A32="","",INDEX(Sales!$E$5:$E$20004,(MATCH($C$7,Sales!$B$5:$B$20004,0)+19))) | E32: =IF($A32="","",INDEX(Sales!$J$5:$J$20004,(MATCH($C$7,Sales!$B$5:$B$20004,0)+19))) | F32: =IF($A32="","",INDEX(Sales!$K$5:$K$20004,(MATCH($C$7,Sales!$B$5:$B$20004,0)+19))) | G32: =IF($A32="","",N(INDEX(Sales!$G$5:$G$20004,(MATCH($C$7,Sales!$B$5:$B$20004,0)+19)))) | H32: =IF($A32="","",INDEX(Sales!$L$5:$L$20004,(MATCH($C$7,Sales!$B$5:$B$20004,0)+19))) | I32: =IF($A32="","",INDEX(Sales!$M$5:$M$20004,(MATCH($C$7,Sales!$B$5:$B$20004,0)+19))) | J32: =IF($A32="","",INDEX(Sales!$N$5:$N$20004,(MATCH($C$7,Sales!$B$5:$B$20004,0)+19))+INDEX(Sales!$O$5:$O$20004,(MATCH($C$7,Sales!$B$5:$B$20004,0)+19))+INDEX(Sales!$P$5:$P$20004,(MATCH($C$7,Sales!$B$5:$B$20004,0)+19))) | K32: =IF($A32="","",INDEX(Sales!$Q$5:$Q$20004,(MATCH($C$7,Sales!$B$5:$B$20004,0)+19)))
B34: =IF(COUNTIF(A13:A32,">0")>=20,"⚠ More than 20 lines: split the invoice","") | H34: Taxable Value | K34: =SUMIFS(Sales!$L$5:$L$20004,Sales!$B$5:$B$20004,$C$7)
B35: ="Bank: "&CoBank | H35: CGST | K35: =SUMIFS(Sales!$N$5:$N$20004,Sales!$B$5:$B$20004,$C$7)
B36: Goods once sold will be taken back only as per store policy. | H36: SGST | K36: =SUMIFS(Sales!$O$5:$O$20004,Sales!$B$5:$B$20004,$C$7)
H37: IGST | K37: =SUMIFS(Sales!$P$5:$P$20004,Sales!$B$5:$B$20004,$C$7)
B38: Receiver's Signature | H38: Round Off | K38: =ROUND(SUM(K34:K37),0)-SUM(K34:K37)
H39: INVOICE TOTAL | K39: =SUM(K34:K38)
H41: ="For "&CoName
H43: Authorised Signatory

Sheet Reports
A1: 📊 REPORTS: MONTHLY P&L, GST, EXPENSES | N1: ◀ Home
A2: Financial-year view built from all registers. Nothing to type here.
A4: Month | B4: Sales (₹) | C4: COGS (₹) | D4: Gross Profit (₹) | E4: GP % | F4: Expenses (₹) | G4: Other Income (₹) | H4: Stock Loss/Gain (₹) | I4: Net Profit (₹) | J4: Purchases (₹) | K4: GST Output (₹) | L4: GST Input (₹) | M4: Net GST Payable (₹)
A5: =EDATE(FYStart,0) | B5: =SUMIFS(Sales!$L$5:$L$20004,Sales!$A$5:$A$20004,">="&$A5,Sales!$A$5:$A$20004,"<"&EDATE($A5,1)) | C5: =SUMIFS(Sales!$R$5:$R$20004,Sales!$A$5:$A$20004,">="&$A5,Sales!$A$5:$A$20004,"<"&EDATE($A5,1)) | D5: =B5-C5 | E5: =IF(B5=0,0,D5/B5) | F5: =SUMIFS(CashBook!$G$5:$G$20004,CashBook!$C$5:$C$20004,"Expense",CashBook!$A$5:$A$20004,">="&$A5,CashBook!$A$5:$A$20004,"<"&EDATE($A5,1)) | G5: =SUMIFS(CashBook!$G$5:$G$20004,CashBook!$C$5:$C$20004,"Other Income",CashBook!$A$5:$A$20004,">="&$A5,CashBook!$A$5:$A$20004,"<"&EDATE($A5,1)) | H5: =SUMIFS(Adjustments!$G$5:$G$2004,Adjustments!$A$5:$A$2004,">="&$A5,Adjustments!$A$5:$A$2004,"<"&EDATE($A5,1)) | I5: =D5-F5+G5+H5 | J5: =SUMIFS(Purchases!$K$5:$K$20004,Purchases!$A$5:$A$20004,">="&$A5,Purchases!$A$5:$A$20004,"<"&EDATE($A5,1)) | K5: =SUMIFS(Sales!$N$5:$N$20004,Sales!$A$5:$A$20004,">="&$A5,Sales!$A$5:$A$20004,"<"&EDATE($A5,1))+SUMIFS(Sales!$O$5:$O$20004,Sales!$A$5:$A$20004,">="&$A5,Sales!$A$5:$A$20004,"<"&EDATE($A5,1))+SUMIFS(Sales!$P$5:$P$20004,Sales!$A$5:$A$20004,">="&$A5,Sales!$A$5:$A$20004,"<"&EDATE($A5,1)) | L5: =SUMIFS(Purchases!$M$5:$M$20004,Purchases!$A$5:$A$20004,">="&$A5,Purchases!$A$5:$A$20004,"<"&EDATE($A5,1))+SUMIFS(Purchases!$N$5:$N$20004,Purchases!$A$5:$A$20004,">="&$A5,Purchases!$A$5:$A$20004,"<"&EDATE($A5,1))+SUMIFS(Purchases!$O$5:$O$20004,Purchases!$A$5:$A$20004,">="&$A5,Purchases!$A$5:$A$20004,"<"&EDATE($A5,1)) | M5: =K5-L5
A6: =EDATE(FYStart,1) | B6: =SUMIFS(Sales!$L$5:$L$20004,Sales!$A$5:$A$20004,">="&$A6,Sales!$A$5:$A$20004,"<"&EDATE($A6,1)) | C6: =SUMIFS(Sales!$R$5:$R$20004,Sales!$A$5:$A$20004,">="&$A6,Sales!$A$5:$A$20004,"<"&EDATE($A6,1)) | D6: =B6-C6 | E6: =IF(B6=0,0,D6/B6) | F6: =SUMIFS(CashBook!$G$5:$G$20004,CashBook!$C$5:$C$20004,"Expense",CashBook!$A$5:$A$20004,">="&$A6,CashBook!$A$5:$A$20004,"<"&EDATE($A6,1)) | G6: =SUMIFS(CashBook!$G$5:$G$20004,CashBook!$C$5:$C$20004,"Other Income",CashBook!$A$5:$A$20004,">="&$A6,CashBook!$A$5:$A$20004,"<"&EDATE($A6,1)) | H6: =SUMIFS(Adjustments!$G$5:$G$2004,Adjustments!$A$5:$A$2004,">="&$A6,Adjustments!$A$5:$A$2004,"<"&EDATE($A6,1)) | I6: =D6-F6+G6+H6 | J6: =SUMIFS(Purchases!$K$5:$K$20004,Purchases!$A$5:$A$20004,">="&$A6,Purchases!$A$5:$A$20004,"<"&EDATE($A6,1)) | K6: =SUMIFS(Sales!$N$5:$N$20004,Sales!$A$5:$A$20004,">="&$A6,Sales!$A$5:$A$20004,"<"&EDATE($A6,1))+SUMIFS(Sales!$O$5:$O$20004,Sales!$A$5:$A$20004,">="&$A6,Sales!$A$5:$A$20004,"<"&EDATE($A6,1))+SUMIFS(Sales!$P$5:$P$20004,Sales!$A$5:$A$20004,">="&$A6,Sales!$A$5:$A$20004,"<"&EDATE($A6,1)) | L6: =SUMIFS(Purchases!$M$5:$M$20004,Purchases!$A$5:$A$20004,">="&$A6,Purchases!$A$5:$A$20004,"<"&EDATE($A6,1))+SUMIFS(Purchases!$N$5:$N$20004,Purchases!$A$5:$A$20004,">="&$A6,Purchases!$A$5:$A$20004,"<"&EDATE($A6,1))+SUMIFS(Purchases!$O$5:$O$20004,Purchases!$A$5:$A$20004,">="&$A6,Purchases!$A$5:$A$20004,"<"&EDATE($A6,1)) | M6: =K6-L6
A7: =EDATE(FYStart,2) | B7: =SUMIFS(Sales!$L$5:$L$20004,Sales!$A$5:$A$20004,">="&$A7,Sales!$A$5:$A$20004,"<"&EDATE($A7,1)) | C7: =SUMIFS(Sales!$R$5:$R$20004,Sales!$A$5:$A$20004,">="&$A7,Sales!$A$5:$A$20004,"<"&EDATE($A7,1)) | D7: =B7-C7 | E7: =IF(B7=0,0,D7/B7) | F7: =SUMIFS(CashBook!$G$5:$G$20004,CashBook!$C$5:$C$20004,"Expense",CashBook!$A$5:$A$20004,">="&$A7,CashBook!$A$5:$A$20004,"<"&EDATE($A7,1)) | G7: =SUMIFS(CashBook!$G$5:$G$20004,CashBook!$C$5:$C$20004,"Other Income",CashBook!$A$5:$A$20004,">="&$A7,CashBook!$A$5:$A$20004,"<"&EDATE($A7,1)) | H7: =SUMIFS(Adjustments!$G$5:$G$2004,Adjustments!$A$5:$A$2004,">="&$A7,Adjustments!$A$5:$A$2004,"<"&EDATE($A7,1)) | I7: =D7-F7+G7+H7 | J7: =SUMIFS(Purchases!$K$5:$K$20004,Purchases!$A$5:$A$20004,">="&$A7,Purchases!$A$5:$A$20004,"<"&EDATE($A7,1)) | K7: =SUMIFS(Sales!$N$5:$N$20004,Sales!$A$5:$A$20004,">="&$A7,Sales!$A$5:$A$20004,"<"&EDATE($A7,1))+SUMIFS(Sales!$O$5:$O$20004,Sales!$A$5:$A$20004,">="&$A7,Sales!$A$5:$A$20004,"<"&EDATE($A7,1))+SUMIFS(Sales!$P$5:$P$20004,Sales!$A$5:$A$20004,">="&$A7,Sales!$A$5:$A$20004,"<"&EDATE($A7,1)) | L7: =SUMIFS(Purchases!$M$5:$M$20004,Purchases!$A$5:$A$20004,">="&$A7,Purchases!$A$5:$A$20004,"<"&EDATE($A7,1))+SUMIFS(Purchases!$N$5:$N$20004,Purchases!$A$5:$A$20004,">="&$A7,Purchases!$A$5:$A$20004,"<"&EDATE($A7,1))+SUMIFS(Purchases!$O$5:$O$20004,Purchases!$A$5:$A$20004,">="&$A7,Purchases!$A$5:$A$20004,"<"&EDATE($A7,1)) | M7: =K7-L7
A8: =EDATE(FYStart,3) | B8: =SUMIFS(Sales!$L$5:$L$20004,Sales!$A$5:$A$20004,">="&$A8,Sales!$A$5:$A$20004,"<"&EDATE($A8,1)) | C8: =SUMIFS(Sales!$R$5:$R$20004,Sales!$A$5:$A$20004,">="&$A8,Sales!$A$5:$A$20004,"<"&EDATE($A8,1)) | D8: =B8-C8 | E8: =IF(B8=0,0,D8/B8) | F8: =SUMIFS(CashBook!$G$5:$G$20004,CashBook!$C$5:$C$20004,"Expense",CashBook!$A$5:$A$20004,">="&$A8,CashBook!$A$5:$A$20004,"<"&EDATE($A8,1)) | G8: =SUMIFS(CashBook!$G$5:$G$20004,CashBook!$C$5:$C$20004,"Other Income",CashBook!$A$5:$A$20004,">="&$A8,CashBook!$A$5:$A$20004,"<"&EDATE($A8,1)) | H8: =SUMIFS(Adjustments!$G$5:$G$2004,Adjustments!$A$5:$A$2004,">="&$A8,Adjustments!$A$5:$A$2004,"<"&EDATE($A8,1)) | I8: =D8-F8+G8+H8 | J8: =SUMIFS(Purchases!$K$5:$K$20004,Purchases!$A$5:$A$20004,">="&$A8,Purchases!$A$5:$A$20004,"<"&EDATE($A8,1)) | K8: =SUMIFS(Sales!$N$5:$N$20004,Sales!$A$5:$A$20004,">="&$A8,Sales!$A$5:$A$20004,"<"&EDATE($A8,1))+SUMIFS(Sales!$O$5:$O$20004,Sales!$A$5:$A$20004,">="&$A8,Sales!$A$5:$A$20004,"<"&EDATE($A8,1))+SUMIFS(Sales!$P$5:$P$20004,Sales!$A$5:$A$20004,">="&$A8,Sales!$A$5:$A$20004,"<"&EDATE($A8,1)) | L8: =SUMIFS(Purchases!$M$5:$M$20004,Purchases!$A$5:$A$20004,">="&$A8,Purchases!$A$5:$A$20004,"<"&EDATE($A8,1))+SUMIFS(Purchases!$N$5:$N$20004,Purchases!$A$5:$A$20004,">="&$A8,Purchases!$A$5:$A$20004,"<"&EDATE($A8,1))+SUMIFS(Purchases!$O$5:$O$20004,Purchases!$A$5:$A$20004,">="&$A8,Purchases!$A$5:$A$20004,"<"&EDATE($A8,1)) | M8: =K8-L8
A9: =EDATE(FYStart,4) | B9: =SUMIFS(Sales!$L$5:$L$20004,Sales!$A$5:$A$20004,">="&$A9,Sales!$A$5:$A$20004,"<"&EDATE($A9,1)) | C9: =SUMIFS(Sales!$R$5:$R$20004,Sales!$A$5:$A$20004,">="&$A9,Sales!$A$5:$A$20004,"<"&EDATE($A9,1)) | D9: =B9-C9 | E9: =IF(B9=0,0,D9/B9) | F9: =SUMIFS(CashBook!$G$5:$G$20004,CashBook!$C$5:$C$20004,"Expense",CashBook!$A$5:$A$20004,">="&$A9,CashBook!$A$5:$A$20004,"<"&EDATE($A9,1)) | G9: =SUMIFS(CashBook!$G$5:$G$20004,CashBook!$C$5:$C$20004,"Other Income",CashBook!$A$5:$A$20004,">="&$A9,CashBook!$A$5:$A$20004,"<"&EDATE($A9,1)) | H9: =SUMIFS(Adjustments!$G$5:$G$2004,Adjustments!$A$5:$A$2004,">="&$A9,Adjustments!$A$5:$A$2004,"<"&EDATE($A9,1)) | I9: =D9-F9+G9+H9 | J9: =SUMIFS(Purchases!$K$5:$K$20004,Purchases!$A$5:$A$20004,">="&$A9,Purchases!$A$5:$A$20004,"<"&EDATE($A9,1)) | K9: =SUMIFS(Sales!$N$5:$N$20004,Sales!$A$5:$A$20004,">="&$A9,Sales!$A$5:$A$20004,"<"&EDATE($A9,1))+SUMIFS(Sales!$O$5:$O$20004,Sales!$A$5:$A$20004,">="&$A9,Sales!$A$5:$A$20004,"<"&EDATE($A9,1))+SUMIFS(Sales!$P$5:$P$20004,Sales!$A$5:$A$20004,">="&$A9,Sales!$A$5:$A$20004,"<"&EDATE($A9,1)) | L9: =SUMIFS(Purchases!$M$5:$M$20004,Purchases!$A$5:$A$20004,">="&$A9,Purchases!$A$5:$A$20004,"<"&EDATE($A9,1))+SUMIFS(Purchases!$N$5:$N$20004,Purchases!$A$5:$A$20004,">="&$A9,Purchases!$A$5:$A$20004,"<"&EDATE($A9,1))+SUMIFS(Purchases!$O$5:$O$20004,Purchases!$A$5:$A$20004,">="&$A9,Purchases!$A$5:$A$20004,"<"&EDATE($A9,1)) | M9: =K9-L9
A10: =EDATE(FYStart,5) | B10: =SUMIFS(Sales!$L$5:$L$20004,Sales!$A$5:$A$20004,">="&$A10,Sales!$A$5:$A$20004,"<"&EDATE($A10,1)) | C10: =SUMIFS(Sales!$R$5:$R$20004,Sales!$A$5:$A$20004,">="&$A10,Sales!$A$5:$A$20004,"<"&EDATE($A10,1)) | D10: =B10-C10 | E10: =IF(B10=0,0,D10/B10) | F10: =SUMIFS(CashBook!$G$5:$G$20004,CashBook!$C$5:$C$20004,"Expense",CashBook!$A$5:$A$20004,">="&$A10,CashBook!$A$5:$A$20004,"<"&EDATE($A10,1)) | G10: =SUMIFS(CashBook!$G$5:$G$20004,CashBook!$C$5:$C$20004,"Other Income",CashBook!$A$5:$A$20004,">="&$A10,CashBook!$A$5:$A$20004,"<"&EDATE($A10,1)) | H10: =SUMIFS(Adjustments!$G$5:$G$2004,Adjustments!$A$5:$A$2004,">="&$A10,Adjustments!$A$5:$A$2004,"<"&EDATE($A10,1)) | I10: =D10-F10+G10+H10 | J10: =SUMIFS(Purchases!$K$5:$K$20004,Purchases!$A$5:$A$20004,">="&$A10,Purchases!$A$5:$A$20004,"<"&EDATE($A10,1)) | K10: =SUMIFS(Sales!$N$5:$N$20004,Sales!$A$5:$A$20004,">="&$A10,Sales!$A$5:$A$20004,"<"&EDATE($A10,1))+SUMIFS(Sales!$O$5:$O$20004,Sales!$A$5:$A$20004,">="&$A10,Sales!$A$5:$A$20004,"<"&EDATE($A10,1))+SUMIFS(Sales!$P$5:$P$20004,Sales!$A$5:$A$20004,">="&$A10,Sales!$A$5:$A$20004,"<"&EDATE($A10,1)) | L10: =SUMIFS(Purchases!$M$5:$M$20004,Purchases!$A$5:$A$20004,">="&$A10,Purchases!$A$5:$A$20004,"<"&EDATE($A10,1))+SUMIFS(Purchases!$N$5:$N$20004,Purchases!$A$5:$A$20004,">="&$A10,Purchases!$A$5:$A$20004,"<"&EDATE($A10,1))+SUMIFS(Purchases!$O$5:$O$20004,Purchases!$A$5:$A$20004,">="&$A10,Purchases!$A$5:$A$20004,"<"&EDATE($A10,1)) | M10: =K10-L10
A11: =EDATE(FYStart,6) | B11: =SUMIFS(Sales!$L$5:$L$20004,Sales!$A$5:$A$20004,">="&$A11,Sales!$A$5:$A$20004,"<"&EDATE($A11,1)) | C11: =SUMIFS(Sales!$R$5:$R$20004,Sales!$A$5:$A$20004,">="&$A11,Sales!$A$5:$A$20004,"<"&EDATE($A11,1)) | D11: =B11-C11 | E11: =IF(B11=0,0,D11/B11) | F11: =SUMIFS(CashBook!$G$5:$G$20004,CashBook!$C$5:$C$20004,"Expense",CashBook!$A$5:$A$20004,">="&$A11,CashBook!$A$5:$A$20004,"<"&EDATE($A11,1)) | G11: =SUMIFS(CashBook!$G$5:$G$20004,CashBook!$C$5:$C$20004,"Other Income",CashBook!$A$5:$A$20004,">="&$A11,CashBook!$A$5:$A$20004,"<"&EDATE($A11,1)) | H11: =SUMIFS(Adjustments!$G$5:$G$2004,Adjustments!$A$5:$A$2004,">="&$A11,Adjustments!$A$5:$A$2004,"<"&EDATE($A11,1)) | I11: =D11-F11+G11+H11 | J11: =SUMIFS(Purchases!$K$5:$K$20004,Purchases!$A$5:$A$20004,">="&$A11,Purchases!$A$5:$A$20004,"<"&EDATE($A11,1)) | K11: =SUMIFS(Sales!$N$5:$N$20004,Sales!$A$5:$A$20004,">="&$A11,Sales!$A$5:$A$20004,"<"&EDATE($A11,1))+SUMIFS(Sales!$O$5:$O$20004,Sales!$A$5:$A$20004,">="&$A11,Sales!$A$5:$A$20004,"<"&EDATE($A11,1))+SUMIFS(Sales!$P$5:$P$20004,Sales!$A$5:$A$20004,">="&$A11,Sales!$A$5:$A$20004,"<"&EDATE($A11,1)) | L11: =SUMIFS(Purchases!$M$5:$M$20004,Purchases!$A$5:$A$20004,">="&$A11,Purchases!$A$5:$A$20004,"<"&EDATE($A11,1))+SUMIFS(Purchases!$N$5:$N$20004,Purchases!$A$5:$A$20004,">="&$A11,Purchases!$A$5:$A$20004,"<"&EDATE($A11,1))+SUMIFS(Purchases!$O$5:$O$20004,Purchases!$A$5:$A$20004,">="&$A11,Purchases!$A$5:$A$20004,"<"&EDATE($A11,1)) | M11: =K11-L11
A12: =EDATE(FYStart,7) | B12: =SUMIFS(Sales!$L$5:$L$20004,Sales!$A$5:$A$20004,">="&$A12,Sales!$A$5:$A$20004,"<"&EDATE($A12,1)) | C12: =SUMIFS(Sales!$R$5:$R$20004,Sales!$A$5:$A$20004,">="&$A12,Sales!$A$5:$A$20004,"<"&EDATE($A12,1)) | D12: =B12-C12 | E12: =IF(B12=0,0,D12/B12) | F12: =SUMIFS(CashBook!$G$5:$G$20004,CashBook!$C$5:$C$20004,"Expense",CashBook!$A$5:$A$20004,">="&$A12,CashBook!$A$5:$A$20004,"<"&EDATE($A12,1)) | G12: =SUMIFS(CashBook!$G$5:$G$20004,CashBook!$C$5:$C$20004,"Other Income",CashBook!$A$5:$A$20004,">="&$A12,CashBook!$A$5:$A$20004,"<"&EDATE($A12,1)) | H12: =SUMIFS(Adjustments!$G$5:$G$2004,Adjustments!$A$5:$A$2004,">="&$A12,Adjustments!$A$5:$A$2004,"<"&EDATE($A12,1)) | I12: =D12-F12+G12+H12 | J12: =SUMIFS(Purchases!$K$5:$K$20004,Purchases!$A$5:$A$20004,">="&$A12,Purchases!$A$5:$A$20004,"<"&EDATE($A12,1)) | K12: =SUMIFS(Sales!$N$5:$N$20004,Sales!$A$5:$A$20004,">="&$A12,Sales!$A$5:$A$20004,"<"&EDATE($A12,1))+SUMIFS(Sales!$O$5:$O$20004,Sales!$A$5:$A$20004,">="&$A12,Sales!$A$5:$A$20004,"<"&EDATE($A12,1))+SUMIFS(Sales!$P$5:$P$20004,Sales!$A$5:$A$20004,">="&$A12,Sales!$A$5:$A$20004,"<"&EDATE($A12,1)) | L12: =SUMIFS(Purchases!$M$5:$M$20004,Purchases!$A$5:$A$20004,">="&$A12,Purchases!$A$5:$A$20004,"<"&EDATE($A12,1))+SUMIFS(Purchases!$N$5:$N$20004,Purchases!$A$5:$A$20004,">="&$A12,Purchases!$A$5:$A$20004,"<"&EDATE($A12,1))+SUMIFS(Purchases!$O$5:$O$20004,Purchases!$A$5:$A$20004,">="&$A12,Purchases!$A$5:$A$20004,"<"&EDATE($A12,1)) | M12: =K12-L12
A13: =EDATE(FYStart,8) | B13: =SUMIFS(Sales!$L$5:$L$20004,Sales!$A$5:$A$20004,">="&$A13,Sales!$A$5:$A$20004,"<"&EDATE($A13,1)) | C13: =SUMIFS(Sales!$R$5:$R$20004,Sales!$A$5:$A$20004,">="&$A13,Sales!$A$5:$A$20004,"<"&EDATE($A13,1)) | D13: =B13-C13 | E13: =IF(B13=0,0,D13/B13) | F13: =SUMIFS(CashBook!$G$5:$G$20004,CashBook!$C$5:$C$20004,"Expense",CashBook!$A$5:$A$20004,">="&$A13,CashBook!$A$5:$A$20004,"<"&EDATE($A13,1)) | G13: =SUMIFS(CashBook!$G$5:$G$20004,CashBook!$C$5:$C$20004,"Other Income",CashBook!$A$5:$A$20004,">="&$A13,CashBook!$A$5:$A$20004,"<"&EDATE($A13,1)) | H13: =SUMIFS(Adjustments!$G$5:$G$2004,Adjustments!$A$5:$A$2004,">="&$A13,Adjustments!$A$5:$A$2004,"<"&EDATE($A13,1)) | I13: =D13-F13+G13+H13 | J13: =SUMIFS(Purchases!$K$5:$K$20004,Purchases!$A$5:$A$20004,">="&$A13,Purchases!$A$5:$A$20004,"<"&EDATE($A13,1)) | K13: =SUMIFS(Sales!$N$5:$N$20004,Sales!$A$5:$A$20004,">="&$A13,Sales!$A$5:$A$20004,"<"&EDATE($A13,1))+SUMIFS(Sales!$O$5:$O$20004,Sales!$A$5:$A$20004,">="&$A13,Sales!$A$5:$A$20004,"<"&EDATE($A13,1))+SUMIFS(Sales!$P$5:$P$20004,Sales!$A$5:$A$20004,">="&$A13,Sales!$A$5:$A$20004,"<"&EDATE($A13,1)) | L13: =SUMIFS(Purchases!$M$5:$M$20004,Purchases!$A$5:$A$20004,">="&$A13,Purchases!$A$5:$A$20004,"<"&EDATE($A13,1))+SUMIFS(Purchases!$N$5:$N$20004,Purchases!$A$5:$A$20004,">="&$A13,Purchases!$A$5:$A$20004,"<"&EDATE($A13,1))+SUMIFS(Purchases!$O$5:$O$20004,Purchases!$A$5:$A$20004,">="&$A13,Purchases!$A$5:$A$20004,"<"&EDATE($A13,1)) | M13: =K13-L13
A14: =EDATE(FYStart,9) | B14: =SUMIFS(Sales!$L$5:$L$20004,Sales!$A$5:$A$20004,">="&$A14,Sales!$A$5:$A$20004,"<"&EDATE($A14,1)) | C14: =SUMIFS(Sales!$R$5:$R$20004,Sales!$A$5:$A$20004,">="&$A14,Sales!$A$5:$A$20004,"<"&EDATE($A14,1)) | D14: =B14-C14 | E14: =IF(B14=0,0,D14/B14) | F14: =SUMIFS(CashBook!$G$5:$G$20004,CashBook!$C$5:$C$20004,"Expense",CashBook!$A$5:$A$20004,">="&$A14,CashBook!$A$5:$A$20004,"<"&EDATE($A14,1)) | G14: =SUMIFS(CashBook!$G$5:$G$20004,CashBook!$C$5:$C$20004,"Other Income",CashBook!$A$5:$A$20004,">="&$A14,CashBook!$A$5:$A$20004,"<"&EDATE($A14,1)) | H14: =SUMIFS(Adjustments!$G$5:$G$2004,Adjustments!$A$5:$A$2004,">="&$A14,Adjustments!$A$5:$A$2004,"<"&EDATE($A14,1)) | I14: =D14-F14+G14+H14 | J14: =SUMIFS(Purchases!$K$5:$K$20004,Purchases!$A$5:$A$20004,">="&$A14,Purchases!$A$5:$A$20004,"<"&EDATE($A14,1)) | K14: =SUMIFS(Sales!$N$5:$N$20004,Sales!$A$5:$A$20004,">="&$A14,Sales!$A$5:$A$20004,"<"&EDATE($A14,1))+SUMIFS(Sales!$O$5:$O$20004,Sales!$A$5:$A$20004,">="&$A14,Sales!$A$5:$A$20004,"<"&EDATE($A14,1))+SUMIFS(Sales!$P$5:$P$20004,Sales!$A$5:$A$20004,">="&$A14,Sales!$A$5:$A$20004,"<"&EDATE($A14,1)) | L14: =SUMIFS(Purchases!$M$5:$M$20004,Purchases!$A$5:$A$20004,">="&$A14,Purchases!$A$5:$A$20004,"<"&EDATE($A14,1))+SUMIFS(Purchases!$N$5:$N$20004,Purchases!$A$5:$A$20004,">="&$A14,Purchases!$A$5:$A$20004,"<"&EDATE($A14,1))+SUMIFS(Purchases!$O$5:$O$20004,Purchases!$A$5:$A$20004,">="&$A14,Purchases!$A$5:$A$20004,"<"&EDATE($A14,1)) | M14: =K14-L14
A15: =EDATE(FYStart,10) | B15: =SUMIFS(Sales!$L$5:$L$20004,Sales!$A$5:$A$20004,">="&$A15,Sales!$A$5:$A$20004,"<"&EDATE($A15,1)) | C15: =SUMIFS(Sales!$R$5:$R$20004,Sales!$A$5:$A$20004,">="&$A15,Sales!$A$5:$A$20004,"<"&EDATE($A15,1)) | D15: =B15-C15 | E15: =IF(B15=0,0,D15/B15) | F15: =SUMIFS(CashBook!$G$5:$G$20004,CashBook!$C$5:$C$20004,"Expense",CashBook!$A$5:$A$20004,">="&$A15,CashBook!$A$5:$A$20004,"<"&EDATE($A15,1)) | G15: =SUMIFS(CashBook!$G$5:$G$20004,CashBook!$C$5:$C$20004,"Other Income",CashBook!$A$5:$A$20004,">="&$A15,CashBook!$A$5:$A$20004,"<"&EDATE($A15,1)) | H15: =SUMIFS(Adjustments!$G$5:$G$2004,Adjustments!$A$5:$A$2004,">="&$A15,Adjustments!$A$5:$A$2004,"<"&EDATE($A15,1)) | I15: =D15-F15+G15+H15 | J15: =SUMIFS(Purchases!$K$5:$K$20004,Purchases!$A$5:$A$20004,">="&$A15,Purchases!$A$5:$A$20004,"<"&EDATE($A15,1)) | K15: =SUMIFS(Sales!$N$5:$N$20004,Sales!$A$5:$A$20004,">="&$A15,Sales!$A$5:$A$20004,"<"&EDATE($A15,1))+SUMIFS(Sales!$O$5:$O$20004,Sales!$A$5:$A$20004,">="&$A15,Sales!$A$5:$A$20004,"<"&EDATE($A15,1))+SUMIFS(Sales!$P$5:$P$20004,Sales!$A$5:$A$20004,">="&$A15,Sales!$A$5:$A$20004,"<"&EDATE($A15,1)) | L15: =SUMIFS(Purchases!$M$5:$M$20004,Purchases!$A$5:$A$20004,">="&$A15,Purchases!$A$5:$A$20004,"<"&EDATE($A15,1))+SUMIFS(Purchases!$N$5:$N$20004,Purchases!$A$5:$A$20004,">="&$A15,Purchases!$A$5:$A$20004,"<"&EDATE($A15,1))+SUMIFS(Purchases!$O$5:$O$20004,Purchases!$A$5:$A$20004,">="&$A15,Purchases!$A$5:$A$20004,"<"&EDATE($A15,1)) | M15: =K15-L15
A16: =EDATE(FYStart,11) | B16: =SUMIFS(Sales!$L$5:$L$20004,Sales!$A$5:$A$20004,">="&$A16,Sales!$A$5:$A$20004,"<"&EDATE($A16,1)) | C16: =SUMIFS(Sales!$R$5:$R$20004,Sales!$A$5:$A$20004,">="&$A16,Sales!$A$5:$A$20004,"<"&EDATE($A16,1)) | D16: =B16-C16 | E16: =IF(B16=0,0,D16/B16) | F16: =SUMIFS(CashBook!$G$5:$G$20004,CashBook!$C$5:$C$20004,"Expense",CashBook!$A$5:$A$20004,">="&$A16,CashBook!$A$5:$A$20004,"<"&EDATE($A16,1)) | G16: =SUMIFS(CashBook!$G$5:$G$20004,CashBook!$C$5:$C$20004,"Other Income",CashBook!$A$5:$A$20004,">="&$A16,CashBook!$A$5:$A$20004,"<"&EDATE($A16,1)) | H16: =SUMIFS(Adjustments!$G$5:$G$2004,Adjustments!$A$5:$A$2004,">="&$A16,Adjustments!$A$5:$A$2004,"<"&EDATE($A16,1)) | I16: =D16-F16+G16+H16 | J16: =SUMIFS(Purchases!$K$5:$K$20004,Purchases!$A$5:$A$20004,">="&$A16,Purchases!$A$5:$A$20004,"<"&EDATE($A16,1)) | K16: =SUMIFS(Sales!$N$5:$N$20004,Sales!$A$5:$A$20004,">="&$A16,Sales!$A$5:$A$20004,"<"&EDATE($A16,1))+SUMIFS(Sales!$O$5:$O$20004,Sales!$A$5:$A$20004,">="&$A16,Sales!$A$5:$A$20004,"<"&EDATE($A16,1))+SUMIFS(Sales!$P$5:$P$20004,Sales!$A$5:$A$20004,">="&$A16,Sales!$A$5:$A$20004,"<"&EDATE($A16,1)) | L16: =SUMIFS(Purchases!$M$5:$M$20004,Purchases!$A$5:$A$20004,">="&$A16,Purchases!$A$5:$A$20004,"<"&EDATE($A16,1))+SUMIFS(Purchases!$N$5:$N$20004,Purchases!$A$5:$A$20004,">="&$A16,Purchases!$A$5:$A$20004,"<"&EDATE($A16,1))+SUMIFS(Purchases!$O$5:$O$20004,Purchases!$A$5:$A$20004,">="&$A16,Purchases!$A$5:$A$20004,"<"&EDATE($A16,1)) | M16: =K16-L16
A17: FY TOTAL | B17: =SUM(B5:B16) | C17: =SUM(C5:C16) | D17: =SUM(D5:D16) | E17: =IF(B17=0,0,D17/B17) | F17: =SUM(F5:F16) | G17: =SUM(G5:G16) | H17: =SUM(H5:H16) | I17: =SUM(I5:I16) | J17: =SUM(J5:J16) | K17: =SUM(K5:K16) | L17: =SUM(L5:L16) | M17: =SUM(M5:M16)
A18: Net Profit = Gross Profit − Expenses + Other Income + Stock Adjustment value (losses are negative). Purchases are capitalised into stock; only COGS hits profit.
A21: GST RATE-WISE SUMMARY (FY) — ready for GSTR-1 / GSTR-3B | H21: EXPENSES BY HEAD (FY)
A22: GST Rate | B22: Sales Taxable (₹) | C22: Output Tax (₹) | D22: Purch. Taxable (₹) | E22: Input Tax (₹) | F22: Net (₹) | H22: Head | I22: Amount (₹) | J22: Share
A23: =IF(Settings!F5="","",Settings!F5) | B23: =IF($A23="","",SUMIFS(Sales!$L$5:$L$20004,Sales!$M$5:$M$20004,$A23,Sales!$A$5:$A$20004,">="&FYStart,Sales!$A$5:$A$20004,"<"&EDATE(FYStart,12))) | C23: =IF($A23="","",SUMIFS(Sales!$N$5:$N$20004,Sales!$M$5:$M$20004,$A23,Sales!$A$5:$A$20004,">="&FYStart,Sales!$A$5:$A$20004,"<"&EDATE(FYStart,12))+SUMIFS(Sales!$O$5:$O$20004,Sales!$M$5:$M$20004,$A23,Sales!$A$5:$A$20004,">="&FYStart,Sales!$A$5:$A$20004,"<"&EDATE(FYStart,12))+SUMIFS(Sales!$P$5:$P$20004,Sales!$M$5:$M$20004,$A23,Sales!$A$5:$A$20004,">="&FYStart,Sales!$A$5:$A$20004,"<"&EDATE(FYStart,12))) | D23: =IF($A23="","",SUMIFS(Purchases!$K$5:$K$20004,Purchases!$L$5:$L$20004,$A23,Purchases!$A$5:$A$20004,">="&FYStart,Purchases!$A$5:$A$20004,"<"&EDATE(FYStart,12))) | E23: =IF($A23="","",SUMIFS(Purchases!$M$5:$M$20004,Purchases!$L$5:$L$20004,$A23,Purchases!$A$5:$A$20004,">="&FYStart,Purchases!$A$5:$A$20004,"<"&EDATE(FYStart,12))+SUMIFS(Purchases!$N$5:$N$20004,Purchases!$L$5:$L$20004,$A23,Purchases!$A$5:$A$20004,">="&FYStart,Purchases!$A$5:$A$20004,"<"&EDATE(FYStart,12))+SUMIFS(Purchases!$O$5:$O$20004,Purchases!$L$5:$L$20004,$A23,Purchases!$A$5:$A$20004,">="&FYStart,Purchases!$A$5:$A$20004,"<"&EDATE(FYStart,12))) | F23: =IF($A23="","",C23-E23) | H23: =IF(Settings!I5="","",Settings!I5) | I23: =IF(H23="","",SUMIFS(CashBook!$G$5:$G$20004,CashBook!$C$5:$C$20004,"Expense",CashBook!$E$5:$E$20004,H23,CashBook!$A$5:$A$20004,">="&FYStart,CashBook!$A$5:$A$20004,"<"&EDATE(FYStart,12))) | J23: =IF(H23="","",IF(SUM($I$23:$I$34)=0,0,I23/SUM($I$23:$I$34)))
A24: =IF(Settings!F6="","",Settings!F6) | B24: =IF($A24="","",SUMIFS(Sales!$L$5:$L$20004,Sales!$M$5:$M$20004,$A24,Sales!$A$5:$A$20004,">="&FYStart,Sales!$A$5:$A$20004,"<"&EDATE(FYStart,12))) | C24: =IF($A24="","",SUMIFS(Sales!$N$5:$N$20004,Sales!$M$5:$M$20004,$A24,Sales!$A$5:$A$20004,">="&FYStart,Sales!$A$5:$A$20004,"<"&EDATE(FYStart,12))+SUMIFS(Sales!$O$5:$O$20004,Sales!$M$5:$M$20004,$A24,Sales!$A$5:$A$20004,">="&FYStart,Sales!$A$5:$A$20004,"<"&EDATE(FYStart,12))+SUMIFS(Sales!$P$5:$P$20004,Sales!$M$5:$M$20004,$A24,Sales!$A$5:$A$20004,">="&FYStart,Sales!$A$5:$A$20004,"<"&EDATE(FYStart,12))) | D24: =IF($A24="","",SUMIFS(Purchases!$K$5:$K$20004,Purchases!$L$5:$L$20004,$A24,Purchases!$A$5:$A$20004,">="&FYStart,Purchases!$A$5:$A$20004,"<"&EDATE(FYStart,12))) | E24: =IF($A24="","",SUMIFS(Purchases!$M$5:$M$20004,Purchases!$L$5:$L$20004,$A24,Purchases!$A$5:$A$20004,">="&FYStart,Purchases!$A$5:$A$20004,"<"&EDATE(FYStart,12))+SUMIFS(Purchases!$N$5:$N$20004,Purchases!$L$5:$L$20004,$A24,Purchases!$A$5:$A$20004,">="&FYStart,Purchases!$A$5:$A$20004,"<"&EDATE(FYStart,12))+SUMIFS(Purchases!$O$5:$O$20004,Purchases!$L$5:$L$20004,$A24,Purchases!$A$5:$A$20004,">="&FYStart,Purchases!$A$5:$A$20004,"<"&EDATE(FYStart,12))) | F24: =IF($A24="","",C24-E24) | H24: =IF(Settings!I6="","",Settings!I6) | I24: =IF(H24="","",SUMIFS(CashBook!$G$5:$G$20004,CashBook!$C$5:$C$20004,"Expense",CashBook!$E$5:$E$20004,H24,CashBook!$A$5:$A$20004,">="&FYStart,CashBook!$A$5:$A$20004,"<"&EDATE(FYStart,12))) | J24: =IF(H24="","",IF(SUM($I$23:$I$34)=0,0,I24/SUM($I$23:$I$34)))
A25: =IF(Settings!F7="","",Settings!F7) | B25: =IF($A25="","",SUMIFS(Sales!$L$5:$L$20004,Sales!$M$5:$M$20004,$A25,Sales!$A$5:$A$20004,">="&FYStart,Sales!$A$5:$A$20004,"<"&EDATE(FYStart,12))) | C25: =IF($A25="","",SUMIFS(Sales!$N$5:$N$20004,Sales!$M$5:$M$20004,$A25,Sales!$A$5:$A$20004,">="&FYStart,Sales!$A$5:$A$20004,"<"&EDATE(FYStart,12))+SUMIFS(Sales!$O$5:$O$20004,Sales!$M$5:$M$20004,$A25,Sales!$A$5:$A$20004,">="&FYStart,Sales!$A$5:$A$20004,"<"&EDATE(FYStart,12))+SUMIFS(Sales!$P$5:$P$20004,Sales!$M$5:$M$20004,$A25,Sales!$A$5:$A$20004,">="&FYStart,Sales!$A$5:$A$20004,"<"&EDATE(FYStart,12))) | D25: =IF($A25="","",SUMIFS(Purchases!$K$5:$K$20004,Purchases!$L$5:$L$20004,$A25,Purchases!$A$5:$A$20004,">="&FYStart,Purchases!$A$5:$A$20004,"<"&EDATE(FYStart,12))) | E25: =IF($A25="","",SUMIFS(Purchases!$M$5:$M$20004,Purchases!$L$5:$L$20004,$A25,Purchases!$A$5:$A$20004,">="&FYStart,Purchases!$A$5:$A$20004,"<"&EDATE(FYStart,12))+SUMIFS(Purchases!$N$5:$N$20004,Purchases!$L$5:$L$20004,$A25,Purchases!$A$5:$A$20004,">="&FYStart,Purchases!$A$5:$A$20004,"<"&EDATE(FYStart,12))+SUMIFS(Purchases!$O$5:$O$20004,Purchases!$L$5:$L$20004,$A25,Purchases!$A$5:$A$20004,">="&FYStart,Purchases!$A$5:$A$20004,"<"&EDATE(FYStart,12))) | F25: =IF($A25="","",C25-E25) | H25: =IF(Settings!I7="","",Settings!I7) | I25: =IF(H25="","",SUMIFS(CashBook!$G$5:$G$20004,CashBook!$C$5:$C$20004,"Expense",CashBook!$E$5:$E$20004,H25,CashBook!$A$5:$A$20004,">="&FYStart,CashBook!$A$5:$A$20004,"<"&EDATE(FYStart,12))) | J25: =IF(H25="","",IF(SUM($I$23:$I$34)=0,0,I25/SUM($I$23:$I$34)))
A26: =IF(Settings!F8="","",Settings!F8) | B26: =IF($A26="","",SUMIFS(Sales!$L$5:$L$20004,Sales!$M$5:$M$20004,$A26,Sales!$A$5:$A$20004,">="&FYStart,Sales!$A$5:$A$20004,"<"&EDATE(FYStart,12))) | C26: =IF($A26="","",SUMIFS(Sales!$N$5:$N$20004,Sales!$M$5:$M$20004,$A26,Sales!$A$5:$A$20004,">="&FYStart,Sales!$A$5:$A$20004,"<"&EDATE(FYStart,12))+SUMIFS(Sales!$O$5:$O$20004,Sales!$M$5:$M$20004,$A26,Sales!$A$5:$A$20004,">="&FYStart,Sales!$A$5:$A$20004,"<"&EDATE(FYStart,12))+SUMIFS(Sales!$P$5:$P$20004,Sales!$M$5:$M$20004,$A26,Sales!$A$5:$A$20004,">="&FYStart,Sales!$A$5:$A$20004,"<"&EDATE(FYStart,12))) | D26: =IF($A26="","",SUMIFS(Purchases!$K$5:$K$20004,Purchases!$L$5:$L$20004,$A26,Purchases!$A$5:$A$20004,">="&FYStart,Purchases!$A$5:$A$20004,"<"&EDATE(FYStart,12))) | E26: =IF($A26="","",SUMIFS(Purchases!$M$5:$M$20004,Purchases!$L$5:$L$20004,$A26,Purchases!$A$5:$A$20004,">="&FYStart,Purchases!$A$5:$A$20004,"<"&EDATE(FYStart,12))+SUMIFS(Purchases!$N$5:$N$20004,Purchases!$L$5:$L$20004,$A26,Purchases!$A$5:$A$20004,">="&FYStart,Purchases!$A$5:$A$20004,"<"&EDATE(FYStart,12))+SUMIFS(Purchases!$O$5:$O$20004,Purchases!$L$5:$L$20004,$A26,Purchases!$A$5:$A$20004,">="&FYStart,Purchases!$A$5:$A$20004,"<"&EDATE(FYStart,12))) | F26: =IF($A26="","",C26-E26) | H26: =IF(Settings!I8="","",Settings!I8) | I26: =IF(H26="","",SUMIFS(CashBook!$G$5:$G$20004,CashBook!$C$5:$C$20004,"Expense",CashBook!$E$5:$E$20004,H26,CashBook!$A$5:$A$20004,">="&FYStart,CashBook!$A$5:$A$20004,"<"&EDATE(FYStart,12))) | J26: =IF(H26="","",IF(SUM($I$23:$I$34)=0,0,I26/SUM($I$23:$I$34)))
A27: =IF(Settings!F9="","",Settings!F9) | B27: =IF($A27="","",SUMIFS(Sales!$L$5:$L$20004,Sales!$M$5:$M$20004,$A27,Sales!$A$5:$A$20004,">="&FYStart,Sales!$A$5:$A$20004,"<"&EDATE(FYStart,12))) | C27: =IF($A27="","",SUMIFS(Sales!$N$5:$N$20004,Sales!$M$5:$M$20004,$A27,Sales!$A$5:$A$20004,">="&FYStart,Sales!$A$5:$A$20004,"<"&EDATE(FYStart,12))+SUMIFS(Sales!$O$5:$O$20004,Sales!$M$5:$M$20004,$A27,Sales!$A$5:$A$20004,">="&FYStart,Sales!$A$5:$A$20004,"<"&EDATE(FYStart,12))+SUMIFS(Sales!$P$5:$P$20004,Sales!$M$5:$M$20004,$A27,Sales!$A$5:$A$20004,">="&FYStart,Sales!$A$5:$A$20004,"<"&EDATE(FYStart,12))) | D27: =IF($A27="","",SUMIFS(Purchases!$K$5:$K$20004,Purchases!$L$5:$L$20004,$A27,Purchases!$A$5:$A$20004,">="&FYStart,Purchases!$A$5:$A$20004,"<"&EDATE(FYStart,12))) | E27: =IF($A27="","",SUMIFS(Purchases!$M$5:$M$20004,Purchases!$L$5:$L$20004,$A27,Purchases!$A$5:$A$20004,">="&FYStart,Purchases!$A$5:$A$20004,"<"&EDATE(FYStart,12))+SUMIFS(Purchases!$N$5:$N$20004,Purchases!$L$5:$L$20004,$A27,Purchases!$A$5:$A$20004,">="&FYStart,Purchases!$A$5:$A$20004,"<"&EDATE(FYStart,12))+SUMIFS(Purchases!$O$5:$O$20004,Purchases!$L$5:$L$20004,$A27,Purchases!$A$5:$A$20004,">="&FYStart,Purchases!$A$5:$A$20004,"<"&EDATE(FYStart,12))) | F27: =IF($A27="","",C27-E27) | H27: =IF(Settings!I9="","",Settings!I9) | I27: =IF(H27="","",SUMIFS(CashBook!$G$5:$G$20004,CashBook!$C$5:$C$20004,"Expense",CashBook!$E$5:$E$20004,H27,CashBook!$A$5:$A$20004,">="&FYStart,CashBook!$A$5:$A$20004,"<"&EDATE(FYStart,12))) | J27: =IF(H27="","",IF(SUM($I$23:$I$34)=0,0,I27/SUM($I$23:$I$34)))
A28: =IF(Settings!F10="","",Settings!F10) | B28: =IF($A28="","",SUMIFS(Sales!$L$5:$L$20004,Sales!$M$5:$M$20004,$A28,Sales!$A$5:$A$20004,">="&FYStart,Sales!$A$5:$A$20004,"<"&EDATE(FYStart,12))) | C28: =IF($A28="","",SUMIFS(Sales!$N$5:$N$20004,Sales!$M$5:$M$20004,$A28,Sales!$A$5:$A$20004,">="&FYStart,Sales!$A$5:$A$20004,"<"&EDATE(FYStart,12))+SUMIFS(Sales!$O$5:$O$20004,Sales!$M$5:$M$20004,$A28,Sales!$A$5:$A$20004,">="&FYStart,Sales!$A$5:$A$20004,"<"&EDATE(FYStart,12))+SUMIFS(Sales!$P$5:$P$20004,Sales!$M$5:$M$20004,$A28,Sales!$A$5:$A$20004,">="&FYStart,Sales!$A$5:$A$20004,"<"&EDATE(FYStart,12))) | D28: =IF($A28="","",SUMIFS(Purchases!$K$5:$K$20004,Purchases!$L$5:$L$20004,$A28,Purchases!$A$5:$A$20004,">="&FYStart,Purchases!$A$5:$A$20004,"<"&EDATE(FYStart,12))) | E28: =IF($A28="","",SUMIFS(Purchases!$M$5:$M$20004,Purchases!$L$5:$L$20004,$A28,Purchases!$A$5:$A$20004,">="&FYStart,Purchases!$A$5:$A$20004,"<"&EDATE(FYStart,12))+SUMIFS(Purchases!$N$5:$N$20004,Purchases!$L$5:$L$20004,$A28,Purchases!$A$5:$A$20004,">="&FYStart,Purchases!$A$5:$A$20004,"<"&EDATE(FYStart,12))+SUMIFS(Purchases!$O$5:$O$20004,Purchases!$L$5:$L$20004,$A28,Purchases!$A$5:$A$20004,">="&FYStart,Purchases!$A$5:$A$20004,"<"&EDATE(FYStart,12))) | F28: =IF($A28="","",C28-E28) | H28: =IF(Settings!I10="","",Settings!I10) | I28: =IF(H28="","",SUMIFS(CashBook!$G$5:$G$20004,CashBook!$C$5:$C$20004,"Expense",CashBook!$E$5:$E$20004,H28,CashBook!$A$5:$A$20004,">="&FYStart,CashBook!$A$5:$A$20004,"<"&EDATE(FYStart,12))) | J28: =IF(H28="","",IF(SUM($I$23:$I$34)=0,0,I28/SUM($I$23:$I$34)))
A29: =IF(Settings!F11="","",Settings!F11) | B29: =IF($A29="","",SUMIFS(Sales!$L$5:$L$20004,Sales!$M$5:$M$20004,$A29,Sales!$A$5:$A$20004,">="&FYStart,Sales!$A$5:$A$20004,"<"&EDATE(FYStart,12))) | C29: =IF($A29="","",SUMIFS(Sales!$N$5:$N$20004,Sales!$M$5:$M$20004,$A29,Sales!$A$5:$A$20004,">="&FYStart,Sales!$A$5:$A$20004,"<"&EDATE(FYStart,12))+SUMIFS(Sales!$O$5:$O$20004,Sales!$M$5:$M$20004,$A29,Sales!$A$5:$A$20004,">="&FYStart,Sales!$A$5:$A$20004,"<"&EDATE(FYStart,12))+SUMIFS(Sales!$P$5:$P$20004,Sales!$M$5:$M$20004,$A29,Sales!$A$5:$A$20004,">="&FYStart,Sales!$A$5:$A$20004,"<"&EDATE(FYStart,12))) | D29: =IF($A29="","",SUMIFS(Purchases!$K$5:$K$20004,Purchases!$L$5:$L$20004,$A29,Purchases!$A$5:$A$20004,">="&FYStart,Purchases!$A$5:$A$20004,"<"&EDATE(FYStart,12))) | E29: =IF($A29="","",SUMIFS(Purchases!$M$5:$M$20004,Purchases!$L$5:$L$20004,$A29,Purchases!$A$5:$A$20004,">="&FYStart,Purchases!$A$5:$A$20004,"<"&EDATE(FYStart,12))+SUMIFS(Purchases!$N$5:$N$20004,Purchases!$L$5:$L$20004,$A29,Purchases!$A$5:$A$20004,">="&FYStart,Purchases!$A$5:$A$20004,"<"&EDATE(FYStart,12))+SUMIFS(Purchases!$O$5:$O$20004,Purchases!$L$5:$L$20004,$A29,Purchases!$A$5:$A$20004,">="&FYStart,Purchases!$A$5:$A$20004,"<"&EDATE(FYStart,12))) | F29: =IF($A29="","",C29-E29) | H29: =IF(Settings!I11="","",Settings!I11) | I29: =IF(H29="","",SUMIFS(CashBook!$G$5:$G$20004,CashBook!$C$5:$C$20004,"Expense",CashBook!$E$5:$E$20004,H29,CashBook!$A$5:$A$20004,">="&FYStart,CashBook!$A$5:$A$20004,"<"&EDATE(FYStart,12))) | J29: =IF(H29="","",IF(SUM($I$23:$I$34)=0,0,I29/SUM($I$23:$I$34)))
A30: =IF(Settings!F12="","",Settings!F12) | B30: =IF($A30="","",SUMIFS(Sales!$L$5:$L$20004,Sales!$M$5:$M$20004,$A30,Sales!$A$5:$A$20004,">="&FYStart,Sales!$A$5:$A$20004,"<"&EDATE(FYStart,12))) | C30: =IF($A30="","",SUMIFS(Sales!$N$5:$N$20004,Sales!$M$5:$M$20004,$A30,Sales!$A$5:$A$20004,">="&FYStart,Sales!$A$5:$A$20004,"<"&EDATE(FYStart,12))+SUMIFS(Sales!$O$5:$O$20004,Sales!$M$5:$M$20004,$A30,Sales!$A$5:$A$20004,">="&FYStart,Sales!$A$5:$A$20004,"<"&EDATE(FYStart,12))+SUMIFS(Sales!$P$5:$P$20004,Sales!$M$5:$M$20004,$A30,Sales!$A$5:$A$20004,">="&FYStart,Sales!$A$5:$A$20004,"<"&EDATE(FYStart,12))) | D30: =IF($A30="","",SUMIFS(Purchases!$K$5:$K$20004,Purchases!$L$5:$L$20004,$A30,Purchases!$A$5:$A$20004,">="&FYStart,Purchases!$A$5:$A$20004,"<"&EDATE(FYStart,12))) | E30: =IF($A30="","",SUMIFS(Purchases!$M$5:$M$20004,Purchases!$L$5:$L$20004,$A30,Purchases!$A$5:$A$20004,">="&FYStart,Purchases!$A$5:$A$20004,"<"&EDATE(FYStart,12))+SUMIFS(Purchases!$N$5:$N$20004,Purchases!$L$5:$L$20004,$A30,Purchases!$A$5:$A$20004,">="&FYStart,Purchases!$A$5:$A$20004,"<"&EDATE(FYStart,12))+SUMIFS(Purchases!$O$5:$O$20004,Purchases!$L$5:$L$20004,$A30,Purchases!$A$5:$A$20004,">="&FYStart,Purchases!$A$5:$A$20004,"<"&EDATE(FYStart,12))) | F30: =IF($A30="","",C30-E30) | H30: =IF(Settings!I12="","",Settings!I12) | I30: =IF(H30="","",SUMIFS(CashBook!$G$5:$G$20004,CashBook!$C$5:$C$20004,"Expense",CashBook!$E$5:$E$20004,H30,CashBook!$A$5:$A$20004,">="&FYStart,CashBook!$A$5:$A$20004,"<"&EDATE(FYStart,12))) | J30: =IF(H30="","",IF(SUM($I$23:$I$34)=0,0,I30/SUM($I$23:$I$34)))
H31: =IF(Settings!I13="","",Settings!I13) | I31: =IF(H31="","",SUMIFS(CashBook!$G$5:$G$20004,CashBook!$C$5:$C$20004,"Expense",CashBook!$E$5:$E$20004,H31,CashBook!$A$5:$A$20004,">="&FYStart,CashBook!$A$5:$A$20004,"<"&EDATE(FYStart,12))) | J31: =IF(H31="","",IF(SUM($I$23:$I$34)=0,0,I31/SUM($I$23:$I$34)))
H32: =IF(Settings!I14="","",Settings!I14) | I32: =IF(H32="","",SUMIFS(CashBook!$G$5:$G$20004,CashBook!$C$5:$C$20004,"Expense",CashBook!$E$5:$E$20004,H32,CashBook!$A$5:$A$20004,">="&FYStart,CashBook!$A$5:$A$20004,"<"&EDATE(FYStart,12))) | J32: =IF(H32="","",IF(SUM($I$23:$I$34)=0,0,I32/SUM($I$23:$I$34)))
H33: =IF(Settings!I15="","",Settings!I15) | I33: =IF(H33="","",SUMIFS(CashBook!$G$5:$G$20004,CashBook!$C$5:$C$20004,"Expense",CashBook!$E$5:$E$20004,H33,CashBook!$A$5:$A$20004,">="&FYStart,CashBook!$A$5:$A$20004,"<"&EDATE(FYStart,12))) | J33: =IF(H33="","",IF(SUM($I$23:$I$34)=0,0,I33/SUM($I$23:$I$34)))
H34: =IF(Settings!I16="","",Settings!I16) | I34: =IF(H34="","",SUMIFS(CashBook!$G$5:$G$20004,CashBook!$C$5:$C$20004,"Expense",CashBook!$E$5:$E$20004,H34,CashBook!$A$5:$A$20004,">="&FYStart,CashBook!$A$5:$A$20004,"<"&EDATE(FYStart,12))) | J34: =IF(H34="","",IF(SUM($I$23:$I$34)=0,0,I34/SUM($I$23:$I$34)))

Sheet Settings
A1: ⚙ SETTINGS & MASTER LISTS | N1: ◀ Home
A2: Set this up once. Every list here feeds the dropdowns across the ERP.
F3: GST slabs: 5/18/40% apply post GST-2.0 (Sep-2025); 12/28% kept for legacy items.
A4: Company Name | B4: Your Trading Co. | D4: Categories | E4: Units | F4: GST Rates | G4: Pay Modes | H4: Voucher Types | I4: Expense Heads | J4: Party Types | K4: Delivery Status | L4: Adj. Reasons | M4: States
A5: Address | B5: Shop 12, Main Market, Jaipur | D5: Grocery | E5: Pcs | F5: 0 | G5: Credit | H5: Receipt | I5: Rent | J5: Customer | K5: Pending | L5: Damage | M5: Andhra Pradesh
A6: GSTIN | B6: 08ABCDE1234F1Z5 | D6: FMCG | E6: Kg | F6: 0.05 | G6: Cash | H6: Payment | I6: Salary | J6: Supplier | K6: Packed | L6: Expiry | M6: Arunachal Pradesh
A7: Home State (for GST) | B7: Rajasthan | D7: Electrical | E7: Ltr | F7: 0.12 | G7: Bank | H7: Expense | I7: Electricity | J7: Both | K7: Dispatched | L7: Theft / Loss | M7: Assam
A8: Phone / Email | B8: +91 98xxxxxx00 | D8: Hardware | E8: Box | F8: 0.18 | G8: UPI | H8: Other Income | I8: Transport / Freight | K8: Delivered | L8: Count Correction | M8: Bihar
A9: Financial Year Start | B9: 46113 | D9: Stationery | E9: Bag | F9: 0.28 | H9: Capital In | I9: Packing | K9: Returned | L9: Sample / Free | M9: Chhattisgarh
A10: Report As-Of Date | B10: =TODAY() | D10: Garments | E10: Mtr | F10: 0.4 | H10: Drawings | I10: Telephone / Internet | L10: Sales Return | M10: Goa
A11: Invoice Prefix | B11: INV- | D11: Other | E11: Dozen | F11: 0.03 | H11: Transfer In | I11: Repairs | L11: Purchase Return | M11: Gujarat
A12: Dead-Stock Threshold (days) | B12: 90 | E12: Pack | F12: 0.0025 | H12: Transfer Out | I12: Bank Charges | L12: Opening Fix | M12: Haryana
A13: Bank Details (on invoice) | B13: SBI A/c 0000000000 · IFSC SBIN0000000 | I13: Misc | M13: Himachal Pradesh
M14: Jharkhand
M15: Karnataka
A16: Cash / Bank Accounts | M16: Kerala
A17: Account | B17: Opening Balance (₹) | M17: Madhya Pradesh
A18: Cash | B18: 50000 | M18: Maharashtra
A19: Bank | B19: 250000 | M19: Manipur
A20: UPI | B20: 0 | M20: Meghalaya
M21: Mizoram
M22: Nagaland
M23: Odisha
M24: Punjab
M25: Rajasthan
M26: Sikkim
A27: Opening balances are your figures on FY start - replace the sample values. | M27: Tamil Nadu
M28: Telangana
M29: Tripura
M30: Uttar Pradesh
M31: Uttarakhand
M32: West Bengal
M33: Delhi
M34: Jammu and Kashmir
M35: Ladakh
M36: Puducherry
M37: Chandigarh
M38: Dadra & Nagar Haveli and Daman & Diu
M39: Lakshadweep
M40: Andaman & Nicobar

Sheet Guide
B1: ❓ HOW SMARTTRADER ERP WORKS | E1: ◀ Home
B4: DAILY FLOW: PROCURE → STOCK → SELL → DELIVER → COLLECT
B5: 1. Set up once | C5: Settings: company, GSTIN, home state, FY start, opening cash/bank. Items: product list with opening stock. Parties: customers & suppliers with state and credit limit.
B6: 2. Buy (Purchases) | C6: Pick supplier and item from dropdowns, type qty. Rate blank = standard purchase rate. 'Paid Via' blank = on credit (creates payable).
B7: 3. Stock updates itself | C7: Items sheet instantly shows closing stock, weighted-average cost, stock value and REORDER / OUT OF STOCK / DEAD STOCK alerts.
B8: 4. Sell (Sales) | C8: One line per item; keep all lines of an invoice together. CGST+SGST or IGST is chosen automatically from customer state vs. your home state. 'Stock Check' warns on negative stock or selling below cost.
B9: 5. Print invoice | C9: Invoice sheet shows the latest invoice automatically. Type any invoice number in the cream cell to reprint. Ctrl+P (fits one A4 page). Doubles as delivery challan.
B10: 6. Deliver | C10: Set the Delivery column (Pending / Packed / Dispatched / Delivered). Dashboard counts what is still pending.
B11: 7. Collect & pay (CashBook) | C11: Receipt = money from customer; Payment = money to supplier; Expense = shop costs; Transfer In/Out moves money between Cash/Bank/UPI (enter both legs).
B12: 8. Review | C12: Dashboard for the live picture, Reports for monthly P&L, GST rate-wise summary and expense analysis.
B14: PAIN POINTS THIS SOLVES
B15: Stock never matches | C15: Single source of truth: stock = opening + purchases − sales ± adjustments. No manual stock register.
B16: Don't know real profit | C16: Every sale line carries COGS at weighted-average cost, so gross and net profit are exact per line, item, month.
B17: Money stuck with customers | C17: Party ledger with credit limit, credit days, OVERDUE / OVER LIMIT flags and Days Unpaid.
B18: Running out / overstock | C18: Reorder level + suggested order qty, days-of-cover, and dead-stock detection (no sale in N days).
B19: GST headache | C19: Automatic CGST/SGST vs IGST split, rate-wise output vs input summary per FY, net payable on dashboard.
B20: Double entry for cash sales | C20: 'Paid Via' on the bill itself books cash/bank/UPI immediately - no separate receipt needed.
B21: Typing errors | C21: Dropdowns everywhere, unique-name checks, qty/date validation, row-level 'Check' columns.
B22: Slow, crashing Excel files | C22: See SPEED DESIGN below.
B24: SPEED DESIGN (why it stays fast)
B25: No volatile functions | C25: No OFFSET/INDIRECT in cell formulas; TODAY() appears once (Settings!B10). Volatile names are used only by dropdowns, which are not recalculated.
B26: Bounded ranges | C26: All lookups use fixed ranges (20,000 transaction rows, 2000 items, 1000 parties) - never whole-column A:A references.
B27: Match once, reuse | C27: Each transaction row runs one MATCH into a hidden helper column, then several cheap INDEX calls reuse it.
B28: SUMIFS engine | C28: All aggregation uses SUMIFS/COUNTIFS - Excel's fastest multi-threaded aggregation functions. No SUMPRODUCT or array formulas.
B29: Extra boost (optional) | C29: Import ERP_Macros.bas (File ▸ Save As .xlsm, Alt+F11 ▸ File ▸ Import) for one-click Fast Mode, new invoice, PDF invoice, backup and archive.
B31: RULES & LIMITS
B32: Colour code | C32: Blue text on cream = you type. Black/grey = formula, never overwrite. Green = linked from another sheet.
B33: Sample data | C33: Rows already filled are DEMO data. Clear only the cream input cells (or run ClearDemoData macro) before going live.
B34: Capacity | C34: 20,000 lines per register per year. At year end: Save As a new file, set new FY start, carry forward closing stock as Opening Qty/Rate and party balances as Opening Bal.
B35: Returns | C35: Sales return: Adjustments with +qty, reason 'Sales Return', plus a Payment / credit in CashBook. Purchase return: −qty and a Receipt from supplier.
B36: Costing method | C36: Weighted-average cost over the year (opening + all purchases). COGS uses the current average, the standard method for traders.
B37: Assumption | C37: Currency ₹ and Indian GST structure. Rates in Settings are editable; verify slabs with your CA.
B39: C ENGINE EDITION (SmartTrader64.xll)
B40: What it is | C40: A native Excel add-in written in C. Stock, cost, GST, party ledgers and the cash book are posted in one pass by compiled code - six formulas instead of ~100,000. Results are identical to the formula edition, cell for cell.
B41: Install once | C41: 1) Copy SmartTrader64.xll (or SmartTrader32.xll for 32-bit Office) to a folder, e.g. Documents\SmartTrader. 2) Right-click it ▸ Properties ▸ tick 'Unblock' ▸ OK (Windows blocks add-ins downloaded from the internet). 3) Excel ▸ File ▸ Options ▸ Add-ins ▸ Manage: Excel Add-ins ▸ Go ▸ Browse ▸ pick the .xll ▸ OK.
B42: Check it works | C42: Dashboard top-right shows '✔ SmartTrader C Engine 1.0'. A red '⚠ C engine not loaded' means step 3 was skipped and the grey columns show NAME errors until the add-in is loaded. Your typed data is never affected.
B43: Which .xll? | C43: Excel ▸ File ▸ Account ▸ About Excel shows '64-bit' or '32-bit'. Use the matching file.
B44: Capacity | C44: 20,000 lines per register, 2,000 items, 1,000 parties. A full recalculation of the sample data takes about 5 ms.
B45: Do not | C45: Sort the register sheets (the grey output blocks are single array formulas; use the filter arrows instead) or type inside grey columns.
B46: Platforms | C46: Excel for Windows (2010 and later, 32- or 64-bit). On Mac / Excel Online use the formula edition (SmartTrader_ERP.xlsx), which has the same layout.
